Workbook

Sheet Presupuesto ventas
A1: ingresos netos
A3: producto | B3: unidad | C3: 45748 | D3: 45778 | E3: 45809 | F3: 45839 | G3: 45870 | H3: 45901 | I3: 45931 | J3: 45962 | K3: 45992 | L3: 46023 | M3: 46054 | N3: 46082 | O3: total por producto
A4: CLINKER | B4: Toneladas | C4: 0 | D4: 0 | E4: 0 | F4: 0 | G4: 0 | H4: 0 | I4: 0 | J4: 0 | K4: 0 | L4: 0 | M4: 0 | N4: 0 | O4: =+SUM(C4:N4) -> 0
A5: Cemento IP25 | B5: Bolsas | C5: 351413.71 | D5: 339393.93 | E5: 354494.76 | F5: 354619.42 | G5: 345523.46 | H5: 305317.84 | I5: 350631.79 | J5: 331024.39 | K5: 360057.09 | L5: 340934.61 | M5: 349272.37 | N5: 317190.1 | O5: =+SUM(C5:N5) -> 4099873.5
B6: A granel | O6: =+SUM(C6:N6) -> 0
A7: Cemento IP30 | B7: Bolsas | C7: 9917167.4 | D7: 10623303 | E7: 10114239 | F7: 9180119.7 | G7: 11350210 | H7: 9717166.1 | I7: 9416123.8 | J7: 10121937 | K7: 10249955 | L7: 10694999 | M7: 8412943.5 | N7: 6945764.2 | O7: =+SUM(C7:N7) -> 1.1674393e+08
B8: A granel | C8: 6233365.5 | D8: 2807792.8 | E8: 1937351.6 | F8: 2872826.7 | G8: 4727104.4 | H8: 2137879.9 | I8: 3843703.1 | J8: 3350387.3 | K8: 3055433.9 | L8: 1785578.6 | M8: 1710313.9 | N8: 3143108.2 | O8: =+SUM(C8:N8) -> 37604846
A9: Cemento IP40 | B9: Bolsas | C9: 11498586 | D9: 10917741 | E9: 11735029 | F9: 11930289 | G9: 14115209 | H9: 12782124 | I9: 13468257 | J9: 14666851 | K9: 15490903 | L9: 15376967 | M9: 16134130 | N9: 11715671 | O9: =+SUM(C9:N9) -> 1.5983176e+08
B10: A granel | C10: 6282807.4 | D10: 4251963.7 | E10: 6063528 | F10: 6524106.1 | G10: 5807621.4 | H10: 7617110.6 | I10: 8130409.7 | J10: 12250267 | K10: 7081478.3 | L10: 13920110 | M10: 6369997 | N10: 12632613 | O10: =+SUM(C10:N10) -> 96932013
A11: Yeso | B11: Bolsas | C11: 689397.3 | D11: 880324.34 | E11: 1006161.7 | F11: 1013142.4 | G11: 1070280 | H11: 920451.52 | I11: 911122.72 | J11: 929140.22 | K11: 914150.9 | L11: 917600.9 | M11: 830730.1 | N11: 615386.07 | O11: =+SUM(C11:N11) -> 10697888
A12: Cemento Cola | B12: Bolsas | C12: 2881182.5 | D12: 2750900.9 | E12: 2728908.4 | F12: 3116659.5 | G12: 3177942 | H12: 3016014.6 | I12: 2901398.2 | J12: 2904481.4 | K12: 3540754.3 | L12: 2783464.4 | M12: 2562275.2 | N12: 1750975.3 | O12: =+SUM(C12:N12) -> 34114957
A13: Cemento cola 2 | C13: 363935.5 | D13: 363239.5 | E13: 362717.5 | F13: 364283.5 | G13: 364979.5 | H13: 365153.5 | I13: 362891.5 | J13: 366023.5 | K13: 368459.5 | L13: 371069.5 | M13: 371765.5 | N13: 360281.5 | O13: =+SUM(C13:N13) -> 4384800
A14: Mortero de Revoque | B14: Bolsas | C14: 28048.8 | D14: 35322.003 | E14: 40156.412 | F14: 45343.983 | G14: 42359.043 | H14: 36673.374 | I14: 36474.905 | J14: 36971.333 | K14: 36794.596 | L14: 36882.199 | M14: 33452.283 | N14: 24754.11 | O14: =+SUM(C14:N14) -> 433233.04
A15: Mortero de Mampostería | B15: Bolsas | C15: 59461.89 | D15: 59461.89 | E15: 59461.89 | F15: 59461.89 | G15: 59461.89 | H15: 59461.89 | I15: 59461.89 | J15: 59461.89 | K15: 59461.89 | L15: 59461.89 | M15: 59461.89 | N15: 59461.89 | O15: =+SUM(C15:N15) -> 713542.68
A16: Puzolana Molida | B16: Toneladas | C16: 0 | D16: 0 | E16: 0 | F16: 0 | G16: 0 | H16: 0 | I16: 0 | J16: 0 | K16: 0 | L16: 0 | M16: 0 | N16: 0 | O16: =+SUM(C16:N16) -> 0
A17: total mensual | B17: 0.87 | C17: =+SUM(C4:C16) -> 38305366 | D17: =+SUM(D4:D16) -> 33029443 | E17: =+SUM(E4:E16) -> 34402049 | F17: =+SUM(F4:F16) -> 35460852 | G17: =+SUM(G4:G16) -> 41060690 | H17: =+SUM(H4:H16) -> 36957353 | I17: =+SUM(I4:I16) -> 39480474 | J17: =+SUM(J4:J16) -> 45016544 | ... N17: =+SUM(N4:N16) -> 37565206 | O17: =+SUM(C17:N17) -> 4.6555684e+08
A18: costo de produccion de lo vendido
A19: producto | B19: unidad | C19: 45748 | D19: 45778 | E19: 45809 | F19: 45839 | G19: 45870 | H19: 45901 | I19: 45931 | J19: 45962 | K19: 45992 | L19: 46023 | M19: 46054 | N19: 46082 | O19: total por producto
A20: CLINKER | B20: Toneladas | C20: 0 | D20: 0 | E20: 0 | F20: 0 | G20: 0 | H20: 0 | I20: 0 | J20: 0 | K20: 0 | L20: 0 | M20: 0 | N20: 0 | O20: =+SUM(C20:N20) -> 0
A21: Cemento IP25 | B21: Bolsas | C21: 0 | D21: 0 | E21: 0 | F21: 0 | G21: 0 | H21: 0 | I21: 0 | J21: 0 | K21: 0 | L21: 0 | M21: 0 | N21: 0 | O21: =+SUM(C21:N21) -> 0
B22: A granel | C22: 350251.28 | D22: 350284.91 | E22: 350251.28 | F22: 350284.91 | G22: 350251.28 | H22: 350284.91 | I22: 350284.91 | J22: 350251.28 | K22: 350284.91 | L22: 350284.91 | M22: 350284.91 | N22: 350284.91 | O22: =+SUM(C22:N22) -> 4203284.4
A23: Cemento IP30 | B23: Bolsas | C23: 8636287.3 | D23: 9303755.5 | E23: 8832844 | F23: 8116655.2 | G23: 10291015 | H23: 8524291.3 | I23: 8325319.5 | J23: 8873063.4 | K23: 8974658.4 | L23: 9588897.9 | M23: 7341892.4 | N23: 6132347.8 | O23: =+SUM(C23:N23) -> 1.0294103e+08
B24: A granel | C24: 4852204.9 | D24: 2198066.8 | E24: 1512352 | F24: 2270467.4 | G24: 3831127.5 | H24: 1676405.4 | I24: 3037775.6 | J24: 2625319 | K24: 2391365.6 | L24: 1431014.4 | M24: 1334175.5 | N24: 2480522.5 | O24: =+SUM(C24:N24) -> 29640797
A25: Cemento IP40 | B25: Bolsas | C25: 10208375 | D25: 9713790.2 | E25: 10481998 | F25: 10644784 | G25: 12727556 | H25: 11487535 | I25: 12074988 | J25: 12728267 | K25: 13460538 | L25: 13633820 | M25: 14004581 | N25: 10549959 | O25: =+SUM(C25:N25) -> 1.4171619e+08
B26: A granel | C26: 4897752 | D26: 3466537.9 | E26: 4775753.4 | F26: 4981911.9 | G26: 4641535.9 | H26: 6188034.2 | I26: 6782613 | J26: 10529331 | K26: 5606895.6 | L26: 11945707 | M26: 5425933.2 | N26: 10866049 | O26: =+SUM(C26:N26) -> 80108054
A27: Yeso | B27: Bolsas | C27: 537446.51 | D27: 677079.16 | E27: 770055.68 | F27: 869534.1 | G27: 825511.55 | H27: 706943.1 | I27: 704249.65 | J27: 716142.45 | K27: 705588.37 | L27: 709256.93 | M27: 638935.01 | N27: 474313.86 | O27: =+SUM(C27:N27) -> 8335056.4
A28: Cemento Cola | B28: Bolsas | C28: 1677738 | D28: 1604502.5 | E28: 1593636.3 | F28: 1813372.9 | G28: 1846007.2 | H28: 1751231.1 | I28: 1693671.8 | J28: 1683033.3 | K28: 2040087.9 | L28: 1594067.6 | M28: 1465033.9 | N28: 1028454.1 | O28: =+SUM(C28:N28) -> 19790836
A29: Cemento cola 2 | O29: =+SUM(C29:N29) -> 0
A30: Mortero de Revoque | B30: Bolsas | C30: 22936.232 | D30: 28895.277 | E30: 32863.231 | F30: 37108.64 | G30: 35229.953 | H30: 30169.789 | I30: 30054.895 | J30: 30562.494 | K30: 30111.986 | L30: 30268.499 | M30: 27267.545 | N30: 20242.079 | O30: =+SUM(C30:N30) -> 355710.62
A31: Mortero de Mampostería | B31: Bolsas | O31: =+SUM(C31:N31) -> 0
A32: Puzolana Molida | B32: Toneladas | C32: 0 | D32: 0 | E32: 0 | F32: 0 | G32: 0 | H32: 0 | I32: 0 | J32: 0 | K32: 0 | L32: 0 | M32: 0 | N32: 0 | O32: =+SUM(C32:N32) -> 0
A33: total mensual | B33: Bs | C33: =+SUM(C20:C32) -> 31182991 | D33: =+SUM(D20:D32) -> 27342912 | E33: =+SUM(E20:E32) -> 28349754 | F33: =+SUM(F20:F32) -> 29084119 | G33: =+SUM(G20:G32) -> 34548234 | H33: =+SUM(H20:H32) -> 30714895 | I33: =+SUM(I20:I32) -> 32998958 | J33: =+SUM(J20:J32) -> 37535970 | ... N33: =+SUM(N20:N32) -> 31902173 | O33: =+SUM(C33:N33) -> 3.8709096e+08
A36: producto | B36: unidad | C36: IT | D36: CV | E36: margen bruto | F36: MC (%)
A37: CLINKER | B37: Toneladas | C37: =+O4 -> 0 | D37: =+O20 -> 0 | E37: =+C37-D37 -> 0
A38: Cemento IP25 | B38: Bolsas | C38: =+O5 -> 4099873.5 | D38: =+O22 -> 4203284.4 | E38: =+C38-D38 -> -103410.92 | F38: =+E38/C38 -> -0.025222954
B39: A granel | C39: =+O6 -> 0 | E39: =+C39-D39 -> 0
A40: Cemento IP30 | B40: Bolsas | C40: =+O7 -> 1.1674393e+08 | D40: =+O23 -> 1.0294103e+08 | E40: =+C40-D40 -> 13802900 | F40: =+E40/C40 -> 0.11823227
B41: A granel | C41: =+O8 -> 37604846 | D41: =+O24 -> 29640797 | E41: =+C41-D41 -> 7964049.3 | F41: =+E41/C41 -> 0.21178253
A42: Cemento IP40 | B42: Bolsas | C42: =+O9 -> 1.5983176e+08 | D42: =+O25 -> 1.4171619e+08 | E42: =+C42-D42 -> 18115563 | F42: =+E42/C42 -> 0.11334145
B43: A granel | C43: =+O10 -> 96932013 | D43: =+O26 -> 80108054 | E43: =+C43-D43 -> 16823959 | F43: =+E43/C43 -> 0.17356452
A44: Yeso | B44: Bolsas | C44: =+O11 -> 10697888 | D44: =+O27 -> 8335056.4 | E44: =+C44-D44 -> 2362831.8 | F44: =+E44/C44 -> 0.22086899
A45: Cemento Cola | B45: Bolsas | C45: =+O12+O13 -> 38499757 | D45: =+O28 -> 19790836 | E45: =+C45-D45 -> 18708920 | F45: =+E45/C45 -> 0.48594905
A46: Mortero de Revoque | B46: Bolsas | C46: =+O14 -> 433233.04 | D46: =+O30 -> 355710.62 | E46: =+C46-D46 -> 77522.422 | F46: =+E46/C46 -> 0.17893931
A47: Mortero de Mampostería | B47: Bolsas | C47: =+O15 -> 713542.68 | D47: =+O31 -> 0 | E47: =+C47-D47 -> 713542.68 | F47: =+E47/C47 -> 1
A48: Puzolana Molida | B48: Toneladas | C48: =+O16 -> 0 | D48: =+O32 -> 0 | E48: =+C48-D48 -> 0
A49: total mensual | C49: =+SUM(C37:C48) -> 4.6555684e+08 | D49: =+SUM(D37:D48) -> 3.8709096e+08 | E49: =+C49-D49 -> 78465877 | F49: =+E49/C49 -> 0.16854199
A51: Cantidades
A52: Cemento (eq. bolsas) | C52: =C5+C7+C8*20+C9+C10*20 -> 2.7209063e+08 | D52: =D5+D7+D8*20+D9+D10*20 -> 1.6307557e+08 | E52: =E5+E7+E8*20+E9+E10*20 -> 1.8222136e+08 | F52: =F5+F7+F8*20+F9+F10*20 -> 2.0940368e+08 | G52: =G5+G7+G8*20+G9+G10*20 -> 2.3650546e+08 | H52: =H5+H7+H8*20+H9+H10*20 -> 2.1790442e+08 | I52: =I5+I7+I8*20+I9+I10*20 -> 2.6271727e+08 | J52: =J5+J7+J8*20+J9+J10*20 -> 3.3713289e+08 | ... N52: =N5+N7+N8*20+N9+N10*20 -> 3.3449306e+08

Sheet Presupuesto 25
A1: P R E S U P U E S T O D E L E S T A D O D E R E S U L T A D O S
A3: C O D I G O | B3: D E T A L L E D E C U E N T A | C3: 45397 | D3: 45427 | E3: 45457 | F3: 45487 | G3: 45517 | H3: 45547 | I3: 45577 | J3: 45607 | K3: 45637 | L3: 45667 | M3: 45697 | N3: 45727 | O3: TOTAL
C4: Bs | D4: Bs | E4: Bs | F4: Bs | G4: Bs | H4: Bs | I4: Bs | J4: Bs | K4: Bs | L4: Bs | M4: Bs | N4: Bs | O4: Bs
A6: 3 0 00 00 | B6: I N G R E S O S | C6: =+C8 -> 39913012 | D6: =+D8 -> 34637088 | E6: =+E8 -> 36009694 | F6: =+F8 -> 37068498 | G6: =+G8 -> 42668336 | H6: =+H8 -> 38564999 | I6: =+I8 -> 41088120 | J6: =+J8 -> 46624190 | ... N6: =+N8 -> 39172852 | O6: =SUM(C6:N6) -> 4.8484858e+08
A8: 3 1 00 00 | B8: INGRESOS NETOS | C8: =+C9+C17 -> 39913012 | D8: =+D9+D17 -> 34637088 | E8: =+E9+E17 -> 36009694 | F8: =+F9+F17 -> 37068498 | G8: =+G9+G17 -> 42668336 | H8: =+H9+H17 -> 38564999 | I8: =+I9+I17 -> 41088120 | J8: =+J9+J17 -> 46624190 | ... N8: =+N9+N17 -> 39172852 | O8: =SUM(C8:N8) -> 4.8484858e+08
A9: 3 1 01 00 | B9: INGRESOS OPERATIVOS | C9: =SUM(C10:C10)+C16 -> 39913012 | D9: =SUM(D10:D10)+D16 -> 34637088 | E9: =SUM(E10:E10)+E16 -> 36009694 | F9: =SUM(F10:F10)+F16 -> 37068498 | G9: =SUM(G10:G10)+G16 -> 42668336 | H9: =SUM(H10:H10)+H16 -> 38564999 | I9: =SUM(I10:I10)+I16 -> 41088120 | J9: =SUM(J10:J10)+J16 -> 46624190 | ... N9: =SUM(N10:N10)+N16 -> 39172852 | O9: =SUM(C9:N9) -> 4.8484858e+08
A10: 3 1 01 01 | B10: INGRESOS POR VTA. DE PRODUCTOS | C10: =SUM(C11:C15) -> 38305366 | D10: =SUM(D11:D15) -> 33029443 | E10: =SUM(E11:E15) -> 34402049 | F10: =SUM(F11:F15) -> 35460852 | G10: =SUM(G11:G15) -> 41060690 | H10: =SUM(H11:H15) -> 36957353 | I10: =SUM(I11:I15) -> 39480474 | J10: =SUM(J11:J15) -> 45016544 | ... N10: =SUM(N11:N15) -> 37565206 | O10: =SUM(C10:N10) -> 4.6555684e+08
B11: CEMENTO | C11: 34283340 | D11: 28940194 | E11: 30204643 | F11: 30861961 | G11: 36345667 | H11: 32559598 | I11: 35209125 | J11: 40720466 | K11: 36237827 | L11: 42118590 | M11: 32976657 | N11: 34754347 | O11: =SUM(C11:N11) -> 4.1521242e+08
B12: YESO | C12: 689397.3 | D12: 880324.34 | E12: 1006161.7 | F12: 1013142.4 | G12: 1070280 | H12: 920451.52 | I12: 911122.72 | J12: 929140.22 | K12: 914150.9 | L12: 917600.9 | M12: 830730.1 | N12: 615386.07 | O12: =SUM(C12:N12) -> 10697888
B13: MORTEROS SECOS | C13: 3332628.7 | D13: 3208924.3 | E13: 3191244.2 | F13: 3585748.8 | G13: 3644742.4 | H13: 3477303.4 | I13: 3360226.5 | J13: 3366938.1 | K13: 4005470.3 | L13: 3250878 | M13: 3026954.8 | N13: 2195472.8 | O13: =SUM(C13:N13) -> 39646532
B14: PUZOLANA MOLIDA | C14: 0 | D14: 0 | E14: 0 | F14: 0 | G14: 0 | H14: 0 | I14: 0 | J14: 0 | K14: 0 | L14: 0 | M14: 0 | N14: 0 | O14: =SUM(C14:N14) -> 0
B15: CLINKER | C15: 0 | D15: 0 | E15: 0 | F15: 0 | G15: 0 | H15: 0 | I15: 0 | J15: 0 | K15: 0 | L15: 0 | M15: 0 | N15: 0 | O15: =SUM(C15:N15) -> 0
B16: SERVICIO FLETES Y ESTIBAJES | C16: 1607645.6 | D16: 1607645.6 | E16: 1607645.6 | F16: 1607645.6 | G16: 1607645.6 | H16: 1607645.6 | I16: 1607645.6 | J16: 1607645.6 | K16: 1607645.6 | L16: 1607645.6 | M16: 1607645.6 | N16: 1607645.6 | O16: =SUM(C16:N16) -> 19291748
A17: 3 1 02 00 | B17: INGRESOS NO OPERATIVOS | C17: =SUM(C18:C22) -> 0 | D17: =SUM(D18:D22) -> 0 | E17: =SUM(E18:E22) -> 0 | F17: =SUM(F18:F22) -> 0 | G17: =SUM(G18:G22) -> 0 | H17: =SUM(H18:H22) -> 0 | I17: =SUM(I18:I22) -> 0 | J17: =SUM(J18:J22) -> 0 | ... N17: =SUM(N18:N22) -> 0 | O17: =SUM(C17:N17) -> 0
A18: 3 1 02 01 | B18: PULPERIAS Y MAT. ALMACEN | O18: =SUM(C18:N18) -> 0
A19: 3 1 02 02 | B19: VENTA DE ACTIVOS
A20: 3 1 02 03 | B20: INGRESOS FINANCIEROS | O20: =SUM(C20:N20) -> 0
A21: 3 1 02 04 | B21: OTROS INGRESOS Y RESIDUOS | O21: =SUM(C21:N21) -> 0
O22: =SUM(C22:N22) -> 0
A23: 3 1 03 00 | B23: DESCUENTOS, DEVOLUCIONES, REBAJAS | C23: =SUM(C24) -> 0 | D23: =SUM(D24) -> 0 | E23: =SUM(E24) -> 0 | F23: =SUM(F24) -> 0 | G23: =SUM(G24) -> 0 | H23: =SUM(H24) -> 0 | I23: =SUM(I24) -> 0 | J23: =SUM(J24) -> 0 | ... N23: =SUM(N24) -> 0 | O23: =SUM(C23:N23) -> 0
A24: 3 1 03 01 | B24: DESCUENTOS, DEVOLUCIONES, REBAJAS | D24: 0 | E24: 0 | F24: 0 | G24: 0 | H24: 0 | I24: 0 | J24: 0 | K24: 0 | L24: 0 | M24: 0 | N24: 0 | O24: =SUM(C24:N24) -> 0
O25: =SUM(C25:N25) -> 0
A26: 4 0 00 00 | B26: G A S T O S | C26: =C27+C40+C55+C70+C74+C78+C82 -> 38385752 | D26: =D27+D40+D55+D70+D74+D78+D82 -> 34363744 | E26: =E27+E40+E55+E70+E74+E78+E82 -> 35417917 | F26: =F27+F40+F55+F70+F74+F78+F82 -> 36188793 | G26: =G27+G40+G55+G70+G74+G78+G82 -> 41846006 | H26: =H27+H40+H55+H70+H74+H78+H82 -> 37871173 | I26: =I27+I40+I55+I70+I74+I78+I82 -> 40242239 | J26: =J27+J40+J55+J70+J74+J78+J82 -> 44970151 | ... N26: =N27+N40+N55+N70+N74+N78+N82 -> 39079411 | O26: =SUM(C26:N26) -> 4.7372727e+08
A27: 4 1 00 00 | B27: COSTO DE PRODUCCION DE LO VENDIDO | C27: =+C28+C35 -> 31191325 | D27: =+D28+D35 -> 27351246 | E27: =+E28+E35 -> 28358087 | F27: =+F28+F35 -> 29092452 | G27: =+G28+G35 -> 34556567 | H27: =+H28+H35 -> 30723229 | I27: =+I28+I35 -> 33007291 | J27: =+J28+J35 -> 37544304 | ... N27: =+N28+N35 -> 31910506 | O27: =SUM(C27:N27) -> 3.8719096e+08
A28: 4 1 01 00 | B28: COSTO DE PRODUCCION DE LO VENDIDO | C28: =SUM(C29) -> 31182991 | D28: =SUM(D29) -> 27342912 | E28: =SUM(E29) -> 28349754 | F28: =SUM(F29) -> 29084119 | G28: =SUM(G29) -> 34548234 | H28: =SUM(H29) -> 30714895 | I28: =SUM(I29) -> 32998958 | J28: =SUM(J29) -> 37535970 | ... N28: =SUM(N29) -> 31902173 | O28: =SUM(C28:N28) -> 3.8709096e+08
A29: 4 1 01 01 | B29: COSTO DE PRODUCCION DE LO VENDIDO | C29: =SUM(C30:C34) -> 31182991 | D29: =SUM(D30:D34) -> 27342912 | E29: =SUM(E30:E34) -> 28349754 | F29: =SUM(F30:F34) -> 29084119 | G29: =SUM(G30:G34) -> 34548234 | H29: =SUM(H30:H34) -> 30714895 | I29: =SUM(I30:I34) -> 32998958 | J29: =SUM(J30:J34) -> 37535970 | ... N29: =SUM(N30:N34) -> 31902173 | O29: =SUM(C29:N29) -> 3.8709096e+08
B30: CEMENTO | C30: 28944871 | D30: 25032435 | E30: 25953199 | F30: 26364103 | G30: 31841485 | H30: 28226551 | I30: 30570981 | J30: 35106232 | K30: 30783742 | L30: 36949725 | M30: 28456867 | N30: 30379163 | O30: =SUM(C30:N30) -> 3.5860936e+08
B31: YESO | C31: 537446.51 | D31: 677079.16 | E31: 770055.68 | F31: 869534.1 | G31: 825511.55 | H31: 706943.1 | I31: 704249.65 | J31: 716142.45 | K31: 705588.37 | L31: 709256.93 | M31: 638935.01 | N31: 474313.86 | O31: =SUM(C31:N31) -> 8335056.4
B32: MORTEROS SECOS | C32: 1700674.2 | D32: 1633397.8 | E32: 1626499.5 | F32: 1850481.5 | G32: 1881237.2 | H32: 1781400.9 | I32: 1723726.7 | J32: 1713595.8 | K32: 2070199.9 | L32: 1624336.1 | M32: 1492301.4 | N32: 1048696.1 | O32: =SUM(C32:N32) -> 20146547
B33: PUZOLANA MOLIDA | C33: 0 | D33: 0 | E33: 0 | F33: 0 | G33: 0 | H33: 0 | I33: 0 | J33: 0 | K33: 0 | L33: 0 | M33: 0 | N33: 0 | O33: =SUM(C33:N33) -> 0
B34: CLINKER | C34: 0 | D34: 0 | E34: 0 | F34: 0 | G34: 0 | H34: 0 | I34: 0 | J34: 0 | K34: 0 | L34: 0 | M34: 0 | N34: 0 | O34: =SUM(C34:N34) -> 0
A35: 4 1 0 2 00 | B35: EGRESOS NO OPERATIVOS | C35: =+C36 -> 8333.33 | D35: =+D36 -> 8333.33 | E35: =+E36 -> 8333.33 | F35: =+F36 -> 8333.33 | G35: =+G36 -> 8333.33 | H35: =+H36 -> 8333.33 | I35: =+I36 -> 8333.33 | J35: =+J36 -> 8333.33 | ... N35: =+N36 -> 8333.37 | O35: =SUM(C35:N35) -> 100000
A36: 4 1 0 2 01 | B36: EGRESOS NO OPERATIVOS | C36: =+C37+C38 -> 8333.33 | D36: =+D37+D38 -> 8333.33 | E36: =+E37+E38 -> 8333.33 | F36: =+F37+F38 -> 8333.33 | G36: =+G37+G38 -> 8333.33 | H36: =+H37+H38 -> 8333.33 | I36: =+I37+I38 -> 8333.33 | J36: =+J37+J38 -> 8333.33 | ... N36: =+N37+N38 -> 8333.37 | O36: =SUM(C36:N36) -> 100000
B37: FABRICACION Y MONTAJE | C37: 0 | D37: 0 | E37: 0 | F37: 0 | G37: 0 | H37: 0 | I37: 0 | J37: 0 | K37: 0 | L37: 0 | M37: 0 | N37: 0 | O37: =SUM(C37:N37) -> 0
B38: PLANTA AGREGADOS | C38: 8333.33 | D38: 8333.33 | E38: 8333.33 | F38: 8333.33 | G38: 8333.33 | H38: 8333.33 | I38: 8333.33 | J38: 8333.33 | K38: 8333.33 | L38: 8333.33 | M38: 8333.33 | N38: 8333.37 | O38: =SUM(C38:N38) -> 100000
B39: REP.MANTTO. ACTIVOS | C39: 989.53144 | D39: 989.53144 | E39: 989.53144 | F39: 989.53144 | G39: 989.53144 | H39: 989.53144 | I39: 989.53144 | J39: 989.53144 | K39: 989.53144 | L39: 989.53144 | M39: 989.53144 | N39: 989.53144 | O39: =SUM(C39:N39) -> 11874.377
A40: 4 2 00 00 | B40: GASTOS DE ADMINISTRACION | C40: =C41+C45+C48+C52 -> 978326.19 | D40: =D41+D45+D48+D52 -> 978326.19 | E40: =E41+E45+E48+E52 -> 978326.19 | F40: =F41+F45+F48+F52 -> 978326.19 | G40: =G41+G45+G48+G52 -> 978326.19 | H40: =H41+H45+H48+H52 -> 978326.19 | I40: =I41+I45+I48+I52 -> 978326.19 | J40: =J41+J45+J48+J52 -> 978326.19 | ... N40: =N41+N45+N48+N52 -> 978326.19 | O40: =SUM(C40:N40) -> 11739914
A41: 4 2 01 00 | B41: OBRA DE MANO | C41: =SUM(C42:C44) -> 556964.24 | D41: =SUM(D42:D44) -> 556964.24 | E41: =SUM(E42:E44) -> 556964.24 | F41: =SUM(F42:F44) -> 556964.24 | G41: =SUM(G42:G44) -> 556964.24 | H41: =SUM(H42:H44) -> 556964.24 | I41: =SUM(I42:I44) -> 556964.24 | J41: =SUM(J42:J44) -> 556964.24 | ... N41: =SUM(N42:N44) -> 556964.24 | O41: =SUM(C41:N41) -> 6683570.9
A42: 4 2 01 01 | B42: SUELDOS Y SALARIOS | C42: 401362.2 | D42: 401362.2 | E42: 401362.2 | F42: 401362.2 | G42: 401362.2 | H42: 401362.2 | I42: 401362.2 | J42: 401362.2 | K42: 401362.2 | L42: 401362.2 | M42: 401362.2 | N42: 401362.2 | O42: =SUM(C42:N42) -> 4816346.4
A43: 4 2 01 02 | B43: APORTES PATRONALES | C43: 67734.639 | D43: 67734.639 | E43: 67734.639 | F43: 67734.639 | G43: 67734.639 | H43: 67734.639 | I43: 67734.639 | J43: 67734.639 | K43: 67734.639 | L43: 67734.639 | M43: 67734.639 | N43: 67734.639 | O43: =SUM(C43:N43) -> 812815.67
A44: 4 2 01 03 | B44: BENEFICIOS SOCIALES | C44: 87867.402 | D44: 87867.402 | E44: 87867.402 | F44: 87867.402 | G44: 87867.402 | H44: 87867.402 | I44: 87867.402 | J44: 87867.402 | K44: 87867.402 | L44: 87867.402 | M44: 87867.402 | N44: 87867.402 | O44: =SUM(C44:N44) -> 1054408.8
A45: 4 2 02 00 | B45: MATERIALES DE ALMACEN | C45: =SUM(C46:C47) -> 11296.678 | D45: =SUM(D46:D47) -> 11296.678 | E45: =SUM(E46:E47) -> 11296.678 | F45: =SUM(F46:F47) -> 11296.678 | G45: =SUM(G46:G47) -> 11296.678 | H45: =SUM(H46:H47) -> 11296.678 | I45: =SUM(I46:I47) -> 11296.678 | J45: =SUM(J46:J47) -> 11296.678 | ... N45: =SUM(N46:N47) -> 11296.678 | O45: =SUM(C45:N45) -> 135560.14
A46: 4 2 02 01 | B46: MATERIALES DE ALMACEN | C46: 11296.678 | D46: 11296.678 | E46: 11296.678 | F46: 11296.678 | G46: 11296.678 | H46: 11296.678 | I46: 11296.678 | J46: 11296.678 | K46: 11296.678 | L46: 11296.678 | M46: 11296.678 | N46: 11296.678 | O46: =SUM(C46:N46) -> 135560.14
A47: 4 2 02 02 | B47: GASTOS DE SERVICIOS | O47: =SUM(C47:N47) -> 0
A48: 4 2 03 00 | B48: GASTOS GENERALES | C48: =SUM(C49:C51) -> 397790.83 | D48: =SUM(D49:D51) -> 397790.83 | E48: =SUM(E49:E51) -> 397790.83 | F48: =SUM(F49:F51) -> 397790.83 | G48: =SUM(G49:G51) -> 397790.83 | H48: =SUM(H49:H51) -> 397790.83 | I48: =SUM(I49:I51) -> 397790.83 | J48: =SUM(J49:J51) -> 397790.83 | ... N48: =SUM(N49:N51) -> 397790.83 | O48: =SUM(C48:N48) -> 4773489.9
A49: 4 2 03 01 | B49: GASTOS GENERALES | C49: 379726.99 | D49: 379726.99 | E49: 379726.99 | F49: 379726.99 | G49: 379726.99 | H49: 379726.99 | I49: 379726.99 | J49: 379726.99 | K49: 379726.99 | L49: 379726.99 | M49: 379726.99 | N49: 379726.99 | O49: =SUM(C49:N49) -> 4556723.9
A50: 4 2 03 02 | B50: OTROS GASTOS | C50: 0 | D50: 0 | E50: 0 | F50: 0 | G50: 0 | H50: 0 | I50: 0 | J50: 0 | K50: 0 | L50: 0 | M50: 0 | N50: 0 | O50: =SUM(C50:N50) -> 0
A51: 4 2 03 03 | B51: AYUDA COMUNITARIA | C51: 18063.84 | D51: 18063.84 | E51: 18063.84 | F51: 18063.84 | G51: 18063.84 | H51: 18063.84 | I51: 18063.84 | J51: 18063.84 | K51: 18063.84 | L51: 18063.84 | M51: 18063.84 | N51: 18063.84 | O51: =SUM(C51:N51) -> 216766.08
A52: 4 2 04 00 | B52: DEPRECIACION DEL ACTIVO FIJO | C52: =SUM(C53) -> 12274.439 | D52: =SUM(D53) -> 12274.439 | E52: =SUM(E53) -> 12274.439 | F52: =SUM(F53) -> 12274.439 | G52: =SUM(G53) -> 12274.439 | H52: =SUM(H53) -> 12274.439 | I52: =SUM(I53) -> 12274.439 | J52: =SUM(J53) -> 12274.439 | ... N52: =SUM(N53) -> 12274.439 | O52: =SUM(C52:N52) -> 147293.27
A53: 4 2 04 01 | B53: DEPRECIACION DEL ACTIVO FIJO | C53: 12274.439 | D53: 12274.439 | E53: 12274.439 | F53: 12274.439 | G53: 12274.439 | H53: 12274.439 | I53: 12274.439 | J53: 12274.439 | K53: 12274.439 | L53: 12274.439 | M53: 12274.439 | N53: 12274.439 | O53: =SUM(C53:N53) -> 147293.27
O54: =SUM(C54:N54) -> 0
A55: 4 3 00 00 | B55: GASTOS DE COMERCIALIZACION | C55: =C56+C63+C67+C60 -> 3706864.3 | D55: =D56+D63+D67+D60 -> 3706864.3 | E55: =E56+E63+E67+E60 -> 3706864.3 | F55: =F56+F63+F67+F60 -> 3706864.3 | G55: =G56+G63+G67+G60 -> 3706864.3 | H55: =H56+H63+H67+H60 -> 3706864.3 | I55: =I56+I63+I67+I60 -> 3706864.3 | J55: =J56+J63+J67+J60 -> 3706864.3 | ... N55: =N56+N63+N67+N60 -> 3706864.3 | O55: =SUM(C55:N55) -> 44482372
A56: 4 3 01 00 | B56: OBRA DE MANO | C56: =SUM(C57:C59) -> 1146462 | D56: =SUM(D57:D59) -> 1146462 | E56: =SUM(E57:E59) -> 1146462 | F56: =SUM(F57:F59) -> 1146462 | G56: =SUM(G57:G59) -> 1146462 | H56: =SUM(H57:H59) -> 1146462 | I56: =SUM(I57:I59) -> 1146462 | J56: =SUM(J57:J59) -> 1146462 | ... N56: =SUM(N57:N59) -> 1146462 | O56: =SUM(C56:N56) -> 13757544
A57: 4 3 01 01 | B57: SUELDOS Y SALARIOS | C57: 837598.39 | D57: 837598.39 | E57: 837598.39 | F57: 837598.39 | G57: 837598.39 | H57: 837598.39 | I57: 837598.39 | J57: 837598.39 | K57: 837598.39 | L57: 837598.39 | M57: 837598.39 | N57: 837598.39 | O57: =SUM(C57:N57) -> 10051181
A58: 4 3 01 02 | B58: APORTES PATRONALES | C58: 144765.76 | D58: 144765.76 | E58: 144765.76 | F58: 144765.76 | G58: 144765.76 | H58: 144765.76 | I58: 144765.76 | J58: 144765.76 | K58: 144765.76 | L58: 144765.76 | M58: 144765.76 | N58: 144765.76 | O58: =SUM(C58:N58) -> 1737189.1
A59: 4 3 01 03 | B59: BENEFICIOS SOCIALES | C59: 164097.84 | D59: 164097.84 | E59: 164097.84 | F59: 164097.84 | G59: 164097.84 | H59: 164097.84 | I59: 164097.84 | J59: 164097.84 | K59: 164097.84 | L59: 164097.84 | M59: 164097.84 | N59: 164097.84 | O59: =SUM(C59:N59) -> 1969174.1
A60: 4 3 02 00 | B60: MATERIALES DE ALMACEN | C60: =SUM(C61:C62) -> 175308.48 | D60: =SUM(D61:D62) -> 175308.48 | E60: =SUM(E61:E62) -> 175308.48 | F60: =SUM(F61:F62) -> 175308.48 | G60: =SUM(G61:G62) -> 175308.48 | H60: =SUM(H61:H62) -> 175308.48 | I60: =SUM(I61:I62) -> 175308.48 | J60: =SUM(J61:J62) -> 175308.48 | ... N60: =SUM(N61:N62) -> 175308.48 | O60: =SUM(C60:N60) -> 2103701.8
A61: 4 3 02 01 | B61: MATERIALES DE ALMACEN | C61: 175308.48 | D61: 175308.48 | E61: 175308.48 | F61: 175308.48 | G61: 175308.48 | H61: 175308.48 | I61: 175308.48 | J61: 175308.48 | K61: 175308.48 | L61: 175308.48 | M61: 175308.48 | N61: 175308.48 | O61: =SUM(C61:N61) -> 2103701.8
A62: 4 3 02 02 | B62: GASTOS DE SERVICIOS | O62: =SUM(C62:N62) -> 0
A63: 4 3 03 00 | B63: GASTOS GENERALES | C63: =SUM(C64:C66) -> 2385093.9 | D63: =SUM(D64:D66) -> 2385093.9 | E63: =SUM(E64:E66) -> 2385093.9 | F63: =SUM(F64:F66) -> 2385093.9 | G63: =SUM(G64:G66) -> 2385093.9 | H63: =SUM(H64:H66) -> 2385093.9 | I63: =SUM(I64:I66) -> 2385093.9 | J63: =SUM(J64:J66) -> 2385093.9 | ... N63: =SUM(N64:N66) -> 2385093.9 | O63: =SUM(C63:N63) -> 28621126
A64: 4 3 03 01 | B64: GASTOS GENERALES | C64: 2385093.9 | D64: 2385093.9 | E64: 2385093.9 | F64: 2385093.9 | G64: 2385093.9 | H64: 2385093.9 | I64: 2385093.9 | J64: 2385093.9 | K64: 2385093.9 | L64: 2385093.9 | M64: 2385093.9 | N64: 2385093.9 | O64: =SUM(C64:N64) -> 28621126
A65: 4 3 03 02 | B65: OTROS GASTOS | O65: =SUM(C65:N65) -> 0
A66: 4 3 03 03 | B66: AYUDA COMUNITARIA | C66: 0 | D66: 0 | E66: 0 | F66: 0 | G66: 0 | H66: 0 | I66: 0 | J66: 0 | K66: 0 | L66: 0 | M66: 0 | N66: 0 | O66: =SUM(C66:N66) -> 0
A67: 4 3 04 00 | B67: DEPRECIACION DEL ACTIVO FIJO | C67: =SUM(C68) -> 0 | D67: =SUM(D68) -> 0 | E67: =SUM(E68) -> 0 | F67: =SUM(F68) -> 0 | G67: =SUM(G68) -> 0 | H67: =SUM(H68) -> 0 | I67: =SUM(I68) -> 0 | J67: =SUM(J68) -> 0 | ... N67: =SUM(N68) -> 0 | O67: =SUM(C67:N67) -> 0
A68: 4 3 04 01 | B68: DEPRECIACION DEL ACTIVO FIJO | C68: 0 | D68: 0 | E68: 0 | F68: 0 | G68: 0 | H68: 0 | I68: 0 | J68: 0 | K68: 0 | L68: 0 | M68: 0 | N68: 0 | O68: =SUM(C68:N68) -> 0
A70: 4 4 00 00 | B70: GASTOS FINANCIEROS | C70: =C71 -> 1091527.2 | D70: =D71 -> 1091527.2 | E70: =E71 -> 1091527.2 | F70: =F71 -> 1091527.2 | G70: =G71 -> 1091527.2 | H70: =H71 -> 1091527.2 | I70: =I71 -> 1091527.2 | J70: =J71 -> 1091527.2 | ... N70: =N71 -> 1091527.2 | O70: =SUM(C70:N70) -> 13098326
A71: 4 4 01 00 | B71: GASTOS FINANCIEROS | C71: =SUM(C72) -> 1091527.2 | D71: =SUM(D72) -> 1091527.2 | E71: =SUM(E72) -> 1091527.2 | F71: =SUM(F72) -> 1091527.2 | G71: =SUM(G72) -> 1091527.2 | H71: =SUM(H72) -> 1091527.2 | I71: =SUM(I72) -> 1091527.2 | J71: =SUM(J72) -> 1091527.2 | ... N71: =SUM(N72) -> 1091527.2 | O71: =SUM(C71:N71) -> 13098326
A72: 4 4 01 01 | B72: INTERESES | C72: 1091527.2 | D72: 1091527.2 | E72: 1091527.2 | F72: 1091527.2 | G72: 1091527.2 | H72: 1091527.2 | I72: 1091527.2 | J72: 1091527.2 | K72: 1091527.2 | L72: 1091527.2 | M72: 1091527.2 | N72: 1091527.2 | O72: =SUM(C72:N72) -> 13098326
O73: =SUM(C73:N73) -> 0
A74: 4 5 00 00 | B74: GASTOS TRIBUTARIOS | C74: =C75 -> 1417709.6 | D74: =D75 -> 1235781.2 | E74: =E75 -> 1283112.4 | F74: =F75 -> 1319622.9 | G74: =G75 -> 1512720.7 | H74: =H75 -> 1371226.4 | I74: =I75 -> 1458230.5 | J74: =J75 -> 1649129.5 | ... N74: =N75 -> 1392186.8 | O74: =SUM(C74:N74) -> 17215703
A75: 4 5 01 00 | B75: GASTOS TRIBUTARIOS | C75: =SUM(C76:C77) -> 1417709.6 | D75: =SUM(D76:D77) -> 1235781.2 | E75: =SUM(E76:E77) -> 1283112.4 | F75: =SUM(F76:F77) -> 1319622.9 | G75: =SUM(G76:G77) -> 1512720.7 | H75: =SUM(H76:H77) -> 1371226.4 | I75: =SUM(I76:I77) -> 1458230.5 | J75: =SUM(J76:J77) -> 1649129.5 | ... N75: =SUM(N76:N77) -> 1392186.8 | O75: =SUM(C75:N75) -> 17215703
A76: 4 5 01 01 | B76: GASTOS TRIBUTARIOS | C76: 1369292.1 | D76: 1187363.7 | E76: 1234695 | F76: 1271205.4 | G76: 1464303.3 | H76: 1322808.9 | I76: 1409813.1 | J76: 1600712.1 | K76: 1467639.8 | L76: 1644523.3 | M76: 1318567.1 | N76: 1343769.4 | O76: =SUM(C76:N76) -> 16634693
A77: 4 5 01 05 | B77: PATENTES MINERAS | C77: 48417.441 | D77: 48417.441 | E77: 48417.441 | F77: 48417.441 | G77: 48417.441 | H77: 48417.441 | I77: 48417.441 | J77: 48417.441 | K77: 48417.441 | L77: 48417.441 | M77: 48417.441 | N77: 48417.441 | O77: =SUM(C77:N77) -> 581009.29
A78: 4 6 00 00 | B78: PERDIDAS Y GANANCIAS | C78: =C79 -> 0 | D78: =D79 -> 0 | E78: =E79 -> 0 | F78: =F79 -> 0 | G78: =G79 -> 0 | H78: =H79 -> 0 | I78: =I79 -> 0 | J78: =J79 -> 0 | ... N78: =N79 -> 0 | O78: =SUM(C78:N78) -> 0
A79: 4 6 01 00 | B79: PERDIDAS Y GANANCIAS | C79: =SUM(C80:C81) -> 0 | D79: =SUM(D80:D81) -> 0 | E79: =SUM(E80:E81) -> 0 | F79: =SUM(F80:F81) -> 0 | G79: =SUM(G80:G81) -> 0 | H79: =SUM(H80:H81) -> 0 | I79: =SUM(I80:I81) -> 0 | J79: =SUM(J80:J81) -> 0 | ... N79: =SUM(N80:N81) -> 0 | O79: =SUM(C79:N79) -> 0
A80: 4 6 01 01 | B80: PERDIDAS Y GANANCIAS | C80: 0 | D80: 0 | E80: 0 | F80: 0 | G80: 0 | H80: 0 | I80: 0 | J80: 0 | K80: 0 | L80: 0 | M80: 0 | N80: 0 | O80: =SUM(C80:N80) -> 0
B81: INGRESOS POR VTA. BANCO COMUNIDAD | C81: 0 | D81: 0 | E81: 0 | F81: 0 | G81: 0 | H81: 0 | I81: 0 | J81: 0 | K81: 0 | L81: 0 | M81: 0 | N81: 0 | O81: =SUM(C81:N81) -> 0
A82: 4 700 00 | B82: CORRECCION MONETARIA | C82: =C83 -> 0 | D82: =D83 -> 0 | E82: =E83 -> 0 | F82: =F83 -> 0 | G82: =G83 -> 0 | H82: =H83 -> 0 | I82: =I83 -> 0 | J82: =J83 -> 0 | ... N82: =N83 -> 0 | O82: =SUM(C82:N82) -> 0
A83: 4 7 01 00 | B83: AJUSTES MONETARIOS P/INFLACION | C83: =SUM(C84) -> 0 | D83: =SUM(D84) -> 0 | E83: =SUM(E84) -> 0 | F83: =SUM(F84) -> 0 | G83: =SUM(G84) -> 0 | H83: =SUM(H84) -> 0 | I83: =SUM(I84) -> 0 | J83: =SUM(J84) -> 0 | ... N83: =SUM(N84) -> 0 | O83: =SUM(C83:N83) -> 0
A84: 4 7 01 01 | B84: AJUSTE POR INF. Y TEN. DE BIENES | C84: 0 | D84: 0 | E84: 0 | F84: 0 | G84: 0 | H84: 0 | I84: 0 | J84: 0 | K84: 0 | L84: 0 | M84: 0 | N84: 0 | O84: =SUM(C84:N84) -> 0
O85: =SUM(C85:N85) -> 0
A86: T O T A L U T I L I D A D (+) / P E R D I D A (-) | C86: =C6-C26 -> 1527260 | D86: =D6-D26 -> 273344.04 | E86: =E6-E26 -> 591777.13 | F86: =F6-F26 -> 879704.63 | G86: =G6-G26 -> 822329.89 | H86: =H6-H26 -> 693826.25 | I86: =I6-I26 -> 845880.52 | J86: =J6-J26 -> 1654039.1 | ... O86: =O6-O26 -> 11121310
B88: Depreciacion | C88: =+'[1]4a. Cemento'!B118+'[1]4b.Yeso'!B114+'[1]4c.Morteros'!B115+'[1]4d.Adm'!B101+'[1]4e.Comer.'!B111 -> 2020006 | D88: =+'[1]4a. Cemento'!C118+'[1]4b.Yeso'!C114+'[1]4c.Morteros'!C115+'[1]4d.Adm'!C101+'[1]4e.Comer.'!C111 -> 2020006 | E88: =+'[1]4a. Cemento'!D118+'[1]4b.Yeso'!D114+'[1]4c.Morteros'!D115+'[1]4d.Adm'!D101+'[1]4e.Comer.'!D111 -> 2020006 | F88: =+'[1]4a. Cemento'!E118+'[1]4b.Yeso'!E114+'[1]4c.Morteros'!E115+'[1]4d.Adm'!E101+'[1]4e.Comer.'!E111 -> 2020006 | G88: =+'[1]4a. Cemento'!F118+'[1]4b.Yeso'!F114+'[1]4c.Morteros'!F115+'[1]4d.Adm'!F101+'[1]4e.Comer.'!F111 -> 2020006 | H88: =+'[1]4a. Cemento'!G118+'[1]4b.Yeso'!G114+'[1]4c.Morteros'!G115+'[1]4d.Adm'!G101+'[1]4e.Comer.'!G111 -> 2020006 | I88: =+'[1]4a. Cemento'!H118+'[1]4b.Yeso'!H114+'[1]4c.Morteros'!H115+'[1]4d.Adm'!H101+'[1]4e.Comer.'!H111 -> 2020006 | J88: =+'[1]4a. Cemento'!I118+'[1]4b.Yeso'!I114+'[1]4c.Morteros'!I115+'[1]4d.Adm'!I101+'[1]4e.Comer.'!I111 -> 2020006 | ... N88: =+'[1]4a. Cemento'!M118+'[1]4b.Yeso'!M114+'[1]4c.Morteros'!M115+'[1]4d.Adm'!M101+'[1]4e.Comer.'!M111 -> 2020006

Sheet BCO
A1: BANCO PyME DE LA COMUNIDAD S.A.
A2: COMPOSICIÓN ACCIONARIA AL 31 de agosto de 2025
A4: Nº | B4: NOMBRE O RAZON SOCIAL DEL ACCIONISTA | C4: Composición Accionaria al 31.08.2025
C5: Paquete accionario - Bs | D5: Cantidad de acciones (*) | E5: Participación accionaria | F5: Paquete accionario - USD.
A6: 1 | B6: Cooperativa Multiactiva COBOCE R.L | C6: 33002900 | D6: 3300290 | E6: 0.54158866 | F6: 4810918.4
A7: 2 | B7: OIKOCREDIT, Ecumenical Development Cooperative Society U.A. | C7: 10250610 | D7: 1025061 | E7: 0.16821606 | F7: 1494258
A8: 3 | B8: Otros accionistas | C8: 17683690 | D8: 1768369 | E8: 0.29019532 | F8: 2577797.4
A9: TOTALES | C9: 60937200 | D9: 6093720 | E9: 1 | F9: 8882973.8
A10: (*) | B10: A valor nominal de Bs10 por acción
B12: DETERMINACIÓN DEL VALOR PATRIMONIAL PROPORCIONAL (VPP)
B14: DETALLE | C14: Valores
B15: Patrimonio (P) al 31.08.2025 en Bs | C15: 48226221 | H15: VPP: Valor Patrimonial Proporcional
B16: Capital Social Preferente (CSP) en Bs | C16: 0 | H16: P: Patrimonio
B17: Aportes Pendientes de Capitalización (APC) en Bs | C17: 53625.59 | D17: VPP = | E17: P - CSP - APC - DAAP | H17: CSP: Capital Social Preferente
B18: Dividendos Acumulativos de las Acciones Preferentes (DAAP) en Bs | C18: 0 | E18: NAOC | H18: APC: Aportes Pendientes de Capitalización
B19: Número de Acciones Ordinarias en Circulación (NAOC) | C19: 6093720 | H19: DAAP: Dividendos Acumulativos de las Acciones Preferentes
B20: Valor patrimonial proporcional - VPP en Bs | C20: 7.9052853 | H20: NAOC: Número de Acciones Ordinarias en Circulación
B21: Valor nominal de las acciones - Bs | C21: 10
A23: COMPOSICIÓN ACCIONARIA AL VPP AL 31 de agosto de 2025
A25: Nº | B25: NOMBRE O RAZON SOCIAL DEL ACCIONISTA | C25: Composición Accionaria al 31.08.2025 | F25: Composición accionaria al VPP al 31.08.2025
C26: Paquete accionario - Bs | D26: Cantidad de acciones (*) | E26: Participación accionaria | F26: Patirmonio contable - Bs | G26: VPP - Bs | H26: Paquete accionario al VPP - Bs | I26: Paquete accionario al VPP - USD.
A27: 1 | B27: Cooperativa Multiactiva COBOCE R.L | C27: 33002900 | D27: 3300290 | E27: 0.54158872 | F27: 48226221 | G27: 7.9052853 | H27: 26089734 | I27: 3803168.2
A28: 2 | B28: OIKOCREDIT, Ecumenical Development Cooperative Society U.A. | C28: 10250610 | D28: 1025061 | E28: 0.16821597 | F28: 48226221 | G28: 7.9052853 | H28: 8103399.7 | I28: 1181253.6
A29: 3 | B29: Otros accionistas | C29: 17683690 | D29: 1768369 | E29: 0.29019532 | F29: 48226221 | G29: 7.9052853 | H29: 13979461 | I29: 2037822.4
A30: TOTALES | C30: 60937200 | D30: 6093720 | E30: 1 | H30: 48172595 | I30: 7022244.2
A31: (*) | B31: A valor nominal de Bs10 por acción
B33: PAQUETE ACCIONARIO DE COBOCE AL VPP AL 31.08.2025
B35: DETALLE | C35: Bs | D35: USD. | G35: OTRAS CUENTAS PATRIMONIALES
B36: Aporte inicial en efectivo | C36: 11725000 | D36: 2263513.5 | H36: APORTES NO CAPITALIZADOS | I36: 53625.59
B37: Aportes adicionales en efectivo | C37: 43571970 | D37: 4088241.6 | H37: RESERVAS | I37: 4507876.4
B38: Reducción Voluntaria de Capital Pagado | C38: -43409586 | D38: -6327927.9 | H38: RESULTADOS ACUMULADOS | I38: -17272481
B39: Total aportes realizados en efectivo | C39: 11887384 | D39: 23827.173 | H39: TOTAL OTRAS CUENTAS PATRIMONIALES | I39: -12710979
B40: Capitalización de utilidades | C40: 21115510 | D40: 3078062.7 | H40: CAPITAL PAGADO | I40: 60937200
B41: Paquete accionario (Capital Social) | C41: 33002894 | D41: 4810917.6 | H41: TOTAL PATRIMONIO | I41: 48226221
B42: Distribución de otras cuentas patrimoniales | C42: -6913165.9 | D42: -1007750.1
B43: Paquete accionario al VVP | C43: 26089728 | D43: 3803167.4
B44: Número de acciones de COBOCE | C44: 3300290
B45: Valor Patrimonial Proporcional de las acciones de COBOCE | C45: 7.9052836

Sheet Ventas
A1: Gestion | B1: Ventas | C1: tasa de crecimiento en ventas
A2: =+'EEFF proyectados'!N1 -> 2020 | B2: =+'EEFF proyectados'!N5 -> 3.7943563e+08
A3: =+A2+1 -> 2021 | B3: =+'EEFF proyectados'!AA5 -> 3.5215099e+08 | C3: =+B3/B2-1 -> -0.071908492
A4: =+A3+1 -> 2022 | B4: =+'EEFF proyectados'!AN5 -> 4.1815596e+08 | C4: =+B4/B3-1 -> 0.18743373
A5: =+A4+1 -> 2023 | B5: =+'EEFF proyectados'!BA5 -> 4.3776462e+08 | C5: =+B5/B4-1 -> 0.046893168
A6: =+A5+1 -> 2024 | B6: =+'EEFF proyectados'!BN5 -> 4.3212218e+08 | C6: =+B6/B5-1 -> -0.012889213 | H6: Monto | I6: 200000
A7: =+A6+1 -> 2025 | B7: =+B6*(1+C7) -> 6.6581192e+08 | C7: =+('Control y Supuestos'!F56/MONTH('Control y Supuestos'!F52)*12*0.7)/'Control y Supuestos'!E56 -> 0.54079554 | H7: Precio de compra | I7: 49
A8: =+A7+1 -> 2026 | B8: =+B7*(1+C8) -> 6.6581192e+08 | C8: 0 | H8: Cantidad | I8: =+ROUND(I6/I7,0) -> 4082
A9: =+A8+1 -> 2027 | B9: =+B8*(1+C9) -> 6.6581192e+08 | C9: 0 | H9: Precio de venta | I9: 53
A10: =+A9+1 -> 2028 | B10: =+B9*(1+C10) -> 6.6581192e+08 | C10: 0 | H10: margen unitario | I10: =+I9-I7 -> 4
A11: =+A10+1 -> 2029 | B11: =+B10*(1+C11) -> 6.6581192e+08 | C11: 0 | H11: margen de utilidad | I11: =+I10*I8 -> 16328
A12: =+A11+1 -> 2030 | B12: =+B11*(1+C12) -> 6.6581192e+08 | C12: 0

Sheet Obligaciones financieras
N1: Nro de la operación | Q1: 3167401 | S1: Plan Banco | AE1: Nro de la operación | AG1: 2767412 | AT1: Nro de la operación | AV1: 2764418 | BI1: Nro de la operación | BK1: 1271559 | BX1: Nro de la operación | BZ1: 1358960 | CN1: Nro de la operación | CP1: 1295150 | CW1: Nro de la operación | CY1: 101194346 | DF1: Nro de la operación | DH1: 315101121500077 | DO1: Nro de la operación | DQ1: 315101121500078f | EG1: Nro de la operación | EI1: 315101121500021 | EQ1: Nro de la operación | ES1: 2010014418 | EZ1: Nro de la operación | FB1: 2010014118 | FI1: Nro de la operación | FK1: 2010013918 | FR1: Nro de la operación | FT1: 2010014218 | GA1: Nro de la operación | GC1: 2010014318 | GJ1: Nro de la operación | GL1: 2010014018
N2: Entidad | Q2: Fideicomiso - Banco Unión | S2: 1. | T2: Visitar el lunes al banco, habilitando al doctor Murillo como representante | AE2: Entidad | AG2: Banco Unión | AT2: Entidad | AV2: Banco Unión | BI2: Entidad | BK2: Banco Bisa | BX2: Entidad | BZ2: Banco Bisa | CN2: Entidad | CP2: Banco Bisa | CW2: Entidad | CY2: Banco Ganadero | DF2: Entidad | DH2: Banco de Desarrollo Productivo | DO2: Entidad | DQ2: Banco de Desarrollo Productivo | EG2: Entidad | EI2: Banco de Desarrollo Productivo | EQ2: Entidad | ES2: BNB leasing | EZ2: Entidad | FB2: BNB leasing | FI2: Entidad | FK2: BNB leasing | FR2: Entidad | FT2: BNB leasing | GA2: Entidad | GC2: BNB leasing | GJ2: Entidad | GL2: BNB leasing
N3: Cod. Entidad | Q3: FID - BUN | S3: 2 | T3: tenemos un periodo de 30 dias para comenzar la demanda (coboce no presenta demanda Banco no presenta ejecucion) | AE3: Cod. Entidad | AG3: BUN | AT3: Cod. Entidad | AV3: BUN | BI3: Cod. Entidad | BK3: BIS | BX3: Cod. Entidad | BZ3: BIS | CN3: Cod. Entidad | CP3: BIS | CW3: Cod. Entidad | CY3: GAN | DF3: Cod. Entidad | DH3: BDP | DO3: Cod. Entidad | DQ3: BDP | EG3: Cod. Entidad | EI3: BDP | EQ3: Cod. Entidad | ES3: BNL | EZ3: Cod. Entidad | FB3: BNL | FI3: Cod. Entidad | FK3: BNL | FR3: Cod. Entidad | FT3: BNL | GA3: Cod. Entidad | GC3: BNL | GJ3: Cod. Entidad | GL3: BNL
N4: Moneda | Q4: Bolivanos | S4: 3 | T4: Dacion en pago (BANCO y PILAT) | AE4: Moneda | AG4: Bolivanos | AT4: Moneda | AV4: Bolivanos | BI4: Moneda | BK4: Bolivanos | BX4: Moneda | BZ4: Bolivanos | CN4: Moneda | CP4: Bolivanos | CW4: Moneda | CY4: Bolivanos | DF4: Moneda | DH4: Bolivanos | DO4: Moneda | DQ4: Bolivanos | EG4: Moneda | EI4: Bolivanos | EQ4: Moneda | ES4: Bolivanos | EZ4: Moneda | FB4: Bolivanos | FI4: Moneda | FK4: Bolivanos | FR4: Moneda | FT4: Bolivanos | GA4: Moneda | GC4: Bolivanos | GJ4: Moneda | GL4: Bolivanos
N5: Tasa | Q5: 0.06 | S5: 4 | T5: Alternativamente hacemos seguimiento a la demanda del bnaco antes que dicte la sentencia preliminar del banco para parar | AE5: Tasa | AG5: 0.055 | AT5: Tasa | AV5: 0.06 | BI5: Tasa | BK5: 0.06 | BX5: Tasa | BZ5: 0.06 | CN5: Tasa | CP5: 0.06 | CW5: Tasa | CY5: 0.06 | DF5: Tasa | DH5: 0.058 | DO5: Tasa | DQ5: 0.0582 | EG5: Tasa | EI5: 0.0599 | EQ5: Tasa | ES5: 0.06 | EZ5: Tasa | FB5: 0.06 | FI5: Tasa | FK5: 0.06 | FR5: Tasa | FT5: 0.06 | GA5: Tasa | GC5: 0.06 | GJ5: Tasa | GL5: 0.06
N6: Periodicidad | Q6: Trimestral | S6: 5 | AE6: Periodicidad | AG6: Trimestral | AT6: Periodicidad | AV6: Trimestral | BI6: Periodicidad | BK6: Trimestral | BX6: Periodicidad | BZ6: Trimestral | CN6: Periodicidad | CP6: Trimestral | CW6: Periodicidad | CY6: Mensual | DF6: Periodicidad | DH6: Trimestral | DO6: Periodicidad | DQ6: Trimestral | EG6: Periodicidad | EI6: Trimestral | EQ6: Periodicidad | ES6: Trimestral | EZ6: Periodicidad | FB6: Trimestral | FI6: Periodicidad | FK6: Trimestral | FR6: Periodicidad | FT6: Trimestral | GA6: Periodicidad | GC6: Trimestral | GJ6: Periodicidad | GL6: Trimestral
N7: inicio
N8: vencimiento | Q8: =+MAX(O25:O822) -> 48248 | AE8: vencimiento | AG8: =+MAX(AE25:AE822) -> 48058 | AT8: vencimiento | AV8: =+MAX(AT25:AT822) -> 48997 | BI8: vencimiento | BK8: =+MAX(BI25:BI822) -> 47107 | BX8: vencimiento | BZ8: =+MAX(BX25:BX822) -> 47398 | CN8: vencimiento | CP8: =+MAX(CN25:CN822) -> 47375 | CW8: vencimiento | CY8: =+MAX(CW25:CW822) -> 46609 | DF8: vencimiento | DH8: =+MAX(DF25:DF822) -> 49111 | DO8: vencimiento | DQ8: =+MAX(DO25:DO822) -> 48765 | EG8: vencimiento | EI8: =+MAX(EG25:EG822) -> 49111 | EQ8: vencimiento | ES8: =+MAX(EQ25:EQ822) -> 46552 | EZ8: vencimiento | FB8: =+MAX(EZ25:EZ822) -> 46552 | FI8: vencimiento | FK8: =+MAX(FI25:FI822) -> 46552 | FR8: vencimiento | FT8: =+MAX(FR25:FR822) -> 46552 | GA8: vencimiento | GC8: =+MAX(GA25:GA822) -> 46714 | GJ8: vencimiento | GL8: =+MAX(GJ25:GJ822) -> 46714
N9: plazo | Q9: =+Q8-[2]Caracteristicas!$I$19 -> 2348 | AG9: =+AG8-[2]Caracteristicas!$I$19 -> 2158 | AV9: =+AV8-[2]Caracteristicas!$I$19 -> 3097 | BK9: =+BK8-[2]Caracteristicas!$I$19 -> 1207 | BZ9: =+BZ8-[2]Caracteristicas!$I$19 -> 1498 | CP9: =+CP8-[2]Caracteristicas!$I$19 -> 1475 | CY9: =+CY8-[2]Caracteristicas!$I$19 -> 709 | DH9: =+DH8-[2]Caracteristicas!$I$19 -> 3211 | DQ9: =+DQ8-[2]Caracteristicas!$I$19 -> 2865 | EI9: =+EI8-[2]Caracteristicas!$I$19 -> 3211 | ES9: =+ES8-[2]Caracteristicas!$I$19 -> 652 | FB9: =+FB8-[2]Caracteristicas!$I$19 -> 652 | FK9: =+FK8-[2]Caracteristicas!$I$19 -> 652 | FT9: =+FT8-[2]Caracteristicas!$I$19 -> 652 | GC9: =+GC8-[2]Caracteristicas!$I$19 -> 814 | GL9: =+GL8-[2]Caracteristicas!$I$19 -> 814
N10: Saldo a capital inicial
N11: Saldo Adeudado | Q11: =+Q13/Q12 -> 2.3034329e+08 | AG11: =+AG13/AG12 -> 1241907.9 | AV11: =+AV13/AV12 -> 51796168 | BK11: =+BK13/BK12 -> 53476614 | BZ11: =+BZ13/BZ12 -> 4838608.1 | CP11: =+CP13/CP12 -> 1669085.9 | CY11: =+CY13/CY12 -> 29810000 | DH11: =+DH13/DH12 -> 9174681.5 | DQ11: =+DQ13/DQ12 -> 8467855 | EI11: =+EI13/EI12 -> 2794681.5 | ES11: =+ES13/ES12 -> 309433.84 | FB11: =+FB13/FB12 -> 309433.84 | FK11: =+FK13/FK12 -> 309433.84 | FT11: =+FT13/FT12 -> 309433.84 | GC11: =+GC13/GC12 -> 388403.55 | GL11: =+GL13/GL12 -> 388403.55
N12: % correspondiente a CEMENTO | Q12: 0.57390185 | AE12: % correspondiente a CEMENTO | AG12: 1 | AT12: % correspondiente a CEMENTO | AV12: =+AV13/AV15 -> 0.3088359 | BI12: % correspondiente a CEMENTO | BK12: 1 | BX12: % correspondiente a CEMENTO | BZ12: =+CA27/254312.71 -> 0.22702943 | CN12: % correspondiente a CEMENTO | CP12: 1 | CW12: % correspondiente a CEMENTO | CY12: =++CY13/CY15 -> 0.86082018 | DF12: % correspondiente a CEMENTO | DH12: 0.99370812 | DO12: % correspondiente a CEMENTO | DQ12: =+DQ13/DQ15 -> 0.13104947 | DR12: Antes | DT12: 0.38897016 | EG12: % correspondiente a CEMENTO | EI12: 1 | EQ12: % correspondiente a CEMENTO | ES12: 1 | EZ12: % correspondiente a CEMENTO | FB12: 1 | FI12: % correspondiente a CEMENTO | FK12: 1 | FR12: % correspondiente a CEMENTO | FT12: 1 | GA12: % correspondiente a CEMENTO | GC12: 1 | GE12: 100 | GJ12: % correspondiente a CEMENTO | GL12: 1
N13: Saldo Adeudado CEMENTO | Q13: =+Q29 -> 1.3219444e+08 | AE13: Saldo Adeudado CEMENTO | AG13: =+AG27 -> 1241907.9 | AT13: Saldo Adeudado CEMENTO | AV13: =+AV28 -> 15996516 | BI13: Saldo Adeudado CEMENTO | BK13: =+BK26 -> 53476614 | BX13: Saldo Adeudado CEMENTO | BZ13: =+BZ27+CB24 -> 1098506.4 | CN13: Saldo Adeudado CEMENTO | CP13: =+CP26 -> 1669085.9 | CW13: Saldo Adeudado CEMENTO | CY13: =+CY26 -> 25661049 | DF13: Saldo Adeudado CEMENTO | DH13: =+DH26 -> 9116955.5 | DO13: Saldo Adeudado CEMENTO | DQ13: =+DQ25 -> 1109707.9 | DR13: Transferencia a CERAMIL | DT13: =+DT12*DQ11 -> 3293742.9 | DU13: =+DT13-DQ13 -> 2184035 | EG13: Saldo Adeudado CEMENTO | EI13: =+EI27 -> 2794681.5 | EQ13: Saldo Adeudado CEMENTO | ES13: =+ES26 -> 309433.84 | EZ13: Saldo Adeudado CEMENTO | FB13: =+FB26 -> 309433.84 | FI13: Saldo Adeudado CEMENTO | FK13: =+FK26 -> 309433.84 | FR13: Saldo Adeudado CEMENTO | FT13: =+FT26 -> 309433.84 | GA13: Saldo Adeudado CEMENTO | GC13: =+GC26 -> 388403.55 | GE13: =+GE12/13.8 -> 7.2463768 | GJ13: Saldo Adeudado CEMENTO | GL13: =+GL26 -> 388403.55
N14: Monto desembolsado
N15: Total de Saldo Adeudado | Q15: 2.3061769e+08 | AE15: Total de Saldo Adeudado | AG15: =+AG12*AG13 -> 1241907.9 | AT15: Total de Saldo Adeudado | AV15: =+SUM([3]Consolidado1!$C$241:$C$245) -> 51796168 | AY15: =187920.41+6784.89+626.79 -> 195332.09 | BI15: Total de Saldo Adeudado | BK15: =+BK25 -> 53476614 | BX15: Total de Saldo Adeudado | BZ15: =+BZ13/BZ12 -> 4838608.1 | CN15: Total de Saldo Adeudado | CP15: 1460450.1 | CW15: Total de Saldo Adeudado | CY15: =+SUM([3]Consolidado1!$C$323:$C$328) -> 29810000 | DF15: Total de Saldo Adeudado | DH15: =+DH13/DH12 -> 9174681.5 | DO15: Total de Saldo Adeudado | DQ15: =+SUM([3]Consolidado1!$C$315:$C$319) -> 8467855 | EG15: Total de Saldo Adeudado | EQ15: Total de Saldo Adeudado | ES15: 346343.01 | EZ15: Total de Saldo Adeudado | FB15: 346343.01 | FI15: Total de Saldo Adeudado | FK15: 346343.01 | FR15: Total de Saldo Adeudado | FT15: 346343.01 | GA15: Total de Saldo Adeudado | GC15: 426409.54 | GJ15: Total de Saldo Adeudado | GL15: 426409.54
N16: Total de Intereses Diferidos | Q16: 16433143 | AE16: Total de Intereses Diferidos | AT16: Total de Intereses Diferidos | BI16: Total de Intereses Diferidos | BX16: Total de Intereses Diferidos | CN16: Total de Intereses Diferidos | CW16: Total de Intereses Diferidos | DF16: Total de Intereses Diferidos | DO16: Total de Intereses Diferidos | EG16: Total de Intereses Diferidos | EQ16: Total de Intereses Diferidos | EZ16: Total de Intereses Diferidos | FI16: Total de Intereses Diferidos | FR16: Total de Intereses Diferidos | GA16: Total de Intereses Diferidos | GJ16: Total de Intereses Diferidos
N17: Intereses DIferidos CEMENTO | Q17: =+Q16*Q12 -> 9431010.9 | AE17: Intereses DIferidos CEMENTO | AT17: Intereses DIferidos CEMENTO | BI17: Intereses DIferidos CEMENTO | BX17: Intereses DIferidos CEMENTO | CN17: Intereses DIferidos CEMENTO | CW17: Intereses DIferidos CEMENTO | DF17: Intereses DIferidos CEMENTO | DO17: Intereses DIferidos CEMENTO | EG17: Intereses DIferidos CEMENTO | EQ17: Intereses DIferidos CEMENTO | EZ17: Intereses DIferidos CEMENTO | FI17: Intereses DIferidos CEMENTO | FR17: Intereses DIferidos CEMENTO | GA17: Intereses DIferidos CEMENTO | GJ17: Intereses DIferidos CEMENTO
N18: # Cuotas Intereses Diferidos | Q18: 20 | AE18: # Cuotas Intereses Diferidos | AT18: # Cuotas Intereses Diferidos | BI18: # Cuotas Intereses Diferidos | BX18: # Cuotas Intereses Diferidos | CN18: # Cuotas Intereses Diferidos | CW18: # Cuotas Intereses Diferidos | DF18: # Cuotas Intereses Diferidos | DO18: # Cuotas Intereses Diferidos | EG18: # Cuotas Intereses Diferidos | EQ18: # Cuotas Intereses Diferidos | EZ18: # Cuotas Intereses Diferidos | FI18: # Cuotas Intereses Diferidos | FR18: # Cuotas Intereses Diferidos | GA18: # Cuotas Intereses Diferidos | GJ18: # Cuotas Intereses Diferidos
N19: Amortización Trimenstral 1er Año | Q19: 68600 | AE19: Amortización Trimenstral | AG19: 51840.79 | AT19: Amortización Trimenstral | AV19: 51840.79 | BI19: Amortización Trimenstral | BK19: 51840.79 | BX19: Amortización Trimenstral | BZ19: =+CA26 -> 57736.47 | CN19: Amortización Trimenstral | CW19: Amortización Trimenstral | DF19: Amortización Trimenstral | DO19: Amortización Trimenstral | EG19: Amortización Trimenstral | EQ19: Amortización Trimenstral | EZ19: Amortización Trimenstral | FI19: Amortización Trimenstral | FR19: Amortización Trimenstral | GA19: Amortización Trimenstral | GJ19: Amortización Trimenstral
N20: Amort. Trim 1er año CEMENTO | Q20: =+Q19*Q12 -> 39369.667
N21: Amortización 5to trimestre | Q21: 30369494
A23: N | B23: semana | C23: Dia | D23: Desembolsos | E23: Saldo adeudado | F23: Capital | G23: Intereses | H23: Total Cuota | I23: Por pagar | J23: Entidad | M23: N | N23: Fin mes | O23: Fecha | P23: Desembolsos | Q23: Saldo adeudado | R23: Amortización | S23: Intereses corrientes | T23: Intereses diferidos | U23: Total Cuota | V23: Número de cuota | W23: fecha de pago | X23: dias de mora | Y23: pago a capital | Z23: intereses corrientes | AA23: cuota pagada | AC23: N | AD23: Fin mes | AE23: Fecha | AF23: Desembolsos | AG23: Saldo adeudado | AH23: Amortización | AI23: Intereses corrientes | AJ23: Total Cuota | AK23: Número de cuota | AL23: fecha de pago | AM23: pago a capital | AN23: intereses corrientes | AO23: cuota pagada | AR23: N | AS23: Fin mes | AT23: Fecha | AU23: Desembolsos | AV23: Saldo adeudado | AW23: Amortización | AX23: Intereses corrientes | AY23: Total Cuota | AZ23: Número de cuota | BA23: fecha de pago | BB23: dias de mora | BC23: pago a capital | BD23: intereses corrientes | BE23: cuota pagada | BG23: N | BH23: Fin mes | BI23: Fecha | BJ23: Desembolsos | BK23: Saldo adeudado | BL23: Amortización | BM23: Intereses corrientes | BN23: Interes prorroga y gracia | BO23: Total Cuota | BP23: Número de cuota | BQ23: fecha de pago | BR23: pago a capital | BS23: intereses corrientes | BT23: cuota pagada | BV23: N | BW23: Fin mes | BX23: Fecha | BY23: Desembolsos | BZ23: Saldo adeudado | CA23: Amortización | CB23: Amortización cap diferido | CC23: Intereses corrientes | CD23: Intereses prorroga gracia | CE23: Total Cuota | CF23: Número de cuota | CG23: fecha de pago | CH23: pago a capital | CI23: intereses corrientes | CJ23: cuota pagada | CL23: N | CM23: Fin mes | CN23: Fecha | CO23: Desembolsos | CP23: Saldo adeudado | CQ23: Amortización | CR23: Intereses corrientes | CS23: Total Cuota | CU23: N | CV23: Fin mes | CW23: Fecha | CX23: Desembolsos | CY23: Saldo adeudado | CZ23: Amortización | DA23: Intereses corrientes | DB23: Total Cuota | DD23: N | DE23: Fin mes | DF23: Fecha | DG23: Desembolsos | DH23: Saldo adeudado | DI23: Amortización | DJ23: Intereses corrientes | DK23: Total Cuota | DM23: N | DN23: Fin mes | DO23: Fecha | DP23: Desembolsos | DQ23: Saldo adeudado | DR23: Amortización | DS23: Intereses corrientes | DT23: Total Cuota | EE23: N | EF23: Fin mes | EG23: Fecha | EH23: Desembolsos | EI23: Saldo adeudado | EJ23: Amortización | EK23: Intereses corrientes | EL23: Intereses prorroga gracia | EM23: Total Cuota | EO23: N | EP23: Fin mes | EQ23: Fecha | ER23: Desembolsos | ES23: Saldo adeudado | ET23: Amortización | EU23: Intereses corrientes | EV23: Total Cuota | EX23: N | EY23: Fin mes | EZ23: Fecha | FA23: Desembolsos | FB23: Saldo adeudado | FC23: Amortización | FD23: Intereses corrientes | FE23: Total Cuota | FG23: N | FH23: Fin mes | FI23: Fecha | FJ23: Desembolsos | FK23: Saldo adeudado | FL23: Amortización | FM23: Intereses corrientes | FN23: Total Cuota | FP23: N | FQ23: Fin mes | FR23: Fecha | FS23: Desembolsos | FT23: Saldo adeudado | FU23: Amortización | FV23: Intereses corrientes | FW23: Total Cuota | FY23: N | FZ23: Fin mes | GA23: Fecha | GB23: Desembolsos | GC23: Saldo adeudado | GD23: Amortización | GE23: Intereses corrientes | GF23: Total Cuota | GH23: N | GI23: Fin mes | GJ23: Fecha | GK23: Desembolsos | GL23: Saldo adeudado | GM23: Amortización | GN23: Intereses corrientes | GO23: Total Cuota
F24: =+SUM(F26:F1150) -> 2.4637401e+08 | G24: =+SUM(G26:G1150) -> 48100039 | R24: =+SUM(R30:R1150) -> 1.3219444e+08 | AH24: =+SUM(AH28:AH1150) -> 1241907.9 | AW24: =+SUM(AW29:AW1150) -> 15996516 | BL24: =+SUM(BL29:BL1150) -> 53476614 | CA24: =+SUM(CA28:CA1150) -> 1039256.4 | CB24: =+SUM(CB28:CB1150) -> 59249.999 | CQ24: =+SUM(CQ28:CQ1150) -> 1669085.9 | CZ24: =+SUM(CZ27:CZ1150) -> 25661049 | DI24: =+SUM(DI27:DI1150) -> 9116955.5 | DR24: =+SUM(DR27:DR1150) -> 1109708 | EJ24: =+SUM(EJ27:EJ1150) -> 2794681.5 | ET24: =+SUM(ET27:ET1150) -> 309433.84 | FC24: =+SUM(FC27:FC1150) -> 309433.84 | FL24: =+SUM(FL27:FL1150) -> 309433.84 | FU24: =+SUM(FU27:FU1150) -> 309433.84 | GD24: =+SUM(GD27:GD1150) -> 388403.55 | GM24: =+SUM(GM27:GM1150) -> 388403.55
A25: 0 | B25: =+WEEKNUM(C25,2) -> 35 | C25: 45900 | E25: =+SUM(F26:F1150) -> 2.4637401e+08 | M25: 0 | N25: =+EOMONTH(O25,0) -> 45535 | O25: 45506 | P25: =+Q13 -> 1.3219444e+08 | Q25: 1.3235192e+08 | AC25: 0 | AD25: =+EOMONTH(AE25,0) -> 45716 | AE25: 45712 | AG25: 1345589.5 | AR25: 0 | AS25: =+EOMONTH(AT25,0) -> 45657 | AT25: 45656 | AV25: 15996516 | BG25: 0 | BH25: =+EOMONTH(BI25,0) -> 45747 | BI25: 45736 | BK25: 53476614 | BV25: 0 | BW25: =+EOMONTH(BX25,0) -> 45688 | BX25: 45677 | BZ25: 1154729.4 | CL25: 0 | CM25: =+EOMONTH(CN25,0) -> 45716 | CN25: 45700 | CP25: 1669085.9 | CU25: 0 | CV25: =+EOMONTH(CW25,0) -> 45869 | CW25: 45848 | CY25: 26010061 | DD25: 0 | DE25: =+EOMONTH(DF25,0) -> 45747 | DF25: 45721 | DH25: 9116955.5 | DM25: 0 | DN25: =+EOMONTH(DO25,0) -> 45747 | DO25: 45721 | DQ25: 1109707.9 | EE25: 0 | EF25: =+EOMONTH(EG25,0) -> 45657 | EG25: 45657 | EI25: 2794681.5 | EO25: 0 | EP25: =+EOMONTH(EQ25,0) -> 45747 | EQ25: =+EQ26-90 -> 45742 | ES25: 346343.01 | EX25: 0 | EY25: =+EOMONTH(EZ25,0) -> 45747 | EZ25: =+EZ26-90 -> 45742 | FB25: 346343.01 | FG25: 0 | FH25: =+EOMONTH(FI25,0) -> 45747 | FI25: =+FI26-90 -> 45742 | FK25: 346343.01 | FP25: 0 | FQ25: =+EOMONTH(FR25,0) -> 45747 | FR25: =+FR26-90 -> 45742 | FT25: 346343.01 | FY25: 0 | FZ25: =+EOMONTH(GA25,0) -> 45747 | GA25: =+GA26-90 -> 45724 | GC25: 426409.54 | GH25: 0 | GI25: =+EOMONTH(GJ25,0) -> 45747 | GJ25: 45724 | GL25: 426409.54
A26: 1 | B26: =+WEEKNUM(C26,2) -> 40 | C26: =+EOMONTH(C25,1) -> 45930 | E26: =+E25+D26-F26 -> 2.457966e+08 | F26: =+SUMIF(N:N,C26,R:R)+SUMIF(AD:AD,C26,AH:AH)+SUMIF(AS:AS,C26,AW:AW)+SUMIF(BH:BH,C26,BL:BL)+SUMIF(BW:BW,C26,CA:CA)+SUMIF(BW:BW,C26,CB:CB)+SUMIF(CM:CM,C26,CQ:CQ)+SUMIF(CV:CV,C26,CZ:CZ)+SUMIF(DE:DE,C26,DI:DI)+SUMIF(DN:DN,C26,DR:DR)+SUMIF(DW:DW,C26,EA:EA)+SUMIF(EF:EF,C26,EJ:EJ)+SUMIF(EP:EP,C26,ET:ET)+SUMIF(EY:EY,C26,FC:FC)+SUMIF(FH:FH,C26,FL:FL)+SUMIF(FQ:FQ,C26,FU:FU)+SUMIF(FZ:FZ,C26,GD:GD)+SUMIF(GI:GI,C26,GM:GM) -> 577412.41 | G26: =+SUMIF(N:N,C26,S:S)+SUMIF(N:N,C26,T:T)+SUMIF(AD:AD,C26,AI:AI)+SUMIF(AS:AS,C26,AX:AX)+SUMIF(BH:BH,C26,BM:BM)+SUMIF(BW:BW,C26,CD:CD)+SUMIF(BW:BW,C26,CC:CC)+SUMIF(CM:CM,C26,CR:CR)+SUMIF(CV:CV,C26,DA:DA)+SUMIF(DE:DE,C26,DJ:DJ)+SUMIF(DN:DN,C26,DS:DS)+SUMIF(DX:DX,C26,EB:EB)+SUMIF(EG:EG,C26,EK:EK)+SUMIF(EP:EP,C26,EU:EU)+SUMIF(EY:EY,C26,FD:FD)+SUMIF(FH:FH,C26,FM:FM)+SUMIF(FQ:FQ,C26,FV:FV)+SUMIF(FZ:FZ,C26,GE:GE)+SUMIF(GI:GI,C26,GN:GN) -> 1126666.7 | H26: =+SUM(F26:G26) -> 1704079.2 | M26: 1 | N26: =+EOMONTH(O26,0) -> 45626 | O26: 45611 | Q26: =+Q25-R26 -> 1.3231255e+08 | R26: =+$Q$20 -> 39369.667 | S26: =+Q25*Q$5*(O26-O25)/360 -> 2316158.6 | T26: =+$Q$17/$Q$18 -> 471550.55 | U26: =+SUM(R26:T26) -> 2827078.8 | AC26: 1 | AD26: =+EOMONTH(AE26,0) -> 45808 | AE26: 45779 | AG26: =+AG25+AF26-AH26 -> 1293748.7 | AH26: =+AG19 -> 51840.79 | AI26: =+AG25*AG$5*(AE26-AE25)/360 -> 13773.604 | AJ26: =+SUM(AH26:AI26) -> 65614.394 | AK26: 1 | AL26: 45796 | AM26: =+AH26 -> 51840.79 | AN26: =+AG25*AG$5*(AL26-AE25)/360 -> 17268.399 | AO26: =+AN26+AM26 -> 69109.189 | AR26: 1 | AS26: =+EOMONTH(AT26,0) -> 45716 | AT26: 45708 | AV26: 15996516 | AW26: 0 | AX26: =+AV25*AV$5*(AT26-AT25)/360 -> 138636.47 | AY26: =+SUM(AW26:AX26) -> 138636.47 | AZ26: 1 | BA26: 45744 | BB26: =+BA26-AT26 -> 36 | BC26: =+AW26 -> 0 | BD26: =+AV25*AV$5*(BA26-AT25)/360 -> 234615.57 | BE26: =+BD26+BC26 -> 234615.57 | BG26: 1 | BH26: =+EOMONTH(BI26,0) -> 45838 | BI26: 45828 | BK26: =+BK25+BJ26-BL26 -> 53476614 | BL26: 0 | BM26: =+BK25*BK$5*(BI26-BI25)/360 -> 819974.75 | BN26: 82616.23 | BO26: =+SUM(BL26:BN26) -> 902590.98 | BP26: 1 | BQ26: 45828 | BR26: =+BL26 -> 0 | BS26: =+BK25*BK$5*(BQ26-BI25)/360 -> 819974.75 | BT26: =+BS26+BR26+BN26 -> 902590.98 | BV26: 1 | BW26: =+EOMONTH(BX26,0) -> 45716 | BX26: 45702 | BZ26: =+BZ25+BY26-CA26 -> 1096992.9 | CA26: 57736.47 | CB26: 0 | CC26: =+BZ25*BZ$5*(BX26-BX25)/360 -> 4811.3725 | CD26: 1642.8395 | CE26: =+SUM(CA26:CD26) -> 64190.682 | CF26: 1 | CG26: 45702 | CH26: =+CA26 -> 57736.47 | CI26: =+BZ25*BZ$5*(CG26-BX25)/360 -> 4811.3725 | CJ26: =+CI26+CH26+CD26 -> 64190.682 | CL26: 1 | CM26: =+EOMONTH(CN26,0) -> 45838 | CN26: 45822 | CP26: =+CP25+CO26-CQ26 -> 1669085.9 | CQ26: 0 | CR26: 29209.003 | CS26: =+SUM(CQ26:CR26) -> 29209.003 | CU26: 1 | CV26: =+EOMONTH(CW26,0) -> 45900 | CW26: 45879 | CY26: =+CY25+CX26-CZ26 -> 25661049 | CZ26: 349011.21 | DA26: =+CY25*CY$5*(CW26-CW25)/360 -> 134385.31 | DB26: =+SUM(CZ26:DA26) -> 483396.52 | DD26: 1 | DE26: =+EOMONTH(DF26,0) -> 45838 | DF26: 45838 | DH26: =+DH25+DG26-DI26 -> 9116955.5 | DI26: 0 | DJ26: 138152.48 | DK26: =+SUM(DI26:DJ26) -> 138152.48 | DM26: 1 | DN26: =+EOMONTH(DO26,0) -> 45838 | DO26: 45838 | DQ26: =+DQ25-DR26 -> 1109707.9 | DR26: 0 | DS26: 16421.12 | DT26: =+SUM(DR26:DS26) -> 16421.12 | EE26: 1 | EF26: =+EOMONTH(EG26,0) -> 45747 | EG26: 45721 | EI26: =+EI25+EH26-EJ26 -> 2794681.5 | EJ26: 0 | EK26: 17114.156 | EL26: 86.4 | EM26: =+SUM(EJ26:EL26) -> 17200.556 | EO26: 1 | EP26: =+EOMONTH(EQ26,0) -> 45838 | EQ26: 45832 | ES26: =+ES25-ET26 -> 309433.84 | ET26: 36909.17 | EU26: 4285.87 | EV26: =+SUM(ET26:EU26) -> 41195.04 | EX26: 1 | EY26: =+EOMONTH(EZ26,0) -> 45838 | EZ26: 45832 | FB26: =+FB25-FC26 -> 309433.84 | FC26: 36909.17 | FD26: 4285.87 | FE26: =+SUM(FC26:FD26) -> 41195.04 | FG26: 1 | FH26: =+EOMONTH(FI26,0) -> 45838 | FI26: 45832 | FK26: =+FK25-FL26 -> 309433.84 | FL26: 36909.17 | FM26: 4285.87 | FN26: =+SUM(FL26:FM26) -> 41195.04 | FP26: 1 | FQ26: =+EOMONTH(FR26,0) -> 45838 | FR26: 45832 | FT26: =+FT25-FU26 -> 309433.84 | FU26: 36909.17 | FV26: 4285.87 | FW26: =+SUM(FU26:FV26) -> 41195.04 | FY26: 1 | FZ26: =+EOMONTH(GA26,0) -> 45838 | GA26: 45814 | GC26: =+GC25-GD26 -> 388403.55 | GD26: 38005.99 | GE26: 5069.14 | GF26: =+SUM(GD26:GE26) -> 43075.13 | GH26: 1 | GI26: =+EOMONTH(GJ26,0) -> 45838 | GJ26: 45814 | GL26: 388403.55 | GM26: 38005.99 | GN26: 5069.14 | GO26: 43075.13
A27: 2 | B27: =+WEEKNUM(C27,2) -> 44 | C27: =+EOMONTH(C26,1) -> 45961 | E27: =+E26+D27-F27 -> 2.4538703e+08 | F27: =+SUMIF(N:N,C27,R:R)+SUMIF(AD:AD,C27,AH:AH)+SUMIF(AS:AS,C27,AW:AW)+SUMIF(BH:BH,C27,BL:BL)+SUMIF(BW:BW,C27,CA:CA)+SUMIF(BW:BW,C27,CB:CB)+SUMIF(CM:CM,C27,CQ:CQ)+SUMIF(CV:CV,C27,CZ:CZ)+SUMIF(DE:DE,C27,DI:DI)+SUMIF(DN:DN,C27,DR:DR)+SUMIF(DW:DW,C27,EA:EA)+SUMIF(EF:EF,C27,EJ:EJ)+SUMIF(EP:EP,C27,ET:ET)+SUMIF(EY:EY,C27,FC:FC)+SUMIF(FH:FH,C27,FL:FL)+SUMIF(FQ:FQ,C27,FU:FU)+SUMIF(FZ:FZ,C27,GD:GD)+SUMIF(GI:GI,C27,GM:GM) -> 409569.11 | G27: =+SUMIF(N:N,C27,S:S)+SUMIF(N:N,C27,T:T)+SUMIF(AD:AD,C27,AI:AI)+SUMIF(AS:AS,C27,AX:AX)+SUMIF(BH:BH,C27,BM:BM)+SUMIF(BW:BW,C27,CD:CD)+SUMIF(BW:BW,C27,CC:CC)+SUMIF(CM:CM,C27,CR:CR)+SUMIF(CV:CV,C27,DA:DA)+SUMIF(DE:DE,C27,DJ:DJ)+SUMIF(DN:DN,C27,DS:DS)+SUMIF(DX:DX,C27,EB:EB)+SUMIF(EG:EG,C27,EK:EK)+SUMIF(EP:EP,C27,EU:EU)+SUMIF(EY:EY,C27,FD:FD)+SUMIF(FH:FH,C27,FM:FM)+SUMIF(FQ:FQ,C27,FV:FV)+SUMIF(FZ:FZ,C27,GE:GE)+SUMIF(GI:GI,C27,GN:GN) -> 161719.77 | H27: =+SUM(F27:G27) -> 571288.88 | M27: 2 | N27: =+EOMONTH(O27,0) -> 45716 | O27: 45703 | Q27: =+Q26-R27 -> 1.3227318e+08 | R27: =+$Q$20 -> 39369.667 | S27: =+Q26*Q$5*(O27-O26)/360 -> 2028792.4 | T27: =+$Q$17/$Q$18 -> 471550.55 | U27: =+SUM(R27:T27) -> 2539712.7 | W27: 45703 | AC27: 2 | AD27: =+EOMONTH(AE27,0) -> 45900 | AE27: 45871 | AG27: =+AG26+AF27-AH27 -> 1241907.9 | AH27: =+AH26 -> 51840.79 | AI27: =+AG26*AG$5*(AE27-AE26)/360 -> 18184.357 | AJ27: =+SUM(AH27:AI27) -> 70025.147 | AK27: 2 | AL27: =+TODAY() -> 46090 | AM27: =+AH27 -> 51840.79 | AN27: =+AG26*AG$5*(AL27-AL26)/360 -> 58110.88 | AO27: =+AN27+AM27 -> 109951.67 | AR27: 2 | AS27: =+EOMONTH(AT27,0) -> 45808 | AT27: 45797 | AV27: =+AV26+AU27-AW27 -> 15996516 | AW27: 0 | AX27: =+AV26*AV$5*(AT27-AT26)/360 -> 237281.65 | AY27: =+SUM(AW27:AX27) -> 237281.65 | AZ27: 2 | BA27: 45838 | BB27: =+BA27-AT27 -> 41 | BC27: =+AW27 -> 0 | BD27: =+AV26*AV$5*(BA27-BA26)/360 -> 250612.08 | BE27: =+BD27+BC27 -> 250612.08 | BG27: 2 | BH27: =+EOMONTH(BI27,0) -> 45930 | BI27: 45920 | BK27: =+BK26+BJ27-BL27 -> 53476614 | BL27: 0 | BM27: =+BK26*BK$5*(BI27-BI26)/360 -> 819974.75 | BN27: 82616.23 | BO27: =+SUM(BL27:BN27) -> 902590.98 | BP27: 2 | BQ27: 45920 | BR27: =+BL27 -> 0 | BS27: =+BK26*BK$5*(BQ27-BQ26)/360 -> 819974.75 | BT27: =+BS27+BR27+BN27 -> 902590.98 | BV27: 2 | BW27: =+EOMONTH(BX27,0) -> 45869 | BX27: 45858 | BZ27: =+BZ26+BY27-CA27 -> 1039256.4 | CA27: 57736.47 | CB27: 2821.4285 | CC27: =+BZ26*BZ$5*(BX27-BX26)/360 -> 28521.816 | CD27: 1642.8395 | CE27: =+SUM(CA27:CD27) -> 90722.554 | CF27: 2 | CG27: 45866 | CH27: =+CA27 -> 57736.47 | CI27: =+BZ26*BZ$5*(CG27-CG26)/360 -> 29984.473 | CJ27: =+CI27+CH27+CD27 -> 89363.783 | CL27: 2 | CM27: =+EOMONTH(CN27,0) -> 45930 | CN27: 45914 | CP27: =+CP26+CO27-CQ27 -> 1669085.9 | CQ27: 0 | CR27: 22393.569 | CS27: =+SUM(CQ27:CR27) -> 22393.569 | CU27: 2 | CV27: =+EOMONTH(CW27,0) -> 45930 | CW27: 45910 | CY27: =+CY26+CX27-CZ27 -> 25312038 | CZ27: 349011.21 | DA27: =+CY26*CY$5*(CW27-CW26)/360 -> 132582.09 | DB27: =+SUM(CZ27:DA27) -> 481593.3 | DD27: 2 | DE27: =+EOMONTH(DF27,0) -> 45930 | DF27: 45925 | DH27: =+DH26+DG27-DI27 -> 9116955.5 | DI27: 0 | DJ27: 127789.32 | DK27: =+SUM(DI27:DJ27) -> 127789.32 | DM27: 2 | DN27: =+EOMONTH(DO27,0) -> 45961 | DO27: 45936 | DQ27: =+DQ26-DR27 -> 1109707.9 | DR27: 0 | DS27: =+DQ26*(DO27-DO26)*$DQ$5/360 -> 17581.472 | DT27: =+SUM(DR27:DS27) -> 17581.472 | EE27: 2 | EF27: =+EOMONTH(EG27,0) -> 45838 | EG27: 45838 | EI27: =+EI26+EH27-EJ27 -> 2794681.5 | EJ27: 0 | EK27: 38370.47 | EL27: 19844.48 | EM27: =+SUM(EJ27:EL27) -> 58214.95 | EO27: 2 | EP27: =+EOMONTH(EQ27,0) -> 45930 | EQ27: 45922 | ES27: =+ES26-ET27 -> 271740.35 | ET27: 37693.49 | EU27: 3732.23 | EV27: =+SUM(ET27:EU27) -> 41425.72 | EX27: 2 | EY27: =+EOMONTH(EZ27,0) -> 45930 | EZ27: 45922 | FB27: =+FB26-FC27 -> 271740.35 | FC27: 37693.49 | FD27: 3732.23 | FE27: =+SUM(FC27:FD27) -> 41425.72 | FG27: 2 | FH27: =+EOMONTH(FI27,0) -> 45930 | FI27: 45922 | FK27: =+FK26-FL27 -> 271740.35 | FL27: 37693.49 | FM27: 3732.23 | FN27: =+SUM(FL27:FM27) -> 41425.72 | FP27: 2 | FQ27: =+EOMONTH(FR27,0) -> 45930 | FR27: 45922 | FT27: =+FT26-FU27 -> 271740.35 | FU27: 37693.49 | FV27: 3732.23 | FW27: =+SUM(FU27:FV27) -> 41425.72 | FY27: 2 | FZ27: =+EOMONTH(GA27,0) -> 45930 | GA27: 45904 | GC27: =+GC26-GD27 -> 349589.93 | GD27: 38813.62 | GE27: 4499.05 | GF27: =+SUM(GD27:GE27) -> 43312.67 | GH27: 2 | GI27: =+EOMONTH(GJ27,0) -> 45930 | GJ27: 45904 | GL27: 349589.93 | GM27: 38813.62 | GN27: 4499.05 | GO27: 43312.67
A28: 3 | B28: =+WEEKNUM(C28,2) -> 48 | C28: =+EOMONTH(C27,1) -> 45991 | E28: =+E27+D28-F28 -> 2.1461668e+08 | F28: =+SUMIF(N:N,C28,R:R)+SUMIF(AD:AD,C28,AH:AH)+SUMIF(AS:AS,C28,AW:AW)+SUMIF(BH:BH,C28,BL:BL)+SUMIF(BW:BW,C28,CA:CA)+SUMIF(BW:BW,C28,CB:CB)+SUMIF(CM:CM,C28,CQ:CQ)+SUMIF(CV:CV,C28,CZ:CZ)+SUMIF(DE:DE,C28,DI:DI)+SUMIF(DN:DN,C28,DR:DR)+SUMIF(DW:DW,C28,EA:EA)+SUMIF(EF:EF,C28,EJ:EJ)+SUMIF(EP:EP,C28,ET:ET)+SUMIF(EY:EY,C28,FC:FC)+SUMIF(FH:FH,C28,FL:FL)+SUMIF(FQ:FQ,C28,FU:FU)+SUMIF(FZ:FZ,C28,GD:GD)+SUMIF(GI:GI,C28,GM:GM) -> 30770346 | G28: =+SUMIF(N:N,C28,S:S)+SUMIF(N:N,C28,T:T)+SUMIF(AD:AD,C28,AI:AI)+SUMIF(AS:AS,C28,AX:AX)+SUMIF(BH:BH,C28,BM:BM)+SUMIF(BW:BW,C28,CD:CD)+SUMIF(BW:BW,C28,CC:CC)+SUMIF(CM:CM,C28,CR:CR)+SUMIF(CV:CV,C28,DA:DA)+SUMIF(DE:DE,C28,DJ:DJ)+SUMIF(DN:DN,C28,DS:DS)+SUMIF(DX:DX,C28,EB:EB)+SUMIF(EG:EG,C28,EK:EK)+SUMIF(EP:EP,C28,EU:EU)+SUMIF(EY:EY,C28,FD:FD)+SUMIF(FH:FH,C28,FM:FM)+SUMIF(FQ:FQ,C28,FV:FV)+SUMIF(FZ:FZ,C28,GE:GE)+SUMIF(GI:GI,C28,GN:GN) -> 2890243.2 | H28: =+SUM(F28:G28) -> 33660590 | I28: =+AA28 -> 9042540.4 | J28: Fideicomiso | M28: 3 | N28: =+EOMONTH(O28,0) -> 45808 | O28: 45792 | Q28: =+Q27-R28 -> 1.3223381e+08 | R28: =+$Q$20 -> 39369.667 | S28: =+Q27*Q$5*(O28-O27)/360 -> 1962052.2 | T28: =+$Q$17/$Q$18 -> 471550.55 | U28: =+SUM(R28:T28) -> 2472972.4 | V28: 3 | W28: =+TODAY() -> 46090 | X28: =+W28-W27 -> 387 | Y28: =+R28 -> 39369.667 | Z28: =+Q27*Q$5*(W28-O27)/360 -> 8531620.2 | AA28: =+Z28+Y28+T28 -> 9042540.4 | AC28: 3 | AD28: =+EOMONTH(AE28,0) -> 45991 | AE28: 45963 | AG28: =+AG27+AF28-AH28 -> 1190067.1 | AH28: =+AH27 -> 51840.79 | AI28: =+AG27*AG$5*(AE28-AE27)/360 -> 17455.706 | AJ28: =+SUM(AH28:AI28) -> 69296.496 | AR28: 3 | AS28: =+EOMONTH(AT28,0) -> 45900 | AT28: 45889 | AV28: =+AV27+AU28-AW28 -> 15996516 | AW28: 0 | AX28: =+AV27*AV$5*(AT28-AT27)/360 -> 245279.91 | AY28: =+SUM(AW28:AX28) -> 245279.91 | AZ28: 3 | BA28: =+TODAY() -> 46090 | BB28: =+BA28-AT28 -> 201 | BC28: =+AW28 -> 0 | BD28: =+AV27*AV$5*(BA28-BA27)/360 -> 671853.67 | BE28: =+BD28+BC28 -> 671853.67 | BG28: 3 | BH28: =+EOMONTH(BI28,0) -> 46022 | BI28: 46011 | BK28: =+BK27+BJ28-BL28 -> 53476614 | BL28: 0 | BM28: =+BK27*BK$5*(BI28-BI27)/360 -> 811061.98 | BN28: 82616.23 | BO28: =+SUM(BL28:BN28) -> 893678.21 | BV28: 3 | BW28: =+EOMONTH(BX28,0) -> 45961 | BX28: 45950 | BZ28: =+BZ27+BY28-CA28 -> 981519.98 | CA28: 57736.47 | CB28: 2821.4285 | CC28: =+BZ27*BZ$5*(BX28-BX27)/360 -> 15935.266 | CD28: 1642.8395 | CE28: =+SUM(CA28:CD28) -> 78136.004 | CL28: 3 | CM28: =+EOMONTH(CN28,0) -> 46022 | CN28: 46005 | CP28: =+CP27+CO28-CQ28 -> 1564768 | CQ28: 104317.86 | CR28: 22150.161 | CS28: =+SUM(CQ28:CR28) -> 126468.02 | CU28: 3 | CV28: =+EOMONTH(CW28,0) -> 45961 | CW28: 45940 | CY28: =+CY27+CX28-CZ28 -> 24963027 | CZ28: 349011.21 | DA28: =+CY27*CY$5*(CW28-CW27)/360 -> 126560.19 | DB28: =+SUM(CZ28:DA28) -> 475571.4 | DD28: 3 | DE28: =+EOMONTH(DF28,0) -> 46022 | DF28: 46017 | DH28: =+DH27+DG28-DI28 -> 9116955.5 | DI28: 0 | DJ28: 135133.54 | DK28: =+SUM(DI28:DJ28) -> 135133.54 | DM28: 3 | DN28: =+EOMONTH(DO28,0) -> 46053 | DO28: 46027 | DQ28: =+DQ27-DR28 -> 1109707.9 | DR28: 0 | DS28: =+DQ27*(DO28-DO27)*$DQ$5/360 -> 16325.652 | DT28: =+SUM(DR28:DS28) -> 16325.652 | EE28: 3 | EF28: =+EOMONTH(EG28,0) -> 45930 | EG28: 45925 | EI28: =+EI27+EH28-EJ28 -> 2794681.5 | EJ28: 0 | EK28: 17027.76 | EM28: =+SUM(EJ28:EL28) -> 17027.76 | EO28: 3 | EP28: =+EOMONTH(EQ28,0) -> 46022 | EQ28: 46012 | ES28: =+ES27-ET28 -> 233245.87 | ET28: 38494.48 | EU28: 3166.83 | EV28: =+SUM(ET28:EU28) -> 41661.31 | EX28: 3 | EY28: =+EOMONTH(EZ28,0) -> 46022 | EZ28: 46012 | FB28: =+FB27-FC28 -> 233245.87 | FC28: 38494.48 | FD28: 3166.83 | FE28: =+SUM(FC28:FD28) -> 41661.31 | FG28: 3 | FH28: =+EOMONTH(FI28,0) -> 46022 | FI28: 46012 | FK28: =+FK27-FL28 -> 233245.87 | FL28: 38494.48 | FM28: 3166.83 | FN28: =+SUM(FL28:FM28) -> 41661.31 | FP28: 3 | FQ28: =+EOMONTH(FR28,0) -> 46022 | FR28: 46012 | FT28: =+FT27-FU28 -> 233245.87 | FU28: 38494.48 | FV28: 3166.83 | FW28: =+SUM(FU28:FV28) -> 41661.31 | FY28: 3 | FZ28: =+EOMONTH(GA28,0) -> 46022 | GA28: 45994 | GC28: =+GC27-GD28 -> 309951.52 | GD28: 39638.41 | GE28: 3916.84 | GF28: =+SUM(GD28:GE28) -> 43555.25 | GH28: 3 | GI28: =+EOMONTH(GJ28,0) -> 46022 | GJ28: 45994 | GL28: 309951.52 | GM28: 39638.41 | GN28: 3916.84 | GO28: 43555.25
A29: 4 | B29: =+WEEKNUM(C29,2) -> 53 | C29: =+EOMONTH(C28,1) -> 46022 | E29: =+E28+D29-F29 -> 2.139301e+08 | F29: =+SUMIF(N:N,C29,R:R)+SUMIF(AD:AD,C29,AH:AH)+SUMIF(AS:AS,C29,AW:AW)+SUMIF(BH:BH,C29,BL:BL)+SUMIF(BW:BW,C29,CA:CA)+SUMIF(BW:BW,C29,CB:CB)+SUMIF(CM:CM,C29,CQ:CQ)+SUMIF(CV:CV,C29,CZ:CZ)+SUMIF(DE:DE,C29,DI:DI)+SUMIF(DN:DN,C29,DR:DR)+SUMIF(DW:DW,C29,EA:EA)+SUMIF(EF:EF,C29,EJ:EJ)+SUMIF(EP:EP,C29,ET:ET)+SUMIF(EY:EY,C29,FC:FC)+SUMIF(FH:FH,C29,FL:FL)+SUMIF(FQ:FQ,C29,FU:FU)+SUMIF(FZ:FZ,C29,GD:GD)+SUMIF(GI:GI,C29,GM:GM) -> 686583.81 | G29: =+SUMIF(N:N,C29,S:S)+SUMIF(N:N,C29,T:T)+SUMIF(AD:AD,C29,AI:AI)+SUMIF(AS:AS,C29,AX:AX)+SUMIF(BH:BH,C29,BM:BM)+SUMIF(BW:BW,C29,CD:CD)+SUMIF(BW:BW,C29,CC:CC)+SUMIF(CM:CM,C29,CR:CR)+SUMIF(CV:CV,C29,DA:DA)+SUMIF(DE:DE,C29,DJ:DJ)+SUMIF(DN:DN,C29,DS:DS)+SUMIF(DX:DX,C29,EB:EB)+SUMIF(EG:EG,C29,EK:EK)+SUMIF(EP:EP,C29,EU:EU)+SUMIF(EY:EY,C29,FD:FD)+SUMIF(FH:FH,C29,FM:FM)+SUMIF(FQ:FQ,C29,FV:FV)+SUMIF(FZ:FZ,C29,GE:GE)+SUMIF(GI:GI,C29,GN:GN) -> 1111916.8 | H29: =+SUM(F29:G29) -> 1798500.6 | M29: 4 | N29: =+EOMONTH(O29,0) -> 45900 | O29: 45884 | Q29: =+Q28-R29 -> 1.3219444e+08 | R29: =+$Q$20 -> 39369.667 | S29: =+Q28*Q$5*(O29-O28)/360 -> 2027585.1 | T29: =+$Q$17/$Q$18 -> 471550.55 | U29: =+SUM(R29:T29) -> 2538505.3 | V29: 4 | W29: =+TODAY() -> 46090 | Y29: =+R29 -> 39369.667 | AA29: =+Y29 -> 39369.667 | AC29: 4 | AD29: =+EOMONTH(AE29,0) -> 46081 | AE29: 46055 | AG29: =+AG28+AF29-AH29 -> 1138226.3 | AH29: =+AH28 -> 51840.79 | AI29: =+AG28*AG$5*(AE29-AE28)/360 -> 16727.055 | AJ29: =+SUM(AH29:AI29) -> 68567.845 | AR29: 4 | AS29: =+EOMONTH(AT29,0) -> 45991 | AT29: 45981 | AV29: =+AV28+AU29-AW29 -> 15996516 | AW29: 0 | AX29: =+AV28*AV$5*(AT29-AT28)/360 -> 245279.91 | AY29: =+SUM(AW29:AX29) -> 245279.91 | BG29: 4 | BH29: =+EOMONTH(BI29,0) -> 46112 | BI29: 46101 | BK29: =+BK28+BJ29-BL29 -> 53476614 | BL29: 0 | BM29: =+BK28*BK$5*(BI29-BI28)/360 -> 802149.21 | BN29: 82616.23 | BO29: =+SUM(BL29:BN29) -> 884765.44 | BV29: 4 | BW29: =+EOMONTH(BX29,0) -> 46053 | BX29: 46042 | BZ29: =+BZ28+BY29-CA29 -> 923783.51 | CA29: 57736.47 | CB29: 2821.4285 | CC29: =+BZ28*BZ$5*(BX29-BX28)/360 -> 15049.973 | CD29: 1642.8395 | CE29: =+SUM(CA29:CD29) -> 77250.711 | CL29: 4 | CM29: =+EOMONTH(CN29,0) -> 46112 | CN29: 46095 | CP29: =+CP28+CO29-CQ29 -> 1460450.1 | CQ29: 104317.86 | CR29: 20341.984 | CS29: =+SUM(CQ29:CR29) -> 124659.84 | CU29: 4 | CV29: =+EOMONTH(CW29,0) -> 45991 | CW29: 45971 | CY29: =+CY28+CX29-CZ29 -> 24614016 | CZ29: 349011.21 | DA29: =+CY28*CY$5*(CW29-CW28)/360 -> 128975.64 | DB29: =+SUM(CZ29:DA29) -> 477986.85 | DD29: 4 | DE29: =+EOMONTH(DF29,0) -> 46112 | DF29: 46107 | DH29: =+DH28+DG29-DI29 -> 9102050 | DI29: 14905.56 | DJ29: 132195.85 | DK29: =+SUM(DI29:DJ29) -> 147101.41 | DM29: 4 | DN29: =+EOMONTH(DO29,0) -> 46142 | DO29: 46118 | DQ29: =+DQ28-DR29 -> 1107774.2 | DR29: 1933.63 | DS29: =+DQ28*(DO29-DO28)*$DQ$5/360 -> 16325.652 | DT29: =+SUM(DR29:DS29) -> 18259.282 | EE29: 4 | EF29: =+EOMONTH(EG29,0) -> 46022 | EG29: 46017 | EI29: =+EI28+EH29-EJ29 -> 2794681.5 | EJ29: 0 | EK29: 18006.37 | EL29: 0 | EM29: =+SUM(EJ29:EL29) -> 18006.37 | EO29: 4 | EP29: =+EOMONTH(EQ29,0) -> 46112 | EQ29: 46102 | ES29: =+ES28-ET29 -> 193933.38 | ET29: 39312.49 | EU29: 2589.41 | EV29: =+SUM(ET29:EU29) -> 41901.9 | EX29: 4 | EY29: =+EOMONTH(EZ29,0) -> 46112 | EZ29: 46102 | FB29: =+FB28-FC29 -> 193933.38 | FC29: 39312.49 | FD29: 2589.41 | FE29: =+SUM(FC29:FD29) -> 41901.9 | FG29: 4 | FH29: =+EOMONTH(FI29,0) -> 46112 | FI29: 46102 | FK29: =+FK28-FL29 -> 193933.38 | FL29: 39312.49 | FM29: 2589.41 | FN29: =+SUM(FL29:FM29) -> 41901.9 | FP29: 4 | FQ29: =+EOMONTH(FR29,0) -> 46112 | FR29: 46102 | FT29: =+FT28-FU29 -> 193933.38 | FU29: 39312.49 | FV29: 2589.41 | FW29: =+SUM(FU29:FV29) -> 41901.9 | FY29: 4 | FZ29: =+EOMONTH(GA29,0) -> 46112 | GA29: 46084 | GC29: =+GC28-GD29 -> 269470.8 | GD29: 40480.72 | GE29: 3322.26 | GF29: =+SUM(GD29:GE29) -> 43802.98 | GH29: 4 | GI29: =+EOMONTH(GJ29,0) -> 46112 | GJ29: 46084 | GL29: 269470.8 | GM29: 40480.72 | GN29: 3322.26 | GO29: 43802.98
A30: 5 | B30: =+WEEKNUM(C30,2) -> 5 | C30: =+EOMONTH(C29,1) -> 46053 | E30: =+E29+D30-F30 -> 2.1352053e+08 | F30: =+SUMIF(N:N,C30,R:R)+SUMIF(AD:AD,C30,AH:AH)+SUMIF(AS:AS,C30,AW:AW)+SUMIF(BH:BH,C30,BL:BL)+SUMIF(BW:BW,C30,CA:CA)+SUMIF(BW:BW,C30,CB:CB)+SUMIF(CM:CM,C30,CQ:CQ)+SUMIF(CV:CV,C30,CZ:CZ)+SUMIF(DE:DE,C30,DI:DI)+SUMIF(DN:DN,C30,DR:DR)+SUMIF(DW:DW,C30,EA:EA)+SUMIF(EF:EF,C30,EJ:EJ)+SUMIF(EP:EP,C30,ET:ET)+SUMIF(EY:EY,C30,FC:FC)+SUMIF(FH:FH,C30,FL:FL)+SUMIF(FQ:FQ,C30,FU:FU)+SUMIF(FZ:FZ,C30,GD:GD)+SUMIF(GI:GI,C30,GM:GM) -> 409569.11 | G30: =+SUMIF(N:N,C30,S:S)+SUMIF(N:N,C30,T:T)+SUMIF(AD:AD,C30,AI:AI)+SUMIF(AS:AS,C30,AX:AX)+SUMIF(BH:BH,C30,BM:BM)+SUMIF(BW:BW,C30,CD:CD)+SUMIF(BW:BW,C30,CC:CC)+SUMIF(CM:CM,C30,CR:CR)+SUMIF(CV:CV,C30,DA:DA)+SUMIF(DE:DE,C30,DJ:DJ)+SUMIF(DN:DN,C30,DS:DS)+SUMIF(DX:DX,C30,EB:EB)+SUMIF(EG:EG,C30,EK:EK)+SUMIF(EP:EP,C30,EU:EU)+SUMIF(EY:EY,C30,FD:FD)+SUMIF(FH:FH,C30,FM:FM)+SUMIF(FQ:FQ,C30,FV:FV)+SUMIF(FZ:FZ,C30,GE:GE)+SUMIF(GI:GI,C30,GN:GN) -> 158387.66 | H30: =+SUM(F30:G30) -> 567956.76 | I30: =+F30 -> 409569.11 | J30: Union | M30: 5 | N30: =+EOMONTH(O30,0) -> 45991 | O30: =+DATE(YEAR(O29),MONTH(O29)+3,DAY(O29)) -> 45976 | Q30: =+Q29-R30 -> 1.0182495e+08 | R30: =+Q21 -> 30369494 | S30: =+Q29*Q$5*(O30-O29)/360 -> 2026981.4 | T30: =+$Q$17/$Q$18 -> 471550.55 | U30: =+SUM(R30:T30) -> 32868026 | AC30: 5 | AD30: =+EOMONTH(AE30,0) -> 46173 | AE30: 46144 | AG30: =+AG29+AF30-AH30 -> 1086385.6 | AH30: =+AH29 -> 51840.79 | AI30: =+AG29*AG$5*(AE30-AE29)/360 -> 15476.717 | AJ30: =+SUM(AH30:AI30) -> 67317.507 | AR30: 5 | AS30: =+EOMONTH(AT30,0) -> 46081 | AT30: 46073 | AV30: =+AV29+AU30-AW30 -> 15996516 | AW30: 0 | AX30: =+AV29*AV$5*(AT30-AT29)/360 -> 245279.91 | AY30: =+SUM(AW30:AX30) -> 245279.91 | BG30: 5 | BH30: =+EOMONTH(BI30,0) -> 46203 | BI30: 46193 | BK30: =+BK29+BJ30-BL30 -> 53476614 | BL30: 0 | BM30: =+BK29*BK$5*(BI30-BI29)/360 -> 819974.75 | BN30: 82616.23 | BO30: =+SUM(BL30:BN30) -> 902590.98 | BV30: 5 | BW30: =+EOMONTH(BX30,0) -> 46142 | BX30: 46132 | BZ30: =+BZ29+BY30-CA30 -> 866047.04 | CA30: 57736.47 | CB30: 2821.4285 | CC30: =+BZ29*BZ$5*(BX30-BX29)/360 -> 13856.753 | CD30: 1642.8395 | CE30: =+SUM(CA30:CD30) -> 76057.491 | CL30: 5 | CM30: =+EOMONTH(CN30,0) -> 46203 | CN30: 46187 | CP30: =+CP29+CO30-CQ30 -> 1356132.3 | CQ30: 104317.86 | CR30: 19194.488 | CS30: =+SUM(CQ30:CR30) -> 123512.35 | CU30: 5 | CV30: =+EOMONTH(CW30,0) -> 46022 | CW30: 46001 | CY30: =+CY29+CX30-CZ30 -> 24265005 | CZ30: 349011.21 | DA30: =+CY29*CY$5*(CW30-CW29)/360 -> 123070.08 | DB30: =+SUM(CZ30:DA30) -> 472081.29 | DD30: 5 | DE30: =+EOMONTH(DF30,0) -> 46203 | DF30: 46198 | DH30: =+DH29+DG30-DI30 -> 9087144.4 | DI30: 14905.62 | DJ30: 133446.17 | DK30: =+SUM(DI30:DJ30) -> 148351.79 | DM30: 5 | DN30: =+EOMONTH(DO30,0) -> 46234 | DO30: 46209 | DQ30: =+DQ29-DR30 -> 1105840.6 | DR30: 1933.65 | DS30: =+DQ29*(DO30-DO29)*$DQ$5/360 -> 16297.205 | DT30: =+SUM(DR30:DS30) -> 18230.855 | EE30: 5 | EF30: =+EOMONTH(EG30,0) -> 46112 | EG30: 46107 | EI30: =+EI29+EH30-EJ30 -> 2789681.5 | EJ30: 5000.03 | EK30: 18235.06 | EM30: =+SUM(EJ30:EL30) -> 23235.09 | EO30: 5 | EP30: =+EOMONTH(EQ30,0) -> 46203 | EQ30: 46192 | ES30: =+ES29-ET30 -> 153785.5 | ET30: 40147.88 | EU30: 1999.73 | EV30: =+SUM(ET30:EU30) -> 42147.61 | EX30: 5 | EY30: =+EOMONTH(EZ30,0) -> 46203 | EZ30: 46192 | FB30: =+FB29-FC30 -> 153785.5 | FC30: 40147.88 | FD30: 1999.73 | FE30: =+SUM(FC30:FD30) -> 42147.61 | FG30: 5 | FH30: =+EOMONTH(FI30,0) -> 46203 | FI30: 46192 | FK30: =+FK29-FL30 -> 153785.5 | FL30: 40147.88 | FM30: 1999.73 | FN30: =+SUM(FL30:FM30) -> 42147.61 | FP30: 5 | FQ30: =+EOMONTH(FR30,0) -> 46203 | FR30: 46192 | FT30: =+FT29-FU30 -> 153785.5 | FU30: 40147.88 | FV30: 1999.73 | FW30: =+SUM(FU30:FV30) -> 42147.61 | FY30: 5 | FZ30: =+EOMONTH(GA30,0) -> 46203 | GA30: 46174 | GC30: =+GC29-GD30 -> 228129.86 | GD30: 41340.94 | GE30: 2715.05 | GF30: =+SUM(GD30:GE30) -> 44055.99 | GH30: 5 | GI30: =+EOMONTH(GJ30,0) -> 46203 | GJ30: 46174 | GL30: 228129.86 | GM30: 41340.94 | GN30: 2715.05 | GO30: 44055.99
A31: 6 | B31: =+WEEKNUM(C31,2) -> 9 | C31: =+EOMONTH(C30,1) -> 46081 | E31: =+E30+D31-F31 -> 2.0904668e+08 | F31: =+SUMIF(N:N,C31,R:R)+SUMIF(AD:AD,C31,AH:AH)+SUMIF(AS:AS,C31,AW:AW)+SUMIF(BH:BH,C31,BL:BL)+SUMIF(BW:BW,C31,CA:CA)+SUMIF(BW:BW,C31,CB:CB)+SUMIF(CM:CM,C31,CQ:CQ)+SUMIF(CV:CV,C31,CZ:CZ)+SUMIF(DE:DE,C31,DI:DI)+SUMIF(DN:DN,C31,DR:DR)+SUMIF(DW:DW,C31,EA:EA)+SUMIF(EF:EF,C31,EJ:EJ)+SUMIF(EP:EP,C31,ET:ET)+SUMIF(EY:EY,C31,FC:FC)+SUMIF(FH:FH,C31,FL:FL)+SUMIF(FQ:FQ,C31,FU:FU)+SUMIF(FZ:FZ,C31,GD:GD)+SUMIF(GI:GI,C31,GM:GM) -> 4473849.9 | G31: =+SUMIF(N:N,C31,S:S)+SUMIF(N:N,C31,T:T)+SUMIF(AD:AD,C31,AI:AI)+SUMIF(AS:AS,C31,AX:AX)+SUMIF(BH:BH,C31,BM:BM)+SUMIF(BW:BW,C31,CD:CD)+SUMIF(BW:BW,C31,CC:CC)+SUMIF(CM:CM,C31,CR:CR)+SUMIF(CV:CV,C31,DA:DA)+SUMIF(DE:DE,C31,DJ:DJ)+SUMIF(DN:DN,C31,DS:DS)+SUMIF(DX:DX,C31,EB:EB)+SUMIF(EG:EG,C31,EK:EK)+SUMIF(EP:EP,C31,EU:EU)+SUMIF(EY:EY,C31,FD:FD)+SUMIF(FH:FH,C31,FM:FM)+SUMIF(FQ:FQ,C31,FV:FV)+SUMIF(FZ:FZ,C31,GE:GE)+SUMIF(GI:GI,C31,GN:GN) -> 2418439.3 | H31: =+SUM(F31:G31) -> 6892289.2 | M31: 6 | N31: =+EOMONTH(O31,0) -> 46081 | O31: =+DATE(YEAR(O30),MONTH(O30)+3,DAY(O30)) -> 46068 | Q31: =+Q30-R31 -> 97751949 | R31: =+$Q$30/25 -> 4072997.9 | S31: =+Q30*Q$5*(O31-O30)/360 -> 1561315.9 | T31: =+$Q$17/$Q$18 -> 471550.55 | U31: =+SUM(R31:T31) -> 6105864.3 | AC31: 6 | AD31: =+EOMONTH(AE31,0) -> 46265 | AE31: 46236 | AG31: =+AG30+AF31-AH31 -> 1034544.8 | AH31: =+AH30 -> 51840.79 | AI31: =+AG30*AG$5*(AE31-AE30)/360 -> 15269.753 | AJ31: =+SUM(AH31:AI31) -> 67110.543 | AR31: 6 | AS31: =+EOMONTH(AT31,0) -> 46173 | AT31: 46162 | AV31: =+AV30+AU31-AW31 -> 15996516 | AW31: 0 | AX31: =+AV30*AV$5*(AT31-AT30)/360 -> 237281.65 | AY31: =+SUM(AW31:AX31) -> 237281.65 | BG31: 6 | BH31: =+EOMONTH(BI31,0) -> 46295 | BI31: 46285 | BK31: =+BK30+BJ31-BL31 -> 48128953 | BL31: =+BK28/10 -> 5347661.4 | BM31: =+BK30*BK$5*(BI31-BI30)/360 -> 819974.75 | BN31: 82616.23 | BO31: =+SUM(BL31:BN31) -> 6250252.4 | BV31: 6 | BW31: =+EOMONTH(BX31,0) -> 46234 | BX31: 46223 | BZ31: =+BZ30+BY31-CA31 -> 808310.57 | CA31: 57736.47 | CB31: 2821.4285 | CC31: =+BZ30*BZ$5*(BX31-BX30)/360 -> 13135.047 | CD31: 1642.8395 | CE31: =+SUM(CA31:CD31) -> 75335.785 | CL31: 6 | CM31: =+EOMONTH(CN31,0) -> 46295 | CN31: 46279 | CP31: =+CP30+CO31-CQ31 -> 1251814.4 | CQ31: 104317.86 | CR31: 17594.947 | CS31: =+SUM(CQ31:CR31) -> 121912.81 | CU31: 6 | CV31: =+EOMONTH(CW31,0) -> 46053 | CW31: 46032 | CY31: =+CY30+CX31-CZ31 -> 23915993 | CZ31: 349011.21 | DA31: =+CY30*CY$5*(CW31-CW30)/360 -> 125369.19 | DB31: =+SUM(CZ31:DA31) -> 474380.4 | DD31: 6 | DE31: =+EOMONTH(DF31,0) -> 46295 | DF31: 46289 | DH31: =+DH30+DG31-DI31 -> 8803171.1 | DI31: 283973.26 | DJ31: 133227.63 | DK31: =+SUM(DI31:DJ31) -> 417200.89 | DM31: 6 | DN31: =+EOMONTH(DO31,0) -> 46326 | DO31: 46300 | DQ31: =+DQ30-DR31 -> 1066346.3 | DR31: 39494.31 | DS31: =+DQ30*(DO31-DO30)*$DQ$5/360 -> 16268.758 | DT31: =+SUM(DR31:DS31) -> 55763.068 | EE31: 6 | EF31: =+EOMONTH(EG31,0) -> 46203 | EG31: 46198 | EI31: =+EI30+EH31-EJ31 -> 2784681.5 | EJ31: 5000 | EK31: 18355.08 | EM31: =+SUM(EJ31:EL31) -> 23355.08 | EO31: 6 | EP31: =+EOMONTH(EQ31,0) -> 46295 | EQ31: 46282 | ES31: =+ES30-ET31 -> 112784.48 | ET31: 41001.02 | EU31: 1397.51 | EV31: =+SUM(ET31:EU31) -> 42398.53 | EX31: 6 | EY31: =+EOMONTH(EZ31,0) -> 46295 | EZ31: 46282 | FB31: =+FB30-FC31 -> 112784.48 | FC31: 41001.02 | FD31: 1397.51 | FE31: =+SUM(FC31:FD31) -> 42398.53 | FG31: 6 | FH31: =+EOMONTH(FI31,0) -> 46295 | FI31: 46282 | FK31: =+FK30-FL31 -> 112784.48 | FL31: 41001.02 | FM31: 1397.51 | FN31: =+SUM(FL31:FM31) -> 42398.53 | FP31: 6 | FQ31: =+EOMONTH(FR31,0) -> 46295 | FR31: 46282 | FT31: =+FT30-FU31 -> 112784.48 | FU31: 41001.02 | FV31: 1397.51 | FW31: =+SUM(FU31:FV31) -> 42398.53 | FY31: 6 | FZ31: =+EOMONTH(GA31,0) -> 46265 | GA31: 46264 | GC31: =+GC30-GD31 -> 185910.43 | GD31: 42219.43 | GE31: 2094.94 | GF31: =+SUM(GD31:GE31) -> 44314.37 | GH31: 6 | GI31: =+EOMONTH(GJ31,0) -> 46265 | GJ31: 46264 | GL31: 185910.43 | GM31: 42219.43 | GN31: 2094.94 | GO31: 44314.37
A32: 7 | B32: =+WEEKNUM(C32,2) -> 14 | C32: =+EOMONTH(C31,1) -> 46112 | E32: =+E31+D32-F32 -> 2.0833523e+08 | F32: =+SUMIF(N:N,C32,R:R)+SUMIF(AD:AD,C32,AH:AH)+SUMIF(AS:AS,C32,AW:AW)+SUMIF(BH:BH,C32,BL:BL)+SUMIF(BW:BW,C32,CA:CA)+SUMIF(BW:BW,C32,CB:CB)+SUMIF(CM:CM,C32,CQ:CQ)+SUMIF(CV:CV,C32,CZ:CZ)+SUMIF(DE:DE,C32,DI:DI)+SUMIF(DN:DN,C32,DR:DR)+SUMIF(DW:DW,C32,EA:EA)+SUMIF(EF:EF,C32,EJ:EJ)+SUMIF(EP:EP,C32,ET:ET)+SUMIF(EY:EY,C32,FC:FC)+SUMIF(FH:FH,C32,FL:FL)+SUMIF(FQ:FQ,C32,FU:FU)+SUMIF(FZ:FZ,C32,GD:GD)+SUMIF(GI:GI,C32,GM:GM) -> 711446.06 | G32: =+SUMIF(N:N,C32,S:S)+SUMIF(N:N,C32,T:T)+SUMIF(AD:AD,C32,AI:AI)+SUMIF(AS:AS,C32,AX:AX)+SUMIF(BH:BH,C32,BM:BM)+SUMIF(BW:BW,C32,CD:CD)+SUMIF(BW:BW,C32,CC:CC)+SUMIF(CM:CM,C32,CR:CR)+SUMIF(CV:CV,C32,DA:DA)+SUMIF(DE:DE,C32,DJ:DJ)+SUMIF(DN:DN,C32,DS:DS)+SUMIF(DX:DX,C32,EB:EB)+SUMIF(EG:EG,C32,EK:EK)+SUMIF(EP:EP,C32,EU:EU)+SUMIF(EY:EY,C32,FD:FD)+SUMIF(FH:FH,C32,FM:FM)+SUMIF(FQ:FQ,C32,FV:FV)+SUMIF(FZ:FZ,C32,GE:GE)+SUMIF(GI:GI,C32,GN:GN) -> 1081668.5 | H32: =+SUM(F32:G32) -> 1793114.5 | I32: =+H32 -> 1793114.5 | J32: BDP | M32: 7 | N32: =+EOMONTH(O32,0) -> 46173 | O32: =+DATE(YEAR(O31),MONTH(O31)+3,DAY(O31)) -> 46157 | Q32: =+Q31-R32 -> 93678951 | R32: =+$Q$30/25 -> 4072997.9 | S32: =+Q31*Q$5*(O32-O31)/360 -> 1449987.2 | T32: =+$Q$17/$Q$18 -> 471550.55 | U32: =+SUM(R32:T32) -> 5994535.7 | AC32: 7 | AD32: =+EOMONTH(AE32,0) -> 46356 | AE32: 46328 | AG32: =+AG31+AF32-AH32 -> 982703.98 | AH32: =+AH31 -> 51840.79 | AI32: =+AG31*AG$5*(AE32-AE31)/360 -> 14541.101 | AJ32: =+SUM(AH32:AI32) -> 66381.891 | AR32: 7 | AS32: =+EOMONTH(AT32,0) -> 46265 | AT32: 46254 | AV32: =+AV31+AU32-AW32 -> 15471469 | AW32: 525047.46 | AX32: =+AV31*AV$5*(AT32-AT31)/360 -> 245279.91 | AY32: =+SUM(AW32:AX32) -> 770327.38 | BG32: 7 | BH32: =+EOMONTH(BI32,0) -> 46387 | BI32: 46376 | BK32: =+BK31+BJ32-BL32 -> 42781291 | BL32: =+BL31 -> 5347661.4 | BM32: =+BK31*BK$5*(BI32-BI31)/360 -> 729955.78 | BN32: 82616.23 | BO32: =+SUM(BL32:BN32) -> 6160233.4 | BV32: 7 | BW32: =+EOMONTH(BX32,0) -> 46326 | BX32: 46315 | BZ32: =+BZ31+BY32-CA32 -> 750574.1 | CA32: 57736.47 | CB32: 2821.4285 | CC32: =+BZ31*BZ$5*(BX32-BX31)/360 -> 12394.095 | CD32: 1642.8395 | CE32: =+SUM(CA32:CD32) -> 74594.833 | CL32: 7 | CM32: =+EOMONTH(CN32,0) -> 46387 | CN32: 46370 | CP32: =+CP31+CO32-CQ32 -> 1147496.5 | CQ32: 104317.86 | CR32: 15821.544 | CS32: =+SUM(CQ32:CR32) -> 120139.4 | CU32: 7 | CV32: =+EOMONTH(CW32,0) -> 46081 | CW32: 46063 | CY32: =+CY31+CX32-CZ32 -> 23566982 | CZ32: 349011.21 | DA32: =+CY31*CY$5*(CW32-CW31)/360 -> 123565.97 | DB32: =+SUM(CZ32:DA32) -> 472577.18 | DD32: 7 | DE32: =+EOMONTH(DF32,0) -> 46387 | DF32: 46380 | DH32: =+DH31+DG32-DI32 -> 8519197.8 | DI32: 283973.26 | DJ32: 129064.27 | DK32: =+SUM(DI32:DJ32) -> 413037.53 | DM32: 7 | DN32: =+EOMONTH(DO32,0) -> 46418 | DO32: 46392 | DQ32: =+DQ31-DR32 -> 1026852 | DR32: 39494.31 | DS32: =+DQ31*(DO32-DO31)*$DQ$5/360 -> 15860.124 | DT32: =+SUM(DR32:DS32) -> 55354.434 | EE32: 7 | EF32: =+EOMONTH(EG32,0) -> 46295 | EG32: 46289 | EI32: =+EI31+EH32-EJ32 -> 2744464.6 | EJ32: 40216.85 | EK32: 18279.37 | EM32: =+SUM(EJ32:EL32) -> 58496.22 | EO32: 7 | EP32: =+EOMONTH(EQ32,0) -> 46387 | EQ32: 46372 | ES32: =+ES31-ET32 -> 70912.104 | ET32: 41872.38 | EU32: 782.49 | EV32: =+SUM(ET32:EU32) -> 42654.87 | EX32: 7 | EY32: =+EOMONTH(EZ32,0) -> 46387 | EZ32: 46372 | FB32: =+FB31-FC32 -> 70912.104 | FC32: 41872.38 | FD32: 782.49 | FE32: =+SUM(FC32:FD32) -> 42654.87 | FG32: 7 | FH32: =+EOMONTH(FI32,0) -> 46387 | FI32: 46372 | FK32: =+FK31-FL32 -> 70912.104 | FL32: 41872.38 | FM32: 782.49 | FN32: =+SUM(FL32:FM32) -> 42654.87 | FP32: 7 | FQ32: =+EOMONTH(FR32,0) -> 46387 | FR32: 46372 | FT32: =+FT31-FU32 -> 70912.104 | FU32: 41872.38 | FV32: 782.49 | FW32: =+SUM(FU32:FV32) -> 42654.87 | FY32: 7 | FZ32: =+EOMONTH(GA32,0) -> 46356 | GA32: 46354 | GC32: =+GC31-GD32 -> 142793.83 | GD32: 43116.6 | GE32: 1461.65 | GF32: =+SUM(GD32:GE32) -> 44578.25 | GH32: 7 | GI32: =+EOMONTH(GJ32,0) -> 46356 | GJ32: 46354 | GL32: 142793.83 | GM32: 43116.6 | GN32: 1461.65 | GO32: 44578.25
A33: 8 | B33: =+WEEKNUM(C33,2) -> 18 | C33: =+EOMONTH(C32,1) -> 46142 | E33: =+E32+D33-F33 -> 2.0792373e+08 | F33: =+SUMIF(N:N,C33,R:R)+SUMIF(AD:AD,C33,AH:AH)+SUMIF(AS:AS,C33,AW:AW)+SUMIF(BH:BH,C33,BL:BL)+SUMIF(BW:BW,C33,CA:CA)+SUMIF(BW:BW,C33,CB:CB)+SUMIF(CM:CM,C33,CQ:CQ)+SUMIF(CV:CV,C33,CZ:CZ)+SUMIF(DE:DE,C33,DI:DI)+SUMIF(DN:DN,C33,DR:DR)+SUMIF(DW:DW,C33,EA:EA)+SUMIF(EF:EF,C33,EJ:EJ)+SUMIF(EP:EP,C33,ET:ET)+SUMIF(EY:EY,C33,FC:FC)+SUMIF(FH:FH,C33,FL:FL)+SUMIF(FQ:FQ,C33,FU:FU)+SUMIF(FZ:FZ,C33,GD:GD)+SUMIF(GI:GI,C33,GM:GM) -> 411502.74 | G33: =+SUMIF(N:N,C33,S:S)+SUMIF(N:N,C33,T:T)+SUMIF(AD:AD,C33,AI:AI)+SUMIF(AS:AS,C33,AX:AX)+SUMIF(BH:BH,C33,BM:BM)+SUMIF(BW:BW,C33,CD:CD)+SUMIF(BW:BW,C33,CC:CC)+SUMIF(CM:CM,C33,CR:CR)+SUMIF(CV:CV,C33,DA:DA)+SUMIF(DE:DE,C33,DJ:DJ)+SUMIF(DN:DN,C33,DS:DS)+SUMIF(DX:DX,C33,EB:EB)+SUMIF(EG:EG,C33,EK:EK)+SUMIF(EP:EP,C33,EU:EU)+SUMIF(EY:EY,C33,FD:FD)+SUMIF(FH:FH,C33,FM:FM)+SUMIF(FQ:FQ,C33,FV:FV)+SUMIF(FZ:FZ,C33,GE:GE)+SUMIF(GI:GI,C33,GN:GN) -> 151784.76 | H33: =+SUM(F33:G33) -> 563287.5 | I33: =+H33 -> 563287.5 | J33: BNB Leasing | M33: 8 | N33: =+EOMONTH(O33,0) -> 46265 | O33: =+DATE(YEAR(O32),MONTH(O32)+3,DAY(O32)) -> 46249 | Q33: =+Q32-R33 -> 89605953 | R33: =+$Q$30/25 -> 4072997.9 | S33: =+Q32*Q$5*(O33-O32)/360 -> 1436410.6 | T33: =+$Q$17/$Q$18 -> 471550.55 | U33: =+SUM(R33:T33) -> 5980959 | AC33: 8 | AD33: =+EOMONTH(AE33,0) -> 46446 | AE33: 46420 | AG33: =+AG32+AF33-AH33 -> 930863.19 | AH33: =+AH32 -> 51840.79 | AI33: =+AG32*AG$5*(AE33-AE32)/360 -> 13812.45 | AJ33: =+SUM(AH33:AI33) -> 65653.24 | AR33: 8 | AS33: =+EOMONTH(AT33,0) -> 46356 | AT33: 46346 | AV33: =+AV32+AU33-AW33 -> 14946421 | AW33: 525047.46 | AX33: =+AV32*AV$5*(AT33-AT32)/360 -> 237229.19 | AY33: =+SUM(AW33:AX33) -> 762276.65 | BG33: 8 | BH33: =+EOMONTH(BI33,0) -> 46477 | BI33: 46466 | BK33: =+BK32+BJ33-BL33 -> 37433630 | BL33: =+BL32 -> 5347661.4 | BM33: =+BK32*BK$5*(BI33-BI32)/360 -> 641719.37 | BN33: 82616.23 | BO33: =+SUM(BL33:BN33) -> 6071997 | BV33: 8 | BW33: =+EOMONTH(BX33,0) -> 46418 | BX33: 46407 | BZ33: =+BZ32+BY33-CA33 -> 692837.63 | CA33: 57736.47 | CB33: 2821.4285 | CC33: =+BZ32*BZ$5*(BX33-BX32)/360 -> 11508.803 | CD33: 1642.8395 | CE33: =+SUM(CA33:CD33) -> 73709.541 | CL33: 8 | CM33: =+EOMONTH(CN33,0) -> 46477 | CN33: 46460 | CP33: =+CP32+CO33-CQ33 -> 1043178.7 | CQ33: 104317.86 | CR33: 14082.913 | CS33: =+SUM(CQ33:CR33) -> 118400.77 | CU33: 8 | CV33: =+EOMONTH(CW33,0) -> 46112 | CW33: 46091 | CY33: =+CY32+CX33-CZ33 -> 23217971 | CZ33: 349011.21 | DA33: =+CY32*CY$5*(CW33-CW32)/360 -> 109979.25 | DB33: =+SUM(CZ33:DA33) -> 458990.46 | DD33: 8 | DE33: =+EOMONTH(DF33,0) -> 46477 | DF33: 46471 | DH33: =+DH32+DG33-DI33 -> 8235224.6 | DI33: 283973.26 | DJ33: 124900.9 | DK33: =+SUM(DI33:DJ33) -> 408874.16 | DM33: 8 | DN33: =+EOMONTH(DO33,0) -> 46507 | DO33: 46482 | DQ33: =+DQ32-DR33 -> 987357.66 | DR33: 39494.31 | DS33: =+DQ32*(DO33-DO32)*$DQ$5/360 -> 14940.696 | DT33: =+SUM(DR33:DS33) -> 54435.006 | EE33: 8 | EF33: =+EOMONTH(EG33,0) -> 46387 | EG33: 46380 | EI33: =+EI32+EH33-EJ33 -> 2704247.8 | EJ33: 40216.85 | EK33: 17670.43 | EM33: =+SUM(EJ33:EL33) -> 57887.28 | EO33: 8 | EP33: =+EOMONTH(EQ33,0) -> 46477 | EQ33: 46462 | ES33: =+ES32-ET33 -> 41229.074 | ET33: 29683.03 | EU33: 17605.8 | EV33: =+SUM(ET33:EU33) -> 47288.83 | EX33: 8 | EY33: =+EOMONTH(EZ33,0) -> 46477 | EZ33: 46462 | FB33: =+FB32-FC33 -> 41229.074 | FC33: 29683.03 | FD33: 17605.8 | FE33: =+SUM(FC33:FD33) -> 47288.83 | FG33: 8 | FH33: =+EOMONTH(FI33,0) -> 46477 | FI33: 46462 | FK33: =+FK32-FL33 -> 41229.074 | FL33: 29683.03 | FM33: 17605.8 | FN33: =+SUM(FL33:FM33) -> 47288.83 | FP33: 8 | FQ33: =+EOMONTH(FR33,0) -> 46477 | FR33: 46462 | FT33: =+FT32-FU33 -> 41229.074 | FU33: 29683.03 | FV33: 17605.8 | FW33: =+SUM(FU33:FV33) -> 47288.83 | FY33: 8 | FZ33: =+EOMONTH(GA33,0) -> 46446 | GA33: 46444 | GC33: =+GC32-GD33 -> 98761.04 | GD33: 44032.79 | GE33: 814.9 | GF33: =+SUM(GD33:GE33) -> 44847.69 | GH33: 8 | GI33: =+EOMONTH(GJ33,0) -> 46446 | GJ33: 46444 | GL33: 98761.04 | GM33: 44032.79 | GN33: 814.9 | GO33: 44847.69
A34: 9 | B34: =+WEEKNUM(C34,2) -> 22 | C34: =+EOMONTH(C33,1) -> 46173 | E34: =+E33+D34-F34 -> 2.0344988e+08 | F34: =+SUMIF(N:N,C34,R:R)+SUMIF(AD:AD,C34,AH:AH)+SUMIF(AS:AS,C34,AW:AW)+SUMIF(BH:BH,C34,BL:BL)+SUMIF(BW:BW,C34,CA:CA)+SUMIF(BW:BW,C34,CB:CB)+SUMIF(CM:CM,C34,CQ:CQ)+SUMIF(CV:CV,C34,CZ:CZ)+SUMIF(DE:DE,C34,DI:DI)+SUMIF(DN:DN,C34,DR:DR)+SUMIF(DW:DW,C34,EA:EA)+SUMIF(EF:EF,C34,EJ:EJ)+SUMIF(EP:EP,C34,ET:ET)+SUMIF(EY:EY,C34,FC:FC)+SUMIF(FH:FH,C34,FL:FL)+SUMIF(FQ:FQ,C34,FU:FU)+SUMIF(FZ:FZ,C34,GD:GD)+SUMIF(GI:GI,C34,GM:GM) -> 4473849.9 | G34: =+SUMIF(N:N,C34,S:S)+SUMIF(N:N,C34,T:T)+SUMIF(AD:AD,C34,AI:AI)+SUMIF(AS:AS,C34,AX:AX)+SUMIF(BH:BH,C34,BM:BM)+SUMIF(BW:BW,C34,CD:CD)+SUMIF(BW:BW,C34,CC:CC)+SUMIF(CM:CM,C34,CR:CR)+SUMIF(CV:CV,C34,DA:DA)+SUMIF(DE:DE,C34,DJ:DJ)+SUMIF(DN:DN,C34,DS:DS)+SUMIF(DX:DX,C34,EB:EB)+SUMIF(EG:EG,C34,EK:EK)+SUMIF(EP:EP,C34,EU:EU)+SUMIF(EY:EY,C34,FD:FD)+SUMIF(FH:FH,C34,FM:FM)+SUMIF(FQ:FQ,C34,FV:FV)+SUMIF(FZ:FZ,C34,GE:GE)+SUMIF(GI:GI,C34,GN:GN) -> 2288641 | H34: =+SUM(F34:G34) -> 6762490.8 | M34: 9 | N34: =+EOMONTH(O34,0) -> 46356 | O34: =+DATE(YEAR(O33),MONTH(O33)+3,DAY(O33)) -> 46341 | Q34: =+Q33-R34 -> 85532956 | R34: =+$Q$30/25 -> 4072997.9 | S34: =+Q33*Q$5*(O34-O33)/360 -> 1373958 | T34: =+$Q$17/$Q$18 -> 471550.55 | U34: =+SUM(R34:T34) -> 5918506.4 | AC34: 9 | AD34: =+EOMONTH(AE34,0) -> 46538 | AE34: 46509 | AG34: =+AG33+AF34-AH34 -> 879022.4 | AH34: =+AH33 -> 51840.79 | AI34: =+AG33*AG$5*(AE34-AE33)/360 -> 12657.154 | AJ34: =+SUM(AH34:AI34) -> 64497.944 | AR34: 9 | AS34: =+EOMONTH(AT34,0) -> 46446 | AT34: 46438 | AV34: =+AV33+AU34-AW34 -> 14421374 | AW34: 525047.46 | AX34: =+AV33*AV$5*(AT34-AT33)/360 -> 229178.46 | AY34: =+SUM(AW34:AX34) -> 754225.92 | BG34: 9 | BH34: =+EOMONTH(BI34,0) -> 46568 | BI34: 46558 | BK34: =+BK33+BJ34-BL34 -> 32085968 | BL34: =+BL33 -> 5347661.4 | BM34: =+BK33*BK$5*(BI34-BI33)/360 -> 573982.32 | BN34: 82616.23 | BO34: =+SUM(BL34:BN34) -> 6004260 | BV34: 9 | BW34: =+EOMONTH(BX34,0) -> 46507 | BX34: 46497 | BZ34: =+BZ33+BY34-CA34 -> 635101.16 | CA34: 57736.47 | CB34: 2821.4285 | CC34: =+BZ33*BZ$5*(BX34-BX33)/360 -> 10392.564 | CD34: 1642.8395 | CE34: =+SUM(CA34:CD34) -> 72593.302 | CL34: 9 | CM34: =+EOMONTH(CN34,0) -> 46568 | CN34: 46552 | CP34: =+CP33+CO34-CQ34 -> 938860.83 | CQ34: 104317.86 | CR34: 12796.326 | CS34: =+SUM(CQ34:CR34) -> 117114.19 | CU34: 9 | CV34: =+EOMONTH(CW34,0) -> 46142 | CW34: 46122 | CY34: =+CY33+CX34-CZ34 -> 22868960 | CZ34: 349011.21 | DA34: =+CY33*CY$5*(CW34-CW33)/360 -> 119959.52 | DB34: =+SUM(CZ34:DA34) -> 468970.73 | DD34: 9 | DE34: =+EOMONTH(DF34,0) -> 46568 | DF34: 46562 | DH34: =+DH33+DG34-DI34 -> 7951251.3 | DI34: 283973.26 | DJ34: 120737.54 | DK34: =+SUM(DI34:DJ34) -> 404710.8 | DM34: 9 | DN34: =+EOMONTH(DO34,0) -> 46599 | DO34: 46573 | DQ34: =+DQ33-DR34 -> 947863.35 | DR34: 39494.31 | DS34: =+DQ33*(DO34-DO33)*$DQ$5/360 -> 14525.677 | DT34: =+SUM(DR34:DS34) -> 54019.987 | EE34: 9 | EF34: =+EOMONTH(EG34,0) -> 46477 | EG34: 46471 | EI34: =+EI33+EH34-EJ34 -> 2664030.9 | EJ34: 40216.85 | EK34: 17061.49 | EM34: =+SUM(EJ34:EL34) -> 57278.34 | EO34: 9 | EP34: =+EOMONTH(EQ34,0) -> 46568 | EQ34: 46552 | ES34: =+ES33-ET34 -> 10293.844 | ET34: 30935.23 | EU34: 14697.99 | EV34: =+SUM(ET34:EU34) -> 45633.22 | EX34: 9 | EY34: =+EOMONTH(EZ34,0) -> 46568 | EZ34: 46552 | FB34: =+FB33-FC34 -> 10293.844 | FC34: 30935.23 | FD34: 14697.99 | FE34: =+SUM(FC34:FD34) -> 45633.22 | FG34: 9 | FH34: =+EOMONTH(FI34,0) -> 46568 | FI34: 46552 | FK34: =+FK33-FL34 -> 10293.844 | FL34: 30935.23 | FM34: 14697.99 | FN34: =+SUM(FL34:FM34) -> 45633.22 | FP34: 9 | FQ34: =+EOMONTH(FR34,0) -> 46568 | FR34: 46552 | FT34: =+FT33-FU34 -> 10293.844 | FU34: 30935.23 | FV34: 14697.99 | FW34: =+SUM(FU34:FV34) -> 45633.22 | FY34: 9 | FZ34: =+EOMONTH(GA34,0) -> 46538 | GA34: 46534 | GC34: =+GC33-GD34 -> 70279.53 | GD34: 28481.51 | GE34: 18828.9 | GF34: =+SUM(GD34:GE34) -> 47310.41 | GH34: 9 | GI34: =+EOMONTH(GJ34,0) -> 46538 | GJ34: 46534 | GL34: 70279.53 | GM34: 28481.51 | GN34: 18828.9 | GO34: 47310.41
A35: 10 | B35: =+WEEKNUM(C35,2) -> 27 | C35: =+EOMONTH(C34,1) -> 46203 | E35: =+E34+D35-F35 -> 2.0273337e+08 | F35: =+SUMIF(N:N,C35,R:R)+SUMIF(AD:AD,C35,AH:AH)+SUMIF(AS:AS,C35,AW:AW)+SUMIF(BH:BH,C35,BL:BL)+SUMIF(BW:BW,C35,CA:CA)+SUMIF(BW:BW,C35,CB:CB)+SUMIF(CM:CM,C35,CQ:CQ)+SUMIF(CV:CV,C35,CZ:CZ)+SUMIF(DE:DE,C35,DI:DI)+SUMIF(DN:DN,C35,DR:DR)+SUMIF(DW:DW,C35,EA:EA)+SUMIF(EF:EF,C35,EJ:EJ)+SUMIF(EP:EP,C35,ET:ET)+SUMIF(EY:EY,C35,FC:FC)+SUMIF(FH:FH,C35,FL:FL)+SUMIF(FQ:FQ,C35,FU:FU)+SUMIF(FZ:FZ,C35,GD:GD)+SUMIF(GI:GI,C35,GM:GM) -> 716508.09 | G35: =+SUMIF(N:N,C35,S:S)+SUMIF(N:N,C35,T:T)+SUMIF(AD:AD,C35,AI:AI)+SUMIF(AS:AS,C35,AX:AX)+SUMIF(BH:BH,C35,BM:BM)+SUMIF(BW:BW,C35,CD:CD)+SUMIF(BW:BW,C35,CC:CC)+SUMIF(CM:CM,C35,CR:CR)+SUMIF(CV:CV,C35,DA:DA)+SUMIF(DE:DE,C35,DJ:DJ)+SUMIF(DN:DN,C35,DS:DS)+SUMIF(DX:DX,C35,EB:EB)+SUMIF(EG:EG,C35,EK:EK)+SUMIF(EP:EP,C35,EU:EU)+SUMIF(EY:EY,C35,FD:FD)+SUMIF(FH:FH,C35,FM:FM)+SUMIF(FQ:FQ,C35,FV:FV)+SUMIF(FZ:FZ,C35,GE:GE)+SUMIF(GI:GI,C35,GN:GN) -> 1102397.5 | H35: =+SUM(F35:G35) -> 1818905.6 | I35: 0 | M35: 10 | N35: =+EOMONTH(O35,0) -> 46446 | O35: =+DATE(YEAR(O34),MONTH(O34)+3,DAY(O34)) -> 46433 | Q35: =+Q34-R35 -> 81459958 | R35: =+$Q$30/25 -> 4072997.9 | S35: =+Q34*Q$5*(O35-O34)/360 -> 1311505.3 | T35: =+$Q$17/$Q$18 -> 471550.55 | U35: =+SUM(R35:T35) -> 5856053.7 | AC35: 10 | AD35: =+EOMONTH(AE35,0) -> 46630 | AE35: 46601 | AG35: =+AG34+AF35-AH35 -> 827181.61 | AH35: =+AH34 -> 51840.79 | AI35: =+AG34*AG$5*(AE35-AE34)/360 -> 12355.148 | AJ35: =+SUM(AH35:AI35) -> 64195.938 | AR35: 10 | AS35: =+EOMONTH(AT35,0) -> 46538 | AT35: 46527 | AV35: =+AV34+AU35-AW35 -> 13896326 | AW35: 525047.46 | AX35: =+AV34*AV$5*(AT35-AT34)/360 -> 213917.04 | AY35: =+SUM(AW35:AX35) -> 738964.51 | BG35: 10 | BH35: =+EOMONTH(BI35,0) -> 46660 | BI35: 46650 | BK35: =+BK34+BJ35-BL35 -> 26738307 | BL35: =+BL34 -> 5347661.4 | BM35: =+BK34*BK$5*(BI35-BI34)/360 -> 491984.85 | BN35: 82616.23 | BO35: =+SUM(BL35:BN35) -> 5922262.5 | BV35: 10 | BW35: =+EOMONTH(BX35,0) -> 46599 | BX35: 46588 | BZ35: =+BZ34+BY35-CA35 -> 577364.69 | CA35: 57736.47 | CB35: 2821.4285 | CC35: =+BZ34*BZ$5*(BX35-BX34)/360 -> 9632.3676 | CD35: 1642.8395 | CE35: =+SUM(CA35:CD35) -> 71833.106 | CL35: 10 | CM35: =+EOMONTH(CN35,0) -> 46660 | CN35: 46644 | CP35: =+CP34+CO35-CQ35 -> 834542.97 | CQ35: 104317.86 | CR35: 11196.785 | CS35: =+SUM(CQ35:CR35) -> 115514.65 | CU35: 10 | CV35: =+EOMONTH(CW35,0) -> 46173 | CW35: 46152 | CY35: =+CY34+CX35-CZ35 -> 22519949 | CZ35: 349011.21 | DA35: =+CY34*CY$5*(CW35-CW34)/360 -> 114344.8 | DB35: =+SUM(CZ35:DA35) -> 463356.01 | DD35: 10 | DE35: =+EOMONTH(DF35,0) -> 46660 | DF35: 46653 | DH35: =+DH34+DG35-DI35 -> 7667278.1 | DI35: 283973.26 | DJ35: 116574.18 | DK35: =+SUM(DI35:DJ35) -> 400547.44 | DM35: 10 | DN35: =+EOMONTH(DO35,0) -> 46691 | DO35: 46665 | DQ35: =+DQ34-DR35 -> 908369.04 | DR35: 39494.31 | DS35: =+DQ34*(DO35-DO34)*$DQ$5/360 -> 14097.888 | DT35: =+SUM(DR35:DS35) -> 53592.198 | EE35: 10 | EF35: =+EOMONTH(EG35,0) -> 46568 | EG35: 46562 | EI35: =+EI34+EH35-EJ35 -> 2623814.1 | EJ35: 40216.85 | EK35: 16452.55 | EM35: =+SUM(EJ35:EL35) -> 56669.4 | EO35: 10 | EP35: =+EOMONTH(EQ35,0) -> 46568 | EQ35: 46552 | ES35: =+ES34-ET35 -> 0.0040000001 | ET35: 10293.84 | EU35: 0 | EV35: =+SUM(ET35:EU35) -> 10293.84 | EX35: 10 | EY35: =+EOMONTH(EZ35,0) -> 46568 | EZ35: 46552 | FB35: =+FB34-FC35 -> 0.0040000001 | FC35: 10293.84 | FD35: 0 | FE35: =+SUM(FC35:FD35) -> 10293.84 | FG35: 10 | FH35: =+EOMONTH(FI35,0) -> 46568 | FI35: 46552 | FK35: =+FK34-FL35 -> 0.0040000001 | FL35: 10293.84 | FM35: 0 | FN35: =+SUM(FL35:FM35) -> 10293.84 | FP35: 10 | FQ35: =+EOMONTH(FR35,0) -> 46568 | FR35: 46552 | FT35: =+FT34-FU35 -> 0.0040000001 | FU35: 10293.84 | FV35: 0 | FW35: =+SUM(FU35:FV35) -> 10293.84 | FY35: 10 | FZ35: =+EOMONTH(GA35,0) -> 46630 | GA35: 46624 | GC35: =+GC34-GD35 -> 40596.5 | GD35: 29683.03 | GE35: 12324.06 | GF35: =+SUM(GD35:GE35) -> 42007.09 | GH35: 10 | GI35: =+EOMONTH(GJ35,0) -> 46630 | GJ35: 46624 | GL35: 40596.5 | GM35: 29683.03 | GN35: 12324.06 | GO35: 42007.09
A36: 11 | B36: =+WEEKNUM(C36,2) -> 31 | C36: =+EOMONTH(C35,1) -> 46234 | E36: =+E35+D36-F36 -> 2.0108724e+08 | F36: =+SUMIF(N:N,C36,R:R)+SUMIF(AD:AD,C36,AH:AH)+SUMIF(AS:AS,C36,AW:AW)+SUMIF(BH:BH,C36,BL:BL)+SUMIF(BW:BW,C36,CA:CA)+SUMIF(BW:BW,C36,CB:CB)+SUMIF(CM:CM,C36,CQ:CQ)+SUMIF(CV:CV,C36,CZ:CZ)+SUMIF(DE:DE,C36,DI:DI)+SUMIF(DN:DN,C36,DR:DR)+SUMIF(DW:DW,C36,EA:EA)+SUMIF(EF:EF,C36,EJ:EJ)+SUMIF(EP:EP,C36,ET:ET)+SUMIF(EY:EY,C36,FC:FC)+SUMIF(FH:FH,C36,FL:FL)+SUMIF(FQ:FQ,C36,FU:FU)+SUMIF(FZ:FZ,C36,GD:GD)+SUMIF(GI:GI,C36,GM:GM) -> 1646129.9 | G36: =+SUMIF(N:N,C36,S:S)+SUMIF(N:N,C36,T:T)+SUMIF(AD:AD,C36,AI:AI)+SUMIF(AS:AS,C36,AX:AX)+SUMIF(BH:BH,C36,BM:BM)+SUMIF(BW:BW,C36,CD:CD)+SUMIF(BW:BW,C36,CC:CC)+SUMIF(CM:CM,C36,CR:CR)+SUMIF(CV:CV,C36,DA:DA)+SUMIF(DE:DE,C36,DJ:DJ)+SUMIF(DN:DN,C36,DS:DS)+SUMIF(DX:DX,C36,EB:EB)+SUMIF(EG:EG,C36,EK:EK)+SUMIF(EP:EP,C36,EU:EU)+SUMIF(EY:EY,C36,FD:FD)+SUMIF(FH:FH,C36,FM:FM)+SUMIF(FQ:FQ,C36,FV:FV)+SUMIF(FZ:FZ,C36,GE:GE)+SUMIF(GI:GI,C36,GN:GN) -> 141929.78 | H36: =+SUM(F36:G36) -> 1788059.7 | M36: 11 | N36: =+EOMONTH(O36,0) -> 46538 | O36: =+DATE(YEAR(O35),MONTH(O35)+3,DAY(O35)) -> 46522 | Q36: =+Q35-R36 -> 77386960 | R36: =+$Q$30/25 -> 4072997.9 | S36: =+Q35*Q$5*(O36-O35)/360 -> 1208322.7 | T36: =+$Q$17/$Q$18 -> 471550.55 | U36: =+SUM(R36:T36) -> 5752871.1 | AC36: 11 | AD36: =+EOMONTH(AE36,0) -> 46721 | AE36: 46693 | AG36: =+AG35+AF36-AH36 -> 775340.82 | AH36: =+AH35 -> 51840.79 | AI36: =+AG35*AG$5*(AE36-AE35)/360 -> 11626.497 | AJ36: =+SUM(AH36:AI36) -> 63467.287 | AR36: 11 | AS36: =+EOMONTH(AT36,0) -> 46630 | AT36: 46619 | AV36: =+AV35+AU36-AW36 -> 13371279 | AW36: 525047.46 | AX36: =+AV35*AV$5*(AT36-AT35)/360 -> 213077 | AY36: =+SUM(AW36:AX36) -> 738124.47 | BG36: 11 | BH36: =+EOMONTH(BI36,0) -> 46752 | BI36: 46741 | BK36: =+BK35+BJ36-BL36 -> 21390646 | BL36: =+BL35 -> 5347661.4 | BM36: =+BK35*BK$5*(BI36-BI35)/360 -> 405530.99 | BN36: 82616.23 | BO36: =+SUM(BL36:BN36) -> 5835808.6 | BV36: 11 | BW36: =+EOMONTH(BX36,0) -> 46691 | BX36: 46680 | BZ36: =+BZ35+BY36-CA36 -> 519628.22 | CA36: 57736.47 | CB36: 2821.4285 | CC36: =+BZ35*BZ$5*(BX36-BX35)/360 -> 8852.9252 | CD36: 1642.8395 | CE36: =+SUM(CA36:CD36) -> 71053.663 | CL36: 11 | CM36: =+EOMONTH(CN36,0) -> 46752 | CN36: 46735 | CP36: =+CP35+CO36-CQ36 -> 730225.11 | CQ36: 104317.86 | CR36: 9492.9269 | CS36: =+SUM(CQ36:CR36) -> 113810.79 | CU36: 11 | CV36: =+EOMONTH(CW36,0) -> 46203 | CW36: 46183 | CY36: =+CY35+CX36-CZ36 -> 22170937 | CZ36: 349011.21 | DA36: =+CY35*CY$5*(CW36-CW35)/360 -> 116353.07 | DB36: =+SUM(CZ36:DA36) -> 465364.28 | DD36: 11 | DE36: =+EOMONTH(DF36,0) -> 46752 | DF36: 46744 | DH36: =+DH35+DG36-DI36 -> 7383304.8 | DI36: 283973.26 | DJ36: 112410.82 | DK36: =+SUM(DI36:DJ36) -> 396384.08 | DM36: 11 | DN36: =+EOMONTH(DO36,0) -> 46783 | DO36: 46757 | DQ36: =+DQ35-DR36 -> 868874.73 | DR36: 39494.31 | DS36: =+DQ35*(DO36-DO35)*$DQ$5/360 -> 13510.476 | DT36: =+SUM(DR36:DS36) -> 53004.786 | EE36: 11 | EF36: =+EOMONTH(EG36,0) -> 46660 | EG36: 46653 | EI36: =+EI35+EH36-EJ36 -> 2583597.2 | EJ36: 40216.85 | EK36: 15843.61 | EM36: =+SUM(EJ36:EL36) -> 56060.46 | FY36: 11 | FZ36: =+EOMONTH(GA36,0) -> 46721 | GA36: 46714 | GC36: =+GC35-GD36 -> 10293.84 | GD36: 30302.66 | GE36: 16975.03 | GF36: =+SUM(GD36:GE36) -> 47277.69 | GH36: 11 | GI36: =+EOMONTH(GJ36,0) -> 46721 | GJ36: 46714 | GL36: 10293.84 | GM36: 30302.66 | GN36: 16975.03 | GO36: 47277.69
A37: 12 | B37: =+WEEKNUM(C37,2) -> 36 | C37: =+EOMONTH(C36,1) -> 46265 | E37: =+E36+D37-F37 -> 1.9476928e+08 | F37: =+SUMIF(N:N,C37,R:R)+SUMIF(AD:AD,C37,AH:AH)+SUMIF(AS:AS,C37,AW:AW)+SUMIF(BH:BH,C37,BL:BL)+SUMIF(BW:BW,C37,CA:CA)+SUMIF(BW:BW,C37,CB:CB)+SUMIF(CM:CM,C37,CQ:CQ)+SUMIF(CV:CV,C37,CZ:CZ)+SUMIF(DE:DE,C37,DI:DI)+SUMIF(DN:DN,C37,DR:DR)+SUMIF(DW:DW,C37,EA:EA)+SUMIF(EF:EF,C37,EJ:EJ)+SUMIF(EP:EP,C37,ET:ET)+SUMIF(EY:EY,C37,FC:FC)+SUMIF(FH:FH,C37,FL:FL)+SUMIF(FQ:FQ,C37,FU:FU)+SUMIF(FZ:FZ,C37,GD:GD)+SUMIF(GI:GI,C37,GM:GM) -> 6317963.4 | G37: =+SUMIF(N:N,C37,S:S)+SUMIF(N:N,C37,T:T)+SUMIF(AD:AD,C37,AI:AI)+SUMIF(AS:AS,C37,AX:AX)+SUMIF(BH:BH,C37,BM:BM)+SUMIF(BW:BW,C37,CD:CD)+SUMIF(BW:BW,C37,CC:CC)+SUMIF(CM:CM,C37,CR:CR)+SUMIF(CV:CV,C37,DA:DA)+SUMIF(DE:DE,C37,DJ:DJ)+SUMIF(DN:DN,C37,DS:DS)+SUMIF(DX:DX,C37,EB:EB)+SUMIF(EG:EG,C37,EK:EK)+SUMIF(EP:EP,C37,EU:EU)+SUMIF(EY:EY,C37,FD:FD)+SUMIF(FH:FH,C37,FM:FM)+SUMIF(FQ:FQ,C37,FV:FV)+SUMIF(FZ:FZ,C37,GE:GE)+SUMIF(GI:GI,C37,GN:GN) -> 2279068.4 | H37: =+SUM(F37:G37) -> 8597031.8 | M37: 12 | N37: =+EOMONTH(O37,0) -> 46630 | O37: =+DATE(YEAR(O36),MONTH(O36)+3,DAY(O36)) -> 46614 | Q37: =+Q36-R37 -> 73313962 | R37: =+$Q$30/25 -> 4072997.9 | S37: =+Q36*Q$5*(O37-O36)/360 -> 1186600 | T37: =+$Q$17/$Q$18 -> 471550.55 | U37: =+SUM(R37:T37) -> 5731148.5 | AC37: 12 | AD37: =+EOMONTH(AE37,0) -> 46812 | AE37: 46785 | AG37: =+AG36+AF37-AH37 -> 723500.03 | AH37: =+AH36 -> 51840.79 | AI37: =+AG36*AG$5*(AE37-AE36)/360 -> 10897.846 | AJ37: =+SUM(AH37:AI37) -> 62738.636 | AR37: 12 | AS37: =+EOMONTH(AT37,0) -> 46721 | AT37: 46711 | AV37: =+AV36+AU37-AW37 -> 12846231 | AW37: 525047.46 | AX37: =+AV36*AV$5*(AT37-AT36)/360 -> 205026.27 | AY37: =+SUM(AW37:AX37) -> 730073.74 | BG37: 12 | BH37: =+EOMONTH(BI37,0) -> 46843 | BI37: 46832 | BK37: =+BK36+BJ37-BL37 -> 16042984 | BL37: =+BL36 -> 5347661.4 | BM37: =+BK36*BK$5*(BI37-BI36)/360 -> 324424.79 | BN37: 82616.23 | BO37: =+SUM(BL37:BN37) -> 5754702.4 | BV37: 12 | BW37: =+EOMONTH(BX37,0) -> 46783 | BX37: 46772 | BZ37: =+BZ36+BY37-CA37 -> 461891.75 | CA37: 57736.47 | CB37: 2821.4285 | CC37: =+BZ36*BZ$5*(BX37-BX36)/360 -> 7967.6327 | CD37: 1642.8395 | CE37: =+SUM(CA37:CD37) -> 70168.371 | CL37: 12 | CM37: =+EOMONTH(CN37,0) -> 46843 | CN37: 46826 | CP37: =+CP36+CO37-CQ37 -> 625907.25 | CQ37: 104317.86 | CR37: 7910.7727 | CS37: =+SUM(CQ37:CR37) -> 112228.63 | CU37: 12 | CV37: =+EOMONTH(CW37,0) -> 46234 | CW37: 46213 | CY37: =+CY36+CX37-CZ37 -> 20587299 | CZ37: 1583638.4 | DA37: =+CY36*CY$5*(CW37-CW36)/360 -> 110854.69 | DB37: =+SUM(CZ37:DA37) -> 1694493.1 | DD37: 12 | DE37: =+EOMONTH(DF37,0) -> 46843 | DF37: 46835 | DH37: =+DH36+DG37-DI37 -> 7099331.5 | DI37: 283973.26 | DJ37: 108247.45 | DK37: =+SUM(DI37:DJ37) -> 392220.71 | DM37: 12 | DN37: =+EOMONTH(DO37,0) -> 46873 | DO37: 46848 | DQ37: =+DQ36-DR37 -> 829380.42 | DR37: 39494.31 | DS37: =+DQ36*(DO37-DO36)*$DQ$5/360 -> 12782.595 | DT37: =+SUM(DR37:DS37) -> 52276.905 | EE37: 12 | EF37: =+EOMONTH(EG37,0) -> 46752 | EG37: 46744 | EI37: =+EI36+EH37-EJ37 -> 2543380.4 | EJ37: 40216.85 | EK37: 15234.68 | EM37: =+SUM(EJ37:EL37) -> 55451.53 | FY37: 12 | FZ37: =+EOMONTH(GA37,0) -> 46721 | GA37: 46714 | GC37: =+GC36-GD37 -> 4.3655746e-11 | GD37: 10293.84 | GF37: =+SUM(GD37:GE37) -> 10293.84 | GH37: 12 | GI37: =+EOMONTH(GJ37,0) -> 46721 | GJ37: 46714 | GL37: 4.3655746e-11 | GM37: 10293.84 | GO37: 10293.84
A38: 13 | B38: =+WEEKNUM(C38,2) -> 40 | C38: =+EOMONTH(C37,1) -> 46295 | E38: =+E37+D38-F38 -> 1.8724547e+08 | F38: =+SUMIF(N:N,C38,R:R)+SUMIF(AD:AD,C38,AH:AH)+SUMIF(AS:AS,C38,AW:AW)+SUMIF(BH:BH,C38,BL:BL)+SUMIF(BW:BW,C38,CA:CA)+SUMIF(BW:BW,C38,CB:CB)+SUMIF(CM:CM,C38,CQ:CQ)+SUMIF(CV:CV,C38,CZ:CZ)+SUMIF(DE:DE,C38,DI:DI)+SUMIF(DN:DN,C38,DR:DR)+SUMIF(DW:DW,C38,EA:EA)+SUMIF(EF:EF,C38,EJ:EJ)+SUMIF(EP:EP,C38,ET:ET)+SUMIF(EY:EY,C38,FC:FC)+SUMIF(FH:FH,C38,FL:FL)+SUMIF(FQ:FQ,C38,FU:FU)+SUMIF(FZ:FZ,C38,GD:GD)+SUMIF(GI:GI,C38,GM:GM) -> 7523811.8 | G38: =+SUMIF(N:N,C38,S:S)+SUMIF(N:N,C38,T:T)+SUMIF(AD:AD,C38,AI:AI)+SUMIF(AS:AS,C38,AX:AX)+SUMIF(BH:BH,C38,BM:BM)+SUMIF(BW:BW,C38,CD:CD)+SUMIF(BW:BW,C38,CC:CC)+SUMIF(CM:CM,C38,CR:CR)+SUMIF(CV:CV,C38,DA:DA)+SUMIF(DE:DE,C38,DJ:DJ)+SUMIF(DN:DN,C38,DS:DS)+SUMIF(DX:DX,C38,EB:EB)+SUMIF(EG:EG,C38,EK:EK)+SUMIF(EP:EP,C38,EU:EU)+SUMIF(EY:EY,C38,FD:FD)+SUMIF(FH:FH,C38,FM:FM)+SUMIF(FQ:FQ,C38,FV:FV)+SUMIF(FZ:FZ,C38,GE:GE)+SUMIF(GI:GI,C38,GN:GN) -> 1074572.9 | H38: =+SUM(F38:G38) -> 8598384.8 | I38: =+DB26 -> 483396.52 | J38: Ganadero | M38: 13 | N38: =+EOMONTH(O38,0) -> 46721 | O38: =+DATE(YEAR(O37),MONTH(O37)+3,DAY(O37)) -> 46706 | Q38: =+Q37-R38 -> 69240964 | R38: =+$Q$30/25 -> 4072997.9 | S38: =+Q37*Q$5*(O38-O37)/360 -> 1124147.4 | T38: =+$Q$17/$Q$18 -> 471550.55 | U38: =+SUM(R38:T38) -> 5668695.8 | AC38: 13 | AD38: =+EOMONTH(AE38,0) -> 46904 | AE38: 46875 | AG38: =+AG37+AF38-AH38 -> 671659.24 | AH38: =+AH37 -> 51840.79 | AI38: =+AG37*AG$5*(AE38-AE37)/360 -> 9948.1254 | AJ38: =+SUM(AH38:AI38) -> 61788.915 | AR38: 13 | AS38: =+EOMONTH(AT38,0) -> 46812 | AT38: 46803 | AV38: =+AV37+AU38-AW38 -> 12321184 | AW38: 525047.46 | AX38: =+AV37*AV$5*(AT38-AT37)/360 -> 196975.55 | AY38: =+SUM(AW38:AX38) -> 722023.01 | BG38: 13 | BH38: =+EOMONTH(BI38,0) -> 46934 | BI38: 46924 | BK38: =+BK37+BJ38-BL38 -> 10695323 | BL38: =+BL37 -> 5347661.4 | BM38: =+BK37*BK$5*(BI38-BI37)/360 -> 245992.42 | BN38: 82616.23 | BO38: =+SUM(BL38:BN38) -> 5676270.1 | BV38: 13 | BW38: =+EOMONTH(BX38,0) -> 46873 | BX38: 46863 | BZ38: =+BZ37+BY38-CA38 -> 404155.28 | CA38: 57736.47 | CB38: 2821.4285 | CC38: =+BZ37*BZ$5*(BX38-BX37)/360 -> 7005.3582 | CD38: 1642.8395 | CE38: =+SUM(CA38:CD38) -> 69206.096 | CL38: 13 | CM38: =+EOMONTH(CN38,0) -> 46934 | CN38: 46918 | CP38: =+CP37+CO38-CQ38 -> 521589.39 | CQ38: 104317.86 | CR38: 6398.1638 | CS38: =+SUM(CQ38:CR38) -> 110716.02 | CU38: 13 | CV38: =+EOMONTH(CW38,0) -> 46265 | CW38: 46244 | CY38: =+CY37+CX38-CZ38 -> 19003661 | CZ38: 1583638.4 | DA38: =+CY37*CY$5*(CW38-CW37)/360 -> 106367.71 | DB38: =+SUM(CZ38:DA38) -> 1690006.1 | DD38: 13 | DE38: =+EOMONTH(DF38,0) -> 46934 | DF38: 46926 | DH38: =+DH37+DG38-DI38 -> 6815358.3 | DI38: 283973.26 | DJ38: 104084.09 | DK38: =+SUM(DI38:DJ38) -> 388057.35 | DM38: 13 | DN38: =+EOMONTH(DO38,0) -> 46965 | DO38: 46939 | DQ38: =+DQ37-DR38 -> 789886.11 | DR38: 39494.31 | DS38: =+DQ37*(DO38-DO37)*$DQ$5/360 -> 12201.568 | DT38: =+SUM(DR38:DS38) -> 51695.878 | EE38: 13 | EF38: =+EOMONTH(EG38,0) -> 46843 | EG38: 46835 | EI38: =+EI37+EH38-EJ38 -> 2503163.5 | EJ38: 40216.85 | EK38: 14625.74 | EM38: =+SUM(EJ38:EL38) -> 54842.59
A39: 14 | B39: =+WEEKNUM(C39,2) -> 44 | C39: =+EOMONTH(C38,1) -> 46326 | E39: =+E38+D39-F39 -> 1.8556178e+08 | F39: =+SUMIF(N:N,C39,R:R)+SUMIF(AD:AD,C39,AH:AH)+SUMIF(AS:AS,C39,AW:AW)+SUMIF(BH:BH,C39,BL:BL)+SUMIF(BW:BW,C39,CA:CA)+SUMIF(BW:BW,C39,CB:CB)+SUMIF(CM:CM,C39,CQ:CQ)+SUMIF(CV:CV,C39,CZ:CZ)+SUMIF(DE:DE,C39,DI:DI)+SUMIF(DN:DN,C39,DR:DR)+SUMIF(DW:DW,C39,EA:EA)+SUMIF(EF:EF,C39,EJ:EJ)+SUMIF(EP:EP,C39,ET:ET)+SUMIF(EY:EY,C39,FC:FC)+SUMIF(FH:FH,C39,FL:FL)+SUMIF(FQ:FQ,C39,FU:FU)+SUMIF(FZ:FZ,C39,GD:GD)+SUMIF(GI:GI,C39,GM:GM) -> 1683690.6 | G39: =+SUMIF(N:N,C39,S:S)+SUMIF(N:N,C39,T:T)+SUMIF(AD:AD,C39,AI:AI)+SUMIF(AS:AS,C39,AX:AX)+SUMIF(BH:BH,C39,BM:BM)+SUMIF(BW:BW,C39,CD:CD)+SUMIF(BW:BW,C39,CC:CC)+SUMIF(CM:CM,C39,CR:CR)+SUMIF(CV:CV,C39,DA:DA)+SUMIF(DE:DE,C39,DJ:DJ)+SUMIF(DN:DN,C39,DS:DS)+SUMIF(DX:DX,C39,EB:EB)+SUMIF(EG:EG,C39,EK:EK)+SUMIF(EP:EP,C39,EU:EU)+SUMIF(EY:EY,C39,FD:FD)+SUMIF(FH:FH,C39,FM:FM)+SUMIF(FQ:FQ,C39,FV:FV)+SUMIF(FZ:FZ,C39,GE:GE)+SUMIF(GI:GI,C39,GN:GN) -> 117405.8 | H39: =+SUM(F39:G39) -> 1801096.4 | M39: 14 | N39: =+EOMONTH(O39,0) -> 46812 | O39: =+DATE(YEAR(O38),MONTH(O38)+3,DAY(O38)) -> 46798 | Q39: =+Q38-R39 -> 65167966 | R39: =+$Q$30/25 -> 4072997.9 | S39: =+Q38*Q$5*(O39-O38)/360 -> 1061694.8 | T39: =+$Q$17/$Q$18 -> 471550.55 | U39: =+SUM(R39:T39) -> 5606243.2 | AC39: 14 | AD39: =+EOMONTH(AE39,0) -> 46996 | AE39: 46967 | AG39: =+AG38+AF39-AH39 -> 619818.45 | AH39: =+AH38 -> 51840.79 | AI39: =+AG38*AG$5*(AE39-AE38)/360 -> 9440.5438 | AJ39: =+SUM(AH39:AI39) -> 61281.334 | AR39: 14 | AS39: =+EOMONTH(AT39,0) -> 46904 | AT39: 46893 | AV39: =+AV38+AU39-AW39 -> 11796136 | AW39: 525047.46 | AX39: =+AV38*AV$5*(AT39-AT38)/360 -> 184817.76 | AY39: =+SUM(AW39:AX39) -> 709865.22 | BG39: 14 | BH39: =+EOMONTH(BI39,0) -> 47026 | BI39: 47016 | BK39: =+BK38+BJ39-BL39 -> 5347661.4 | BL39: =+BL38 -> 5347661.4 | BM39: =+BK38*BK$5*(BI39-BI38)/360 -> 163994.95 | BN39: 82616.23 | BO39: =+SUM(BL39:BN39) -> 5594272.6 | BV39: 14 | BW39: =+EOMONTH(BX39,0) -> 46965 | BX39: 46954 | BZ39: =+BZ38+BY39-CA39 -> 346418.81 | CA39: 57736.47 | CB39: 2821.4285 | CC39: =+BZ38*BZ$5*(BX39-BX38)/360 -> 6129.6884 | CD39: 1642.8395 | CE39: =+SUM(CA39:CD39) -> 68330.426 | CL39: 14 | CM39: =+EOMONTH(CN39,0) -> 47026 | CN39: 47010 | CP39: =+CP38+CO39-CQ39 -> 417271.53 | CQ39: 104317.86 | CR39: 4798.6232 | CS39: =+SUM(CQ39:CR39) -> 109116.48 | CU39: 14 | CV39: =+EOMONTH(CW39,0) -> 46295 | CW39: 46275 | CY39: =+CY38+CX39-CZ39 -> 17420022 | CZ39: 1583638.4 | DA39: =+CY38*CY$5*(CW39-CW38)/360 -> 98185.58 | DB39: =+SUM(CZ39:DA39) -> 1681824 | DD39: 14 | DE39: =+EOMONTH(DF39,0) -> 47026 | DF39: 47017 | DH39: =+DH38+DG39-DI39 -> 6531385 | DI39: 283973.26 | DJ39: 99920.72 | DK39: =+SUM(DI39:DJ39) -> 383893.98 | DM39: 14 | DN39: =+EOMONTH(DO39,0) -> 47057 | DO39: 47031 | DQ39: =+DQ38-DR39 -> 750391.8 | DR39: 39494.31 | DS39: =+DQ38*(DO39-DO38)*$DQ$5/360 -> 11748.239 | DT39: =+SUM(DR39:DS39) -> 51242.549 | EE39: 14 | EF39: =+EOMONTH(EG39,0) -> 46934 | EG39: 46926 | EI39: =+EI38+EH39-EJ39 -> 2462946.7 | EJ39: 40216.85 | EK39: 14016.8 | EM39: =+SUM(EJ39:EL39) -> 54233.65
A40: 15 | B40: =+WEEKNUM(C40,2) -> 49 | C40: =+EOMONTH(C39,1) -> 46356 | E40: =+E39+D40-F40 -> 1.7924202e+08 | F40: =+SUMIF(N:N,C40,R:R)+SUMIF(AD:AD,C40,AH:AH)+SUMIF(AS:AS,C40,AW:AW)+SUMIF(BH:BH,C40,BL:BL)+SUMIF(BW:BW,C40,CA:CA)+SUMIF(BW:BW,C40,CB:CB)+SUMIF(CM:CM,C40,CQ:CQ)+SUMIF(CV:CV,C40,CZ:CZ)+SUMIF(DE:DE,C40,DI:DI)+SUMIF(DN:DN,C40,DR:DR)+SUMIF(DW:DW,C40,EA:EA)+SUMIF(EF:EF,C40,EJ:EJ)+SUMIF(EP:EP,C40,ET:ET)+SUMIF(EY:EY,C40,FC:FC)+SUMIF(FH:FH,C40,FL:FL)+SUMIF(FQ:FQ,C40,FU:FU)+SUMIF(FZ:FZ,C40,GD:GD)+SUMIF(GI:GI,C40,GM:GM) -> 6319757.7 | G40: =+SUMIF(N:N,C40,S:S)+SUMIF(N:N,C40,T:T)+SUMIF(AD:AD,C40,AI:AI)+SUMIF(AS:AS,C40,AX:AX)+SUMIF(BH:BH,C40,BM:BM)+SUMIF(BW:BW,C40,CD:CD)+SUMIF(BW:BW,C40,CC:CC)+SUMIF(CM:CM,C40,CR:CR)+SUMIF(CV:CV,C40,DA:DA)+SUMIF(DE:DE,C40,DJ:DJ)+SUMIF(DN:DN,C40,DS:DS)+SUMIF(DX:DX,C40,EB:EB)+SUMIF(EG:EG,C40,EK:EK)+SUMIF(EP:EP,C40,EU:EU)+SUMIF(EY:EY,C40,FD:FD)+SUMIF(FH:FH,C40,FM:FM)+SUMIF(FQ:FQ,C40,FV:FV)+SUMIF(FZ:FZ,C40,GE:GE)+SUMIF(GI:GI,C40,GN:GN) -> 2182023.4 | H40: =+SUM(F40:G40) -> 8501781.1 | M40: 15 | N40: =+EOMONTH(O40,0) -> 46904 | O40: =+DATE(YEAR(O39),MONTH(O39)+3,DAY(O39)) -> 46888 | Q40: =+Q39-R40 -> 61094968 | R40: =+$Q$30/25 -> 4072997.9 | S40: =+Q39*Q$5*(O40-O39)/360 -> 977519.49 | T40: =+$Q$17/$Q$18 -> 471550.55 | U40: =+SUM(R40:T40) -> 5522067.9 | AC40: 15 | AD40: =+EOMONTH(AE40,0) -> 47087 | AE40: 47059 | AG40: =+AG39+AF40-AH40 -> 567977.66 | AH40: =+AH39 -> 51840.79 | AI40: =+AG39*AG$5*(AE40-AE39)/360 -> 8711.8927 | AJ40: =+SUM(AH40:AI40) -> 60552.683 | AR40: 15 | AS40: =+EOMONTH(AT40,0) -> 46996 | AT40: 46985 | AV40: =+AV39+AU40-AW40 -> 11271089 | AW40: 525047.46 | AX40: =+AV39*AV$5*(AT40-AT39)/360 -> 180874.09 | AY40: =+SUM(AW40:AX40) -> 705921.56 | BG40: 15 | BH40: =+EOMONTH(BI40,0) -> 47118 | BI40: 47107 | BK40: =+BK39+BJ40-BL40 -> 0 | BL40: =+BL39 -> 5347661.4 | BM40: =+BK39*BK$5*(BI40-BI39)/360 -> 81106.198 | BN40: 82616.23 | BO40: =+SUM(BL40:BN40) -> 5511383.8 | BV40: 15 | BW40: =+EOMONTH(BX40,0) -> 47057 | BX40: 47046 | BZ40: =+BZ39+BY40-CA40 -> 288682.34 | CA40: 57736.47 | CB40: 2821.4285 | CC40: =+BZ39*BZ$5*(BX40-BX39)/360 -> 5311.7551 | CD40: 1642.8395 | CE40: =+SUM(CA40:CD40) -> 67512.493 | CL40: 15 | CM40: =+EOMONTH(CN40,0) -> 47118 | CN40: 47101 | CP40: =+CP39+CO40-CQ40 -> 312953.67 | CQ40: 104317.86 | CR40: 3164.3101 | CS40: =+SUM(CQ40:CR40) -> 107482.17 | CU40: 15 | CV40: =+EOMONTH(CW40,0) -> 46326 | CW40: 46305 | CY40: =+CY39+CX40-CZ40 -> 15836384 | CZ40: 1583638.4 | DA40: =+CY39*CY$5*(CW40-CW39)/360 -> 87100.111 | DB40: =+SUM(CZ40:DA40) -> 1670738.5 | DD40: 15 | DE40: =+EOMONTH(DF40,0) -> 47118 | DF40: 47108 | DH40: =+DH39+DG40-DI40 -> 6247411.8 | DI40: 283973.26 | DJ40: 95757.36 | DK40: =+SUM(DI40:DJ40) -> 379730.62 | DM40: 15 | DN40: =+EOMONTH(DO40,0) -> 47149 | DO40: 47123 | DQ40: =+DQ39-DR40 -> 710897.49 | DR40: 39494.31 | DS40: =+DQ39*(DO40-DO39)*$DQ$5/360 -> 11160.827 | DT40: =+SUM(DR40:DS40) -> 50655.137 | EE40: 15 | EF40: =+EOMONTH(EG40,0) -> 47026 | EG40: 47017 | EI40: =+EI39+EH40-EJ40 -> 2422729.8 | EJ40: 40216.85 | EK40: 13407.86 | EM40: =+SUM(EJ40:EL40) -> 53624.71
A41: 16 | B41: =+WEEKNUM(C41,2) -> 53 | C41: =+EOMONTH(C40,1) -> 46387 | E41: =+E40+D41-F41 -> 1.7171472e+08 | F41: =+SUMIF(N:N,C41,R:R)+SUMIF(AD:AD,C41,AH:AH)+SUMIF(AS:AS,C41,AW:AW)+SUMIF(BH:BH,C41,BL:BL)+SUMIF(BW:BW,C41,CA:CA)+SUMIF(BW:BW,C41,CB:CB)+SUMIF(CM:CM,C41,CQ:CQ)+SUMIF(CV:CV,C41,CZ:CZ)+SUMIF(DE:DE,C41,DI:DI)+SUMIF(DN:DN,C41,DR:DR)+SUMIF(DW:DW,C41,EA:EA)+SUMIF(EF:EF,C41,EJ:EJ)+SUMIF(EP:EP,C41,ET:ET)+SUMIF(EY:EY,C41,FC:FC)+SUMIF(FH:FH,C41,FL:FL)+SUMIF(FQ:FQ,C41,FU:FU)+SUMIF(FZ:FZ,C41,GD:GD)+SUMIF(GI:GI,C41,GM:GM) -> 7527297.3 | G41: =+SUMIF(N:N,C41,S:S)+SUMIF(N:N,C41,T:T)+SUMIF(AD:AD,C41,AI:AI)+SUMIF(AS:AS,C41,AX:AX)+SUMIF(BH:BH,C41,BM:BM)+SUMIF(BW:BW,C41,CD:CD)+SUMIF(BW:BW,C41,CC:CC)+SUMIF(CM:CM,C41,CR:CR)+SUMIF(CV:CV,C41,DA:DA)+SUMIF(DE:DE,C41,DJ:DJ)+SUMIF(DN:DN,C41,DS:DS)+SUMIF(DX:DX,C41,EB:EB)+SUMIF(EG:EG,C41,EK:EK)+SUMIF(EP:EP,C41,EU:EU)+SUMIF(EY:EY,C41,FD:FD)+SUMIF(FH:FH,C41,FM:FM)+SUMIF(FQ:FQ,C41,FV:FV)+SUMIF(FZ:FZ,C41,GE:GE)+SUMIF(GI:GI,C41,GN:GN) -> 949235.28 | H41: =+SUM(F41:G41) -> 8476532.6 | M41: 16 | N41: =+EOMONTH(O41,0) -> 46996 | O41: =+DATE(YEAR(O40),MONTH(O40)+3,DAY(O40)) -> 46980 | Q41: =+Q40-R41 -> 57021970 | R41: =+$Q$30/25 -> 4072997.9 | S41: =+Q40*Q$5*(O41-O40)/360 -> 936789.51 | T41: =+$Q$17/$Q$18 -> 471550.55 | U41: =+SUM(R41:T41) -> 5481337.9 | AC41: 16 | AD41: =+EOMONTH(AE41,0) -> 47177 | AE41: 47151 | AG41: =+AG40+AF41-AH41 -> 516136.87 | AH41: =+AH40 -> 51840.79 | AI41: =+AG40*AG$5*(AE41-AE40)/360 -> 7983.2416 | AJ41: =+SUM(AH41:AI41) -> 59824.032 | AR41: 16 | AS41: =+EOMONTH(AT41,0) -> 47087 | AT41: 47077 | AV41: =+AV40+AU41-AW41 -> 10746041 | AW41: 525047.46 | AX41: =+AV40*AV$5*(AT41-AT40)/360 -> 172823.36 | AY41: =+SUM(AW41:AX41) -> 697870.83 | BV41: 16 | BW41: =+EOMONTH(BX41,0) -> 47149 | BX41: 47138 | BZ41: =+BZ40+BY41-CA41 -> 230945.87 | CA41: 57736.47 | CB41: 2821.4285 | CC41: =+BZ40*BZ$5*(BX41-BX40)/360 -> 4426.4625 | CD41: 1642.8395 | CE41: =+SUM(CA41:CD41) -> 66627.201 | CL41: 16 | CM41: =+EOMONTH(CN41,0) -> 47208 | CN41: 47191 | CP41: =+CP40+CO41-CQ41 -> 208635.7 | CQ41: 104317.97 | CR41: 1564.7695 | CS41: =+SUM(CQ41:CR41) -> 105882.74 | CU41: 16 | CV41: =+EOMONTH(CW41,0) -> 46356 | CW41: 46336 | CY41: =+CY40+CX41-CZ41 -> 14252745 | CZ41: 1583638.4 | DA41: =+CY40*CY$5*(CW41-CW40)/360 -> 81821.317 | DB41: =+SUM(CZ41:DA41) -> 1665459.7 | DD41: 16 | DE41: =+EOMONTH(DF41,0) -> 47208 | DF41: 47199 | DH41: =+DH40+DG41-DI41 -> 5963438.5 | DI41: 283973.26 | DJ41: 91594 | DK41: =+SUM(DI41:DJ41) -> 375567.26 | DM41: 16 | DN41: =+EOMONTH(DO41,0) -> 47238 | DO41: 47213 | DQ41: =+DQ40-DR41 -> 671403.18 | DR41: 39494.31 | DS41: =+DQ40*(DO41-DO40)*$DQ$5/360 -> 10343.559 | DT41: =+SUM(DR41:DS41) -> 49837.869 | EE41: 16 | EF41: =+EOMONTH(EG41,0) -> 47118 | EG41: 47108 | EI41: =+EI40+EH41-EJ41 -> 2382513 | EJ41: 40216.85 | EK41: 12798.92 | EM41: =+SUM(EJ41:EL41) -> 53015.77
A42: 17 | B42: =+WEEKNUM(C42,2) -> 5 | C42: =+EOMONTH(C41,1) -> 46418 | E42: =+E41+D42-F42 -> 1.7003103e+08 | F42: =+SUMIF(N:N,C42,R:R)+SUMIF(AD:AD,C42,AH:AH)+SUMIF(AS:AS,C42,AW:AW)+SUMIF(BH:BH,C42,BL:BL)+SUMIF(BW:BW,C42,CA:CA)+SUMIF(BW:BW,C42,CB:CB)+SUMIF(CM:CM,C42,CQ:CQ)+SUMIF(CV:CV,C42,CZ:CZ)+SUMIF(DE:DE,C42,DI:DI)+SUMIF(DN:DN,C42,DR:DR)+SUMIF(DW:DW,C42,EA:EA)+SUMIF(EF:EF,C42,EJ:EJ)+SUMIF(EP:EP,C42,ET:ET)+SUMIF(EY:EY,C42,FC:FC)+SUMIF(FH:FH,C42,FL:FL)+SUMIF(FQ:FQ,C42,FU:FU)+SUMIF(FZ:FZ,C42,GD:GD)+SUMIF(GI:GI,C42,GM:GM) -> 1683690.6 | G42: =+SUMIF(N:N,C42,S:S)+SUMIF(N:N,C42,T:T)+SUMIF(AD:AD,C42,AI:AI)+SUMIF(AS:AS,C42,AX:AX)+SUMIF(BH:BH,C42,BM:BM)+SUMIF(BW:BW,C42,CD:CD)+SUMIF(BW:BW,C42,CC:CC)+SUMIF(CM:CM,C42,CR:CR)+SUMIF(CV:CV,C42,DA:DA)+SUMIF(DE:DE,C42,DJ:DJ)+SUMIF(DN:DN,C42,DS:DS)+SUMIF(DX:DX,C42,EB:EB)+SUMIF(EG:EG,C42,EK:EK)+SUMIF(EP:EP,C42,EU:EU)+SUMIF(EY:EY,C42,FD:FD)+SUMIF(FH:FH,C42,FM:FM)+SUMIF(FQ:FQ,C42,FV:FV)+SUMIF(FZ:FZ,C42,GE:GE)+SUMIF(GI:GI,C42,GN:GN) -> 94468.819 | H42: =+SUM(F42:G42) -> 1778159.4 | I42: =+H42 -> 1778159.4 | J42: BISA | M42: 17 | N42: =+EOMONTH(O42,0) -> 47087 | O42: =+DATE(YEAR(O41),MONTH(O41)+3,DAY(O41)) -> 47072 | Q42: =+Q41-R42 -> 52948972 | R42: =+$Q$30/25 -> 4072997.9 | S42: =+Q41*Q$5*(O42-O41)/360 -> 874336.88 | T42: =+$Q$17/$Q$18 -> 471550.55 | U42: =+SUM(R42:T42) -> 5418885.3 | AC42: 17 | AD42: =+EOMONTH(AE42,0) -> 47269 | AE42: 47240 | AG42: =+AG41+AF42-AH42 -> 464296.08 | AH42: =+AH41 -> 51840.79 | AI42: =+AG41*AG$5*(AE42-AE41)/360 -> 7018.0277 | AJ42: =+SUM(AH42:AI42) -> 58858.818 | AR42: 17 | AS42: =+EOMONTH(AT42,0) -> 47177 | AT42: 47169 | AV42: =+AV41+AU42-AW42 -> 10220994 | AW42: 525047.46 | AX42: =+AV41*AV$5*(AT42-AT41)/360 -> 164772.64 | AY42: =+SUM(AW42:AX42) -> 689820.1 | BV42: 17 | BW42: =+EOMONTH(BX42,0) -> 47238 | BX42: 47228 | BZ42: =+BZ41+BY42-CA42 -> 173209.4 | CA42: 57736.47 | CB42: 2821.4285 | CC42: =+BZ41*BZ$5*(BX42-BX41)/360 -> 3464.188 | CD42: 1642.8395 | CE42: =+SUM(CA42:CD42) -> 65664.926 | CL42: 17 | CM42: =+EOMONTH(CN42,0) -> 47299 | CN42: 47283 | CP42: =+CP41+CO42-CQ42 -> 104317.85 | CQ42: 104317.85 | CR42: 55983.92 | CS42: =+SUM(CQ42:CR42) -> 160301.77 | CU42: 17 | CV42: =+EOMONTH(CW42,0) -> 46387 | CW42: 46366 | CY42: =+CY41+CX42-CZ42 -> 12669107 | CZ42: 1583638.4 | DA42: =+CY41*CY$5*(CW42-CW41)/360 -> 71263.727 | DB42: =+SUM(CZ42:DA42) -> 1654902.1 | DD42: 17 | DE42: =+EOMONTH(DF42,0) -> 47299 | DF42: 47291 | DH42: =+DH41+DG42-DI42 -> 5679465.2 | DI42: 283973.26 | DJ42: 88391.41 | DK42: =+SUM(DI42:DJ42) -> 372364.67 | DM42: 17 | DN42: =+EOMONTH(DO42,0) -> 47330 | DO42: 47304 | DQ42: =+DQ41-DR42 -> 631908.87 | DR42: 39494.31 | DS42: =+DQ41*(DO42-DO41)*$DQ$5/360 -> 9877.4598 | DT42: =+SUM(DR42:DS42) -> 49371.77 | EE42: 17 | EF42: =+EOMONTH(EG42,0) -> 47208 | EG42: 47199 | EI42: =+EI41+EH42-EJ42 -> 2342296.1 | EJ42: 40216.85 | EK42: 12189.98 | EM42: =+SUM(EJ42:EL42) -> 52406.83
A43: 18 | B43: =+WEEKNUM(C43,2) -> 9 | C43: =+EOMONTH(C42,1) -> 46446 | E43: =+E42+D43-F43 -> 1.6370944e+08 | F43: =+SUMIF(N:N,C43,R:R)+SUMIF(AD:AD,C43,AH:AH)+SUMIF(AS:AS,C43,AW:AW)+SUMIF(BH:BH,C43,BL:BL)+SUMIF(BW:BW,C43,CA:CA)+SUMIF(BW:BW,C43,CB:CB)+SUMIF(CM:CM,C43,CQ:CQ)+SUMIF(CV:CV,C43,CZ:CZ)+SUMIF(DE:DE,C43,DI:DI)+SUMIF(DN:DN,C43,DR:DR)+SUMIF(DW:DW,C43,EA:EA)+SUMIF(EF:EF,C43,EJ:EJ)+SUMIF(EP:EP,C43,ET:ET)+SUMIF(EY:EY,C43,FC:FC)+SUMIF(FH:FH,C43,FL:FL)+SUMIF(FQ:FQ,C43,FU:FU)+SUMIF(FZ:FZ,C43,GD:GD)+SUMIF(GI:GI,C43,GM:GM) -> 6321590.1 | G43: =+SUMIF(N:N,C43,S:S)+SUMIF(N:N,C43,T:T)+SUMIF(AD:AD,C43,AI:AI)+SUMIF(AS:AS,C43,AX:AX)+SUMIF(BH:BH,C43,BM:BM)+SUMIF(BW:BW,C43,CD:CD)+SUMIF(BW:BW,C43,CC:CC)+SUMIF(CM:CM,C43,CR:CR)+SUMIF(CV:CV,C43,DA:DA)+SUMIF(DE:DE,C43,DJ:DJ)+SUMIF(DN:DN,C43,DS:DS)+SUMIF(DX:DX,C43,EB:EB)+SUMIF(EG:EG,C43,EK:EK)+SUMIF(EP:EP,C43,EU:EU)+SUMIF(EY:EY,C43,FD:FD)+SUMIF(FH:FH,C43,FM:FM)+SUMIF(FQ:FQ,C43,FV:FV)+SUMIF(FZ:FZ,C43,GE:GE)+SUMIF(GI:GI,C43,GN:GN) -> 2084951.5 | H43: =+SUM(F43:G43) -> 8406541.6 | M43: 18 | N43: =+EOMONTH(O43,0) -> 47177 | O43: =+DATE(YEAR(O42),MONTH(O42)+3,DAY(O42)) -> 47164 | Q43: =+Q42-R43 -> 48875975 | R43: =+$Q$30/25 -> 4072997.9 | S43: =+Q42*Q$5*(O43-O42)/360 -> 811884.24 | T43: =+$Q$17/$Q$18 -> 471550.55 | U43: =+SUM(R43:T43) -> 5356432.7 | AC43: 18 | AD43: =+EOMONTH(AE43,0) -> 47361 | AE43: 47332 | AG43: =+AG42+AF43-AH43 -> 412455.29 | AH43: =+AH42 -> 51840.79 | AI43: =+AG42*AG$5*(AE43-AE42)/360 -> 6525.9393 | AJ43: =+SUM(AH43:AI43) -> 58366.729 | AR43: 18 | AS43: =+EOMONTH(AT43,0) -> 47269 | AT43: 47258 | AV43: =+AV42+AU43-AW43 -> 9695946.5 | AW43: 525047.46 | AX43: =+AV42*AV$5*(AT43-AT42)/360 -> 151611.41 | AY43: =+SUM(AW43:AX43) -> 676658.87 | BV43: 18 | BW43: =+EOMONTH(BX43,0) -> 47330 | BX43: 47319 | BZ43: =+BZ42+BY43-CA43 -> 115472.93 | CA43: 57736.47 | CB43: 2821.4285 | CC43: =+BZ42*BZ$5*(BX43-BX42)/360 -> 2627.0092 | CD43: 1642.8395 | CE43: =+SUM(CA43:CD43) -> 64827.747 | CL43: 18 | CM43: =+EOMONTH(CN43,0) -> 47391 | CN43: 47375 | CP43: =+CP42+CO43-CQ43 -> 0 | CQ43: 104317.85 | CR43: 53793.24 | CS43: =+SUM(CQ43:CR43) -> 158111.09 | CU43: 18 | CV43: =+EOMONTH(CW43,0) -> 46418 | CW43: 46397 | CY43: =+CY42+CX43-CZ43 -> 11085469 | CZ43: 1583638.4 | DA43: =+CY42*CY$5*(CW43-CW42)/360 -> 65457.053 | DB43: =+SUM(CZ43:DA43) -> 1649095.4 | DD43: 18 | DE43: =+EOMONTH(DF43,0) -> 47391 | DF43: 47381 | DH43: =+DH42+DG43-DI43 -> 5395492 | DI43: 283973.26 | DJ43: 82352.25 | DK43: =+SUM(DI43:DJ43) -> 366325.51 | DM43: 18 | DN43: =+EOMONTH(DO43,0) -> 47422 | DO43: 47396 | DQ43: =+DQ42-DR43 -> 592414.56 | DR43: 39494.31 | DS43: =+DQ42*(DO43-DO42)*$DQ$5/360 -> 9398.5913 | DT43: =+SUM(DR43:DS43) -> 48892.901 | EE43: 18 | EF43: =+EOMONTH(EG43,0) -> 47299 | EG43: 47291 | EI43: =+EI42+EH43-EJ43 -> 2302079.3 | EJ43: 40216.85 | EK43: 11701.49 | EM43: =+SUM(EJ43:EL43) -> 51918.34
A44: 19 | B44: =+WEEKNUM(C44,2) -> 14 | C44: =+EOMONTH(C43,1) -> 46477 | E44: =+E43+D44-F44 -> 1.562309e+08 | F44: =+SUMIF(N:N,C44,R:R)+SUMIF(AD:AD,C44,AH:AH)+SUMIF(AS:AS,C44,AW:AW)+SUMIF(BH:BH,C44,BL:BL)+SUMIF(BW:BW,C44,CA:CA)+SUMIF(BW:BW,C44,CB:CB)+SUMIF(CM:CM,C44,CQ:CQ)+SUMIF(CV:CV,C44,CZ:CZ)+SUMIF(DE:DE,C44,DI:DI)+SUMIF(DN:DN,C44,DR:DR)+SUMIF(DW:DW,C44,EA:EA)+SUMIF(EF:EF,C44,EJ:EJ)+SUMIF(EP:EP,C44,ET:ET)+SUMIF(EY:EY,C44,FC:FC)+SUMIF(FH:FH,C44,FL:FL)+SUMIF(FQ:FQ,C44,FU:FU)+SUMIF(FZ:FZ,C44,GD:GD)+SUMIF(GI:GI,C44,GM:GM) -> 7478539.9 | G44: =+SUMIF(N:N,C44,S:S)+SUMIF(N:N,C44,T:T)+SUMIF(AD:AD,C44,AI:AI)+SUMIF(AS:AS,C44,AX:AX)+SUMIF(BH:BH,C44,BM:BM)+SUMIF(BW:BW,C44,CD:CD)+SUMIF(BW:BW,C44,CC:CC)+SUMIF(CM:CM,C44,CR:CR)+SUMIF(CV:CV,C44,DA:DA)+SUMIF(DE:DE,C44,DJ:DJ)+SUMIF(DN:DN,C44,DS:DS)+SUMIF(DX:DX,C44,EB:EB)+SUMIF(EG:EG,C44,EK:EK)+SUMIF(EP:EP,C44,EU:EU)+SUMIF(EY:EY,C44,FD:FD)+SUMIF(FH:FH,C44,FM:FM)+SUMIF(FQ:FQ,C44,FV:FV)+SUMIF(FZ:FZ,C44,GE:GE)+SUMIF(GI:GI,C44,GN:GN) -> 895468.26 | H44: =+SUM(F44:G44) -> 8374008.1 | M44: 19 | N44: =+EOMONTH(O44,0) -> 47269 | O44: =+DATE(YEAR(O43),MONTH(O43)+3,DAY(O43)) -> 47253 | Q44: =+Q43-R44 -> 44802977 | R44: =+$Q$30/25 -> 4072997.9 | S44: =+Q43*Q$5*(O44-O43)/360 -> 724993.62 | T44: =+$Q$17/$Q$18 -> 471550.55 | U44: =+SUM(R44:T44) -> 5269542.1 | AC44: 19 | AD44: =+EOMONTH(AE44,0) -> 47452 | AE44: 47424 | AG44: =+AG43+AF44-AH44 -> 360614.5 | AH44: =+AH43 -> 51840.79 | AI44: =+AG43*AG$5*(AE44-AE43)/360 -> 5797.2882 | AJ44: =+SUM(AH44:AI44) -> 57638.078 | AR44: 19 | AS44: =+EOMONTH(AT44,0) -> 47361 | AT44: 47350 | AV44: =+AV43+AU44-AW44 -> 9170899 | AW44: 525047.46 | AX44: =+AV43*AV$5*(AT44-AT43)/360 -> 148671.18 | AY44: =+SUM(AW44:AX44) -> 673718.64 | BV44: 19 | BW44: =+EOMONTH(BX44,0) -> 47422 | BX44: 47398 | BZ44: =+BZ43+BY44-CA44 -> 0.0056757364 | CA44: 115472.92 | CB44: 14107.143 | CC44: =+BZ43*BZ$5*(BX44-BX43)/360 -> 1520.3935 | CD44: 1642.8395 | CE44: =+SUM(CA44:CD44) -> 132743.3 | CU44: 19 | CV44: =+EOMONTH(CW44,0) -> 46446 | CW44: 46428 | CY44: =+CY43+CX44-CZ44 -> 9501830.3 | CZ44: 1583638.4 | DA44: =+CY43*CY$5*(CW44-CW43)/360 -> 57274.922 | DB44: =+SUM(CZ44:DA44) -> 1640913.3 | DD44: 19 | DE44: =+EOMONTH(DF44,0) -> 47483 | DF44: 47472 | DH44: =+DH43+DG44-DI44 -> 5111518.7 | DI44: 283973.26 | DJ44: 79103.91 | DK44: =+SUM(DI44:DJ44) -> 363077.17 | DM44: 19 | DN44: =+EOMONTH(DO44,0) -> 47514 | DO44: 47490 | DQ44: =+DQ43-DR44 -> 552920.25 | DR44: 39494.31 | DS44: =+DQ43*(DO44-DO43)*$DQ$5/360 -> 9002.7266 | DT44: =+SUM(DR44:DS44) -> 48497.037 | EE44: 19 | EF44: =+EOMONTH(EG44,0) -> 47391 | EG44: 47381 | EI44: =+EI43+EH44-EJ44 -> 2261862.4 | EJ44: 40216.85 | EK44: 10858.34 | EM44: =+SUM(EJ44:EL44) -> 51075.19
A45: 20 | B45: =+WEEKNUM(C45,2) -> 18 | C45: =+EOMONTH(C44,1) -> 46507 | E45: =+E44+D45-F45 -> 1.5454721e+08 | F45: =+SUMIF(N:N,C45,R:R)+SUMIF(AD:AD,C45,AH:AH)+SUMIF(AS:AS,C45,AW:AW)+SUMIF(BH:BH,C45,BL:BL)+SUMIF(BW:BW,C45,CA:CA)+SUMIF(BW:BW,C45,CB:CB)+SUMIF(CM:CM,C45,CQ:CQ)+SUMIF(CV:CV,C45,CZ:CZ)+SUMIF(DE:DE,C45,DI:DI)+SUMIF(DN:DN,C45,DR:DR)+SUMIF(DW:DW,C45,EA:EA)+SUMIF(EF:EF,C45,EJ:EJ)+SUMIF(EP:EP,C45,ET:ET)+SUMIF(EY:EY,C45,FC:FC)+SUMIF(FH:FH,C45,FL:FL)+SUMIF(FQ:FQ,C45,FU:FU)+SUMIF(FZ:FZ,C45,GD:GD)+SUMIF(GI:GI,C45,GM:GM) -> 1683690.6 | G45: =+SUMIF(N:N,C45,S:S)+SUMIF(N:N,C45,T:T)+SUMIF(AD:AD,C45,AI:AI)+SUMIF(AS:AS,C45,AX:AX)+SUMIF(BH:BH,C45,BM:BM)+SUMIF(BW:BW,C45,CD:CD)+SUMIF(BW:BW,C45,CC:CC)+SUMIF(CM:CM,C45,CR:CR)+SUMIF(CV:CV,C45,DA:DA)+SUMIF(DE:DE,C45,DJ:DJ)+SUMIF(DN:DN,C45,DS:DS)+SUMIF(DX:DX,C45,EB:EB)+SUMIF(EG:EG,C45,EK:EK)+SUMIF(EP:EP,C45,EU:EU)+SUMIF(EY:EY,C45,FD:FD)+SUMIF(FH:FH,C45,FM:FM)+SUMIF(FQ:FQ,C45,FV:FV)+SUMIF(FZ:FZ,C45,GE:GE)+SUMIF(GI:GI,C45,GN:GN) -> 67886.759 | H45: =+SUM(F45:G45) -> 1751577.3 | M45: 20 | N45: =+EOMONTH(O45,0) -> 47361 | O45: =+DATE(YEAR(O44),MONTH(O44)+3,DAY(O44)) -> 47345 | Q45: =+Q44-R45 -> 40729979 | R45: =+$Q$30/25 -> 4072997.9 | S45: =+Q44*Q$5*(O45-O44)/360 -> 686978.98 | T45: =+$Q$17/$Q$18 -> 471550.55 | U45: =+SUM(R45:T45) -> 5231527.4 | AC45: 20 | AD45: =+EOMONTH(AE45,0) -> 47542 | AE45: 47516 | AG45: =+AG44+AF45-AH45 -> 308773.71 | AH45: =+AH44 -> 51840.79 | AI45: =+AG44*AG$5*(AE45-AE44)/360 -> 5068.6371 | AJ45: =+SUM(AH45:AI45) -> 56909.427 | AR45: 20 | AS45: =+EOMONTH(AT45,0) -> 47452 | AT45: 47442 | AV45: =+AV44+AU45-AW45 -> 8645851.6 | AW45: 525047.46 | AX45: =+AV44*AV$5*(AT45-AT44)/360 -> 140620.45 | AY45: =+SUM(AW45:AX45) -> 665667.92 | CU45: 20 | CV45: =+EOMONTH(CW45,0) -> 46477 | CW45: 46456 | CY45: =+CY44+CX45-CZ45 -> 7918192 | CZ45: 1583638.4 | DA45: =+CY44*CY$5*(CW45-CW44)/360 -> 44341.875 | DB45: =+SUM(CZ45:DA45) -> 1627980.3 | DD45: 20 | DE45: =+EOMONTH(DF45,0) -> 47573 | DF45: 47563 | DH45: =+DH44+DG45-DI45 -> 4827545.5 | DI45: 283973.26 | DJ45: 74940.55 | DK45: =+SUM(DI45:DJ45) -> 358913.81 | DM45: 20 | DN45: =+EOMONTH(DO45,0) -> 47603 | DO45: 47578 | DQ45: =+DQ44-DR45 -> 513425.94 | DR45: 39494.31 | DS45: =+DQ44*(DO45-DO44)*$DQ$5/360 -> 7866.2121 | DT45: =+SUM(DR45:DS45) -> 47360.522 | EE45: 20 | EF45: =+EOMONTH(EG45,0) -> 47483 | EG45: 47472 | EI45: =+EI44+EH45-EJ45 -> 2221645.6 | EJ45: 40216.85 | EK45: 10363.16 | EM45: =+SUM(EJ45:EL45) -> 50580.01
A46: 21 | B46: =+WEEKNUM(C46,2) -> 23 | C46: =+EOMONTH(C45,1) -> 46538 | E46: =+E45+D46-F46 -> 1.4825672e+08 | F46: =+SUMIF(N:N,C46,R:R)+SUMIF(AD:AD,C46,AH:AH)+SUMIF(AS:AS,C46,AW:AW)+SUMIF(BH:BH,C46,BL:BL)+SUMIF(BW:BW,C46,CA:CA)+SUMIF(BW:BW,C46,CB:CB)+SUMIF(CM:CM,C46,CQ:CQ)+SUMIF(CV:CV,C46,CZ:CZ)+SUMIF(DE:DE,C46,DI:DI)+SUMIF(DN:DN,C46,DR:DR)+SUMIF(DW:DW,C46,EA:EA)+SUMIF(EF:EF,C46,EJ:EJ)+SUMIF(EP:EP,C46,ET:ET)+SUMIF(EY:EY,C46,FC:FC)+SUMIF(FH:FH,C46,FL:FL)+SUMIF(FQ:FQ,C46,FU:FU)+SUMIF(FZ:FZ,C46,GD:GD)+SUMIF(GI:GI,C46,GM:GM) -> 6290487.5 | G46: =+SUMIF(N:N,C46,S:S)+SUMIF(N:N,C46,T:T)+SUMIF(AD:AD,C46,AI:AI)+SUMIF(AS:AS,C46,AX:AX)+SUMIF(BH:BH,C46,BM:BM)+SUMIF(BW:BW,C46,CD:CD)+SUMIF(BW:BW,C46,CC:CC)+SUMIF(CM:CM,C46,CR:CR)+SUMIF(CV:CV,C46,DA:DA)+SUMIF(DE:DE,C46,DJ:DJ)+SUMIF(DN:DN,C46,DS:DS)+SUMIF(DX:DX,C46,EB:EB)+SUMIF(EG:EG,C46,EK:EK)+SUMIF(EP:EP,C46,EU:EU)+SUMIF(EY:EY,C46,FD:FD)+SUMIF(FH:FH,C46,FM:FM)+SUMIF(FQ:FQ,C46,FV:FV)+SUMIF(FZ:FZ,C46,GE:GE)+SUMIF(GI:GI,C46,GN:GN) -> 1975778 | H46: =+SUM(F46:G46) -> 8266265.6 | M46: 21 | N46: =+EOMONTH(O46,0) -> 47452 | O46: =+DATE(YEAR(O45),MONTH(O45)+3,DAY(O45)) -> 47437 | Q46: =+Q45-R46 -> 36656981 | R46: =+$Q$30/25 -> 4072997.9 | S46: =+Q45*Q$5*(O46-O45)/360 -> 624526.34 | U46: =+SUM(R46:T46) -> 4697524.2 | AC46: 21 | AD46: =+EOMONTH(AE46,0) -> 47634 | AE46: 47605 | AG46: =+AG45+AF46-AH46 -> 256932.92 | AH46: =+AH45 -> 51840.79 | AI46: =+AG45*AG$5*(AE46-AE45)/360 -> 4198.4648 | AJ46: =+SUM(AH46:AI46) -> 56039.255 | AR46: 21 | AS46: =+EOMONTH(AT46,0) -> 47542 | AT46: 47534 | AV46: =+AV45+AU46-AW46 -> 8120804.1 | AW46: 525047.46 | AX46: =+AV45*AV$5*(AT46-AT45)/360 -> 132569.72 | AY46: =+SUM(AW46:AX46) -> 657617.19 | CU46: 21 | CV46: =+EOMONTH(CW46,0) -> 46507 | CW46: 46487 | CY46: =+CY45+CX46-CZ46 -> 6334553.6 | CZ46: 1583638.4 | DA46: =+CY45*CY$5*(CW46-CW45)/360 -> 40910.659 | DB46: =+SUM(CZ46:DA46) -> 1624549 | DD46: 21 | DE46: =+EOMONTH(DF46,0) -> 47664 | DF46: 47656 | DH46: =+DH45+DG46-DI46 -> 4543572.2 | DI46: 283973.26 | DJ46: 72332.72 | DK46: =+SUM(DI46:DJ46) -> 356305.98 | DM46: 21 | DN46: =+EOMONTH(DO46,0) -> 47695 | DO46: 47669 | DQ46: =+DQ45-DR46 -> 473931.63 | DR46: 39494.31 | DS46: =+DQ45*(DO46-DO45)*$DQ$5/360 -> 7553.3513 | DT46: =+SUM(DR46:DS46) -> 47047.661 | EE46: 21 | EF46: =+EOMONTH(EG46,0) -> 47573 | EG46: 47563 | EI46: =+EI45+EH46-EJ46 -> 2181428.7 | EJ46: 40216.85 | EK46: 9754.22 | EM46: =+SUM(EJ46:EL46) -> 49971.07
A47: 22 | B47: =+WEEKNUM(C47,2) -> 27 | C47: =+EOMONTH(C46,1) -> 46568 | E47: =+E46+D47-F47 -> 1.40732e+08 | F47: =+SUMIF(N:N,C47,R:R)+SUMIF(AD:AD,C47,AH:AH)+SUMIF(AS:AS,C47,AW:AW)+SUMIF(BH:BH,C47,BL:BL)+SUMIF(BW:BW,C47,CA:CA)+SUMIF(BW:BW,C47,CB:CB)+SUMIF(CM:CM,C47,CQ:CQ)+SUMIF(CV:CV,C47,CZ:CZ)+SUMIF(DE:DE,C47,DI:DI)+SUMIF(DN:DN,C47,DR:DR)+SUMIF(DW:DW,C47,EA:EA)+SUMIF(EF:EF,C47,EJ:EJ)+SUMIF(EP:EP,C47,ET:ET)+SUMIF(EY:EY,C47,FC:FC)+SUMIF(FH:FH,C47,FL:FL)+SUMIF(FQ:FQ,C47,FU:FU)+SUMIF(FZ:FZ,C47,GD:GD)+SUMIF(GI:GI,C47,GM:GM) -> 7524724 | G47: =+SUMIF(N:N,C47,S:S)+SUMIF(N:N,C47,T:T)+SUMIF(AD:AD,C47,AI:AI)+SUMIF(AS:AS,C47,AX:AX)+SUMIF(BH:BH,C47,BM:BM)+SUMIF(BW:BW,C47,CD:CD)+SUMIF(BW:BW,C47,CC:CC)+SUMIF(CM:CM,C47,CR:CR)+SUMIF(CV:CV,C47,DA:DA)+SUMIF(DE:DE,C47,DJ:DJ)+SUMIF(DN:DN,C47,DS:DS)+SUMIF(DX:DX,C47,EB:EB)+SUMIF(EG:EG,C47,EK:EK)+SUMIF(EP:EP,C47,EU:EU)+SUMIF(EY:EY,C47,FD:FD)+SUMIF(FH:FH,C47,FM:FM)+SUMIF(FQ:FQ,C47,FV:FV)+SUMIF(FZ:FZ,C47,GE:GE)+SUMIF(GI:GI,C47,GN:GN) -> 790854.55 | H47: =+SUM(F47:G47) -> 8315578.6 | M47: 22 | N47: =+EOMONTH(O47,0) -> 47542 | O47: =+DATE(YEAR(O46),MONTH(O46)+3,DAY(O46)) -> 47529 | Q47: =+Q46-R47 -> 32583983 | R47: =+$Q$30/25 -> 4072997.9 | S47: =+Q46*Q$5*(O47-O46)/360 -> 562073.71 | U47: =+SUM(R47:T47) -> 4635071.6 | AC47: 22 | AD47: =+EOMONTH(AE47,0) -> 47726 | AE47: 47697 | AG47: =+AG46+AF47-AH47 -> 205092.13 | AH47: =+AH46 -> 51840.79 | AI47: =+AG46*AG$5*(AE47-AE46)/360 -> 3611.3349 | AJ47: =+SUM(AH47:AI47) -> 55452.125 | AR47: 22 | AS47: =+EOMONTH(AT47,0) -> 47634 | AT47: 47623 | AV47: =+AV46+AU47-AW47 -> 7595756.6 | AW47: 525047.46 | AX47: =+AV46*AV$5*(AT47-AT46)/360 -> 120458.59 | AY47: =+SUM(AW47:AX47) -> 645506.06 | CU47: 22 | CV47: =+EOMONTH(CW47,0) -> 46538 | CW47: 46517 | CY47: =+CY46+CX47-CZ47 -> 4750915.2 | CZ47: 1583638.4 | DA47: =+CY46*CY$5*(CW47-CW46)/360 -> 31672.768 | DB47: =+SUM(CZ47:DA47) -> 1615311.1 | DD47: 22 | DE47: =+EOMONTH(DF47,0) -> 47756 | DF47: 47745 | DH47: =+DH46+DG47-DI47 -> 4259598.9 | DI47: 283973.26 | DJ47: 65149.78 | DK47: =+SUM(DI47:DJ47) -> 349123.04 | DM47: 22 | DN47: =+EOMONTH(DO47,0) -> 47787 | DO47: 47763 | DQ47: =+DQ46-DR47 -> 434437.32 | DR47: 39494.31 | DS47: =+DQ46*(DO47-DO46)*$DQ$5/360 -> 7202.181 | DT47: =+SUM(DR47:DS47) -> 46696.491 | EE47: 22 | EF47: =+EOMONTH(EG47,0) -> 47664 | EG47: 47656 | EI47: =+EI46+EH47-EJ47 -> 2141211.9 | EJ47: 40216.85 | EK47: 9332.65 | EM47: =+SUM(EJ47:EL47) -> 49549.5
A48: 23 | B48: =+WEEKNUM(C48,2) -> 31 | C48: =+EOMONTH(C47,1) -> 46599 | E48: =+E47+D48-F48 -> 1.3904831e+08 | F48: =+SUMIF(N:N,C48,R:R)+SUMIF(AD:AD,C48,AH:AH)+SUMIF(AS:AS,C48,AW:AW)+SUMIF(BH:BH,C48,BL:BL)+SUMIF(BW:BW,C48,CA:CA)+SUMIF(BW:BW,C48,CB:CB)+SUMIF(CM:CM,C48,CQ:CQ)+SUMIF(CV:CV,C48,CZ:CZ)+SUMIF(DE:DE,C48,DI:DI)+SUMIF(DN:DN,C48,DR:DR)+SUMIF(DW:DW,C48,EA:EA)+SUMIF(EF:EF,C48,EJ:EJ)+SUMIF(EP:EP,C48,ET:ET)+SUMIF(EY:EY,C48,FC:FC)+SUMIF(FH:FH,C48,FL:FL)+SUMIF(FQ:FQ,C48,FU:FU)+SUMIF(FZ:FZ,C48,GD:GD)+SUMIF(GI:GI,C48,GM:GM) -> 1683690.6 | G48: =+SUMIF(N:N,C48,S:S)+SUMIF(N:N,C48,T:T)+SUMIF(AD:AD,C48,AI:AI)+SUMIF(AS:AS,C48,AX:AX)+SUMIF(BH:BH,C48,BM:BM)+SUMIF(BW:BW,C48,CD:CD)+SUMIF(BW:BW,C48,CC:CC)+SUMIF(CM:CM,C48,CR:CR)+SUMIF(CV:CV,C48,DA:DA)+SUMIF(DE:DE,C48,DJ:DJ)+SUMIF(DN:DN,C48,DS:DS)+SUMIF(DX:DX,C48,EB:EB)+SUMIF(EG:EG,C48,EK:EK)+SUMIF(EP:EP,C48,EU:EU)+SUMIF(EY:EY,C48,FD:FD)+SUMIF(FH:FH,C48,FM:FM)+SUMIF(FQ:FQ,C48,FV:FV)+SUMIF(FZ:FZ,C48,GE:GE)+SUMIF(GI:GI,C48,GN:GN) -> 41637.268 | H48: =+SUM(F48:G48) -> 1725327.9 | I48: =+H48 -> 1725327.9 | J48: BISA | M48: 23 | N48: =+EOMONTH(O48,0) -> 47634 | O48: =+DATE(YEAR(O47),MONTH(O47)+3,DAY(O47)) -> 47618 | Q48: =+Q47-R48 -> 28510985 | R48: =+$Q$30/25 -> 4072997.9 | S48: =+Q47*Q$5*(O48-O47)/360 -> 483329.08 | U48: =+SUM(R48:T48) -> 4556327 | AC48: 23 | AD48: =+EOMONTH(AE48,0) -> 47817 | AE48: 47789 | AG48: =+AG47+AF48-AH48 -> 153251.34 | AH48: =+AH47 -> 51840.79 | AI48: =+AG47*AG$5*(AE48-AE47)/360 -> 2882.6838 | AJ48: =+SUM(AH48:AI48) -> 54723.474 | AR48: 23 | AS48: =+EOMONTH(AT48,0) -> 47726 | AT48: 47715 | AV48: =+AV47+AU48-AW48 -> 7070709.2 | AW48: 525047.46 | AX48: =+AV47*AV$5*(AT48-AT47)/360 -> 116468.27 | AY48: =+SUM(AW48:AX48) -> 641515.73 | CU48: 23 | CV48: =+EOMONTH(CW48,0) -> 46568 | CW48: 46548 | CY48: =+CY47+CX48-CZ48 -> 3167276.8 | CZ48: 1583638.4 | DA48: =+CY47*CY$5*(CW48-CW47)/360 -> 24546.395 | DB48: =+SUM(CZ48:DA48) -> 1608184.8 | DD48: 23 | DE48: =+EOMONTH(DF48,0) -> 47848 | DF48: 47836 | DH48: =+DH47+DG48-DI48 -> 3975625.7 | DI48: 283973.26 | DJ48: 62450.45 | DK48: =+SUM(DI48:DJ48) -> 346423.71 | DM48: 23 | DN48: =+EOMONTH(DO48,0) -> 47879 | DO48: 47854 | DQ48: =+DQ47-DR48 -> 394943.01 | DR48: 39494.31 | DS48: =+DQ47*(DO48-DO47)*$DQ$5/360 -> 6391.2971 | DT48: =+SUM(DR48:DS48) -> 45885.607 | EE48: 23 | EF48: =+EOMONTH(EG48,0) -> 47756 | EG48: 47745 | EI48: =+EI47+EH48-EJ48 -> 2100995 | EJ48: 40216.85 | EK48: 8362.36 | EM48: =+SUM(EJ48:EL48) -> 48579.21
A49: 24 | B49: =+WEEKNUM(C49,2) -> 36 | C49: =+EOMONTH(C48,1) -> 46630 | E49: =+E48+D49-F49 -> 1.3275542e+08 | F49: =+SUMIF(N:N,C49,R:R)+SUMIF(AD:AD,C49,AH:AH)+SUMIF(AS:AS,C49,AW:AW)+SUMIF(BH:BH,C49,BL:BL)+SUMIF(BW:BW,C49,CA:CA)+SUMIF(BW:BW,C49,CB:CB)+SUMIF(CM:CM,C49,CQ:CQ)+SUMIF(CV:CV,C49,CZ:CZ)+SUMIF(DE:DE,C49,DI:DI)+SUMIF(DN:DN,C49,DR:DR)+SUMIF(DW:DW,C49,EA:EA)+SUMIF(EF:EF,C49,EJ:EJ)+SUMIF(EP:EP,C49,ET:ET)+SUMIF(EY:EY,C49,FC:FC)+SUMIF(FH:FH,C49,FL:FL)+SUMIF(FQ:FQ,C49,FU:FU)+SUMIF(FZ:FZ,C49,GD:GD)+SUMIF(GI:GI,C49,GM:GM) -> 6292890.6 | G49: =+SUMIF(N:N,C49,S:S)+SUMIF(N:N,C49,T:T)+SUMIF(AD:AD,C49,AI:AI)+SUMIF(AS:AS,C49,AX:AX)+SUMIF(BH:BH,C49,BM:BM)+SUMIF(BW:BW,C49,CD:CD)+SUMIF(BW:BW,C49,CC:CC)+SUMIF(CM:CM,C49,CR:CR)+SUMIF(CV:CV,C49,DA:DA)+SUMIF(DE:DE,C49,DJ:DJ)+SUMIF(DN:DN,C49,DS:DS)+SUMIF(DX:DX,C49,EB:EB)+SUMIF(EG:EG,C49,EK:EK)+SUMIF(EP:EP,C49,EU:EU)+SUMIF(EY:EY,C49,FD:FD)+SUMIF(FH:FH,C49,FM:FM)+SUMIF(FQ:FQ,C49,FV:FV)+SUMIF(FZ:FZ,C49,GE:GE)+SUMIF(GI:GI,C49,GN:GN) -> 1916413 | H49: =+SUM(F49:G49) -> 8209303.6 | M49: 24 | N49: =+EOMONTH(O49,0) -> 47726 | O49: =+DATE(YEAR(O48),MONTH(O48)+3,DAY(O48)) -> 47710 | Q49: =+Q48-R49 -> 24437987 | R49: =+$Q$30/25 -> 4072997.9 | S49: =+Q48*Q$5*(O49-O48)/360 -> 437168.44 | U49: =+SUM(R49:T49) -> 4510166.3 | AC49: 24 | AD49: =+EOMONTH(AE49,0) -> 47907 | AE49: 47881 | AG49: =+AG48+AF49-AH49 -> 101410.55 | AH49: =+AH48 -> 51840.79 | AI49: =+AG48*AG$5*(AE49-AE48)/360 -> 2154.0327 | AJ49: =+SUM(AH49:AI49) -> 53994.823 | AR49: 24 | AS49: =+EOMONTH(AT49,0) -> 47817 | AT49: 47807 | AV49: =+AV48+AU49-AW49 -> 6545661.7 | AW49: 525047.46 | AX49: =+AV48*AV$5*(AT49-AT48)/360 -> 108417.54 | AY49: =+SUM(AW49:AX49) -> 633465.01 | CU49: 24 | CV49: =+EOMONTH(CW49,0) -> 46599 | CW49: 46578 | CY49: =+CY48+CX49-CZ49 -> 1583638.4 | CZ49: 1583638.4 | DA49: =+CY48*CY$5*(CW49-CW48)/360 -> 15836.384 | DB49: =+SUM(CZ49:DA49) -> 1599474.8 | DD49: 24 | DE49: =+EOMONTH(DF49,0) -> 47938 | DF49: 47927 | DH49: =+DH48+DG49-DI49 -> 3691652.4 | DI49: 283973.26 | DJ49: 58287.09 | DK49: =+SUM(DI49:DJ49) -> 342260.35 | DM49: 24 | DN49: =+EOMONTH(DO49,0) -> 47968 | DO49: 47945 | DQ49: =+DQ48-DR49 -> 355448.7 | DR49: 39494.31 | DS49: =+DQ48*(DO49-DO48)*$DQ$5/360 -> 5810.27 | DT49: =+SUM(DR49:DS49) -> 45304.58 | EE49: 24 | EF49: =+EOMONTH(EG49,0) -> 47848 | EG49: 47836 | EI49: =+EI48+EH49-EJ49 -> 2060778.2 | EJ49: 40216.85 | EK49: 7927.41 | EM49: =+SUM(EJ49:EL49) -> 48144.26
A50: 25 | B50: =+WEEKNUM(C50,2) -> 40 | C50: =+EOMONTH(C49,1) -> 46660 | E50: =+E49+D50-F50 -> 1.2697925e+08 | F50: =+SUMIF(N:N,C50,R:R)+SUMIF(AD:AD,C50,AH:AH)+SUMIF(AS:AS,C50,AW:AW)+SUMIF(BH:BH,C50,BL:BL)+SUMIF(BW:BW,C50,CA:CA)+SUMIF(BW:BW,C50,CB:CB)+SUMIF(CM:CM,C50,CQ:CQ)+SUMIF(CV:CV,C50,CZ:CZ)+SUMIF(DE:DE,C50,DI:DI)+SUMIF(DN:DN,C50,DR:DR)+SUMIF(DW:DW,C50,EA:EA)+SUMIF(EF:EF,C50,EJ:EJ)+SUMIF(EP:EP,C50,ET:ET)+SUMIF(EY:EY,C50,FC:FC)+SUMIF(FH:FH,C50,FL:FL)+SUMIF(FQ:FQ,C50,FU:FU)+SUMIF(FZ:FZ,C50,GD:GD)+SUMIF(GI:GI,C50,GM:GM) -> 5776169.4 | G50: =+SUMIF(N:N,C50,S:S)+SUMIF(N:N,C50,T:T)+SUMIF(AD:AD,C50,AI:AI)+SUMIF(AS:AS,C50,AX:AX)+SUMIF(BH:BH,C50,BM:BM)+SUMIF(BW:BW,C50,CD:CD)+SUMIF(BW:BW,C50,CC:CC)+SUMIF(CM:CM,C50,CR:CR)+SUMIF(CV:CV,C50,DA:DA)+SUMIF(DE:DE,C50,DJ:DJ)+SUMIF(DN:DN,C50,DS:DS)+SUMIF(DX:DX,C50,EB:EB)+SUMIF(EG:EG,C50,EK:EK)+SUMIF(EP:EP,C50,EU:EU)+SUMIF(EY:EY,C50,FD:FD)+SUMIF(FH:FH,C50,FM:FM)+SUMIF(FQ:FQ,C50,FV:FV)+SUMIF(FZ:FZ,C50,GE:GE)+SUMIF(GI:GI,C50,GN:GN) -> 619755.81 | H50: =+SUM(F50:G50) -> 6395925.2 | I50: =+H50 -> 6395925.2 | J50: BNB Leasing | M50: 25 | N50: =+EOMONTH(O50,0) -> 47817 | O50: =+DATE(YEAR(O49),MONTH(O49)+3,DAY(O49)) -> 47802 | Q50: =+Q49-R50 -> 20364989 | R50: =+$Q$30/25 -> 4072997.9 | S50: =+Q49*Q$5*(O50-O49)/360 -> 374715.81 | U50: =+SUM(R50:T50) -> 4447713.7 | AC50: 25 | AD50: =+EOMONTH(AE50,0) -> 47999 | AE50: 47970 | AG50: =+AG49+AF50-AH50 -> 49569.76 | AH50: =+AH49 -> 51840.79 | AI50: =+AG49*AG$5*(AE50-AE49)/360 -> 1378.9018 | AJ50: =+SUM(AH50:AI50) -> 53219.692 | AR50: 25 | AS50: =+EOMONTH(AT50,0) -> 47907 | AT50: 47899 | AV50: =+AV49+AU50-AW50 -> 6020614.2 | AW50: 525047.46 | AX50: =+AV49*AV$5*(AT50-AT49)/360 -> 100366.81 | AY50: =+SUM(AW50:AX50) -> 625414.28 | CU50: 25 | CV50: =+EOMONTH(CW50,0) -> 46630 | CW50: 46609 | CY50: =+CY49+CX50-CZ50 -> 0.068803104 | CZ50: 1583638.4 | DA50: =+CY49*CY$5*(CW50-CW49)/360 -> 8182.132 | DB50: =+SUM(CZ50:DA50) -> 1591820.5 | DD50: 25 | DE50: =+EOMONTH(DF50,0) -> 48029 | DF50: 48018 | DH50: =+DH49+DG50-DI50 -> 3407679.2 | DI50: 283973.26 | DJ50: 54123.72 | DK50: =+SUM(DI50:DJ50) -> 338096.98 | DM50: 25 | DN50: =+EOMONTH(DO50,0) -> 48060 | DO50: 48036 | DQ50: =+DQ49-DR50 -> 315954.39 | DR50: 39494.31 | DS50: =+DQ49*(DO50-DO49)*$DQ$5/360 -> 5229.2428 | DT50: =+SUM(DR50:DS50) -> 44723.553 | EE50: 25 | EF50: =+EOMONTH(EG50,0) -> 47938 | EG50: 47927 | EI50: =+EI49+EH50-EJ50 -> 2020561.3 | EJ50: 40216.85 | EK50: 7318.47 | EM50: =+SUM(EJ50:EL50) -> 47535.32
A51: 26 | B51: =+WEEKNUM(C51,2) -> 44 | C51: =+EOMONTH(C50,1) -> 46691 | E51: =+E50+D51-F51 -> 1.2687919e+08 | F51: =+SUMIF(N:N,C51,R:R)+SUMIF(AD:AD,C51,AH:AH)+SUMIF(AS:AS,C51,AW:AW)+SUMIF(BH:BH,C51,BL:BL)+SUMIF(BW:BW,C51,CA:CA)+SUMIF(BW:BW,C51,CB:CB)+SUMIF(CM:CM,C51,CQ:CQ)+SUMIF(CV:CV,C51,CZ:CZ)+SUMIF(DE:DE,C51,DI:DI)+SUMIF(DN:DN,C51,DR:DR)+SUMIF(DW:DW,C51,EA:EA)+SUMIF(EF:EF,C51,EJ:EJ)+SUMIF(EP:EP,C51,ET:ET)+SUMIF(EY:EY,C51,FC:FC)+SUMIF(FH:FH,C51,FL:FL)+SUMIF(FQ:FQ,C51,FU:FU)+SUMIF(FZ:FZ,C51,GD:GD)+SUMIF(GI:GI,C51,GM:GM) -> 100052.21 | G51: =+SUMIF(N:N,C51,S:S)+SUMIF(N:N,C51,T:T)+SUMIF(AD:AD,C51,AI:AI)+SUMIF(AS:AS,C51,AX:AX)+SUMIF(BH:BH,C51,BM:BM)+SUMIF(BW:BW,C51,CD:CD)+SUMIF(BW:BW,C51,CC:CC)+SUMIF(CM:CM,C51,CR:CR)+SUMIF(CV:CV,C51,DA:DA)+SUMIF(DE:DE,C51,DJ:DJ)+SUMIF(DN:DN,C51,DS:DS)+SUMIF(DX:DX,C51,EB:EB)+SUMIF(EG:EG,C51,EK:EK)+SUMIF(EP:EP,C51,EU:EU)+SUMIF(EY:EY,C51,FD:FD)+SUMIF(FH:FH,C51,FM:FM)+SUMIF(FQ:FQ,C51,FV:FV)+SUMIF(FZ:FZ,C51,GE:GE)+SUMIF(GI:GI,C51,GN:GN) -> 24593.652 | H51: =+SUM(F51:G51) -> 124645.86 | M51: 26 | N51: =+EOMONTH(O51,0) -> 47907 | O51: =+DATE(YEAR(O50),MONTH(O50)+3,DAY(O50)) -> 47894 | Q51: =+Q50-R51 -> 16291992 | R51: =+$Q$30/25 -> 4072997.9 | S51: =+Q50*Q$5*(O51-O50)/360 -> 312263.17 | U51: =+SUM(R51:T51) -> 4385261.1 | AC51: 26 | AD51: =+EOMONTH(AE51,0) -> 48060 | AE51: 48058 | AG51: =+AG50+AF51-AH51 -> -4.802132e-10 | AH51: 49569.76 | AI51: =+AG50*AG$5*(AE51-AE50)/360 -> 666.43788 | AJ51: =+SUM(AH51:AI51) -> 50236.198 | AR51: 26 | AS51: =+EOMONTH(AT51,0) -> 47999 | AT51: 47988 | AV51: =+AV50+AU51-AW51 -> 5495566.8 | AW51: 525047.46 | AX51: =+AV50*AV$5*(AT51-AT50)/360 -> 89305.778 | AY51: =+SUM(AW51:AX51) -> 614353.24 | DD51: 26 | DE51: =+EOMONTH(DF51,0) -> 48121 | DF51: 48109 | DH51: =+DH50+DG51-DI51 -> 3123705.9 | DI51: 283973.26 | DJ51: 49960.37 | DK51: =+SUM(DI51:DJ51) -> 333933.63 | DM51: 26 | DN51: =+EOMONTH(DO51,0) -> 48152 | DO51: 48127 | DQ51: =+DQ50-DR51 -> 276460.08 | DR51: 39494.31 | DS51: =+DQ50*(DO51-DO50)*$DQ$5/360 -> 4648.2157 | DT51: =+SUM(DR51:DS51) -> 44142.526 | EE51: 26 | EF51: =+EOMONTH(EG51,0) -> 48029 | EG51: 48018 | EI51: =+EI50+EH51-EJ51 -> 1980344.5 | EJ51: 40216.85 | EK51: 6709.53 | EM51: =+SUM(EJ51:EL51) -> 46926.38
A52: 27 | B52: =+WEEKNUM(C52,2) -> 49 | C52: =+EOMONTH(C51,1) -> 46721 | E52: =+E51+D52-F52 -> 1.2214812e+08 | F52: =+SUMIF(N:N,C52,R:R)+SUMIF(AD:AD,C52,AH:AH)+SUMIF(AS:AS,C52,AW:AW)+SUMIF(BH:BH,C52,BL:BL)+SUMIF(BW:BW,C52,CA:CA)+SUMIF(BW:BW,C52,CB:CB)+SUMIF(CM:CM,C52,CQ:CQ)+SUMIF(CV:CV,C52,CZ:CZ)+SUMIF(DE:DE,C52,DI:DI)+SUMIF(DN:DN,C52,DR:DR)+SUMIF(DW:DW,C52,EA:EA)+SUMIF(EF:EF,C52,EJ:EJ)+SUMIF(EP:EP,C52,ET:ET)+SUMIF(EY:EY,C52,FC:FC)+SUMIF(FH:FH,C52,FL:FL)+SUMIF(FQ:FQ,C52,FU:FU)+SUMIF(FZ:FZ,C52,GD:GD)+SUMIF(GI:GI,C52,GM:GM) -> 4731079.1 | G52: =+SUMIF(N:N,C52,S:S)+SUMIF(N:N,C52,T:T)+SUMIF(AD:AD,C52,AI:AI)+SUMIF(AS:AS,C52,AX:AX)+SUMIF(BH:BH,C52,BM:BM)+SUMIF(BW:BW,C52,CD:CD)+SUMIF(BW:BW,C52,CC:CC)+SUMIF(CM:CM,C52,CR:CR)+SUMIF(CV:CV,C52,DA:DA)+SUMIF(DE:DE,C52,DJ:DJ)+SUMIF(DN:DN,C52,DS:DS)+SUMIF(DX:DX,C52,EB:EB)+SUMIF(EG:EG,C52,EK:EK)+SUMIF(EP:EP,C52,EU:EU)+SUMIF(EY:EY,C52,FD:FD)+SUMIF(FH:FH,C52,FM:FM)+SUMIF(FQ:FQ,C52,FV:FV)+SUMIF(FZ:FZ,C52,GE:GE)+SUMIF(GI:GI,C52,GN:GN) -> 1846300.8 | H52: =+SUM(F52:G52) -> 6577379.9 | M52: 27 | N52: =+EOMONTH(O52,0) -> 47999 | O52: =+DATE(YEAR(O51),MONTH(O51)+3,DAY(O51)) -> 47983 | Q52: =+Q51-R52 -> 12218994 | R52: =+$Q$30/25 -> 4072997.9 | S52: =+Q51*Q$5*(O52-O51)/360 -> 241664.54 | U52: =+SUM(R52:T52) -> 4314662.4 | AR52: 27 | AS52: =+EOMONTH(AT52,0) -> 48091 | AT52: 48080 | AV52: =+AV51+AU52-AW52 -> 4970519.3 | AW52: 525047.46 | AX52: =+AV51*AV$5*(AT52-AT51)/360 -> 84265.357 | AY52: =+SUM(AW52:AX52) -> 609312.82 | DD52: 27 | DE52: =+EOMONTH(DF52,0) -> 48213 | DF52: 48200 | DH52: =+DH51+DG52-DI52 -> 2839732.6 | DI52: 283973.26 | DJ52: 45797 | DK52: =+SUM(DI52:DJ52) -> 329770.26 | DM52: 27 | DN52: =+EOMONTH(DO52,0) -> 48244 | DO52: 48218 | DQ52: =+DQ51-DR52 -> 236965.77 | DR52: 39494.31 | DS52: =+DQ51*(DO52-DO51)*$DQ$5/360 -> 4067.1886 | DT52: =+SUM(DR52:DS52) -> 43561.499 | EE52: 27 | EF52: =+EOMONTH(EG52,0) -> 48121 | EG52: 48109 | EI52: =+EI51+EH52-EJ52 -> 1940127.6 | EJ52: 40216.85 | EK52: 6100.59 | EM52: =+SUM(EJ52:EL52) -> 46317.44
A53: 28 | B53: =+WEEKNUM(C53,2) -> 53 | C53: =+EOMONTH(C52,1) -> 46752 | E53: =+E52+D53-F53 -> 1.1637195e+08 | F53: =+SUMIF(N:N,C53,R:R)+SUMIF(AD:AD,C53,AH:AH)+SUMIF(AS:AS,C53,AW:AW)+SUMIF(BH:BH,C53,BL:BL)+SUMIF(BW:BW,C53,CA:CA)+SUMIF(BW:BW,C53,CB:CB)+SUMIF(CM:CM,C53,CQ:CQ)+SUMIF(CV:CV,C53,CZ:CZ)+SUMIF(DE:DE,C53,DI:DI)+SUMIF(DN:DN,C53,DR:DR)+SUMIF(DW:DW,C53,EA:EA)+SUMIF(EF:EF,C53,EJ:EJ)+SUMIF(EP:EP,C53,ET:ET)+SUMIF(EY:EY,C53,FC:FC)+SUMIF(FH:FH,C53,FL:FL)+SUMIF(FQ:FQ,C53,FU:FU)+SUMIF(FZ:FZ,C53,GD:GD)+SUMIF(GI:GI,C53,GM:GM) -> 5776169.4 | G53: =+SUMIF(N:N,C53,S:S)+SUMIF(N:N,C53,T:T)+SUMIF(AD:AD,C53,AI:AI)+SUMIF(AS:AS,C53,AX:AX)+SUMIF(BH:BH,C53,BM:BM)+SUMIF(BW:BW,C53,CD:CD)+SUMIF(BW:BW,C53,CC:CC)+SUMIF(CM:CM,C53,CR:CR)+SUMIF(CV:CV,C53,DA:DA)+SUMIF(DE:DE,C53,DJ:DJ)+SUMIF(DN:DN,C53,DS:DS)+SUMIF(DX:DX,C53,EB:EB)+SUMIF(EG:EG,C53,EK:EK)+SUMIF(EP:EP,C53,EU:EU)+SUMIF(EY:EY,C53,FD:FD)+SUMIF(FH:FH,C53,FM:FM)+SUMIF(FQ:FQ,C53,FV:FV)+SUMIF(FZ:FZ,C53,GE:GE)+SUMIF(GI:GI,C53,GN:GN) -> 527434.74 | H53: =+SUM(F53:G53) -> 6303604.1 | I53: =+H53 -> 6303604.1 | J53: BDP | M53: 28 | N53: =+EOMONTH(O53,0) -> 48091 | O53: =+DATE(YEAR(O52),MONTH(O52)+3,DAY(O52)) -> 48075 | Q53: =+Q52-R53 -> 8145995.8 | R53: =+$Q$30/25 -> 4072997.9 | S53: =+Q52*Q$5*(O53-O52)/360 -> 187357.9 | U53: =+SUM(R53:T53) -> 4260355.8 | AR53: 28 | AS53: =+EOMONTH(AT53,0) -> 48182 | AT53: 48172 | AV53: =+AV52+AU53-AW53 -> 4445471.8 | AW53: 525047.46 | AX53: =+AV52*AV$5*(AT53-AT52)/360 -> 76214.629 | AY53: =+SUM(AW53:AX53) -> 601262.09 | DD53: 28 | DE53: =+EOMONTH(DF53,0) -> 48304 | DF53: 48291 | DH53: =+DH52+DG53-DI53 -> 2555759.4 | DI53: 283973.26 | DJ53: 41633.64 | DK53: =+SUM(DI53:DJ53) -> 325606.9 | DM53: 28 | DN53: =+EOMONTH(DO53,0) -> 48334 | DO53: 48309 | DQ53: =+DQ52-DR53 -> 197471.46 | DR53: 39494.31 | DS53: =+DQ52*(DO53-DO52)*$DQ$5/360 -> 3486.1615 | DT53: =+SUM(DR53:DS53) -> 42980.471 | EE53: 28 | EF53: =+EOMONTH(EG53,0) -> 48213 | EG53: 48200 | EI53: =+EI52+EH53-EJ53 -> 1899910.8 | EJ53: 40216.85 | EK53: 5491.65 | EM53: =+SUM(EJ53:EL53) -> 45708.5
A54: 29 | B54: =+WEEKNUM(C54,2) -> 6 | C54: =+EOMONTH(C53,1) -> 46783 | E54: =+E53+D54-F54 -> 1.1627189e+08 | F54: =+SUMIF(N:N,C54,R:R)+SUMIF(AD:AD,C54,AH:AH)+SUMIF(AS:AS,C54,AW:AW)+SUMIF(BH:BH,C54,BL:BL)+SUMIF(BW:BW,C54,CA:CA)+SUMIF(BW:BW,C54,CB:CB)+SUMIF(CM:CM,C54,CQ:CQ)+SUMIF(CV:CV,C54,CZ:CZ)+SUMIF(DE:DE,C54,DI:DI)+SUMIF(DN:DN,C54,DR:DR)+SUMIF(DW:DW,C54,EA:EA)+SUMIF(EF:EF,C54,EJ:EJ)+SUMIF(EP:EP,C54,ET:ET)+SUMIF(EY:EY,C54,FC:FC)+SUMIF(FH:FH,C54,FL:FL)+SUMIF(FQ:FQ,C54,FU:FU)+SUMIF(FZ:FZ,C54,GD:GD)+SUMIF(GI:GI,C54,GM:GM) -> 100052.21 | G54: =+SUMIF(N:N,C54,S:S)+SUMIF(N:N,C54,T:T)+SUMIF(AD:AD,C54,AI:AI)+SUMIF(AS:AS,C54,AX:AX)+SUMIF(BH:BH,C54,BM:BM)+SUMIF(BW:BW,C54,CD:CD)+SUMIF(BW:BW,C54,CC:CC)+SUMIF(CM:CM,C54,CR:CR)+SUMIF(CV:CV,C54,DA:DA)+SUMIF(DE:DE,C54,DJ:DJ)+SUMIF(DN:DN,C54,DS:DS)+SUMIF(DX:DX,C54,EB:EB)+SUMIF(EG:EG,C54,EK:EK)+SUMIF(EP:EP,C54,EU:EU)+SUMIF(EY:EY,C54,FD:FD)+SUMIF(FH:FH,C54,FM:FM)+SUMIF(FQ:FQ,C54,FV:FV)+SUMIF(FZ:FZ,C54,GE:GE)+SUMIF(GI:GI,C54,GN:GN) -> 23120.948 | H54: =+SUM(F54:G54) -> 123173.16 | M54: 29 | N54: =+EOMONTH(O54,0) -> 48182 | O54: =+DATE(YEAR(O53),MONTH(O53)+3,DAY(O53)) -> 48167 | Q54: =+Q53-R54 -> 4072997.9 | R54: =+$Q$30/25 -> 4072997.9 | S54: =+Q53*Q$5*(O54-O53)/360 -> 124905.27 | U54: =+SUM(R54:T54) -> 4197903.1 | AR54: 29 | AS54: =+EOMONTH(AT54,0) -> 48273 | AT54: 48264 | AV54: =+AV53+AU54-AW54 -> 3920424.4 | AW54: 525047.46 | AX54: =+AV53*AV$5*(AT54-AT53)/360 -> 68163.902 | AY54: =+SUM(AW54:AX54) -> 593211.37 | DD54: 29 | DE54: =+EOMONTH(DF54,0) -> 48395 | DF54: 48382 | DH54: =+DH53+DG54-DI54 -> 2271786.1 | DI54: 283973.26 | DJ54: 37470.27 | DK54: =+SUM(DI54:DJ54) -> 321443.53 | DM54: 29 | DN54: =+EOMONTH(DO54,0) -> 48426 | DO54: 48400 | DQ54: =+DQ53-DR54 -> 157977.15 | DR54: 39494.31 | DS54: =+DQ53*(DO54-DO53)*$DQ$5/360 -> 2905.1343 | DT54: =+SUM(DR54:DS54) -> 42399.444 | EE54: 29 | EF54: =+EOMONTH(EG54,0) -> 48304 | EG54: 48291 | EI54: =+EI53+EH54-EJ54 -> 1859693.9 | EJ54: 40216.85 | EK54: 4882.71 | EM54: =+SUM(EJ54:EL54) -> 45099.56
A55: 30 | B55: =+WEEKNUM(C55,2) -> 10 | C55: =+EOMONTH(C54,1) -> 46812 | E55: =+E54+D55-F55 -> 1.1162201e+08 | F55: =+SUMIF(N:N,C55,R:R)+SUMIF(AD:AD,C55,AH:AH)+SUMIF(AS:AS,C55,AW:AW)+SUMIF(BH:BH,C55,BL:BL)+SUMIF(BW:BW,C55,CA:CA)+SUMIF(BW:BW,C55,CB:CB)+SUMIF(CM:CM,C55,CQ:CQ)+SUMIF(CV:CV,C55,CZ:CZ)+SUMIF(DE:DE,C55,DI:DI)+SUMIF(DN:DN,C55,DR:DR)+SUMIF(DW:DW,C55,EA:EA)+SUMIF(EF:EF,C55,EJ:EJ)+SUMIF(EP:EP,C55,ET:ET)+SUMIF(EY:EY,C55,FC:FC)+SUMIF(FH:FH,C55,FL:FL)+SUMIF(FQ:FQ,C55,FU:FU)+SUMIF(FZ:FZ,C55,GD:GD)+SUMIF(GI:GI,C55,GM:GM) -> 4649886.1 | G55: =+SUMIF(N:N,C55,S:S)+SUMIF(N:N,C55,T:T)+SUMIF(AD:AD,C55,AI:AI)+SUMIF(AS:AS,C55,AX:AX)+SUMIF(BH:BH,C55,BM:BM)+SUMIF(BW:BW,C55,CD:CD)+SUMIF(BW:BW,C55,CC:CC)+SUMIF(CM:CM,C55,CR:CR)+SUMIF(CV:CV,C55,DA:DA)+SUMIF(DE:DE,C55,DJ:DJ)+SUMIF(DN:DN,C55,DS:DS)+SUMIF(DX:DX,C55,EB:EB)+SUMIF(EG:EG,C55,EK:EK)+SUMIF(EP:EP,C55,EU:EU)+SUMIF(EY:EY,C55,FD:FD)+SUMIF(FH:FH,C55,FM:FM)+SUMIF(FQ:FQ,C55,FV:FV)+SUMIF(FZ:FZ,C55,GE:GE)+SUMIF(GI:GI,C55,GN:GN) -> 1741118.7 | H55: =+SUM(F55:G55) -> 6391004.9 | M55: 30 | N55: =+EOMONTH(O55,0) -> 48273 | O55: =+DATE(YEAR(O54),MONTH(O54)+3,4) -> 48248 | Q55: =+Q54-R55 -> 5.5879354e-08 | R55: =+$Q$30/25 -> 4072997.9 | S55: =+Q54*Q$5*(O55-O54)/360 -> 54985.471 | U55: =+SUM(R55:T55) -> 4127983.4 | AR55: 30 | AS55: =+EOMONTH(AT55,0) -> 48365 | AT55: 48354 | AV55: =+AV54+AU55-AW55 -> 3395376.9 | AW55: 525047.46 | AX55: =+AV54*AV$5*(AT55-AT54)/360 -> 58806.366 | AY55: =+SUM(AW55:AX55) -> 583853.83 | DD55: 30 | DE55: =+EOMONTH(DF55,0) -> 48487 | DF55: 48473 | DH55: =+DH54+DG55-DI55 -> 1987812.9 | DI55: 283973.26 | DJ55: 33306.91 | DK55: =+SUM(DI55:DJ55) -> 317280.17 | DM55: 30 | DN55: =+EOMONTH(DO55,0) -> 48518 | DO55: 48492 | DQ55: =+DQ54-DR55 -> 118482.84 | DR55: 39494.31 | DS55: =+DQ54*(DO55-DO54)*$DQ$5/360 -> 2349.6469 | DT55: =+SUM(DR55:DS55) -> 41843.957 | EE55: 30 | EF55: =+EOMONTH(EG55,0) -> 48395 | EG55: 48382 | EI55: =+EI54+EH55-EJ55 -> 1819477.1 | EJ55: 40216.85 | EK55: 4273.77 | EM55: =+SUM(EJ55:EL55) -> 44490.62
A56: 31 | B56: =+WEEKNUM(C56,2) -> 14 | C56: =+EOMONTH(C55,1) -> 46843 | E56: =+E55+D56-F56 -> 1.0584584e+08 | F56: =+SUMIF(N:N,C56,R:R)+SUMIF(AD:AD,C56,AH:AH)+SUMIF(AS:AS,C56,AW:AW)+SUMIF(BH:BH,C56,BL:BL)+SUMIF(BW:BW,C56,CA:CA)+SUMIF(BW:BW,C56,CB:CB)+SUMIF(CM:CM,C56,CQ:CQ)+SUMIF(CV:CV,C56,CZ:CZ)+SUMIF(DE:DE,C56,DI:DI)+SUMIF(DN:DN,C56,DR:DR)+SUMIF(DW:DW,C56,EA:EA)+SUMIF(EF:EF,C56,EJ:EJ)+SUMIF(EP:EP,C56,ET:ET)+SUMIF(EY:EY,C56,FC:FC)+SUMIF(FH:FH,C56,FL:FL)+SUMIF(FQ:FQ,C56,FU:FU)+SUMIF(FZ:FZ,C56,GD:GD)+SUMIF(GI:GI,C56,GM:GM) -> 5776169.4 | G56: =+SUMIF(N:N,C56,S:S)+SUMIF(N:N,C56,T:T)+SUMIF(AD:AD,C56,AI:AI)+SUMIF(AS:AS,C56,AX:AX)+SUMIF(BH:BH,C56,BM:BM)+SUMIF(BW:BW,C56,CD:CD)+SUMIF(BW:BW,C56,CC:CC)+SUMIF(CM:CM,C56,CR:CR)+SUMIF(CV:CV,C56,DA:DA)+SUMIF(DE:DE,C56,DJ:DJ)+SUMIF(DN:DN,C56,DS:DS)+SUMIF(DX:DX,C56,EB:EB)+SUMIF(EG:EG,C56,EK:EK)+SUMIF(EP:EP,C56,EU:EU)+SUMIF(EY:EY,C56,FD:FD)+SUMIF(FH:FH,C56,FM:FM)+SUMIF(FQ:FQ,C56,FV:FV)+SUMIF(FZ:FZ,C56,GE:GE)+SUMIF(GI:GI,C56,GN:GN) -> 440583.01 | H56: =+SUM(F56:G56) -> 6216752.4 | AR56: 31 | AS56: =+EOMONTH(AT56,0) -> 48457 | AT56: 48446 | AV56: =+AV55+AU56-AW56 -> 2870329.4 | AW56: 525047.46 | AX56: =+AV55*AV$5*(AT56-AT55)/360 -> 52062.446 | AY56: =+SUM(AW56:AX56) -> 577109.91 | DD56: 31 | DE56: =+EOMONTH(DF56,0) -> 48579 | DF56: 48564 | DH56: =+DH55+DG56-DI56 -> 1703839.6 | DI56: 283973.26 | DJ56: 29143.54 | DK56: =+SUM(DI56:DJ56) -> 313116.8 | DM56: 31 | DN56: =+EOMONTH(DO56,0) -> 48610 | DO56: 48584 | DQ56: =+DQ55-DR56 -> 78988.533 | DR56: 39494.31 | DS56: =+DQ55*(DO56-DO55)*$DQ$5/360 -> 1762.2348 | DT56: =+SUM(DR56:DS56) -> 41256.545 | EE56: 31 | EF56: =+EOMONTH(EG56,0) -> 48487 | EG56: 48473 | EI56: =+EI55+EH56-EJ56 -> 1779260.2 | EJ56: 40216.85 | EK56: 3664.84 | EM56: =+SUM(EJ56:EL56) -> 43881.69
A57: 32 | B57: =+WEEKNUM(C57,2) -> 18 | C57: =+EOMONTH(C56,1) -> 46873 | E57: =+E56+D57-F57 -> 1.0574579e+08 | F57: =+SUMIF(N:N,C57,R:R)+SUMIF(AD:AD,C57,AH:AH)+SUMIF(AS:AS,C57,AW:AW)+SUMIF(BH:BH,C57,BL:BL)+SUMIF(BW:BW,C57,CA:CA)+SUMIF(BW:BW,C57,CB:CB)+SUMIF(CM:CM,C57,CQ:CQ)+SUMIF(CV:CV,C57,CZ:CZ)+SUMIF(DE:DE,C57,DI:DI)+SUMIF(DN:DN,C57,DR:DR)+SUMIF(DW:DW,C57,EA:EA)+SUMIF(EF:EF,C57,EJ:EJ)+SUMIF(EP:EP,C57,ET:ET)+SUMIF(EY:EY,C57,FC:FC)+SUMIF(FH:FH,C57,FL:FL)+SUMIF(FQ:FQ,C57,FU:FU)+SUMIF(FZ:FZ,C57,GD:GD)+SUMIF(GI:GI,C57,GM:GM) -> 100052.21 | G57: =+SUMIF(N:N,C57,S:S)+SUMIF(N:N,C57,T:T)+SUMIF(AD:AD,C57,AI:AI)+SUMIF(AS:AS,C57,AX:AX)+SUMIF(BH:BH,C57,BM:BM)+SUMIF(BW:BW,C57,CD:CD)+SUMIF(BW:BW,C57,CC:CC)+SUMIF(CM:CM,C57,CR:CR)+SUMIF(CV:CV,C57,DA:DA)+SUMIF(DE:DE,C57,DJ:DJ)+SUMIF(DN:DN,C57,DS:DS)+SUMIF(DX:DX,C57,EB:EB)+SUMIF(EG:EG,C57,EK:EK)+SUMIF(EP:EP,C57,EU:EU)+SUMIF(EY:EY,C57,FD:FD)+SUMIF(FH:FH,C57,FM:FM)+SUMIF(FQ:FQ,C57,FV:FV)+SUMIF(FZ:FZ,C57,GE:GE)+SUMIF(GI:GI,C57,GN:GN) -> 21430.793 | H57: =+SUM(F57:G57) -> 121483 | AR57: 32 | AS57: =+EOMONTH(AT57,0) -> 48548 | AT57: 48538 | AV57: =+AV56+AU57-AW57 -> 2345282 | AW57: 525047.46 | AX57: =+AV56*AV$5*(AT57-AT56)/360 -> 44011.718 | AY57: =+SUM(AW57:AX57) -> 569059.18 | DD57: 32 | DE57: =+EOMONTH(DF57,0) -> 48669 | DF57: 48655 | DH57: =+DH56+DG57-DI57 -> 1419866.3 | DI57: 283973.26 | DJ57: 24980.18 | DK57: =+SUM(DI57:DJ57) -> 308953.44 | DM57: 32 | DN57: =+EOMONTH(DO57,0) -> 48699 | DO57: 48674 | DQ57: =+DQ56-DR57 -> 39494.223 | DR57: 39494.31 | DS57: =+DQ56*(DO57-DO56)*$DQ$5/360 -> 1149.2832 | DT57: =+SUM(DR57:DS57) -> 40643.593 | EE57: 32 | EF57: =+EOMONTH(EG57,0) -> 48579 | EG57: 48564 | EI57: =+EI56+EH57-EJ57 -> 1739043.4 | EJ57: 40216.85 | EK57: 3055.9 | EM57: =+SUM(EJ57:EL57) -> 43272.75
A58: 33 | B58: =+WEEKNUM(C58,2) -> 23 | C58: =+EOMONTH(C57,1) -> 46904 | E58: =+E57+D58-F58 -> 1.010959e+08 | F58: =+SUMIF(N:N,C58,R:R)+SUMIF(AD:AD,C58,AH:AH)+SUMIF(AS:AS,C58,AW:AW)+SUMIF(BH:BH,C58,BL:BL)+SUMIF(BW:BW,C58,CA:CA)+SUMIF(BW:BW,C58,CB:CB)+SUMIF(CM:CM,C58,CQ:CQ)+SUMIF(CV:CV,C58,CZ:CZ)+SUMIF(DE:DE,C58,DI:DI)+SUMIF(DN:DN,C58,DR:DR)+SUMIF(DW:DW,C58,EA:EA)+SUMIF(EF:EF,C58,EJ:EJ)+SUMIF(EP:EP,C58,ET:ET)+SUMIF(EY:EY,C58,FC:FC)+SUMIF(FH:FH,C58,FL:FL)+SUMIF(FQ:FQ,C58,FU:FU)+SUMIF(FZ:FZ,C58,GD:GD)+SUMIF(GI:GI,C58,GM:GM) -> 4649886.1 | G58: =+SUMIF(N:N,C58,S:S)+SUMIF(N:N,C58,T:T)+SUMIF(AD:AD,C58,AI:AI)+SUMIF(AS:AS,C58,AX:AX)+SUMIF(BH:BH,C58,BM:BM)+SUMIF(BW:BW,C58,CD:CD)+SUMIF(BW:BW,C58,CC:CC)+SUMIF(CM:CM,C58,CR:CR)+SUMIF(CV:CV,C58,DA:DA)+SUMIF(DE:DE,C58,DJ:DJ)+SUMIF(DN:DN,C58,DS:DS)+SUMIF(DX:DX,C58,EB:EB)+SUMIF(EG:EG,C58,EK:EK)+SUMIF(EP:EP,C58,EU:EU)+SUMIF(EY:EY,C58,FD:FD)+SUMIF(FH:FH,C58,FM:FM)+SUMIF(FQ:FQ,C58,FV:FV)+SUMIF(FZ:FZ,C58,GE:GE)+SUMIF(GI:GI,C58,GN:GN) -> 1643835.9 | H58: =+SUM(F58:G58) -> 6293722.1 | AR58: 33 | AS58: =+EOMONTH(AT58,0) -> 48638 | AT58: 48630 | AV58: =+AV57+AU58-AW58 -> 1820234.5 | AW58: 525047.46 | AX58: =+AV57*AV$5*(AT58-AT57)/360 -> 35960.99 | AY58: =+SUM(AW58:AX58) -> 561008.46 | DD58: 33 | DE58: =+EOMONTH(DF58,0) -> 48760 | DF58: 48747 | DH58: =+DH57+DG58-DI58 -> 1135893.1 | DI58: 283973.26 | DJ58: 21045.58 | DK58: =+SUM(DI58:DJ58) -> 305018.84 | DM58: 33 | DN58: =+EOMONTH(DO58,0) -> 48791 | DO58: 48765 | DQ58: =+DQ57-DR58 -> -0.087313402 | DR58: 39494.31 | DS58: =+DQ57*(DO58-DO57)*$DQ$5/360 -> 581.02584 | DT58: =+SUM(DR58:DS58) -> 40075.336 | EE58: 33 | EF58: =+EOMONTH(EG58,0) -> 48669 | EG58: 48655 | EI58: =+EI57+EH58-EJ58 -> 1698826.5 | EJ58: 40216.85 | EK58: 2446.96 | EM58: =+SUM(EJ58:EL58) -> 42663.81
A59: 34 | B59: =+WEEKNUM(C59,2) -> 27 | C59: =+EOMONTH(C58,1) -> 46934 | E59: =+E58+D59-F59 -> 95319731 | F59: =+SUMIF(N:N,C59,R:R)+SUMIF(AD:AD,C59,AH:AH)+SUMIF(AS:AS,C59,AW:AW)+SUMIF(BH:BH,C59,BL:BL)+SUMIF(BW:BW,C59,CA:CA)+SUMIF(BW:BW,C59,CB:CB)+SUMIF(CM:CM,C59,CQ:CQ)+SUMIF(CV:CV,C59,CZ:CZ)+SUMIF(DE:DE,C59,DI:DI)+SUMIF(DN:DN,C59,DR:DR)+SUMIF(DW:DW,C59,EA:EA)+SUMIF(EF:EF,C59,EJ:EJ)+SUMIF(EP:EP,C59,ET:ET)+SUMIF(EY:EY,C59,FC:FC)+SUMIF(FH:FH,C59,FL:FL)+SUMIF(FQ:FQ,C59,FU:FU)+SUMIF(FZ:FZ,C59,GD:GD)+SUMIF(GI:GI,C59,GM:GM) -> 5776169.4 | G59: =+SUMIF(N:N,C59,S:S)+SUMIF(N:N,C59,T:T)+SUMIF(AD:AD,C59,AI:AI)+SUMIF(AS:AS,C59,AX:AX)+SUMIF(BH:BH,C59,BM:BM)+SUMIF(BW:BW,C59,CD:CD)+SUMIF(BW:BW,C59,CC:CC)+SUMIF(CM:CM,C59,CR:CR)+SUMIF(CV:CV,C59,DA:DA)+SUMIF(DE:DE,C59,DJ:DJ)+SUMIF(DN:DN,C59,DS:DS)+SUMIF(DX:DX,C59,EB:EB)+SUMIF(EG:EG,C59,EK:EK)+SUMIF(EP:EP,C59,EU:EU)+SUMIF(EY:EY,C59,FD:FD)+SUMIF(FH:FH,C59,FM:FM)+SUMIF(FQ:FQ,C59,FV:FV)+SUMIF(FZ:FZ,C59,GE:GE)+SUMIF(GI:GI,C59,GN:GN) -> 356474.68 | H59: =+SUM(F59:G59) -> 6132644.1 | AR59: 34 | AS59: =+EOMONTH(AT59,0) -> 48730 | AT59: 48719 | AV59: =+AV58+AU59-AW59 -> 1295187.1 | AW59: 525047.46 | AX59: =+AV58*AV$5*(AT59-AT58)/360 -> 27000.145 | AY59: =+SUM(AW59:AX59) -> 552047.61 | DD59: 34 | DE59: =+EOMONTH(DF59,0) -> 48852 | DF59: 48837 | DH59: =+DH58+DG59-DI59 -> 851919.82 | DI59: 283973.26 | DJ59: 16470.45 | DK59: =+SUM(DI59:DJ59) -> 300443.71 | EE59: 34 | EF59: =+EOMONTH(EG59,0) -> 48760 | EG59: 48747 | EI59: =+EI58+EH59-EJ59 -> 1658609.7 | EJ59: 40216.85 | EK59: 1851.4 | EM59: =+SUM(EJ59:EL59) -> 42068.25
A60: 35 | B60: =+WEEKNUM(C60,2) -> 32 | C60: =+EOMONTH(C59,1) -> 46965 | E60: =+E59+D60-F60 -> 95219679 | F60: =+SUMIF(N:N,C60,R:R)+SUMIF(AD:AD,C60,AH:AH)+SUMIF(AS:AS,C60,AW:AW)+SUMIF(BH:BH,C60,BL:BL)+SUMIF(BW:BW,C60,CA:CA)+SUMIF(BW:BW,C60,CB:CB)+SUMIF(CM:CM,C60,CQ:CQ)+SUMIF(CV:CV,C60,CZ:CZ)+SUMIF(DE:DE,C60,DI:DI)+SUMIF(DN:DN,C60,DR:DR)+SUMIF(DW:DW,C60,EA:EA)+SUMIF(EF:EF,C60,EJ:EJ)+SUMIF(EP:EP,C60,ET:ET)+SUMIF(EY:EY,C60,FC:FC)+SUMIF(FH:FH,C60,FL:FL)+SUMIF(FQ:FQ,C60,FU:FU)+SUMIF(FZ:FZ,C60,GD:GD)+SUMIF(GI:GI,C60,GM:GM) -> 100052.21 | G60: =+SUMIF(N:N,C60,S:S)+SUMIF(N:N,C60,T:T)+SUMIF(AD:AD,C60,AI:AI)+SUMIF(AS:AS,C60,AX:AX)+SUMIF(BH:BH,C60,BM:BM)+SUMIF(BW:BW,C60,CD:CD)+SUMIF(BW:BW,C60,CC:CC)+SUMIF(CM:CM,C60,CR:CR)+SUMIF(CV:CV,C60,DA:DA)+SUMIF(DE:DE,C60,DJ:DJ)+SUMIF(DN:DN,C60,DS:DS)+SUMIF(DX:DX,C60,EB:EB)+SUMIF(EG:EG,C60,EK:EK)+SUMIF(EP:EP,C60,EU:EU)+SUMIF(EY:EY,C60,FD:FD)+SUMIF(FH:FH,C60,FM:FM)+SUMIF(FQ:FQ,C60,FV:FV)+SUMIF(FZ:FZ,C60,GE:GE)+SUMIF(GI:GI,C60,GN:GN) -> 19974.096 | H60: =+SUM(F60:G60) -> 120026.3 | AR60: 35 | AS60: =+EOMONTH(AT60,0) -> 48822 | AT60: 48811 | AV60: =+AV59+AU60-AW60 -> 770139.59 | AW60: 525047.46 | AX60: =+AV59*AV$5*(AT60-AT59)/360 -> 19859.535 | AY60: =+SUM(AW60:AX60) -> 544907 | DD60: 35 | DE60: =+EOMONTH(DF60,0) -> 48944 | DF60: 48928 | DH60: =+DH59+DG60-DI60 -> 567946.56 | DI60: 283973.26 | DJ60: 12490.09 | DK60: =+SUM(DI60:DJ60) -> 296463.35 | EE60: 35 | EF60: =+EOMONTH(EG60,0) -> 48852 | EG60: 48837 | EI60: =+EI59+EH60-EJ60 -> 1618392.8 | EJ60: 40216.87 | EK60: 1222.39 | EM60: =+SUM(EJ60:EL60) -> 41439.26
A61: 36 | B61: =+WEEKNUM(C61,2) -> 36 | C61: =+EOMONTH(C60,1) -> 46996 | E61: =+E60+D61-F61 -> 90569793 | F61: =+SUMIF(N:N,C61,R:R)+SUMIF(AD:AD,C61,AH:AH)+SUMIF(AS:AS,C61,AW:AW)+SUMIF(BH:BH,C61,BL:BL)+SUMIF(BW:BW,C61,CA:CA)+SUMIF(BW:BW,C61,CB:CB)+SUMIF(CM:CM,C61,CQ:CQ)+SUMIF(CV:CV,C61,CZ:CZ)+SUMIF(DE:DE,C61,DI:DI)+SUMIF(DN:DN,C61,DR:DR)+SUMIF(DW:DW,C61,EA:EA)+SUMIF(EF:EF,C61,EJ:EJ)+SUMIF(EP:EP,C61,ET:ET)+SUMIF(EY:EY,C61,FC:FC)+SUMIF(FH:FH,C61,FL:FL)+SUMIF(FQ:FQ,C61,FU:FU)+SUMIF(FZ:FZ,C61,GD:GD)+SUMIF(GI:GI,C61,GM:GM) -> 4649886.1 | G61: =+SUMIF(N:N,C61,S:S)+SUMIF(N:N,C61,T:T)+SUMIF(AD:AD,C61,AI:AI)+SUMIF(AS:AS,C61,AX:AX)+SUMIF(BH:BH,C61,BM:BM)+SUMIF(BW:BW,C61,CD:CD)+SUMIF(BW:BW,C61,CC:CC)+SUMIF(CM:CM,C61,CR:CR)+SUMIF(CV:CV,C61,DA:DA)+SUMIF(DE:DE,C61,DJ:DJ)+SUMIF(DN:DN,C61,DS:DS)+SUMIF(DX:DX,C61,EB:EB)+SUMIF(EG:EG,C61,EK:EK)+SUMIF(EP:EP,C61,EU:EU)+SUMIF(EY:EY,C61,FD:FD)+SUMIF(FH:FH,C61,FM:FM)+SUMIF(FQ:FQ,C61,FV:FV)+SUMIF(FZ:FZ,C61,GE:GE)+SUMIF(GI:GI,C61,GN:GN) -> 1598654.7 | H61: =+SUM(F61:G61) -> 6248540.8 | I61: =+H61 -> 6248540.8 | J61: UNION | AR61: 36 | AS61: =+EOMONTH(AT61,0) -> 48913 | AT61: 48903 | AV61: =+AV60+AU61-AW61 -> 245092.12 | AW61: 525047.46 | AX61: =+AV60*AV$5*(AT61-AT60)/360 -> 11808.807 | AY61: =+SUM(AW61:AX61) -> 536856.27 | DD61: 36 | DE61: =+EOMONTH(DF61,0) -> 49034 | DF61: 49019 | DH61: =+DH60+DG61-DI61 -> 283973.3 | DI61: 283973.26 | DJ61: 8326.73 | DK61: =+SUM(DI61:DJ61) -> 292299.99 | EE61: 36 | EF61: =+EOMONTH(EG61,0) -> 48944 | EG61: 48928 | EI61: =+EI60+EH61-EJ61 -> 1087389.8 | EJ61: 531003.01 | EK61: 620.14 | EM61: =+SUM(EJ61:EL61) -> 531623.15
A62: 37 | B62: =+WEEKNUM(C62,2) -> 40 | C62: =+EOMONTH(C61,1) -> 47026 | E62: =+E61+D62-F62 -> 84793623 | F62: =+SUMIF(N:N,C62,R:R)+SUMIF(AD:AD,C62,AH:AH)+SUMIF(AS:AS,C62,AW:AW)+SUMIF(BH:BH,C62,BL:BL)+SUMIF(BW:BW,C62,CA:CA)+SUMIF(BW:BW,C62,CB:CB)+SUMIF(CM:CM,C62,CQ:CQ)+SUMIF(CV:CV,C62,CZ:CZ)+SUMIF(DE:DE,C62,DI:DI)+SUMIF(DN:DN,C62,DR:DR)+SUMIF(DW:DW,C62,EA:EA)+SUMIF(EF:EF,C62,EJ:EJ)+SUMIF(EP:EP,C62,ET:ET)+SUMIF(EY:EY,C62,FC:FC)+SUMIF(FH:FH,C62,FL:FL)+SUMIF(FQ:FQ,C62,FU:FU)+SUMIF(FZ:FZ,C62,GD:GD)+SUMIF(GI:GI,C62,GM:GM) -> 5776169.4 | G62: =+SUMIF(N:N,C62,S:S)+SUMIF(N:N,C62,T:T)+SUMIF(AD:AD,C62,AI:AI)+SUMIF(AS:AS,C62,AX:AX)+SUMIF(BH:BH,C62,BM:BM)+SUMIF(BW:BW,C62,CD:CD)+SUMIF(BW:BW,C62,CC:CC)+SUMIF(CM:CM,C62,CR:CR)+SUMIF(CV:CV,C62,DA:DA)+SUMIF(DE:DE,C62,DJ:DJ)+SUMIF(DN:DN,C62,DS:DS)+SUMIF(DX:DX,C62,EB:EB)+SUMIF(EG:EG,C62,EK:EK)+SUMIF(EP:EP,C62,EU:EU)+SUMIF(EY:EY,C62,FD:FD)+SUMIF(FH:FH,C62,FM:FM)+SUMIF(FQ:FQ,C62,FV:FV)+SUMIF(FZ:FZ,C62,GE:GE)+SUMIF(GI:GI,C62,GN:GN) -> 268714.29 | H62: =+SUM(F62:G62) -> 6044883.7 | AR62: 37 | AS62: =+EOMONTH(AT62,0) -> 49003 | AT62: 48997 | AV62: =+AV61+AU62-AW62 -> -7.4214768e-09 | AW62: 245092.12 | AX62: =+AV61*AV$5*(AT62-AT61)/360 -> 3839.7766 | AY62: =+SUM(AW62:AX62) -> 248931.9 | DD62: 37 | DE62: =+EOMONTH(DF62,0) -> 49125 | DF62: 49111 | DH62: =+DH61+DG62-DI62 -> 0.038867459 | DI62: 283973.26 | DJ62: 4209.12 | DK62: =+SUM(DI62:DJ62) -> 288182.38 | EE62: 37 | EF62: =+EOMONTH(EG62,0) -> 49034 | EG62: 49019 | EI62: =+EI61+EH62-EJ62 -> 548258.31 | EJ62: 539131.48 | EK62: 88653.24 | EM62: =+SUM(EJ62:EL62) -> 627784.72
A63: 38 | B63: =+WEEKNUM(C63,2) -> 45 | C63: =+EOMONTH(C62,1) -> 47057 | E63: =+E62+D63-F63 -> 84693571 | F63: =+SUMIF(N:N,C63,R:R)+SUMIF(AD:AD,C63,AH:AH)+SUMIF(AS:AS,C63,AW:AW)+SUMIF(BH:BH,C63,BL:BL)+SUMIF(BW:BW,C63,CA:CA)+SUMIF(BW:BW,C63,CB:CB)+SUMIF(CM:CM,C63,CQ:CQ)+SUMIF(CV:CV,C63,CZ:CZ)+SUMIF(DE:DE,C63,DI:DI)+SUMIF(DN:DN,C63,DR:DR)+SUMIF(DW:DW,C63,EA:EA)+SUMIF(EF:EF,C63,EJ:EJ)+SUMIF(EP:EP,C63,ET:ET)+SUMIF(EY:EY,C63,FC:FC)+SUMIF(FH:FH,C63,FL:FL)+SUMIF(FQ:FQ,C63,FU:FU)+SUMIF(FZ:FZ,C63,GD:GD)+SUMIF(GI:GI,C63,GM:GM) -> 100052.21 | G63: =+SUMIF(N:N,C63,S:S)+SUMIF(N:N,C63,T:T)+SUMIF(AD:AD,C63,AI:AI)+SUMIF(AS:AS,C63,AX:AX)+SUMIF(BH:BH,C63,BM:BM)+SUMIF(BW:BW,C63,CD:CD)+SUMIF(BW:BW,C63,CC:CC)+SUMIF(CM:CM,C63,CR:CR)+SUMIF(CV:CV,C63,DA:DA)+SUMIF(DE:DE,C63,DJ:DJ)+SUMIF(DN:DN,C63,DS:DS)+SUMIF(DX:DX,C63,EB:EB)+SUMIF(EG:EG,C63,EK:EK)+SUMIF(EP:EP,C63,EU:EU)+SUMIF(EY:EY,C63,FD:FD)+SUMIF(FH:FH,C63,FM:FM)+SUMIF(FQ:FQ,C63,FV:FV)+SUMIF(FZ:FZ,C63,GE:GE)+SUMIF(GI:GI,C63,GN:GN) -> 18702.834 | H63: =+SUM(F63:G63) -> 118755.04 | EE63: 38 | EF63: =+EOMONTH(EG63,0) -> 49125 | EG63: 49111 | EI63: =+EI62+EH63-EJ63 -> -2.5611371e-09 | EJ63: 548258.31 | EK63: 79526.41 | EM63: =+SUM(EJ63:EL63) -> 627784.72
A64: 39 | B64: =+WEEKNUM(C64,2) -> 49 | C64: =+EOMONTH(C63,1) -> 47087 | E64: =+E63+D64-F64 -> 80043685 | F64: =+SUMIF(N:N,C64,R:R)+SUMIF(AD:AD,C64,AH:AH)+SUMIF(AS:AS,C64,AW:AW)+SUMIF(BH:BH,C64,BL:BL)+SUMIF(BW:BW,C64,CA:CA)+SUMIF(BW:BW,C64,CB:CB)+SUMIF(CM:CM,C64,CQ:CQ)+SUMIF(CV:CV,C64,CZ:CZ)+SUMIF(DE:DE,C64,DI:DI)+SUMIF(DN:DN,C64,DR:DR)+SUMIF(DW:DW,C64,EA:EA)+SUMIF(EF:EF,C64,EJ:EJ)+SUMIF(EP:EP,C64,ET:ET)+SUMIF(EY:EY,C64,FC:FC)+SUMIF(FH:FH,C64,FL:FL)+SUMIF(FQ:FQ,C64,FU:FU)+SUMIF(FZ:FZ,C64,GD:GD)+SUMIF(GI:GI,C64,GM:GM) -> 4649886.1 | G64: =+SUMIF(N:N,C64,S:S)+SUMIF(N:N,C64,T:T)+SUMIF(AD:AD,C64,AI:AI)+SUMIF(AS:AS,C64,AX:AX)+SUMIF(BH:BH,C64,BM:BM)+SUMIF(BW:BW,C64,CD:CD)+SUMIF(BW:BW,C64,CC:CC)+SUMIF(CM:CM,C64,CR:CR)+SUMIF(CV:CV,C64,DA:DA)+SUMIF(DE:DE,C64,DJ:DJ)+SUMIF(DN:DN,C64,DS:DS)+SUMIF(DX:DX,C64,EB:EB)+SUMIF(EG:EG,C64,EK:EK)+SUMIF(EP:EP,C64,EU:EU)+SUMIF(EY:EY,C64,FD:FD)+SUMIF(FH:FH,C64,FM:FM)+SUMIF(FQ:FQ,C64,FV:FV)+SUMIF(FZ:FZ,C64,GE:GE)+SUMIF(GI:GI,C64,GN:GN) -> 1527422.7 | H64: =+SUM(F64:G64) -> 6177308.8
A65: 40 | B65: =+WEEKNUM(C65,2) -> 53 | C65: =+EOMONTH(C64,1) -> 47118 | E65: =+E64+D65-F65 -> 74267516 | F65: =+SUMIF(N:N,C65,R:R)+SUMIF(AD:AD,C65,AH:AH)+SUMIF(AS:AS,C65,AW:AW)+SUMIF(BH:BH,C65,BL:BL)+SUMIF(BW:BW,C65,CA:CA)+SUMIF(BW:BW,C65,CB:CB)+SUMIF(CM:CM,C65,CQ:CQ)+SUMIF(CV:CV,C65,CZ:CZ)+SUMIF(DE:DE,C65,DI:DI)+SUMIF(DN:DN,C65,DR:DR)+SUMIF(DW:DW,C65,EA:EA)+SUMIF(EF:EF,C65,EJ:EJ)+SUMIF(EP:EP,C65,ET:ET)+SUMIF(EY:EY,C65,FC:FC)+SUMIF(FH:FH,C65,FL:FL)+SUMIF(FQ:FQ,C65,FU:FU)+SUMIF(FZ:FZ,C65,GD:GD)+SUMIF(GI:GI,C65,GM:GM) -> 5776169.4 | G65: =+SUMIF(N:N,C65,S:S)+SUMIF(N:N,C65,T:T)+SUMIF(AD:AD,C65,AI:AI)+SUMIF(AS:AS,C65,AX:AX)+SUMIF(BH:BH,C65,BM:BM)+SUMIF(BW:BW,C65,CD:CD)+SUMIF(BW:BW,C65,CC:CC)+SUMIF(CM:CM,C65,CR:CR)+SUMIF(CV:CV,C65,DA:DA)+SUMIF(DE:DE,C65,DJ:DJ)+SUMIF(DN:DN,C65,DS:DS)+SUMIF(DX:DX,C65,EB:EB)+SUMIF(EG:EG,C65,EK:EK)+SUMIF(EP:EP,C65,EU:EU)+SUMIF(EY:EY,C65,FD:FD)+SUMIF(FH:FH,C65,FM:FM)+SUMIF(FQ:FQ,C65,FV:FV)+SUMIF(FZ:FZ,C65,GE:GE)+SUMIF(GI:GI,C65,GN:GN) -> 180027.87 | H65: =+SUM(F65:G65) -> 5956197.2
A66: 41 | B66: =+WEEKNUM(C66,2) -> 5 | C66: =+EOMONTH(C65,1) -> 47149 | E66: =+E65+D66-F66 -> 74167463 | F66: =+SUMIF(N:N,C66,R:R)+SUMIF(AD:AD,C66,AH:AH)+SUMIF(AS:AS,C66,AW:AW)+SUMIF(BH:BH,C66,BL:BL)+SUMIF(BW:BW,C66,CA:CA)+SUMIF(BW:BW,C66,CB:CB)+SUMIF(CM:CM,C66,CQ:CQ)+SUMIF(CV:CV,C66,CZ:CZ)+SUMIF(DE:DE,C66,DI:DI)+SUMIF(DN:DN,C66,DR:DR)+SUMIF(DW:DW,C66,EA:EA)+SUMIF(EF:EF,C66,EJ:EJ)+SUMIF(EP:EP,C66,ET:ET)+SUMIF(EY:EY,C66,FC:FC)+SUMIF(FH:FH,C66,FL:FL)+SUMIF(FQ:FQ,C66,FU:FU)+SUMIF(FZ:FZ,C66,GD:GD)+SUMIF(GI:GI,C66,GM:GM) -> 100052.21 | G66: =+SUMIF(N:N,C66,S:S)+SUMIF(N:N,C66,T:T)+SUMIF(AD:AD,C66,AI:AI)+SUMIF(AS:AS,C66,AX:AX)+SUMIF(BH:BH,C66,BM:BM)+SUMIF(BW:BW,C66,CD:CD)+SUMIF(BW:BW,C66,CC:CC)+SUMIF(CM:CM,C66,CR:CR)+SUMIF(CV:CV,C66,DA:DA)+SUMIF(DE:DE,C66,DJ:DJ)+SUMIF(DN:DN,C66,DS:DS)+SUMIF(DX:DX,C66,EB:EB)+SUMIF(EG:EG,C66,EK:EK)+SUMIF(EP:EP,C66,EU:EU)+SUMIF(EY:EY,C66,FD:FD)+SUMIF(FH:FH,C66,FM:FM)+SUMIF(FQ:FQ,C66,FV:FV)+SUMIF(FZ:FZ,C66,GE:GE)+SUMIF(GI:GI,C66,GN:GN) -> 17230.129 | H66: =+SUM(F66:G66) -> 117282.34
A67: 42 | B67: =+WEEKNUM(C67,2) -> 9 | C67: =+EOMONTH(C66,1) -> 47177 | E67: =+E66+D67-F67 -> 69517577 | F67: =+SUMIF(N:N,C67,R:R)+SUMIF(AD:AD,C67,AH:AH)+SUMIF(AS:AS,C67,AW:AW)+SUMIF(BH:BH,C67,BL:BL)+SUMIF(BW:BW,C67,CA:CA)+SUMIF(BW:BW,C67,CB:CB)+SUMIF(CM:CM,C67,CQ:CQ)+SUMIF(CV:CV,C67,CZ:CZ)+SUMIF(DE:DE,C67,DI:DI)+SUMIF(DN:DN,C67,DR:DR)+SUMIF(DW:DW,C67,EA:EA)+SUMIF(EF:EF,C67,EJ:EJ)+SUMIF(EP:EP,C67,ET:ET)+SUMIF(EY:EY,C67,FC:FC)+SUMIF(FH:FH,C67,FL:FL)+SUMIF(FQ:FQ,C67,FU:FU)+SUMIF(FZ:FZ,C67,GD:GD)+SUMIF(GI:GI,C67,GM:GM) -> 4649886.1 | G67: =+SUMIF(N:N,C67,S:S)+SUMIF(N:N,C67,T:T)+SUMIF(AD:AD,C67,AI:AI)+SUMIF(AS:AS,C67,AX:AX)+SUMIF(BH:BH,C67,BM:BM)+SUMIF(BW:BW,C67,CD:CD)+SUMIF(BW:BW,C67,CC:CC)+SUMIF(CM:CM,C67,CR:CR)+SUMIF(CV:CV,C67,DA:DA)+SUMIF(DE:DE,C67,DJ:DJ)+SUMIF(DN:DN,C67,DS:DS)+SUMIF(DX:DX,C67,EB:EB)+SUMIF(EG:EG,C67,EK:EK)+SUMIF(EP:EP,C67,EU:EU)+SUMIF(EY:EY,C67,FD:FD)+SUMIF(FH:FH,C67,FM:FM)+SUMIF(FQ:FQ,C67,FV:FV)+SUMIF(FZ:FZ,C67,GE:GE)+SUMIF(GI:GI,C67,GN:GN) -> 1456190.7 | H67: =+SUM(F67:G67) -> 6106076.8
A68: 43 | B68: =+WEEKNUM(C68,2) -> 13 | C68: =+EOMONTH(C67,1) -> 47208 | E68: =+E67+D68-F68 -> 69089069 | F68: =+SUMIF(N:N,C68,R:R)+SUMIF(AD:AD,C68,AH:AH)+SUMIF(AS:AS,C68,AW:AW)+SUMIF(BH:BH,C68,BL:BL)+SUMIF(BW:BW,C68,CA:CA)+SUMIF(BW:BW,C68,CB:CB)+SUMIF(CM:CM,C68,CQ:CQ)+SUMIF(CV:CV,C68,CZ:CZ)+SUMIF(DE:DE,C68,DI:DI)+SUMIF(DN:DN,C68,DR:DR)+SUMIF(DW:DW,C68,EA:EA)+SUMIF(EF:EF,C68,EJ:EJ)+SUMIF(EP:EP,C68,ET:ET)+SUMIF(EY:EY,C68,FC:FC)+SUMIF(FH:FH,C68,FL:FL)+SUMIF(FQ:FQ,C68,FU:FU)+SUMIF(FZ:FZ,C68,GD:GD)+SUMIF(GI:GI,C68,GM:GM) -> 428508.08 | G68: =+SUMIF(N:N,C68,S:S)+SUMIF(N:N,C68,T:T)+SUMIF(AD:AD,C68,AI:AI)+SUMIF(AS:AS,C68,AX:AX)+SUMIF(BH:BH,C68,BM:BM)+SUMIF(BW:BW,C68,CD:CD)+SUMIF(BW:BW,C68,CC:CC)+SUMIF(CM:CM,C68,CR:CR)+SUMIF(CV:CV,C68,DA:DA)+SUMIF(DE:DE,C68,DJ:DJ)+SUMIF(DN:DN,C68,DS:DS)+SUMIF(DX:DX,C68,EB:EB)+SUMIF(EG:EG,C68,EK:EK)+SUMIF(EP:EP,C68,EU:EU)+SUMIF(EY:EY,C68,FD:FD)+SUMIF(FH:FH,C68,FM:FM)+SUMIF(FQ:FQ,C68,FV:FV)+SUMIF(FZ:FZ,C68,GE:GE)+SUMIF(GI:GI,C68,GN:GN) -> 93158.77 | H68: =+SUM(F68:G68) -> 521666.85
A69: 44 | B69: =+WEEKNUM(C69,2) -> 18 | C69: =+EOMONTH(C68,1) -> 47238 | E69: =+E68+D69-F69 -> 68989017 | F69: =+SUMIF(N:N,C69,R:R)+SUMIF(AD:AD,C69,AH:AH)+SUMIF(AS:AS,C69,AW:AW)+SUMIF(BH:BH,C69,BL:BL)+SUMIF(BW:BW,C69,CA:CA)+SUMIF(BW:BW,C69,CB:CB)+SUMIF(CM:CM,C69,CQ:CQ)+SUMIF(CV:CV,C69,CZ:CZ)+SUMIF(DE:DE,C69,DI:DI)+SUMIF(DN:DN,C69,DR:DR)+SUMIF(DW:DW,C69,EA:EA)+SUMIF(EF:EF,C69,EJ:EJ)+SUMIF(EP:EP,C69,ET:ET)+SUMIF(EY:EY,C69,FC:FC)+SUMIF(FH:FH,C69,FL:FL)+SUMIF(FQ:FQ,C69,FU:FU)+SUMIF(FZ:FZ,C69,GD:GD)+SUMIF(GI:GI,C69,GM:GM) -> 100052.21 | G69: =+SUMIF(N:N,C69,S:S)+SUMIF(N:N,C69,T:T)+SUMIF(AD:AD,C69,AI:AI)+SUMIF(AS:AS,C69,AX:AX)+SUMIF(BH:BH,C69,BM:BM)+SUMIF(BW:BW,C69,CD:CD)+SUMIF(BW:BW,C69,CC:CC)+SUMIF(CM:CM,C69,CR:CR)+SUMIF(CV:CV,C69,DA:DA)+SUMIF(DE:DE,C69,DJ:DJ)+SUMIF(DN:DN,C69,DS:DS)+SUMIF(DX:DX,C69,EB:EB)+SUMIF(EG:EG,C69,EK:EK)+SUMIF(EP:EP,C69,EU:EU)+SUMIF(EY:EY,C69,FD:FD)+SUMIF(FH:FH,C69,FM:FM)+SUMIF(FQ:FQ,C69,FV:FV)+SUMIF(FZ:FZ,C69,GE:GE)+SUMIF(GI:GI,C69,GN:GN) -> 15450.586 | H69: =+SUM(F69:G69) -> 115502.79 | I69: =+H69 -> 115502.79 | J69: GANADERO
A70: 45 | B70: =+WEEKNUM(C70,2) -> 22 | C70: =+EOMONTH(C69,1) -> 47269 | E70: =+E69+D70-F70 -> 64339131 | F70: =+SUMIF(N:N,C70,R:R)+SUMIF(AD:AD,C70,AH:AH)+SUMIF(AS:AS,C70,AW:AW)+SUMIF(BH:BH,C70,BL:BL)+SUMIF(BW:BW,C70,CA:CA)+SUMIF(BW:BW,C70,CB:CB)+SUMIF(CM:CM,C70,CQ:CQ)+SUMIF(CV:CV,C70,CZ:CZ)+SUMIF(DE:DE,C70,DI:DI)+SUMIF(DN:DN,C70,DR:DR)+SUMIF(DW:DW,C70,EA:EA)+SUMIF(EF:EF,C70,EJ:EJ)+SUMIF(EP:EP,C70,ET:ET)+SUMIF(EY:EY,C70,FC:FC)+SUMIF(FH:FH,C70,FL:FL)+SUMIF(FQ:FQ,C70,FU:FU)+SUMIF(FZ:FZ,C70,GD:GD)+SUMIF(GI:GI,C70,GM:GM) -> 4649886.1 | G70: =+SUMIF(N:N,C70,S:S)+SUMIF(N:N,C70,T:T)+SUMIF(AD:AD,C70,AI:AI)+SUMIF(AS:AS,C70,AX:AX)+SUMIF(BH:BH,C70,BM:BM)+SUMIF(BW:BW,C70,CD:CD)+SUMIF(BW:BW,C70,CC:CC)+SUMIF(CM:CM,C70,CR:CR)+SUMIF(CV:CV,C70,DA:DA)+SUMIF(DE:DE,C70,DJ:DJ)+SUMIF(DN:DN,C70,DS:DS)+SUMIF(DX:DX,C70,EB:EB)+SUMIF(EG:EG,C70,EK:EK)+SUMIF(EP:EP,C70,EU:EU)+SUMIF(EY:EY,C70,FD:FD)+SUMIF(FH:FH,C70,FM:FM)+SUMIF(FQ:FQ,C70,FV:FV)+SUMIF(FZ:FZ,C70,GE:GE)+SUMIF(GI:GI,C70,GN:GN) -> 1355173.6 | H70: =+SUM(F70:G70) -> 6005059.7
A71: 46 | B71: =+WEEKNUM(C71,2) -> 26 | C71: =+EOMONTH(C70,1) -> 47299 | E71: =+E70+D71-F71 -> 63910623 | F71: =+SUMIF(N:N,C71,R:R)+SUMIF(AD:AD,C71,AH:AH)+SUMIF(AS:AS,C71,AW:AW)+SUMIF(BH:BH,C71,BL:BL)+SUMIF(BW:BW,C71,CA:CA)+SUMIF(BW:BW,C71,CB:CB)+SUMIF(CM:CM,C71,CQ:CQ)+SUMIF(CV:CV,C71,CZ:CZ)+SUMIF(DE:DE,C71,DI:DI)+SUMIF(DN:DN,C71,DR:DR)+SUMIF(DW:DW,C71,EA:EA)+SUMIF(EF:EF,C71,EJ:EJ)+SUMIF(EP:EP,C71,ET:ET)+SUMIF(EY:EY,C71,FC:FC)+SUMIF(FH:FH,C71,FL:FL)+SUMIF(FQ:FQ,C71,FU:FU)+SUMIF(FZ:FZ,C71,GD:GD)+SUMIF(GI:GI,C71,GM:GM) -> 428507.96 | G71: =+SUMIF(N:N,C71,S:S)+SUMIF(N:N,C71,T:T)+SUMIF(AD:AD,C71,AI:AI)+SUMIF(AS:AS,C71,AX:AX)+SUMIF(BH:BH,C71,BM:BM)+SUMIF(BW:BW,C71,CD:CD)+SUMIF(BW:BW,C71,CC:CC)+SUMIF(CM:CM,C71,CR:CR)+SUMIF(CV:CV,C71,DA:DA)+SUMIF(DE:DE,C71,DJ:DJ)+SUMIF(DN:DN,C71,DS:DS)+SUMIF(DX:DX,C71,EB:EB)+SUMIF(EG:EG,C71,EK:EK)+SUMIF(EP:EP,C71,EU:EU)+SUMIF(EY:EY,C71,FD:FD)+SUMIF(FH:FH,C71,FM:FM)+SUMIF(FQ:FQ,C71,FV:FV)+SUMIF(FZ:FZ,C71,GE:GE)+SUMIF(GI:GI,C71,GN:GN) -> 144375.33 | H71: =+SUM(F71:G71) -> 572883.29
A72: 47 | B72: =+WEEKNUM(C72,2) -> 31 | C72: =+EOMONTH(C71,1) -> 47330 | E72: =+E71+D72-F72 -> 63810571 | F72: =+SUMIF(N:N,C72,R:R)+SUMIF(AD:AD,C72,AH:AH)+SUMIF(AS:AS,C72,AW:AW)+SUMIF(BH:BH,C72,BL:BL)+SUMIF(BW:BW,C72,CA:CA)+SUMIF(BW:BW,C72,CB:CB)+SUMIF(CM:CM,C72,CQ:CQ)+SUMIF(CV:CV,C72,CZ:CZ)+SUMIF(DE:DE,C72,DI:DI)+SUMIF(DN:DN,C72,DR:DR)+SUMIF(DW:DW,C72,EA:EA)+SUMIF(EF:EF,C72,EJ:EJ)+SUMIF(EP:EP,C72,ET:ET)+SUMIF(EY:EY,C72,FC:FC)+SUMIF(FH:FH,C72,FL:FL)+SUMIF(FQ:FQ,C72,FU:FU)+SUMIF(FZ:FZ,C72,GD:GD)+SUMIF(GI:GI,C72,GM:GM) -> 100052.21 | G72: =+SUMIF(N:N,C72,S:S)+SUMIF(N:N,C72,T:T)+SUMIF(AD:AD,C72,AI:AI)+SUMIF(AS:AS,C72,AX:AX)+SUMIF(BH:BH,C72,BM:BM)+SUMIF(BW:BW,C72,CD:CD)+SUMIF(BW:BW,C72,CC:CC)+SUMIF(CM:CM,C72,CR:CR)+SUMIF(CV:CV,C72,DA:DA)+SUMIF(DE:DE,C72,DJ:DJ)+SUMIF(DN:DN,C72,DS:DS)+SUMIF(DX:DX,C72,EB:EB)+SUMIF(EG:EG,C72,EK:EK)+SUMIF(EP:EP,C72,EU:EU)+SUMIF(EY:EY,C72,FD:FD)+SUMIF(FH:FH,C72,FM:FM)+SUMIF(FQ:FQ,C72,FV:FV)+SUMIF(FZ:FZ,C72,GE:GE)+SUMIF(GI:GI,C72,GN:GN) -> 14147.308 | H72: =+SUM(F72:G72) -> 114199.52
A73: 48 | B73: =+WEEKNUM(C73,2) -> 35 | C73: =+EOMONTH(C72,1) -> 47361 | E73: =+E72+D73-F73 -> 59160684 | F73: =+SUMIF(N:N,C73,R:R)+SUMIF(AD:AD,C73,AH:AH)+SUMIF(AS:AS,C73,AW:AW)+SUMIF(BH:BH,C73,BL:BL)+SUMIF(BW:BW,C73,CA:CA)+SUMIF(BW:BW,C73,CB:CB)+SUMIF(CM:CM,C73,CQ:CQ)+SUMIF(CV:CV,C73,CZ:CZ)+SUMIF(DE:DE,C73,DI:DI)+SUMIF(DN:DN,C73,DR:DR)+SUMIF(DW:DW,C73,EA:EA)+SUMIF(EF:EF,C73,EJ:EJ)+SUMIF(EP:EP,C73,ET:ET)+SUMIF(EY:EY,C73,FC:FC)+SUMIF(FH:FH,C73,FL:FL)+SUMIF(FQ:FQ,C73,FU:FU)+SUMIF(FZ:FZ,C73,GD:GD)+SUMIF(GI:GI,C73,GM:GM) -> 4649886.1 | G73: =+SUMIF(N:N,C73,S:S)+SUMIF(N:N,C73,T:T)+SUMIF(AD:AD,C73,AI:AI)+SUMIF(AS:AS,C73,AX:AX)+SUMIF(BH:BH,C73,BM:BM)+SUMIF(BW:BW,C73,CD:CD)+SUMIF(BW:BW,C73,CC:CC)+SUMIF(CM:CM,C73,CR:CR)+SUMIF(CV:CV,C73,DA:DA)+SUMIF(DE:DE,C73,DJ:DJ)+SUMIF(DN:DN,C73,DS:DS)+SUMIF(DX:DX,C73,EB:EB)+SUMIF(EG:EG,C73,EK:EK)+SUMIF(EP:EP,C73,EU:EU)+SUMIF(EY:EY,C73,FD:FD)+SUMIF(FH:FH,C73,FM:FM)+SUMIF(FQ:FQ,C73,FV:FV)+SUMIF(FZ:FZ,C73,GE:GE)+SUMIF(GI:GI,C73,GN:GN) -> 1313726.6 | H73: =+SUM(F73:G73) -> 5963612.8
A74: 49 | B74: =+WEEKNUM(C74,2) -> 39 | C74: =+EOMONTH(C73,1) -> 47391 | E74: =+E73+D74-F74 -> 58732177 | F74: =+SUMIF(N:N,C74,R:R)+SUMIF(AD:AD,C74,AH:AH)+SUMIF(AS:AS,C74,AW:AW)+SUMIF(BH:BH,C74,BL:BL)+SUMIF(BW:BW,C74,CA:CA)+SUMIF(BW:BW,C74,CB:CB)+SUMIF(CM:CM,C74,CQ:CQ)+SUMIF(CV:CV,C74,CZ:CZ)+SUMIF(DE:DE,C74,DI:DI)+SUMIF(DN:DN,C74,DR:DR)+SUMIF(DW:DW,C74,EA:EA)+SUMIF(EF:EF,C74,EJ:EJ)+SUMIF(EP:EP,C74,ET:ET)+SUMIF(EY:EY,C74,FC:FC)+SUMIF(FH:FH,C74,FL:FL)+SUMIF(FQ:FQ,C74,FU:FU)+SUMIF(FZ:FZ,C74,GD:GD)+SUMIF(GI:GI,C74,GM:GM) -> 428507.96 | G74: =+SUMIF(N:N,C74,S:S)+SUMIF(N:N,C74,T:T)+SUMIF(AD:AD,C74,AI:AI)+SUMIF(AS:AS,C74,AX:AX)+SUMIF(BH:BH,C74,BM:BM)+SUMIF(BW:BW,C74,CD:CD)+SUMIF(BW:BW,C74,CC:CC)+SUMIF(CM:CM,C74,CR:CR)+SUMIF(CV:CV,C74,DA:DA)+SUMIF(DE:DE,C74,DJ:DJ)+SUMIF(DN:DN,C74,DS:DS)+SUMIF(DX:DX,C74,EB:EB)+SUMIF(EG:EG,C74,EK:EK)+SUMIF(EP:EP,C74,EU:EU)+SUMIF(EY:EY,C74,FD:FD)+SUMIF(FH:FH,C74,FM:FM)+SUMIF(FQ:FQ,C74,FV:FV)+SUMIF(FZ:FZ,C74,GE:GE)+SUMIF(GI:GI,C74,GN:GN) -> 136145.49 | H74: =+SUM(F74:G74) -> 564653.45 | I74: =+H74 -> 564653.45 | J74: FIDEICOMISO
A75: 50 | B75: =+WEEKNUM(C75,2) -> 44 | C75: =+EOMONTH(C74,1) -> 47422 | E75: =+E74+D75-F75 -> 58563102 | F75: =+SUMIF(N:N,C75,R:R)+SUMIF(AD:AD,C75,AH:AH)+SUMIF(AS:AS,C75,AW:AW)+SUMIF(BH:BH,C75,BL:BL)+SUMIF(BW:BW,C75,CA:CA)+SUMIF(BW:BW,C75,CB:CB)+SUMIF(CM:CM,C75,CQ:CQ)+SUMIF(CV:CV,C75,CZ:CZ)+SUMIF(DE:DE,C75,DI:DI)+SUMIF(DN:DN,C75,DR:DR)+SUMIF(DW:DW,C75,EA:EA)+SUMIF(EF:EF,C75,EJ:EJ)+SUMIF(EP:EP,C75,ET:ET)+SUMIF(EY:EY,C75,FC:FC)+SUMIF(FH:FH,C75,FL:FL)+SUMIF(FQ:FQ,C75,FU:FU)+SUMIF(FZ:FZ,C75,GD:GD)+SUMIF(GI:GI,C75,GM:GM) -> 169074.38 | G75: =+SUMIF(N:N,C75,S:S)+SUMIF(N:N,C75,T:T)+SUMIF(AD:AD,C75,AI:AI)+SUMIF(AS:AS,C75,AX:AX)+SUMIF(BH:BH,C75,BM:BM)+SUMIF(BW:BW,C75,CD:CD)+SUMIF(BW:BW,C75,CC:CC)+SUMIF(CM:CM,C75,CR:CR)+SUMIF(CV:CV,C75,DA:DA)+SUMIF(DE:DE,C75,DJ:DJ)+SUMIF(DN:DN,C75,DS:DS)+SUMIF(DX:DX,C75,EB:EB)+SUMIF(EG:EG,C75,EK:EK)+SUMIF(EP:EP,C75,EU:EU)+SUMIF(EY:EY,C75,FD:FD)+SUMIF(FH:FH,C75,FM:FM)+SUMIF(FQ:FQ,C75,FV:FV)+SUMIF(FZ:FZ,C75,GE:GE)+SUMIF(GI:GI,C75,GN:GN) -> 12561.824 | H75: =+SUM(F75:G75) -> 181636.2 | I75: =+H75 -> 181636.2
A76: 51 | B76: =+WEEKNUM(C76,2) -> 48 | C76: =+EOMONTH(C75,1) -> 47452 | E76: =+E75+D76-F76 -> 53913216 | F76: =+SUMIF(N:N,C76,R:R)+SUMIF(AD:AD,C76,AH:AH)+SUMIF(AS:AS,C76,AW:AW)+SUMIF(BH:BH,C76,BL:BL)+SUMIF(BW:BW,C76,CA:CA)+SUMIF(BW:BW,C76,CB:CB)+SUMIF(CM:CM,C76,CQ:CQ)+SUMIF(CV:CV,C76,CZ:CZ)+SUMIF(DE:DE,C76,DI:DI)+SUMIF(DN:DN,C76,DR:DR)+SUMIF(DW:DW,C76,EA:EA)+SUMIF(EF:EF,C76,EJ:EJ)+SUMIF(EP:EP,C76,ET:ET)+SUMIF(EY:EY,C76,FC:FC)+SUMIF(FH:FH,C76,FL:FL)+SUMIF(FQ:FQ,C76,FU:FU)+SUMIF(FZ:FZ,C76,GD:GD)+SUMIF(GI:GI,C76,GM:GM) -> 4649886.1 | G76: =+SUMIF(N:N,C76,S:S)+SUMIF(N:N,C76,T:T)+SUMIF(AD:AD,C76,AI:AI)+SUMIF(AS:AS,C76,AX:AX)+SUMIF(BH:BH,C76,BM:BM)+SUMIF(BW:BW,C76,CD:CD)+SUMIF(BW:BW,C76,CC:CC)+SUMIF(CM:CM,C76,CR:CR)+SUMIF(CV:CV,C76,DA:DA)+SUMIF(DE:DE,C76,DJ:DJ)+SUMIF(DN:DN,C76,DS:DS)+SUMIF(DX:DX,C76,EB:EB)+SUMIF(EG:EG,C76,EK:EK)+SUMIF(EP:EP,C76,EU:EU)+SUMIF(EY:EY,C76,FD:FD)+SUMIF(FH:FH,C76,FM:FM)+SUMIF(FQ:FQ,C76,FV:FV)+SUMIF(FZ:FZ,C76,GE:GE)+SUMIF(GI:GI,C76,GN:GN) -> 770944.08 | H76: =+SUM(F76:G76) -> 5420830.2
A77: 52 | B77: =+WEEKNUM(C77,2) -> 53 | C77: =+EOMONTH(C76,1) -> 47483 | E77: =+E76+D77-F77 -> 53589026 | F77: =+SUMIF(N:N,C77,R:R)+SUMIF(AD:AD,C77,AH:AH)+SUMIF(AS:AS,C77,AW:AW)+SUMIF(BH:BH,C77,BL:BL)+SUMIF(BW:BW,C77,CA:CA)+SUMIF(BW:BW,C77,CB:CB)+SUMIF(CM:CM,C77,CQ:CQ)+SUMIF(CV:CV,C77,CZ:CZ)+SUMIF(DE:DE,C77,DI:DI)+SUMIF(DN:DN,C77,DR:DR)+SUMIF(DW:DW,C77,EA:EA)+SUMIF(EF:EF,C77,EJ:EJ)+SUMIF(EP:EP,C77,ET:ET)+SUMIF(EY:EY,C77,FC:FC)+SUMIF(FH:FH,C77,FL:FL)+SUMIF(FQ:FQ,C77,FU:FU)+SUMIF(FZ:FZ,C77,GD:GD)+SUMIF(GI:GI,C77,GM:GM) -> 324190.11 | G77: =+SUMIF(N:N,C77,S:S)+SUMIF(N:N,C77,T:T)+SUMIF(AD:AD,C77,AI:AI)+SUMIF(AS:AS,C77,AX:AX)+SUMIF(BH:BH,C77,BM:BM)+SUMIF(BW:BW,C77,CD:CD)+SUMIF(BW:BW,C77,CC:CC)+SUMIF(CM:CM,C77,CR:CR)+SUMIF(CV:CV,C77,DA:DA)+SUMIF(DE:DE,C77,DJ:DJ)+SUMIF(DN:DN,C77,DS:DS)+SUMIF(DX:DX,C77,EB:EB)+SUMIF(EG:EG,C77,EK:EK)+SUMIF(EP:EP,C77,EU:EU)+SUMIF(EY:EY,C77,FD:FD)+SUMIF(FH:FH,C77,FM:FM)+SUMIF(FQ:FQ,C77,FV:FV)+SUMIF(FZ:FZ,C77,GE:GE)+SUMIF(GI:GI,C77,GN:GN) -> 79103.91 | H77: =+SUM(F77:G77) -> 403294.02
A78: 53 | B78: =+WEEKNUM(C78,2) -> 5 | C78: =+EOMONTH(C77,1) -> 47514 | E78: =+E77+D78-F78 -> 53549532 | F78: =+SUMIF(N:N,C78,R:R)+SUMIF(AD:AD,C78,AH:AH)+SUMIF(AS:AS,C78,AW:AW)+SUMIF(BH:BH,C78,BL:BL)+SUMIF(BW:BW,C78,CA:CA)+SUMIF(BW:BW,C78,CB:CB)+SUMIF(CM:CM,C78,CQ:CQ)+SUMIF(CV:CV,C78,CZ:CZ)+SUMIF(DE:DE,C78,DI:DI)+SUMIF(DN:DN,C78,DR:DR)+SUMIF(DW:DW,C78,EA:EA)+SUMIF(EF:EF,C78,EJ:EJ)+SUMIF(EP:EP,C78,ET:ET)+SUMIF(EY:EY,C78,FC:FC)+SUMIF(FH:FH,C78,FL:FL)+SUMIF(FQ:FQ,C78,FU:FU)+SUMIF(FZ:FZ,C78,GD:GD)+SUMIF(GI:GI,C78,GM:GM) -> 39494.31 | G78: =+SUMIF(N:N,C78,S:S)+SUMIF(N:N,C78,T:T)+SUMIF(AD:AD,C78,AI:AI)+SUMIF(AS:AS,C78,AX:AX)+SUMIF(BH:BH,C78,BM:BM)+SUMIF(BW:BW,C78,CD:CD)+SUMIF(BW:BW,C78,CC:CC)+SUMIF(CM:CM,C78,CR:CR)+SUMIF(CV:CV,C78,DA:DA)+SUMIF(DE:DE,C78,DJ:DJ)+SUMIF(DN:DN,C78,DS:DS)+SUMIF(DX:DX,C78,EB:EB)+SUMIF(EG:EG,C78,EK:EK)+SUMIF(EP:EP,C78,EU:EU)+SUMIF(EY:EY,C78,FD:FD)+SUMIF(FH:FH,C78,FM:FM)+SUMIF(FQ:FQ,C78,FV:FV)+SUMIF(FZ:FZ,C78,GE:GE)+SUMIF(GI:GI,C78,GN:GN) -> 9002.7266 | H78: =+SUM(F78:G78) -> 48497.037
A79: 54 | B79: =+WEEKNUM(C79,2) -> 9 | C79: =+EOMONTH(C78,1) -> 47542 | E79: =+E78+D79-F79 -> 48899645 | F79: =+SUMIF(N:N,C79,R:R)+SUMIF(AD:AD,C79,AH:AH)+SUMIF(AS:AS,C79,AW:AW)+SUMIF(BH:BH,C79,BL:BL)+SUMIF(BW:BW,C79,CA:CA)+SUMIF(BW:BW,C79,CB:CB)+SUMIF(CM:CM,C79,CQ:CQ)+SUMIF(CV:CV,C79,CZ:CZ)+SUMIF(DE:DE,C79,DI:DI)+SUMIF(DN:DN,C79,DR:DR)+SUMIF(DW:DW,C79,EA:EA)+SUMIF(EF:EF,C79,EJ:EJ)+SUMIF(EP:EP,C79,ET:ET)+SUMIF(EY:EY,C79,FC:FC)+SUMIF(FH:FH,C79,FL:FL)+SUMIF(FQ:FQ,C79,FU:FU)+SUMIF(FZ:FZ,C79,GD:GD)+SUMIF(GI:GI,C79,GM:GM) -> 4649886.1 | G79: =+SUMIF(N:N,C79,S:S)+SUMIF(N:N,C79,T:T)+SUMIF(AD:AD,C79,AI:AI)+SUMIF(AS:AS,C79,AX:AX)+SUMIF(BH:BH,C79,BM:BM)+SUMIF(BW:BW,C79,CD:CD)+SUMIF(BW:BW,C79,CC:CC)+SUMIF(CM:CM,C79,CR:CR)+SUMIF(CV:CV,C79,DA:DA)+SUMIF(DE:DE,C79,DJ:DJ)+SUMIF(DN:DN,C79,DS:DS)+SUMIF(DX:DX,C79,EB:EB)+SUMIF(EG:EG,C79,EK:EK)+SUMIF(EP:EP,C79,EU:EU)+SUMIF(EY:EY,C79,FD:FD)+SUMIF(FH:FH,C79,FM:FM)+SUMIF(FQ:FQ,C79,FV:FV)+SUMIF(FZ:FZ,C79,GE:GE)+SUMIF(GI:GI,C79,GN:GN) -> 699712.07 | H79: =+SUM(F79:G79) -> 5349598.2 | I79: =+H79 -> 5349598.2 | J79: UNION
A80: 55 | B80: =+WEEKNUM(C80,2) -> 13 | C80: =+EOMONTH(C79,1) -> 47573 | E80: =+E79+D80-F80 -> 48575455 | F80: =+SUMIF(N:N,C80,R:R)+SUMIF(AD:AD,C80,AH:AH)+SUMIF(AS:AS,C80,AW:AW)+SUMIF(BH:BH,C80,BL:BL)+SUMIF(BW:BW,C80,CA:CA)+SUMIF(BW:BW,C80,CB:CB)+SUMIF(CM:CM,C80,CQ:CQ)+SUMIF(CV:CV,C80,CZ:CZ)+SUMIF(DE:DE,C80,DI:DI)+SUMIF(DN:DN,C80,DR:DR)+SUMIF(DW:DW,C80,EA:EA)+SUMIF(EF:EF,C80,EJ:EJ)+SUMIF(EP:EP,C80,ET:ET)+SUMIF(EY:EY,C80,FC:FC)+SUMIF(FH:FH,C80,FL:FL)+SUMIF(FQ:FQ,C80,FU:FU)+SUMIF(FZ:FZ,C80,GD:GD)+SUMIF(GI:GI,C80,GM:GM) -> 324190.11 | G80: =+SUMIF(N:N,C80,S:S)+SUMIF(N:N,C80,T:T)+SUMIF(AD:AD,C80,AI:AI)+SUMIF(AS:AS,C80,AX:AX)+SUMIF(BH:BH,C80,BM:BM)+SUMIF(BW:BW,C80,CD:CD)+SUMIF(BW:BW,C80,CC:CC)+SUMIF(CM:CM,C80,CR:CR)+SUMIF(CV:CV,C80,DA:DA)+SUMIF(DE:DE,C80,DJ:DJ)+SUMIF(DN:DN,C80,DS:DS)+SUMIF(DX:DX,C80,EB:EB)+SUMIF(EG:EG,C80,EK:EK)+SUMIF(EP:EP,C80,EU:EU)+SUMIF(EY:EY,C80,FD:FD)+SUMIF(FH:FH,C80,FM:FM)+SUMIF(FQ:FQ,C80,FV:FV)+SUMIF(FZ:FZ,C80,GE:GE)+SUMIF(GI:GI,C80,GN:GN) -> 74940.55 | H80: =+SUM(F80:G80) -> 399130.66
A81: 56 | B81: =+WEEKNUM(C81,2) -> 18 | C81: =+EOMONTH(C80,1) -> 47603 | E81: =+E80+D81-F81 -> 48535961 | F81: =+SUMIF(N:N,C81,R:R)+SUMIF(AD:AD,C81,AH:AH)+SUMIF(AS:AS,C81,AW:AW)+SUMIF(BH:BH,C81,BL:BL)+SUMIF(BW:BW,C81,CA:CA)+SUMIF(BW:BW,C81,CB:CB)+SUMIF(CM:CM,C81,CQ:CQ)+SUMIF(CV:CV,C81,CZ:CZ)+SUMIF(DE:DE,C81,DI:DI)+SUMIF(DN:DN,C81,DR:DR)+SUMIF(DW:DW,C81,EA:EA)+SUMIF(EF:EF,C81,EJ:EJ)+SUMIF(EP:EP,C81,ET:ET)+SUMIF(EY:EY,C81,FC:FC)+SUMIF(FH:FH,C81,FL:FL)+SUMIF(FQ:FQ,C81,FU:FU)+SUMIF(FZ:FZ,C81,GD:GD)+SUMIF(GI:GI,C81,GM:GM) -> 39494.31 | G81: =+SUMIF(N:N,C81,S:S)+SUMIF(N:N,C81,T:T)+SUMIF(AD:AD,C81,AI:AI)+SUMIF(AS:AS,C81,AX:AX)+SUMIF(BH:BH,C81,BM:BM)+SUMIF(BW:BW,C81,CD:CD)+SUMIF(BW:BW,C81,CC:CC)+SUMIF(CM:CM,C81,CR:CR)+SUMIF(CV:CV,C81,DA:DA)+SUMIF(DE:DE,C81,DJ:DJ)+SUMIF(DN:DN,C81,DS:DS)+SUMIF(DX:DX,C81,EB:EB)+SUMIF(EG:EG,C81,EK:EK)+SUMIF(EP:EP,C81,EU:EU)+SUMIF(EY:EY,C81,FD:FD)+SUMIF(FH:FH,C81,FM:FM)+SUMIF(FQ:FQ,C81,FV:FV)+SUMIF(FZ:FZ,C81,GE:GE)+SUMIF(GI:GI,C81,GN:GN) -> 7866.2121 | H81: =+SUM(F81:G81) -> 47360.522
A82: 57 | B82: =+WEEKNUM(C82,2) -> 22 | C82: =+EOMONTH(C81,1) -> 47634 | E82: =+E81+D82-F82 -> 43886075 | F82: =+SUMIF(N:N,C82,R:R)+SUMIF(AD:AD,C82,AH:AH)+SUMIF(AS:AS,C82,AW:AW)+SUMIF(BH:BH,C82,BL:BL)+SUMIF(BW:BW,C82,CA:CA)+SUMIF(BW:BW,C82,CB:CB)+SUMIF(CM:CM,C82,CQ:CQ)+SUMIF(CV:CV,C82,CZ:CZ)+SUMIF(DE:DE,C82,DI:DI)+SUMIF(DN:DN,C82,DR:DR)+SUMIF(DW:DW,C82,EA:EA)+SUMIF(EF:EF,C82,EJ:EJ)+SUMIF(EP:EP,C82,ET:ET)+SUMIF(EY:EY,C82,FC:FC)+SUMIF(FH:FH,C82,FL:FL)+SUMIF(FQ:FQ,C82,FU:FU)+SUMIF(FZ:FZ,C82,GD:GD)+SUMIF(GI:GI,C82,GM:GM) -> 4649886.1 | G82: =+SUMIF(N:N,C82,S:S)+SUMIF(N:N,C82,T:T)+SUMIF(AD:AD,C82,AI:AI)+SUMIF(AS:AS,C82,AX:AX)+SUMIF(BH:BH,C82,BM:BM)+SUMIF(BW:BW,C82,CD:CD)+SUMIF(BW:BW,C82,CC:CC)+SUMIF(CM:CM,C82,CR:CR)+SUMIF(CV:CV,C82,DA:DA)+SUMIF(DE:DE,C82,DJ:DJ)+SUMIF(DN:DN,C82,DS:DS)+SUMIF(DX:DX,C82,EB:EB)+SUMIF(EG:EG,C82,EK:EK)+SUMIF(EP:EP,C82,EU:EU)+SUMIF(EY:EY,C82,FD:FD)+SUMIF(FH:FH,C82,FM:FM)+SUMIF(FQ:FQ,C82,FV:FV)+SUMIF(FZ:FZ,C82,GE:GE)+SUMIF(GI:GI,C82,GN:GN) -> 607986.14 | H82: =+SUM(F82:G82) -> 5257872.3
A83: 58 | B83: =+WEEKNUM(C83,2) -> 26 | C83: =+EOMONTH(C82,1) -> 47664 | E83: =+E82+D83-F83 -> 43561885 | F83: =+SUMIF(N:N,C83,R:R)+SUMIF(AD:AD,C83,AH:AH)+SUMIF(AS:AS,C83,AW:AW)+SUMIF(BH:BH,C83,BL:BL)+SUMIF(BW:BW,C83,CA:CA)+SUMIF(BW:BW,C83,CB:CB)+SUMIF(CM:CM,C83,CQ:CQ)+SUMIF(CV:CV,C83,CZ:CZ)+SUMIF(DE:DE,C83,DI:DI)+SUMIF(DN:DN,C83,DR:DR)+SUMIF(DW:DW,C83,EA:EA)+SUMIF(EF:EF,C83,EJ:EJ)+SUMIF(EP:EP,C83,ET:ET)+SUMIF(EY:EY,C83,FC:FC)+SUMIF(FH:FH,C83,FL:FL)+SUMIF(FQ:FQ,C83,FU:FU)+SUMIF(FZ:FZ,C83,GD:GD)+SUMIF(GI:GI,C83,GM:GM) -> 324190.11 | G83: =+SUMIF(N:N,C83,S:S)+SUMIF(N:N,C83,T:T)+SUMIF(AD:AD,C83,AI:AI)+SUMIF(AS:AS,C83,AX:AX)+SUMIF(BH:BH,C83,BM:BM)+SUMIF(BW:BW,C83,CD:CD)+SUMIF(BW:BW,C83,CC:CC)+SUMIF(CM:CM,C83,CR:CR)+SUMIF(CV:CV,C83,DA:DA)+SUMIF(DE:DE,C83,DJ:DJ)+SUMIF(DN:DN,C83,DS:DS)+SUMIF(DX:DX,C83,EB:EB)+SUMIF(EG:EG,C83,EK:EK)+SUMIF(EP:EP,C83,EU:EU)+SUMIF(EY:EY,C83,FD:FD)+SUMIF(FH:FH,C83,FM:FM)+SUMIF(FQ:FQ,C83,FV:FV)+SUMIF(FZ:FZ,C83,GE:GE)+SUMIF(GI:GI,C83,GN:GN) -> 72332.72 | H83: =+SUM(F83:G83) -> 396522.83
A84: 59 | B84: =+WEEKNUM(C84,2) -> 31 | C84: =+EOMONTH(C83,1) -> 47695 | E84: =+E83+D84-F84 -> 43522390 | F84: =+SUMIF(N:N,C84,R:R)+SUMIF(AD:AD,C84,AH:AH)+SUMIF(AS:AS,C84,AW:AW)+SUMIF(BH:BH,C84,BL:BL)+SUMIF(BW:BW,C84,CA:CA)+SUMIF(BW:BW,C84,CB:CB)+SUMIF(CM:CM,C84,CQ:CQ)+SUMIF(CV:CV,C84,CZ:CZ)+SUMIF(DE:DE,C84,DI:DI)+SUMIF(DN:DN,C84,DR:DR)+SUMIF(DW:DW,C84,EA:EA)+SUMIF(EF:EF,C84,EJ:EJ)+SUMIF(EP:EP,C84,ET:ET)+SUMIF(EY:EY,C84,FC:FC)+SUMIF(FH:FH,C84,FL:FL)+SUMIF(FQ:FQ,C84,FU:FU)+SUMIF(FZ:FZ,C84,GD:GD)+SUMIF(GI:GI,C84,GM:GM) -> 39494.31 | G84: =+SUMIF(N:N,C84,S:S)+SUMIF(N:N,C84,T:T)+SUMIF(AD:AD,C84,AI:AI)+SUMIF(AS:AS,C84,AX:AX)+SUMIF(BH:BH,C84,BM:BM)+SUMIF(BW:BW,C84,CD:CD)+SUMIF(BW:BW,C84,CC:CC)+SUMIF(CM:CM,C84,CR:CR)+SUMIF(CV:CV,C84,DA:DA)+SUMIF(DE:DE,C84,DJ:DJ)+SUMIF(DN:DN,C84,DS:DS)+SUMIF(DX:DX,C84,EB:EB)+SUMIF(EG:EG,C84,EK:EK)+SUMIF(EP:EP,C84,EU:EU)+SUMIF(EY:EY,C84,FD:FD)+SUMIF(FH:FH,C84,FM:FM)+SUMIF(FQ:FQ,C84,FV:FV)+SUMIF(FZ:FZ,C84,GE:GE)+SUMIF(GI:GI,C84,GN:GN) -> 7553.3513 | H84: =+SUM(F84:G84) -> 47047.661
A85: 60 | B85: =+WEEKNUM(C85,2) -> 35 | C85: =+EOMONTH(C84,1) -> 47726 | E85: =+E84+D85-F85 -> 38872504 | F85: =+SUMIF(N:N,C85,R:R)+SUMIF(AD:AD,C85,AH:AH)+SUMIF(AS:AS,C85,AW:AW)+SUMIF(BH:BH,C85,BL:BL)+SUMIF(BW:BW,C85,CA:CA)+SUMIF(BW:BW,C85,CB:CB)+SUMIF(CM:CM,C85,CQ:CQ)+SUMIF(CV:CV,C85,CZ:CZ)+SUMIF(DE:DE,C85,DI:DI)+SUMIF(DN:DN,C85,DR:DR)+SUMIF(DW:DW,C85,EA:EA)+SUMIF(EF:EF,C85,EJ:EJ)+SUMIF(EP:EP,C85,ET:ET)+SUMIF(EY:EY,C85,FC:FC)+SUMIF(FH:FH,C85,FL:FL)+SUMIF(FQ:FQ,C85,FU:FU)+SUMIF(FZ:FZ,C85,GD:GD)+SUMIF(GI:GI,C85,GM:GM) -> 4649886.1 | G85: =+SUMIF(N:N,C85,S:S)+SUMIF(N:N,C85,T:T)+SUMIF(AD:AD,C85,AI:AI)+SUMIF(AS:AS,C85,AX:AX)+SUMIF(BH:BH,C85,BM:BM)+SUMIF(BW:BW,C85,CD:CD)+SUMIF(BW:BW,C85,CC:CC)+SUMIF(CM:CM,C85,CR:CR)+SUMIF(CV:CV,C85,DA:DA)+SUMIF(DE:DE,C85,DJ:DJ)+SUMIF(DN:DN,C85,DS:DS)+SUMIF(DX:DX,C85,EB:EB)+SUMIF(EG:EG,C85,EK:EK)+SUMIF(EP:EP,C85,EU:EU)+SUMIF(EY:EY,C85,FD:FD)+SUMIF(FH:FH,C85,FM:FM)+SUMIF(FQ:FQ,C85,FV:FV)+SUMIF(FZ:FZ,C85,GE:GE)+SUMIF(GI:GI,C85,GN:GN) -> 557248.04 | H85: =+SUM(F85:G85) -> 5207134.2
A86: 61 | B86: =+WEEKNUM(C86,2) -> 40 | C86: =+EOMONTH(C85,1) -> 47756 | E86: =+E85+D86-F86 -> 38548314 | F86: =+SUMIF(N:N,C86,R:R)+SUMIF(AD:AD,C86,AH:AH)+SUMIF(AS:AS,C86,AW:AW)+SUMIF(BH:BH,C86,BL:BL)+SUMIF(BW:BW,C86,CA:CA)+SUMIF(BW:BW,C86,CB:CB)+SUMIF(CM:CM,C86,CQ:CQ)+SUMIF(CV:CV,C86,CZ:CZ)+SUMIF(DE:DE,C86,DI:DI)+SUMIF(DN:DN,C86,DR:DR)+SUMIF(DW:DW,C86,EA:EA)+SUMIF(EF:EF,C86,EJ:EJ)+SUMIF(EP:EP,C86,ET:ET)+SUMIF(EY:EY,C86,FC:FC)+SUMIF(FH:FH,C86,FL:FL)+SUMIF(FQ:FQ,C86,FU:FU)+SUMIF(FZ:FZ,C86,GD:GD)+SUMIF(GI:GI,C86,GM:GM) -> 324190.11 | G86: =+SUMIF(N:N,C86,S:S)+SUMIF(N:N,C86,T:T)+SUMIF(AD:AD,C86,AI:AI)+SUMIF(AS:AS,C86,AX:AX)+SUMIF(BH:BH,C86,BM:BM)+SUMIF(BW:BW,C86,CD:CD)+SUMIF(BW:BW,C86,CC:CC)+SUMIF(CM:CM,C86,CR:CR)+SUMIF(CV:CV,C86,DA:DA)+SUMIF(DE:DE,C86,DJ:DJ)+SUMIF(DN:DN,C86,DS:DS)+SUMIF(DX:DX,C86,EB:EB)+SUMIF(EG:EG,C86,EK:EK)+SUMIF(EP:EP,C86,EU:EU)+SUMIF(EY:EY,C86,FD:FD)+SUMIF(FH:FH,C86,FM:FM)+SUMIF(FQ:FQ,C86,FV:FV)+SUMIF(FZ:FZ,C86,GE:GE)+SUMIF(GI:GI,C86,GN:GN) -> 65149.78 | H86: =+SUM(F86:G86) -> 389339.89
A87: 62 | B87: =+WEEKNUM(C87,2) -> 44 | C87: =+EOMONTH(C86,1) -> 47787 | E87: =+E86+D87-F87 -> 38508820 | F87: =+SUMIF(N:N,C87,R:R)+SUMIF(AD:AD,C87,AH:AH)+SUMIF(AS:AS,C87,AW:AW)+SUMIF(BH:BH,C87,BL:BL)+SUMIF(BW:BW,C87,CA:CA)+SUMIF(BW:BW,C87,CB:CB)+SUMIF(CM:CM,C87,CQ:CQ)+SUMIF(CV:CV,C87,CZ:CZ)+SUMIF(DE:DE,C87,DI:DI)+SUMIF(DN:DN,C87,DR:DR)+SUMIF(DW:DW,C87,EA:EA)+SUMIF(EF:EF,C87,EJ:EJ)+SUMIF(EP:EP,C87,ET:ET)+SUMIF(EY:EY,C87,FC:FC)+SUMIF(FH:FH,C87,FL:FL)+SUMIF(FQ:FQ,C87,FU:FU)+SUMIF(FZ:FZ,C87,GD:GD)+SUMIF(GI:GI,C87,GM:GM) -> 39494.31 | G87: =+SUMIF(N:N,C87,S:S)+SUMIF(N:N,C87,T:T)+SUMIF(AD:AD,C87,AI:AI)+SUMIF(AS:AS,C87,AX:AX)+SUMIF(BH:BH,C87,BM:BM)+SUMIF(BW:BW,C87,CD:CD)+SUMIF(BW:BW,C87,CC:CC)+SUMIF(CM:CM,C87,CR:CR)+SUMIF(CV:CV,C87,DA:DA)+SUMIF(DE:DE,C87,DJ:DJ)+SUMIF(DN:DN,C87,DS:DS)+SUMIF(DX:DX,C87,EB:EB)+SUMIF(EG:EG,C87,EK:EK)+SUMIF(EP:EP,C87,EU:EU)+SUMIF(EY:EY,C87,FD:FD)+SUMIF(FH:FH,C87,FM:FM)+SUMIF(FQ:FQ,C87,FV:FV)+SUMIF(FZ:FZ,C87,GE:GE)+SUMIF(GI:GI,C87,GN:GN) -> 7202.181 | H87: =+SUM(F87:G87) -> 46696.491
A88: 63 | B88: =+WEEKNUM(C88,2) -> 48 | C88: =+EOMONTH(C87,1) -> 47817 | E88: =+E87+D88-F88 -> 33858934 | F88: =+SUMIF(N:N,C88,R:R)+SUMIF(AD:AD,C88,AH:AH)+SUMIF(AS:AS,C88,AW:AW)+SUMIF(BH:BH,C88,BL:BL)+SUMIF(BW:BW,C88,CA:CA)+SUMIF(BW:BW,C88,CB:CB)+SUMIF(CM:CM,C88,CQ:CQ)+SUMIF(CV:CV,C88,CZ:CZ)+SUMIF(DE:DE,C88,DI:DI)+SUMIF(DN:DN,C88,DR:DR)+SUMIF(DW:DW,C88,EA:EA)+SUMIF(EF:EF,C88,EJ:EJ)+SUMIF(EP:EP,C88,ET:ET)+SUMIF(EY:EY,C88,FC:FC)+SUMIF(FH:FH,C88,FL:FL)+SUMIF(FQ:FQ,C88,FU:FU)+SUMIF(FZ:FZ,C88,GD:GD)+SUMIF(GI:GI,C88,GM:GM) -> 4649886.1 | G88: =+SUMIF(N:N,C88,S:S)+SUMIF(N:N,C88,T:T)+SUMIF(AD:AD,C88,AI:AI)+SUMIF(AS:AS,C88,AX:AX)+SUMIF(BH:BH,C88,BM:BM)+SUMIF(BW:BW,C88,CD:CD)+SUMIF(BW:BW,C88,CC:CC)+SUMIF(CM:CM,C88,CR:CR)+SUMIF(CV:CV,C88,DA:DA)+SUMIF(DE:DE,C88,DJ:DJ)+SUMIF(DN:DN,C88,DS:DS)+SUMIF(DX:DX,C88,EB:EB)+SUMIF(EG:EG,C88,EK:EK)+SUMIF(EP:EP,C88,EU:EU)+SUMIF(EY:EY,C88,FD:FD)+SUMIF(FH:FH,C88,FM:FM)+SUMIF(FQ:FQ,C88,FV:FV)+SUMIF(FZ:FZ,C88,GE:GE)+SUMIF(GI:GI,C88,GN:GN) -> 486016.03 | H88: =+SUM(F88:G88) -> 5135902.2
A89: 64 | B89: =+WEEKNUM(C89,2) -> 53 | C89: =+EOMONTH(C88,1) -> 47848 | E89: =+E88+D89-F89 -> 33534744 | F89: =+SUMIF(N:N,C89,R:R)+SUMIF(AD:AD,C89,AH:AH)+SUMIF(AS:AS,C89,AW:AW)+SUMIF(BH:BH,C89,BL:BL)+SUMIF(BW:BW,C89,CA:CA)+SUMIF(BW:BW,C89,CB:CB)+SUMIF(CM:CM,C89,CQ:CQ)+SUMIF(CV:CV,C89,CZ:CZ)+SUMIF(DE:DE,C89,DI:DI)+SUMIF(DN:DN,C89,DR:DR)+SUMIF(DW:DW,C89,EA:EA)+SUMIF(EF:EF,C89,EJ:EJ)+SUMIF(EP:EP,C89,ET:ET)+SUMIF(EY:EY,C89,FC:FC)+SUMIF(FH:FH,C89,FL:FL)+SUMIF(FQ:FQ,C89,FU:FU)+SUMIF(FZ:FZ,C89,GD:GD)+SUMIF(GI:GI,C89,GM:GM) -> 324190.11 | G89: =+SUMIF(N:N,C89,S:S)+SUMIF(N:N,C89,T:T)+SUMIF(AD:AD,C89,AI:AI)+SUMIF(AS:AS,C89,AX:AX)+SUMIF(BH:BH,C89,BM:BM)+SUMIF(BW:BW,C89,CD:CD)+SUMIF(BW:BW,C89,CC:CC)+SUMIF(CM:CM,C89,CR:CR)+SUMIF(CV:CV,C89,DA:DA)+SUMIF(DE:DE,C89,DJ:DJ)+SUMIF(DN:DN,C89,DS:DS)+SUMIF(DX:DX,C89,EB:EB)+SUMIF(EG:EG,C89,EK:EK)+SUMIF(EP:EP,C89,EU:EU)+SUMIF(EY:EY,C89,FD:FD)+SUMIF(FH:FH,C89,FM:FM)+SUMIF(FQ:FQ,C89,FV:FV)+SUMIF(FZ:FZ,C89,GE:GE)+SUMIF(GI:GI,C89,GN:GN) -> 62450.45 | H89: =+SUM(F89:G89) -> 386640.56
A90: 65 | B90: =+WEEKNUM(C90,2) -> 5 | C90: =+EOMONTH(C89,1) -> 47879 | E90: =+E89+D90-F90 -> 33495249 | F90: =+SUMIF(N:N,C90,R:R)+SUMIF(AD:AD,C90,AH:AH)+SUMIF(AS:AS,C90,AW:AW)+SUMIF(BH:BH,C90,BL:BL)+SUMIF(BW:BW,C90,CA:CA)+SUMIF(BW:BW,C90,CB:CB)+SUMIF(CM:CM,C90,CQ:CQ)+SUMIF(CV:CV,C90,CZ:CZ)+SUMIF(DE:DE,C90,DI:DI)+SUMIF(DN:DN,C90,DR:DR)+SUMIF(DW:DW,C90,EA:EA)+SUMIF(EF:EF,C90,EJ:EJ)+SUMIF(EP:EP,C90,ET:ET)+SUMIF(EY:EY,C90,FC:FC)+SUMIF(FH:FH,C90,FL:FL)+SUMIF(FQ:FQ,C90,FU:FU)+SUMIF(FZ:FZ,C90,GD:GD)+SUMIF(GI:GI,C90,GM:GM) -> 39494.31 | G90: =+SUMIF(N:N,C90,S:S)+SUMIF(N:N,C90,T:T)+SUMIF(AD:AD,C90,AI:AI)+SUMIF(AS:AS,C90,AX:AX)+SUMIF(BH:BH,C90,BM:BM)+SUMIF(BW:BW,C90,CD:CD)+SUMIF(BW:BW,C90,CC:CC)+SUMIF(CM:CM,C90,CR:CR)+SUMIF(CV:CV,C90,DA:DA)+SUMIF(DE:DE,C90,DJ:DJ)+SUMIF(DN:DN,C90,DS:DS)+SUMIF(DX:DX,C90,EB:EB)+SUMIF(EG:EG,C90,EK:EK)+SUMIF(EP:EP,C90,EU:EU)+SUMIF(EY:EY,C90,FD:FD)+SUMIF(FH:FH,C90,FM:FM)+SUMIF(FQ:FQ,C90,FV:FV)+SUMIF(FZ:FZ,C90,GE:GE)+SUMIF(GI:GI,C90,GN:GN) -> 6391.2971 | H90: =+SUM(F90:G90) -> 45885.607
A91: 66 | B91: =+WEEKNUM(C91,2) -> 9 | C91: =+EOMONTH(C90,1) -> 47907 | E91: =+E90+D91-F91 -> 28845363 | F91: =+SUMIF(N:N,C91,R:R)+SUMIF(AD:AD,C91,AH:AH)+SUMIF(AS:AS,C91,AW:AW)+SUMIF(BH:BH,C91,BL:BL)+SUMIF(BW:BW,C91,CA:CA)+SUMIF(BW:BW,C91,CB:CB)+SUMIF(CM:CM,C91,CQ:CQ)+SUMIF(CV:CV,C91,CZ:CZ)+SUMIF(DE:DE,C91,DI:DI)+SUMIF(DN:DN,C91,DR:DR)+SUMIF(DW:DW,C91,EA:EA)+SUMIF(EF:EF,C91,EJ:EJ)+SUMIF(EP:EP,C91,ET:ET)+SUMIF(EY:EY,C91,FC:FC)+SUMIF(FH:FH,C91,FL:FL)+SUMIF(FQ:FQ,C91,FU:FU)+SUMIF(FZ:FZ,C91,GD:GD)+SUMIF(GI:GI,C91,GM:GM) -> 4649886.1 | G91: =+SUMIF(N:N,C91,S:S)+SUMIF(N:N,C91,T:T)+SUMIF(AD:AD,C91,AI:AI)+SUMIF(AS:AS,C91,AX:AX)+SUMIF(BH:BH,C91,BM:BM)+SUMIF(BW:BW,C91,CD:CD)+SUMIF(BW:BW,C91,CC:CC)+SUMIF(CM:CM,C91,CR:CR)+SUMIF(CV:CV,C91,DA:DA)+SUMIF(DE:DE,C91,DJ:DJ)+SUMIF(DN:DN,C91,DS:DS)+SUMIF(DX:DX,C91,EB:EB)+SUMIF(EG:EG,C91,EK:EK)+SUMIF(EP:EP,C91,EU:EU)+SUMIF(EY:EY,C91,FD:FD)+SUMIF(FH:FH,C91,FM:FM)+SUMIF(FQ:FQ,C91,FV:FV)+SUMIF(FZ:FZ,C91,GE:GE)+SUMIF(GI:GI,C91,GN:GN) -> 414784.02 | H91: =+SUM(F91:G91) -> 5064670.2
... A105: 80 | B105: =+WEEKNUM(C105,2) -> 18 | C105: =+EOMONTH(C104,1) -> 48334 | E105: =+E104+D105-F105 -> 8533349.2 | F105: =+SUMIF(N:N,C105,R:R)+SUMIF(AD:AD,C105,AH:AH)+SUMIF(AS:AS,C105,AW:AW)+SUMIF(BH:BH,C105,BL:BL)+SUMIF(BW:BW,C105,CA:CA)+SUMIF(BW:BW,C105,CB:CB)+SUMIF(CM:CM,C105,CQ:CQ)+SUMIF(CV:CV,C105,CZ:CZ)+SUMIF(DE:DE,C105,DI:DI)+SUMIF(DN:DN,C105,DR:DR)+SUMIF(DW:DW,C105,EA:EA)+SUMIF(EF:EF,C105,EJ:EJ)+SUMIF(EP:EP,C105,ET:ET)+SUMIF(EY:EY,C105,FC:FC)+SUMIF(FH:FH,C105,FL:FL)+SUMIF(FQ:FQ,C105,FU:FU)+SUMIF(FZ:FZ,C105,GD:GD)+SUMIF(GI:GI,C105,GM:GM) -> 39494.31 | G105: =+SUMIF(N:N,C105,S:S)+SUMIF(N:N,C105,T:T)+SUMIF(AD:AD,C105,AI:AI)+SUMIF(AS:AS,C105,AX:AX)+SUMIF(BH:BH,C105,BM:BM)+SUMIF(BW:BW,C105,CD:CD)+SUMIF(BW:BW,C105,CC:CC)+SUMIF(CM:CM,C105,CR:CR)+SUMIF(CV:CV,C105,DA:DA)+SUMIF(DE:DE,C105,DJ:DJ)+SUMIF(DN:DN,C105,DS:DS)+SUMIF(DX:DX,C105,EB:EB)+SUMIF(EG:EG,C105,EK:EK)+SUMIF(EP:EP,C105,EU:EU)+SUMIF(EY:EY,C105,FD:FD)+SUMIF(FH:FH,C105,FM:FM)+SUMIF(FQ:FQ,C105,FV:FV)+SUMIF(FZ:FZ,C105,GE:GE)+SUMIF(GI:GI,C105,GN:GN) -> 3486.1615 | H105: =+SUM(F105:G105) -> 42980.471
A106: 81 | B106: =+WEEKNUM(C106,2) -> 23 | C106: =+EOMONTH(C105,1) -> 48365 | E106: =+E105+D106-F106 -> 8008301.7 | F106: =+SUMIF(N:N,C106,R:R)+SUMIF(AD:AD,C106,AH:AH)+SUMIF(AS:AS,C106,AW:AW)+SUMIF(BH:BH,C106,BL:BL)+SUMIF(BW:BW,C106,CA:CA)+SUMIF(BW:BW,C106,CB:CB)+SUMIF(CM:CM,C106,CQ:CQ)+SUMIF(CV:CV,C106,CZ:CZ)+SUMIF(DE:DE,C106,DI:DI)+SUMIF(DN:DN,C106,DR:DR)+SUMIF(DW:DW,C106,EA:EA)+SUMIF(EF:EF,C106,EJ:EJ)+SUMIF(EP:EP,C106,ET:ET)+SUMIF(EY:EY,C106,FC:FC)+SUMIF(FH:FH,C106,FL:FL)+SUMIF(FQ:FQ,C106,FU:FU)+SUMIF(FZ:FZ,C106,GD:GD)+SUMIF(GI:GI,C106,GM:GM) -> 525047.46 | G106: =+SUMIF(N:N,C106,S:S)+SUMIF(N:N,C106,T:T)+SUMIF(AD:AD,C106,AI:AI)+SUMIF(AS:AS,C106,AX:AX)+SUMIF(BH:BH,C106,BM:BM)+SUMIF(BW:BW,C106,CD:CD)+SUMIF(BW:BW,C106,CC:CC)+SUMIF(CM:CM,C106,CR:CR)+SUMIF(CV:CV,C106,DA:DA)+SUMIF(DE:DE,C106,DJ:DJ)+SUMIF(DN:DN,C106,DS:DS)+SUMIF(DX:DX,C106,EB:EB)+SUMIF(EG:EG,C106,EK:EK)+SUMIF(EP:EP,C106,EU:EU)+SUMIF(EY:EY,C106,FD:FD)+SUMIF(FH:FH,C106,FM:FM)+SUMIF(FQ:FQ,C106,FV:FV)+SUMIF(FZ:FZ,C106,GE:GE)+SUMIF(GI:GI,C106,GN:GN) -> 58806.366 | H106: =+SUM(F106:G106) -> 583853.83 | I106: 0
A107: 82 | B107: =+WEEKNUM(C107,2) -> 27 | C107: =+EOMONTH(C106,1) -> 48395 | E107: =+E106+D107-F107 -> 7684111.6 | F107: =+SUMIF(N:N,C107,R:R)+SUMIF(AD:AD,C107,AH:AH)+SUMIF(AS:AS,C107,AW:AW)+SUMIF(BH:BH,C107,BL:BL)+SUMIF(BW:BW,C107,CA:CA)+SUMIF(BW:BW,C107,CB:CB)+SUMIF(CM:CM,C107,CQ:CQ)+SUMIF(CV:CV,C107,CZ:CZ)+SUMIF(DE:DE,C107,DI:DI)+SUMIF(DN:DN,C107,DR:DR)+SUMIF(DW:DW,C107,EA:EA)+SUMIF(EF:EF,C107,EJ:EJ)+SUMIF(EP:EP,C107,ET:ET)+SUMIF(EY:EY,C107,FC:FC)+SUMIF(FH:FH,C107,FL:FL)+SUMIF(FQ:FQ,C107,FU:FU)+SUMIF(FZ:FZ,C107,GD:GD)+SUMIF(GI:GI,C107,GM:GM) -> 324190.11 | G107: =+SUMIF(N:N,C107,S:S)+SUMIF(N:N,C107,T:T)+SUMIF(AD:AD,C107,AI:AI)+SUMIF(AS:AS,C107,AX:AX)+SUMIF(BH:BH,C107,BM:BM)+SUMIF(BW:BW,C107,CD:CD)+SUMIF(BW:BW,C107,CC:CC)+SUMIF(CM:CM,C107,CR:CR)+SUMIF(CV:CV,C107,DA:DA)+SUMIF(DE:DE,C107,DJ:DJ)+SUMIF(DN:DN,C107,DS:DS)+SUMIF(DX:DX,C107,EB:EB)+SUMIF(EG:EG,C107,EK:EK)+SUMIF(EP:EP,C107,EU:EU)+SUMIF(EY:EY,C107,FD:FD)+SUMIF(FH:FH,C107,FM:FM)+SUMIF(FQ:FQ,C107,FV:FV)+SUMIF(FZ:FZ,C107,GE:GE)+SUMIF(GI:GI,C107,GN:GN) -> 37470.27 | H107: =+SUM(F107:G107) -> 361660.38
A108: 83 | B108: =+WEEKNUM(C108,2) -> 31 | C108: =+EOMONTH(C107,1) -> 48426 | E108: =+E107+D108-F108 -> 7644617.3 | F108: =+SUMIF(N:N,C108,R:R)+SUMIF(AD:AD,C108,AH:AH)+SUMIF(AS:AS,C108,AW:AW)+SUMIF(BH:BH,C108,BL:BL)+SUMIF(BW:BW,C108,CA:CA)+SUMIF(BW:BW,C108,CB:CB)+SUMIF(CM:CM,C108,CQ:CQ)+SUMIF(CV:CV,C108,CZ:CZ)+SUMIF(DE:DE,C108,DI:DI)+SUMIF(DN:DN,C108,DR:DR)+SUMIF(DW:DW,C108,EA:EA)+SUMIF(EF:EF,C108,EJ:EJ)+SUMIF(EP:EP,C108,ET:ET)+SUMIF(EY:EY,C108,FC:FC)+SUMIF(FH:FH,C108,FL:FL)+SUMIF(FQ:FQ,C108,FU:FU)+SUMIF(FZ:FZ,C108,GD:GD)+SUMIF(GI:GI,C108,GM:GM) -> 39494.31 | G108: =+SUMIF(N:N,C108,S:S)+SUMIF(N:N,C108,T:T)+SUMIF(AD:AD,C108,AI:AI)+SUMIF(AS:AS,C108,AX:AX)+SUMIF(BH:BH,C108,BM:BM)+SUMIF(BW:BW,C108,CD:CD)+SUMIF(BW:BW,C108,CC:CC)+SUMIF(CM:CM,C108,CR:CR)+SUMIF(CV:CV,C108,DA:DA)+SUMIF(DE:DE,C108,DJ:DJ)+SUMIF(DN:DN,C108,DS:DS)+SUMIF(DX:DX,C108,EB:EB)+SUMIF(EG:EG,C108,EK:EK)+SUMIF(EP:EP,C108,EU:EU)+SUMIF(EY:EY,C108,FD:FD)+SUMIF(FH:FH,C108,FM:FM)+SUMIF(FQ:FQ,C108,FV:FV)+SUMIF(FZ:FZ,C108,GE:GE)+SUMIF(GI:GI,C108,GN:GN) -> 2905.1343 | H108: =+SUM(F108:G108) -> 42399.444
A109: 84 | B109: =+WEEKNUM(C109,2) -> 36 | C109: =+EOMONTH(C108,1) -> 48457 | E109: =+E108+D109-F109 -> 7119569.8 | F109: =+SUMIF(N:N,C109,R:R)+SUMIF(AD:AD,C109,AH:AH)+SUMIF(AS:AS,C109,AW:AW)+SUMIF(BH:BH,C109,BL:BL)+SUMIF(BW:BW,C109,CA:CA)+SUMIF(BW:BW,C109,CB:CB)+SUMIF(CM:CM,C109,CQ:CQ)+SUMIF(CV:CV,C109,CZ:CZ)+SUMIF(DE:DE,C109,DI:DI)+SUMIF(DN:DN,C109,DR:DR)+SUMIF(DW:DW,C109,EA:EA)+SUMIF(EF:EF,C109,EJ:EJ)+SUMIF(EP:EP,C109,ET:ET)+SUMIF(EY:EY,C109,FC:FC)+SUMIF(FH:FH,C109,FL:FL)+SUMIF(FQ:FQ,C109,FU:FU)+SUMIF(FZ:FZ,C109,GD:GD)+SUMIF(GI:GI,C109,GM:GM) -> 525047.46 | G109: =+SUMIF(N:N,C109,S:S)+SUMIF(N:N,C109,T:T)+SUMIF(AD:AD,C109,AI:AI)+SUMIF(AS:AS,C109,AX:AX)+SUMIF(BH:BH,C109,BM:BM)+SUMIF(BW:BW,C109,CD:CD)+SUMIF(BW:BW,C109,CC:CC)+SUMIF(CM:CM,C109,CR:CR)+SUMIF(CV:CV,C109,DA:DA)+SUMIF(DE:DE,C109,DJ:DJ)+SUMIF(DN:DN,C109,DS:DS)+SUMIF(DX:DX,C109,EB:EB)+SUMIF(EG:EG,C109,EK:EK)+SUMIF(EP:EP,C109,EU:EU)+SUMIF(EY:EY,C109,FD:FD)+SUMIF(FH:FH,C109,FM:FM)+SUMIF(FQ:FQ,C109,FV:FV)+SUMIF(FZ:FZ,C109,GE:GE)+SUMIF(GI:GI,C109,GN:GN) -> 52062.446 | H109: =+SUM(F109:G109) -> 577109.91
A110: 85 | B110: =+WEEKNUM(C110,2) -> 40 | C110: =+EOMONTH(C109,1) -> 48487 | E110: =+E109+D110-F110 -> 6795379.7 | F110: =+SUMIF(N:N,C110,R:R)+SUMIF(AD:AD,C110,AH:AH)+SUMIF(AS:AS,C110,AW:AW)+SUMIF(BH:BH,C110,BL:BL)+SUMIF(BW:BW,C110,CA:CA)+SUMIF(BW:BW,C110,CB:CB)+SUMIF(CM:CM,C110,CQ:CQ)+SUMIF(CV:CV,C110,CZ:CZ)+SUMIF(DE:DE,C110,DI:DI)+SUMIF(DN:DN,C110,DR:DR)+SUMIF(DW:DW,C110,EA:EA)+SUMIF(EF:EF,C110,EJ:EJ)+SUMIF(EP:EP,C110,ET:ET)+SUMIF(EY:EY,C110,FC:FC)+SUMIF(FH:FH,C110,FL:FL)+SUMIF(FQ:FQ,C110,FU:FU)+SUMIF(FZ:FZ,C110,GD:GD)+SUMIF(GI:GI,C110,GM:GM) -> 324190.11 | G110: =+SUMIF(N:N,C110,S:S)+SUMIF(N:N,C110,T:T)+SUMIF(AD:AD,C110,AI:AI)+SUMIF(AS:AS,C110,AX:AX)+SUMIF(BH:BH,C110,BM:BM)+SUMIF(BW:BW,C110,CD:CD)+SUMIF(BW:BW,C110,CC:CC)+SUMIF(CM:CM,C110,CR:CR)+SUMIF(CV:CV,C110,DA:DA)+SUMIF(DE:DE,C110,DJ:DJ)+SUMIF(DN:DN,C110,DS:DS)+SUMIF(DX:DX,C110,EB:EB)+SUMIF(EG:EG,C110,EK:EK)+SUMIF(EP:EP,C110,EU:EU)+SUMIF(EY:EY,C110,FD:FD)+SUMIF(FH:FH,C110,FM:FM)+SUMIF(FQ:FQ,C110,FV:FV)+SUMIF(FZ:FZ,C110,GE:GE)+SUMIF(GI:GI,C110,GN:GN) -> 33306.91 | H110: =+SUM(F110:G110) -> 357497.02
A111: 86 | B111: =+WEEKNUM(C111,2) -> 44 | C111: =+EOMONTH(C110,1) -> 48518 | E111: =+E110+D111-F111 -> 6755885.4 | F111: =+SUMIF(N:N,C111,R:R)+SUMIF(AD:AD,C111,AH:AH)+SUMIF(AS:AS,C111,AW:AW)+SUMIF(BH:BH,C111,BL:BL)+SUMIF(BW:BW,C111,CA:CA)+SUMIF(BW:BW,C111,CB:CB)+SUMIF(CM:CM,C111,CQ:CQ)+SUMIF(CV:CV,C111,CZ:CZ)+SUMIF(DE:DE,C111,DI:DI)+SUMIF(DN:DN,C111,DR:DR)+SUMIF(DW:DW,C111,EA:EA)+SUMIF(EF:EF,C111,EJ:EJ)+SUMIF(EP:EP,C111,ET:ET)+SUMIF(EY:EY,C111,FC:FC)+SUMIF(FH:FH,C111,FL:FL)+SUMIF(FQ:FQ,C111,FU:FU)+SUMIF(FZ:FZ,C111,GD:GD)+SUMIF(GI:GI,C111,GM:GM) -> 39494.31 | G111: =+SUMIF(N:N,C111,S:S)+SUMIF(N:N,C111,T:T)+SUMIF(AD:AD,C111,AI:AI)+SUMIF(AS:AS,C111,AX:AX)+SUMIF(BH:BH,C111,BM:BM)+SUMIF(BW:BW,C111,CD:CD)+SUMIF(BW:BW,C111,CC:CC)+SUMIF(CM:CM,C111,CR:CR)+SUMIF(CV:CV,C111,DA:DA)+SUMIF(DE:DE,C111,DJ:DJ)+SUMIF(DN:DN,C111,DS:DS)+SUMIF(DX:DX,C111,EB:EB)+SUMIF(EG:EG,C111,EK:EK)+SUMIF(EP:EP,C111,EU:EU)+SUMIF(EY:EY,C111,FD:FD)+SUMIF(FH:FH,C111,FM:FM)+SUMIF(FQ:FQ,C111,FV:FV)+SUMIF(FZ:FZ,C111,GE:GE)+SUMIF(GI:GI,C111,GN:GN) -> 2349.6469 | H111: =+SUM(F111:G111) -> 41843.957
A112: 87 | B112: =+WEEKNUM(C112,2) -> 49 | C112: =+EOMONTH(C111,1) -> 48548 | E112: =+E111+D112-F112 -> 6230838 | F112: =+SUMIF(N:N,C112,R:R)+SUMIF(AD:AD,C112,AH:AH)+SUMIF(AS:AS,C112,AW:AW)+SUMIF(BH:BH,C112,BL:BL)+SUMIF(BW:BW,C112,CA:CA)+SUMIF(BW:BW,C112,CB:CB)+SUMIF(CM:CM,C112,CQ:CQ)+SUMIF(CV:CV,C112,CZ:CZ)+SUMIF(DE:DE,C112,DI:DI)+SUMIF(DN:DN,C112,DR:DR)+SUMIF(DW:DW,C112,EA:EA)+SUMIF(EF:EF,C112,EJ:EJ)+SUMIF(EP:EP,C112,ET:ET)+SUMIF(EY:EY,C112,FC:FC)+SUMIF(FH:FH,C112,FL:FL)+SUMIF(FQ:FQ,C112,FU:FU)+SUMIF(FZ:FZ,C112,GD:GD)+SUMIF(GI:GI,C112,GM:GM) -> 525047.46 | G112: =+SUMIF(N:N,C112,S:S)+SUMIF(N:N,C112,T:T)+SUMIF(AD:AD,C112,AI:AI)+SUMIF(AS:AS,C112,AX:AX)+SUMIF(BH:BH,C112,BM:BM)+SUMIF(BW:BW,C112,CD:CD)+SUMIF(BW:BW,C112,CC:CC)+SUMIF(CM:CM,C112,CR:CR)+SUMIF(CV:CV,C112,DA:DA)+SUMIF(DE:DE,C112,DJ:DJ)+SUMIF(DN:DN,C112,DS:DS)+SUMIF(DX:DX,C112,EB:EB)+SUMIF(EG:EG,C112,EK:EK)+SUMIF(EP:EP,C112,EU:EU)+SUMIF(EY:EY,C112,FD:FD)+SUMIF(FH:FH,C112,FM:FM)+SUMIF(FQ:FQ,C112,FV:FV)+SUMIF(FZ:FZ,C112,GE:GE)+SUMIF(GI:GI,C112,GN:GN) -> 44011.718 | H112: =+SUM(F112:G112) -> 569059.18
A113: 88 | B113: =+WEEKNUM(C113,2) -> 53 | C113: =+EOMONTH(C112,1) -> 48579 | E113: =+E112+D113-F113 -> 5906647.8 | F113: =+SUMIF(N:N,C113,R:R)+SUMIF(AD:AD,C113,AH:AH)+SUMIF(AS:AS,C113,AW:AW)+SUMIF(BH:BH,C113,BL:BL)+SUMIF(BW:BW,C113,CA:CA)+SUMIF(BW:BW,C113,CB:CB)+SUMIF(CM:CM,C113,CQ:CQ)+SUMIF(CV:CV,C113,CZ:CZ)+SUMIF(DE:DE,C113,DI:DI)+SUMIF(DN:DN,C113,DR:DR)+SUMIF(DW:DW,C113,EA:EA)+SUMIF(EF:EF,C113,EJ:EJ)+SUMIF(EP:EP,C113,ET:ET)+SUMIF(EY:EY,C113,FC:FC)+SUMIF(FH:FH,C113,FL:FL)+SUMIF(FQ:FQ,C113,FU:FU)+SUMIF(FZ:FZ,C113,GD:GD)+SUMIF(GI:GI,C113,GM:GM) -> 324190.11 | G113: =+SUMIF(N:N,C113,S:S)+SUMIF(N:N,C113,T:T)+SUMIF(AD:AD,C113,AI:AI)+SUMIF(AS:AS,C113,AX:AX)+SUMIF(BH:BH,C113,BM:BM)+SUMIF(BW:BW,C113,CD:CD)+SUMIF(BW:BW,C113,CC:CC)+SUMIF(CM:CM,C113,CR:CR)+SUMIF(CV:CV,C113,DA:DA)+SUMIF(DE:DE,C113,DJ:DJ)+SUMIF(DN:DN,C113,DS:DS)+SUMIF(DX:DX,C113,EB:EB)+SUMIF(EG:EG,C113,EK:EK)+SUMIF(EP:EP,C113,EU:EU)+SUMIF(EY:EY,C113,FD:FD)+SUMIF(FH:FH,C113,FM:FM)+SUMIF(FQ:FQ,C113,FV:FV)+SUMIF(FZ:FZ,C113,GE:GE)+SUMIF(GI:GI,C113,GN:GN) -> 29143.54 | H113: =+SUM(F113:G113) -> 353333.65
A114: 89 | B114: =+WEEKNUM(C114,2) -> 6 | C114: =+EOMONTH(C113,1) -> 48610 | E114: =+E113+D114-F114 -> 5867153.5 | F114: =+SUMIF(N:N,C114,R:R)+SUMIF(AD:AD,C114,AH:AH)+SUMIF(AS:AS,C114,AW:AW)+SUMIF(BH:BH,C114,BL:BL)+SUMIF(BW:BW,C114,CA:CA)+SUMIF(BW:BW,C114,CB:CB)+SUMIF(CM:CM,C114,CQ:CQ)+SUMIF(CV:CV,C114,CZ:CZ)+SUMIF(DE:DE,C114,DI:DI)+SUMIF(DN:DN,C114,DR:DR)+SUMIF(DW:DW,C114,EA:EA)+SUMIF(EF:EF,C114,EJ:EJ)+SUMIF(EP:EP,C114,ET:ET)+SUMIF(EY:EY,C114,FC:FC)+SUMIF(FH:FH,C114,FL:FL)+SUMIF(FQ:FQ,C114,FU:FU)+SUMIF(FZ:FZ,C114,GD:GD)+SUMIF(GI:GI,C114,GM:GM) -> 39494.31 | G114: =+SUMIF(N:N,C114,S:S)+SUMIF(N:N,C114,T:T)+SUMIF(AD:AD,C114,AI:AI)+SUMIF(AS:AS,C114,AX:AX)+SUMIF(BH:BH,C114,BM:BM)+SUMIF(BW:BW,C114,CD:CD)+SUMIF(BW:BW,C114,CC:CC)+SUMIF(CM:CM,C114,CR:CR)+SUMIF(CV:CV,C114,DA:DA)+SUMIF(DE:DE,C114,DJ:DJ)+SUMIF(DN:DN,C114,DS:DS)+SUMIF(DX:DX,C114,EB:EB)+SUMIF(EG:EG,C114,EK:EK)+SUMIF(EP:EP,C114,EU:EU)+SUMIF(EY:EY,C114,FD:FD)+SUMIF(FH:FH,C114,FM:FM)+SUMIF(FQ:FQ,C114,FV:FV)+SUMIF(FZ:FZ,C114,GE:GE)+SUMIF(GI:GI,C114,GN:GN) -> 1762.2348 | H114: =+SUM(F114:G114) -> 41256.545
...

Sheet EEFF proyectados
