Workbook

Sheet Caracteristicas
A1: Nro de la operación | B1: Entidad | C1: Cod. Entidad | D1: Moneda | E1: Tasa | F1: Periodicidad | G1: desembolso | H1: vencimiento | I1: Plazo (dias) | J1: Monto Inicial | K1: Saldo a capital | L1: % adeudado por Cemento | M1: Saldo a capital Cemento | N1: Monto garantia | O1: Garantias | P1: Covenants | Q1: capital en mora | R1: interes en mora | S1: saldo ajustado
A2: 3167401 | B2: =+HLOOKUP($A2,'Obligaciones financieras'!$Q$1:$HV$21,COLUMNS($A2:B2),FALSE) -> Fideicomiso - Banco Unión | C2: =+HLOOKUP($A2,'Obligaciones financieras'!$Q$1:$HV$21,COLUMNS($A2:C2),FALSE) -> FID - BUN | D2: =+HLOOKUP($A2,'Obligaciones financieras'!$Q$1:$HV$21,COLUMNS($A2:D2),FALSE) -> Bolivanos | E2: =+HLOOKUP($A2,'Obligaciones financieras'!$Q$1:$HV$21,COLUMNS($A2:E2),FALSE)*100 -> 6 | F2: =+HLOOKUP($A2,'Obligaciones financieras'!$Q$1:$HV$21,COLUMNS($A2:F2),FALSE) -> Trimestral | G2: 45463 | H2: =+HLOOKUP($A2,'Obligaciones financieras'!$Q$1:$HV$21,COLUMNS($A2:H2),FALSE) -> 48248 | I2: =8*365 -> 2920 | J2: 2.3061769e+08 | K2: =+HLOOKUP($A2,'Obligaciones financieras'!$Q$1:$HV$21,COLUMNS($A2:K2),FALSE) -> 2.3034329e+08 | L2: =+HLOOKUP($A2,'Obligaciones financieras'!$Q$1:$HV$21,COLUMNS($A2:L2),FALSE)*100 -> 57.390185 | M2: =+HLOOKUP($A2,'Obligaciones financieras'!$Q$1:$HV$21,COLUMNS($A2:M2),FALSE) -> 1.3219444e+08 | N2: =+Garantias!R2 -> 2.3762982e+08 | O2: - Existencias de mercaderia - Prendaria | Q2: =SUM('3167401'!C3:C6) -> 157478.67 | R2: 0 | S2: 0
A3: 2767412 | B3: =+HLOOKUP($A3,'Obligaciones financieras'!$Q$1:$HV$21,COLUMNS($A3:B3),FALSE) -> Banco Unión | C3: =+HLOOKUP($A3,'Obligaciones financieras'!$Q$1:$HV$21,COLUMNS($A3:C3),FALSE) -> BUN | D3: =+HLOOKUP($A3,'Obligaciones financieras'!$Q$1:$HV$21,COLUMNS($A3:D3),FALSE) -> Bolivanos | E3: =+HLOOKUP($A3,'Obligaciones financieras'!$Q$1:$HV$21,COLUMNS($A3:E3),FALSE)*100 -> 5.5 | F3: =+HLOOKUP($A3,'Obligaciones financieras'!$Q$1:$HV$21,COLUMNS($A3:F3),FALSE) -> Trimestral | H3: =+HLOOKUP($A3,'Obligaciones financieras'!$Q$1:$HV$21,COLUMNS($A3:H3),FALSE) -> 48058 | K3: =+HLOOKUP($A3,'Obligaciones financieras'!$Q$1:$HV$21,COLUMNS($A3:K3),FALSE) -> 1241907.9 | L3: =+HLOOKUP($A3,'Obligaciones financieras'!$Q$1:$HV$21,COLUMNS($A3:L3),FALSE)*100 -> 100 | M3: =+HLOOKUP($A3,'Obligaciones financieras'!$Q$1:$HV$21,COLUMNS($A3:M3),FALSE) -> 1241907.9
A4: 2764418 | B4: =+HLOOKUP($A4,'Obligaciones financieras'!$Q$1:$HV$21,COLUMNS($A4:B4),FALSE) -> Banco Unión | C4: =+HLOOKUP($A4,'Obligaciones financieras'!$Q$1:$HV$21,COLUMNS($A4:C4),FALSE) -> BUN | D4: =+HLOOKUP($A4,'Obligaciones financieras'!$Q$1:$HV$21,COLUMNS($A4:D4),FALSE) -> Bolivanos | E4: =+HLOOKUP($A4,'Obligaciones financieras'!$Q$1:$HV$21,COLUMNS($A4:E4),FALSE)*100 -> 6 | F4: =+HLOOKUP($A4,'Obligaciones financieras'!$Q$1:$HV$21,COLUMNS($A4:F4),FALSE) -> Trimestral | H4: =+HLOOKUP($A4,'Obligaciones financieras'!$Q$1:$HV$21,COLUMNS($A4:H4),FALSE) -> 48997 | K4: =+HLOOKUP($A4,'Obligaciones financieras'!$Q$1:$HV$21,COLUMNS($A4:K4),FALSE) -> 51796168 | L4: =+HLOOKUP($A4,'Obligaciones financieras'!$Q$1:$HV$21,COLUMNS($A4:L4),FALSE)*100 -> 30.88359 | M4: =+HLOOKUP($A4,'Obligaciones financieras'!$Q$1:$HV$21,COLUMNS($A4:M4),FALSE) -> 15996516
A5: 1271559 | B5: =+HLOOKUP($A5,'Obligaciones financieras'!$Q$1:$HV$21,COLUMNS($A5:B5),FALSE) -> Banco Bisa | C5: =+HLOOKUP($A5,'Obligaciones financieras'!$Q$1:$HV$21,COLUMNS($A5:C5),FALSE) -> BIS | D5: =+HLOOKUP($A5,'Obligaciones financieras'!$Q$1:$HV$21,COLUMNS($A5:D5),FALSE) -> Bolivanos | E5: =+HLOOKUP($A5,'Obligaciones financieras'!$Q$1:$HV$21,COLUMNS($A5:E5),FALSE)*100 -> 6 | F5: =+HLOOKUP($A5,'Obligaciones financieras'!$Q$1:$HV$21,COLUMNS($A5:F5),FALSE) -> Trimestral | H5: =+HLOOKUP($A5,'Obligaciones financieras'!$Q$1:$HV$21,COLUMNS($A5:H5),FALSE) -> 47107 | K5: =+HLOOKUP($A5,'Obligaciones financieras'!$Q$1:$HV$21,COLUMNS($A5:K5),FALSE) -> 53476614 | L5: =+HLOOKUP($A5,'Obligaciones financieras'!$Q$1:$HV$21,COLUMNS($A5:L5),FALSE)*100 -> 100 | M5: =+HLOOKUP($A5,'Obligaciones financieras'!$Q$1:$HV$21,COLUMNS($A5:M5),FALSE) -> 53476614
A6: 1358960 | B6: =+HLOOKUP($A6,'Obligaciones financieras'!$Q$1:$HV$21,COLUMNS($A6:B6),FALSE) -> Banco Bisa | C6: =+HLOOKUP($A6,'Obligaciones financieras'!$Q$1:$HV$21,COLUMNS($A6:C6),FALSE) -> BIS | D6: =+HLOOKUP($A6,'Obligaciones financieras'!$Q$1:$HV$21,COLUMNS($A6:D6),FALSE) -> Bolivanos | E6: =+HLOOKUP($A6,'Obligaciones financieras'!$Q$1:$HV$21,COLUMNS($A6:E6),FALSE)*100 -> 6 | F6: =+HLOOKUP($A6,'Obligaciones financieras'!$Q$1:$HV$21,COLUMNS($A6:F6),FALSE) -> Trimestral | H6: =+HLOOKUP($A6,'Obligaciones financieras'!$Q$1:$HV$21,COLUMNS($A6:H6),FALSE) -> 47398 | K6: =+HLOOKUP($A6,'Obligaciones financieras'!$Q$1:$HV$21,COLUMNS($A6:K6),FALSE) -> 4571867.8 | L6: =+HLOOKUP($A6,'Obligaciones financieras'!$Q$1:$HV$21,COLUMNS($A6:L6),FALSE)*100 -> 22.702943 | M6: =+HLOOKUP($A6,'Obligaciones financieras'!$Q$1:$HV$21,COLUMNS($A6:M6),FALSE) -> 1037948.5
A7: 1295150 | B7: =+HLOOKUP($A7,'Obligaciones financieras'!$Q$1:$HV$21,COLUMNS($A7:B7),FALSE) -> Banco Bisa | C7: =+HLOOKUP($A7,'Obligaciones financieras'!$Q$1:$HV$21,COLUMNS($A7:C7),FALSE) -> BIS | D7: =+HLOOKUP($A7,'Obligaciones financieras'!$Q$1:$HV$21,COLUMNS($A7:D7),FALSE) -> Bolivanos | E7: =+HLOOKUP($A7,'Obligaciones financieras'!$Q$1:$HV$21,COLUMNS($A7:E7),FALSE)*100 -> 6 | F7: =+HLOOKUP($A7,'Obligaciones financieras'!$Q$1:$HV$21,COLUMNS($A7:F7),FALSE) -> Trimestral | H7: =+HLOOKUP($A7,'Obligaciones financieras'!$Q$1:$HV$21,COLUMNS($A7:H7),FALSE) -> 47375 | K7: =+HLOOKUP($A7,'Obligaciones financieras'!$Q$1:$HV$21,COLUMNS($A7:K7),FALSE) -> 1669085.9 | L7: =+HLOOKUP($A7,'Obligaciones financieras'!$Q$1:$HV$21,COLUMNS($A7:L7),FALSE)*100 -> 100 | M7: =+HLOOKUP($A7,'Obligaciones financieras'!$Q$1:$HV$21,COLUMNS($A7:M7),FALSE) -> 1669085.9
A8: 101243178 | B8: =+HLOOKUP($A8,'Obligaciones financieras'!$Q$1:$HV$21,COLUMNS($A8:B8),FALSE) -> Banco Ganadero | C8: =+HLOOKUP($A8,'Obligaciones financieras'!$Q$1:$HV$21,COLUMNS($A8:C8),FALSE) -> GAN | D8: =+HLOOKUP($A8,'Obligaciones financieras'!$Q$1:$HV$21,COLUMNS($A8:D8),FALSE) -> Bolivanos | E8: =+HLOOKUP($A8,'Obligaciones financieras'!$Q$1:$HV$21,COLUMNS($A8:E8),FALSE)*100 -> 6 | F8: =+HLOOKUP($A8,'Obligaciones financieras'!$Q$1:$HV$21,COLUMNS($A8:F8),FALSE) -> Mensual | H8: =+HLOOKUP($A8,'Obligaciones financieras'!$Q$1:$HV$21,COLUMNS($A8:H8),FALSE) -> 46609 | K8: =+HLOOKUP($A8,'Obligaciones financieras'!$Q$1:$HV$21,COLUMNS($A8:K8),FALSE) -> 29810000 | L8: =+HLOOKUP($A8,'Obligaciones financieras'!$Q$1:$HV$21,COLUMNS($A8:L8),FALSE)*100 -> 86.082018 | M8: =+HLOOKUP($A8,'Obligaciones financieras'!$Q$1:$HV$21,COLUMNS($A8:M8),FALSE) -> 25661049
A9: 315101121500077 | B9: =+HLOOKUP($A9,'Obligaciones financieras'!$Q$1:$HV$21,COLUMNS($A9:B9),FALSE) -> Banco de Desarrollo Productivo | C9: =+HLOOKUP($A9,'Obligaciones financieras'!$Q$1:$HV$21,COLUMNS($A9:C9),FALSE) -> BDP | D9: =+HLOOKUP($A9,'Obligaciones financieras'!$Q$1:$HV$21,COLUMNS($A9:D9),FALSE) -> Bolivanos | E9: =+HLOOKUP($A9,'Obligaciones financieras'!$Q$1:$HV$21,COLUMNS($A9:E9),FALSE)*100 -> 5.8 | F9: =+HLOOKUP($A9,'Obligaciones financieras'!$Q$1:$HV$21,COLUMNS($A9:F9),FALSE) -> Trimestral | H9: =+HLOOKUP($A9,'Obligaciones financieras'!$Q$1:$HV$21,COLUMNS($A9:H9),FALSE) -> 49111 | K9: =+HLOOKUP($A9,'Obligaciones financieras'!$Q$1:$HV$21,COLUMNS($A9:K9),FALSE) -> 9174681.5 | L9: =+HLOOKUP($A9,'Obligaciones financieras'!$Q$1:$HV$21,COLUMNS($A9:L9),FALSE)*100 -> 99.370812 | M9: =+HLOOKUP($A9,'Obligaciones financieras'!$Q$1:$HV$21,COLUMNS($A9:M9),FALSE) -> 9116955.5
A10: 315101121500078f | B10: =+HLOOKUP($A10,'Obligaciones financieras'!$Q$1:$HV$21,COLUMNS($A10:B10),FALSE) -> Banco de Desarrollo Productivo | C10: =+HLOOKUP($A10,'Obligaciones financieras'!$Q$1:$HV$21,COLUMNS($A10:C10),FALSE) -> BDP | D10: =+HLOOKUP($A10,'Obligaciones financieras'!$Q$1:$HV$21,COLUMNS($A10:D10),FALSE) -> Bolivanos | E10: =+HLOOKUP($A10,'Obligaciones financieras'!$Q$1:$HV$21,COLUMNS($A10:E10),FALSE)*100 -> 5.82 | F10: =+HLOOKUP($A10,'Obligaciones financieras'!$Q$1:$HV$21,COLUMNS($A10:F10),FALSE) -> Trimestral | H10: =+HLOOKUP($A10,'Obligaciones financieras'!$Q$1:$HV$21,COLUMNS($A10:H10),FALSE) -> 48765 | K10: =+HLOOKUP($A10,'Obligaciones financieras'!$Q$1:$HV$21,COLUMNS($A10:K10),FALSE) -> 8467855 | L10: =+HLOOKUP($A10,'Obligaciones financieras'!$Q$1:$HV$21,COLUMNS($A10:L10),FALSE)*100 -> 13.104947 | M10: =+HLOOKUP($A10,'Obligaciones financieras'!$Q$1:$HV$21,COLUMNS($A10:M10),FALSE) -> 1109707.9
A11: 315101121500021 | B11: =+HLOOKUP($A11,'Obligaciones financieras'!$Q$1:$HV$21,COLUMNS($A11:B11),FALSE) -> Banco de Desarrollo Productivo | C11: =+HLOOKUP($A11,'Obligaciones financieras'!$Q$1:$HV$21,COLUMNS($A11:C11),FALSE) -> BDP | D11: =+HLOOKUP($A11,'Obligaciones financieras'!$Q$1:$HV$21,COLUMNS($A11:D11),FALSE) -> Bolivanos | E11: =+HLOOKUP($A11,'Obligaciones financieras'!$Q$1:$HV$21,COLUMNS($A11:E11),FALSE)*100 -> 5.99 | F11: =+HLOOKUP($A11,'Obligaciones financieras'!$Q$1:$HV$21,COLUMNS($A11:F11),FALSE) -> Trimestral | H11: =+HLOOKUP($A11,'Obligaciones financieras'!$Q$1:$HV$21,COLUMNS($A11:H11),FALSE) -> 49111 | K11: =+HLOOKUP($A11,'Obligaciones financieras'!$Q$1:$HV$21,COLUMNS($A11:K11),FALSE) -> 2794681.5 | L11: =+HLOOKUP($A11,'Obligaciones financieras'!$Q$1:$HV$21,COLUMNS($A11:L11),FALSE)*100 -> 100 | M11: =+HLOOKUP($A11,'Obligaciones financieras'!$Q$1:$HV$21,COLUMNS($A11:M11),FALSE) -> 2794681.5
A12: 2010014418 | B12: =+HLOOKUP($A12,'Obligaciones financieras'!$Q$1:$HV$21,COLUMNS($A12:B12),FALSE) -> BNB leasing | C12: =+HLOOKUP($A12,'Obligaciones financieras'!$Q$1:$HV$21,COLUMNS($A12:C12),FALSE) -> BNL | D12: =+HLOOKUP($A12,'Obligaciones financieras'!$Q$1:$HV$21,COLUMNS($A12:D12),FALSE) -> Bolivanos | E12: =+HLOOKUP($A12,'Obligaciones financieras'!$Q$1:$HV$21,COLUMNS($A12:E12),FALSE)*100 -> 6 | F12: =+HLOOKUP($A12,'Obligaciones financieras'!$Q$1:$HV$21,COLUMNS($A12:F12),FALSE) -> Trimestral | H12: =+HLOOKUP($A12,'Obligaciones financieras'!$Q$1:$HV$21,COLUMNS($A12:H12),FALSE) -> 46552 | K12: =+HLOOKUP($A12,'Obligaciones financieras'!$Q$1:$HV$21,COLUMNS($A12:K12),FALSE) -> 309433.84 | L12: =+HLOOKUP($A12,'Obligaciones financieras'!$Q$1:$HV$21,COLUMNS($A12:L12),FALSE)*100 -> 100 | M12: =+HLOOKUP($A12,'Obligaciones financieras'!$Q$1:$HV$21,COLUMNS($A12:M12),FALSE) -> 309433.84
A13: 2010014118 | B13: =+HLOOKUP($A13,'Obligaciones financieras'!$Q$1:$HV$21,COLUMNS($A13:B13),FALSE) -> BNB leasing | C13: =+HLOOKUP($A13,'Obligaciones financieras'!$Q$1:$HV$21,COLUMNS($A13:C13),FALSE) -> BNL | D13: =+HLOOKUP($A13,'Obligaciones financieras'!$Q$1:$HV$21,COLUMNS($A13:D13),FALSE) -> Bolivanos | E13: =+HLOOKUP($A13,'Obligaciones financieras'!$Q$1:$HV$21,COLUMNS($A13:E13),FALSE)*100 -> 6 | F13: =+HLOOKUP($A13,'Obligaciones financieras'!$Q$1:$HV$21,COLUMNS($A13:F13),FALSE) -> Trimestral | H13: =+HLOOKUP($A13,'Obligaciones financieras'!$Q$1:$HV$21,COLUMNS($A13:H13),FALSE) -> 46552 | K13: =+HLOOKUP($A13,'Obligaciones financieras'!$Q$1:$HV$21,COLUMNS($A13:K13),FALSE) -> 309433.84 | L13: =+HLOOKUP($A13,'Obligaciones financieras'!$Q$1:$HV$21,COLUMNS($A13:L13),FALSE)*100 -> 100 | M13: =+HLOOKUP($A13,'Obligaciones financieras'!$Q$1:$HV$21,COLUMNS($A13:M13),FALSE) -> 309433.84
A14: 2010013918 | B14: =+HLOOKUP($A14,'Obligaciones financieras'!$Q$1:$HV$21,COLUMNS($A14:B14),FALSE) -> BNB leasing | C14: =+HLOOKUP($A14,'Obligaciones financieras'!$Q$1:$HV$21,COLUMNS($A14:C14),FALSE) -> BNL | D14: =+HLOOKUP($A14,'Obligaciones financieras'!$Q$1:$HV$21,COLUMNS($A14:D14),FALSE) -> Bolivanos | E14: =+HLOOKUP($A14,'Obligaciones financieras'!$Q$1:$HV$21,COLUMNS($A14:E14),FALSE)*100 -> 6 | F14: =+HLOOKUP($A14,'Obligaciones financieras'!$Q$1:$HV$21,COLUMNS($A14:F14),FALSE) -> Trimestral | H14: =+HLOOKUP($A14,'Obligaciones financieras'!$Q$1:$HV$21,COLUMNS($A14:H14),FALSE) -> 46552 | K14: =+HLOOKUP($A14,'Obligaciones financieras'!$Q$1:$HV$21,COLUMNS($A14:K14),FALSE) -> 309433.84 | L14: =+HLOOKUP($A14,'Obligaciones financieras'!$Q$1:$HV$21,COLUMNS($A14:L14),FALSE)*100 -> 100 | M14: =+HLOOKUP($A14,'Obligaciones financieras'!$Q$1:$HV$21,COLUMNS($A14:M14),FALSE) -> 309433.84
A15: 2010014218 | B15: =+HLOOKUP($A15,'Obligaciones financieras'!$Q$1:$HV$21,COLUMNS($A15:B15),FALSE) -> BNB leasing | C15: =+HLOOKUP($A15,'Obligaciones financieras'!$Q$1:$HV$21,COLUMNS($A15:C15),FALSE) -> BNL | D15: =+HLOOKUP($A15,'Obligaciones financieras'!$Q$1:$HV$21,COLUMNS($A15:D15),FALSE) -> Bolivanos | E15: =+HLOOKUP($A15,'Obligaciones financieras'!$Q$1:$HV$21,COLUMNS($A15:E15),FALSE)*100 -> 6 | F15: =+HLOOKUP($A15,'Obligaciones financieras'!$Q$1:$HV$21,COLUMNS($A15:F15),FALSE) -> Trimestral | H15: =+HLOOKUP($A15,'Obligaciones financieras'!$Q$1:$HV$21,COLUMNS($A15:H15),FALSE) -> 46552 | K15: =+HLOOKUP($A15,'Obligaciones financieras'!$Q$1:$HV$21,COLUMNS($A15:K15),FALSE) -> 309433.84 | L15: =+HLOOKUP($A15,'Obligaciones financieras'!$Q$1:$HV$21,COLUMNS($A15:L15),FALSE)*100 -> 100 | M15: =+HLOOKUP($A15,'Obligaciones financieras'!$Q$1:$HV$21,COLUMNS($A15:M15),FALSE) -> 309433.84
A16: 2010014318 | B16: =+HLOOKUP($A16,'Obligaciones financieras'!$Q$1:$HV$21,COLUMNS($A16:B16),FALSE) -> BNB leasing | C16: =+HLOOKUP($A16,'Obligaciones financieras'!$Q$1:$HV$21,COLUMNS($A16:C16),FALSE) -> BNL | D16: =+HLOOKUP($A16,'Obligaciones financieras'!$Q$1:$HV$21,COLUMNS($A16:D16),FALSE) -> Bolivanos | E16: =+HLOOKUP($A16,'Obligaciones financieras'!$Q$1:$HV$21,COLUMNS($A16:E16),FALSE)*100 -> 6 | F16: =+HLOOKUP($A16,'Obligaciones financieras'!$Q$1:$HV$21,COLUMNS($A16:F16),FALSE) -> Trimestral | H16: =+HLOOKUP($A16,'Obligaciones financieras'!$Q$1:$HV$21,COLUMNS($A16:H16),FALSE) -> 46714 | K16: =+HLOOKUP($A16,'Obligaciones financieras'!$Q$1:$HV$21,COLUMNS($A16:K16),FALSE) -> 388403.55 | L16: =+HLOOKUP($A16,'Obligaciones financieras'!$Q$1:$HV$21,COLUMNS($A16:L16),FALSE)*100 -> 100 | M16: =+HLOOKUP($A16,'Obligaciones financieras'!$Q$1:$HV$21,COLUMNS($A16:M16),FALSE) -> 388403.55
A17: 2010014018 | B17: =+HLOOKUP($A17,'Obligaciones financieras'!$Q$1:$HV$21,COLUMNS($A17:B17),FALSE) -> BNB leasing | C17: =+HLOOKUP($A17,'Obligaciones financieras'!$Q$1:$HV$21,COLUMNS($A17:C17),FALSE) -> BNL | D17: =+HLOOKUP($A17,'Obligaciones financieras'!$Q$1:$HV$21,COLUMNS($A17:D17),FALSE) -> Bolivanos | E17: =+HLOOKUP($A17,'Obligaciones financieras'!$Q$1:$HV$21,COLUMNS($A17:E17),FALSE)*100 -> 6 | F17: =+HLOOKUP($A17,'Obligaciones financieras'!$Q$1:$HV$21,COLUMNS($A17:F17),FALSE) -> Trimestral | H17: =+HLOOKUP($A17,'Obligaciones financieras'!$Q$1:$HV$21,COLUMNS($A17:H17),FALSE) -> 46714 | K17: =+HLOOKUP($A17,'Obligaciones financieras'!$Q$1:$HV$21,COLUMNS($A17:K17),FALSE) -> 388403.55 | L17: =+HLOOKUP($A17,'Obligaciones financieras'!$Q$1:$HV$21,COLUMNS($A17:L17),FALSE)*100 -> 100 | M17: =+HLOOKUP($A17,'Obligaciones financieras'!$Q$1:$HV$21,COLUMNS($A17:M17),FALSE) -> 388403.55

Sheet info
A1: Nro de la operación | B1: Entidad | C1: Cod. Entidad | D1: Moneda | E1: Tasa | F1: Periodicidad | G1: vencimiento | H1: Saldo a capital | I1: % adeudado por Cemento | J1: Saldo a capital Cemento
A2: 3167401 | B2: Fideicomiso - Banco Unión | C2: FID - BUN | D2: Bolivanos | E2: 6 | F2: Trimestral | G2: 48248 | H2: 2.3034329e+08 | I2: 57.390185 | J2: 1.3219444e+08
A3: 2767412 | B3: Banco Unión | C3: BUN | D3: Bolivanos | E3: 5.5 | F3: Trimestral | G3: 48058 | H3: 1241907.9 | I3: 100 | J3: 1241907.9
A4: 2764418 | B4: Banco Unión | C4: BUN | D4: Bolivanos | E4: 6 | F4: Trimestral | G4: 48997 | H4: 51796168 | I4: 30.88359 | J4: 15996516
A5: 1271559 | B5: Banco Bisa | C5: BIS | D5: Bolivanos | E5: 6 | F5: Trimestral | G5: 47107 | H5: 53476614 | I5: 100 | J5: 53476614
A6: 1358960 | B6: Banco Bisa | C6: BIS | D6: Bolivanos | E6: 6 | F6: Trimestral | G6: 47398 | H6: 4571867.8 | I6: 22.702943 | J6: 1037948.5
A7: 1295150 | B7: Banco Bisa | C7: BIS | D7: Bolivanos | E7: 6 | F7: Trimestral | G7: 47375 | H7: 1669085.9 | I7: 100 | J7: 1669085.9
A8: 101243178 | B8: Banco Ganadero | C8: GAN | D8: Bolivanos | E8: 6 | F8: Mensual | G8: 46609 | H8: 29810000 | I8: 86.082018 | J8: 25661049
A9: 315101121500077 | B9: Banco de Desarrollo Productivo | C9: BDP | D9: Bolivanos | E9: 5.8 | F9: Trimestral | G9: 49111 | H9: 9174681.5 | I9: 99.370812 | J9: 9116955.5
A10: 315101121500078f | B10: Banco de Desarrollo Productivo | C10: BDP | D10: Bolivanos | E10: 5.82 | F10: Trimestral | G10: 48765 | H10: 8467855 | I10: 13.104947 | J10: 1109707.9
A11: 315101121500021 | B11: Banco de Desarrollo Productivo | C11: BDP | D11: Bolivanos | E11: 5.99 | F11: Trimestral | G11: 49111 | H11: 2794681.5 | I11: 100 | J11: 2794681.5
A12: 2010014418 | B12: BNB leasing | C12: BNL | D12: Bolivanos | E12: 6 | F12: Trimestral | G12: 46552 | H12: 309433.84 | I12: 100 | J12: 309433.84
A13: 2010014118 | B13: BNB leasing | C13: BNL | D13: Bolivanos | E13: 6 | F13: Trimestral | G13: 46552 | H13: 309433.84 | I13: 100 | J13: 309433.84
A14: 2010013918 | B14: BNB leasing | C14: BNL | D14: Bolivanos | E14: 6 | F14: Trimestral | G14: 46552 | H14: 309433.84 | I14: 100 | J14: 309433.84
A15: 2010014218 | B15: BNB leasing | C15: BNL | D15: Bolivanos | E15: 6 | F15: Trimestral | G15: 46552 | H15: 309433.84 | I15: 100 | J15: 309433.84
A16: 2010014318 | B16: BNB leasing | C16: BNL | D16: Bolivanos | E16: 6 | F16: Trimestral | G16: 46714 | H16: 388403.55 | I16: 100 | J16: 388403.55
A17: 2010014018 | B17: BNB leasing | C17: BNL | D17: Bolivanos | E17: 6 | F17: Trimestral | G17: 46714 | H17: 388403.55 | I17: 100 | J17: 388403.55

Sheet 3167401
A1: Fecha | B1: Saldo adeudado | C1: Amortización | D1: Intereses corrientes | E1: Intereses diferidos | F1: Total Cuota
A2: 45506 | B2: 1.3235192e+08 | C2: 0 | D2: 0 | E2: 0 | F2: 0
A3: 45611 | B3: 1.3231255e+08 | C3: 39369.667 | D3: 2316158.6 | E3: 471550.55 | F3: 2827078.8
A4: 45703 | B4: 1.3227318e+08 | C4: 39369.667 | D4: 2028792.4 | E4: 471550.55 | F4: 2539712.7
A5: 45792 | B5: 1.3223381e+08 | C5: 39369.667 | D5: 1962052.2 | E5: 471550.55 | F5: 2472972.4
A6: 45884 | B6: 1.3219444e+08 | C6: 39369.667 | D6: 2027585.1 | E6: 471550.55 | F6: 2538505.3
A7: 45976 | B7: 1.0182495e+08 | C7: 30369494 | D7: 2026981.4 | E7: 471550.55 | F7: 32868026
A8: 46068 | B8: 97751949 | C8: 4072997.9 | D8: 1561315.9 | E8: 471550.55 | F8: 6105864.3
A9: 46157 | B9: 93678951 | C9: 4072997.9 | D9: 1449987.2 | E9: 471550.55 | F9: 5994535.7
A10: 46249 | B10: 89605953 | C10: 4072997.9 | D10: 1436410.6 | E10: 471550.55 | F10: 5980959
A11: 46341 | B11: 85532956 | C11: 4072997.9 | D11: 1373958 | E11: 471550.55 | F11: 5918506.4
A12: 46433 | B12: 81459958 | C12: 4072997.9 | D12: 1311505.3 | E12: 471550.55 | F12: 5856053.7
A13: 46522 | B13: 77386960 | C13: 4072997.9 | D13: 1208322.7 | E13: 471550.55 | F13: 5752871.1
... A22: 47345 | B22: 40729979 | C22: 4072997.9 | D22: 686978.98 | E22: 471550.55 | F22: 5231527.4
A23: 47437 | B23: 36656981 | C23: 4072997.9 | D23: 624526.34 | F23: 4697524.2
A24: 47529 | B24: 32583983 | C24: 4072997.9 | D24: 562073.71 | F24: 4635071.6
A25: 47618 | B25: 28510985 | C25: 4072997.9 | D25: 483329.08 | F25: 4556327
A26: 47710 | B26: 24437987 | C26: 4072997.9 | D26: 437168.44 | F26: 4510166.3
A27: 47802 | B27: 20364989 | C27: 4072997.9 | D27: 374715.81 | F27: 4447713.7
A28: 47894 | B28: 16291992 | C28: 4072997.9 | D28: 312263.17 | F28: 4385261.1
A29: 47983 | B29: 12218994 | C29: 4072997.9 | D29: 241664.54 | F29: 4314662.4
A30: 48075 | B30: 8145995.8 | C30: 4072997.9 | D30: 187357.9 | F30: 4260355.8
A31: 48167 | B31: 4072997.9 | C31: 4072997.9 | D31: 124905.27 | F31: 4197903.1
A32: 48248 | B32: 5.5879354e-08 | C32: 4072997.9 | D32: 54985.471 | F32: 4127983.4

Sheet 2767412
A1: Fecha | B1: Saldo adeudado | C1: Amortización | D1: Intereses corrientes | E1: Total Cuota
A2: 45712 | B2: 1345589.5 | C2: 0 | D2: 0 | E2: 0
A3: 45779 | B3: 1293748.7 | C3: 51840.79 | D3: 13773.604 | E3: 65614.394
A4: 45871 | B4: 1241907.9 | C4: 51840.79 | D4: 18184.357 | E4: 70025.147
A5: 45963 | B5: 1190067.1 | C5: 51840.79 | D5: 17455.706 | E5: 69296.496
A6: 46055 | B6: 1138226.3 | C6: 51840.79 | D6: 16727.055 | E6: 68567.845
A7: 46144 | B7: 1086385.6 | C7: 51840.79 | D7: 15476.717 | E7: 67317.507
A8: 46236 | B8: 1034544.8 | C8: 51840.79 | D8: 15269.753 | E8: 67110.543
A9: 46328 | B9: 982703.98 | C9: 51840.79 | D9: 14541.101 | E9: 66381.891
A10: 46420 | B10: 930863.19 | C10: 51840.79 | D10: 13812.45 | E10: 65653.24
A11: 46509 | B11: 879022.4 | C11: 51840.79 | D11: 12657.154 | E11: 64497.944
A12: 46601 | B12: 827181.61 | C12: 51840.79 | D12: 12355.148 | E12: 64195.938
A13: 46693 | B13: 775340.82 | C13: 51840.79 | D13: 11626.497 | E13: 63467.287
... A28: 48058 | B28: -4.802132e-10 | C28: 49569.76 | D28: 666.43788 | E28: 50236.198

Sheet 2764418
A1: Fecha | B1: Saldo adeudado | C1: Amortización | D1: Intereses corrientes | E1: Total Cuota
A2: 45656 | B2: 15996516 | C2: 0 | D2: 0 | E2: 0
A3: 45708 | B3: 15996516 | C3: 0 | D3: 138636.47 | E3: 138636.47
A4: 45797 | B4: 15996516 | C4: 0 | D4: 237281.65 | E4: 237281.65
A5: 45889 | B5: 15996516 | C5: 0 | D5: 245279.91 | E5: 245279.91
A6: 45981 | B6: 15996516 | C6: 0 | D6: 245279.91 | E6: 245279.91
A7: 46073 | B7: 15996516 | C7: 0 | D7: 245279.91 | E7: 245279.91
A8: 46162 | B8: 15996516 | C8: 0 | D8: 237281.65 | E8: 237281.65
A9: 46254 | B9: 15471469 | C9: 525047.46 | D9: 245279.91 | E9: 770327.38
A10: 46346 | B10: 14946421 | C10: 525047.46 | D10: 237229.19 | E10: 762276.65
A11: 46438 | B11: 14421374 | C11: 525047.46 | D11: 229178.46 | E11: 754225.92
A12: 46527 | B12: 13896326 | C12: 525047.46 | D12: 213917.04 | E12: 738964.51
A13: 46619 | B13: 13371279 | C13: 525047.46 | D13: 213077 | E13: 738124.47
... A39: 48997 | B39: -7.4214768e-09 | C39: 245092.12 | D39: 3839.7766 | E39: 248931.9

Sheet 1271559
A1: Fecha | B1: Saldo adeudado | C1: Amortización | D1: Intereses corrientes | E1: Interes prorroga y gracia | F1: Total Cuota
A2: 45736 | B2: 53476614 | C2: 0 | D2: 0 | E2: 0 | F2: 0
A3: 45828 | B3: 53476614 | C3: 0 | D3: 819974.75 | E3: 82616.23 | F3: 902590.98
A4: 45920 | B4: =B3-C4 -> 39476614 | C4: 14000000 | D4: 819974.75 | E4: 82616.23 | F4: 902590.98
A5: 46011 | B5: =B4-C5 -> 39476614 | D5: 355289.53 | E5: 82616.23 | F5: =SUM(C5:E5) -> 437905.76
A6: 46101 | B6: =B5-C6 -> 39476614 | C6: 0 | D6: 592149.21 | E6: 82616.23 | F6: =SUM(C6:E6) -> 674765.44
A7: 46193 | B7: =B6-C7 -> 39476614 | C7: 0 | D7: 605308.08 | E7: 82616.23 | F7: =SUM(C7:E7) -> 687924.31
A8: 46285 | B8: =B7-C8 -> 39476614 | D8: 605308.08 | E8: 82616.23 | F8: =SUM(C8:E8) -> 687924.31
A9: 46376 | B9: =B8-C9 -> 39476614 | D9: 598728.65 | E9: 82616.23 | F9: =SUM(C9:E9) -> 681344.88
A10: 46466 | B10: =B9-C10 -> 37433630 | C10: 2042984.2 | D10: 592149.21 | E10: 82616.23 | F10: =SUM(C10:E10) -> 2717749.7
A11: 46558 | B11: =B10-C11 -> 32085968 | C11: 5347661.4 | D11: 573982.32 | E11: 82616.23 | F11: =SUM(C11:E11) -> 6004260
A12: 46650 | B12: =B11-C12 -> 26738307 | C12: 5347661.4 | D12: 491984.85 | E12: 82616.23 | F12: =SUM(C12:E12) -> 5922262.5
A13: 46741 | B13: =B12-C13 -> 21390646 | C13: 5347661.4 | D13: 405530.99 | E13: 82616.23 | F13: =SUM(C13:E13) -> 5835808.6
A14: 46832 | B14: =B13-C14 -> 16042984 | C14: 5347661.4 | D14: 324424.79 | E14: 82616.23 | F14: =SUM(C14:E14) -> 5754702.4
A15: 46924 | B15: =B14-C15 -> 10695323 | C15: 5347661.4 | D15: 245992.43 | E15: 82616.23 | F15: =SUM(C15:E15) -> 5676270.1
A16: 47016 | B16: =B15-C16 -> 5347661.4 | C16: 5347661.4 | D16: 163994.95 | E16: 82616.23 | F16: =SUM(C16:E16) -> 5594272.6
A17: 47107 | B17: =B16-C17 -> 7.4505806e-09 | C17: 5347661.4 | D17: 81106.2 | E17: 82616.23 | F17: =SUM(C17:E17) -> 5511383.8

Sheet 1358960
A1: Fecha | B1: Saldo adeudado | C1: Amortización | D1: Amortización cap diferido | E1: Intereses corrientes | F1: Intereses prorroga gracia | G1: Total Cuota
A2: 45677 | B2: 1154729.4
A3: 45702 | B3: 1096992.9 | C3: 57736.47 | D3: 0 | E3: 4811.3725 | F3: 1642.8395 | G3: 64190.682
A4: 45858 | B4: 1039256.4 | C4: 57736.47 | D4: 2821.4285 | E4: 28521.816 | F4: 1642.8395 | G4: 90722.554
A5: 45950 | B5: 981519.98 | C5: 57736.47 | D5: 2821.4285 | E5: 15935.266 | F5: 1642.8395 | G5: 78136.004
A6: 46042 | B6: 923783.51 | C6: 57736.47 | D6: 2821.4285 | E6: 15049.973 | F6: 1642.8395 | G6: 77250.711
A7: 46132 | B7: 866047.04 | C7: 57736.47 | D7: 2821.4285 | E7: 13856.753 | F7: 1642.8395 | G7: 76057.491
A8: 46223 | B8: 808310.57 | C8: 57736.47 | D8: 2821.4285 | E8: 13135.047 | F8: 1642.8395 | G8: 75335.785
A9: 46315 | B9: 750574.1 | C9: 57736.47 | D9: 2821.4285 | E9: 12394.095 | F9: 1642.8395 | G9: 74594.833
A10: 46407 | B10: 692837.63 | C10: 57736.47 | D10: 2821.4285 | E10: 11508.803 | F10: 1642.8395 | G10: 73709.541
A11: 46497 | B11: 635101.16 | C11: 57736.47 | D11: 2821.4285 | E11: 10392.564 | F11: 1642.8395 | G11: 72593.302
A12: 46588 | B12: 577364.69 | C12: 57736.47 | D12: 2821.4285 | E12: 9632.3676 | F12: 1642.8395 | G12: 71833.106
A13: 46680 | B13: 519628.22 | C13: 57736.47 | D13: 2821.4285 | E13: 8852.9252 | F13: 1642.8395 | G13: 71053.663
A14: 46772 | B14: 461891.75 | C14: 57736.47 | D14: 2821.4285 | E14: 7967.6327 | F14: 1642.8395 | G14: 70168.371
... A21: 47398 | B21: 0.0056757364 | C21: 115472.92 | D21: 14107.143 | E21: 1520.3935 | F21: 1642.8395 | G21: 132743.3

Sheet 1295150
A1: Fecha | B1: Saldo adeudado | C1: Amortización | D1: Intereses corrientes | E1: Total Cuota
A2: 45700 | B2: 1669085.9 | C2: 0 | D2: 0 | E2: 0
A3: 45822 | B3: 1669085.9 | C3: 0 | D3: 29209.003 | E3: 29209.003
A4: 45914 | B4: 1669085.9 | C4: 0 | D4: 22393.569 | E4: 22393.569
A5: 46005 | B5: 1564768 | C5: 104317.86 | D5: 22150.161 | E5: 126468.02
A6: 46095 | B6: 1460450.1 | C6: 104317.86 | D6: 20341.984 | E6: 124659.84
A7: 46187 | B7: 1356132.3 | C7: 104317.86 | D7: 19194.488 | E7: 123512.35
A8: 46279 | B8: 1251814.4 | C8: 104317.86 | D8: 17594.947 | E8: 121912.81
A9: 46370 | B9: 1147496.5 | C9: 104317.86 | D9: 15821.544 | E9: 120139.4
A10: 46460 | B10: 1043178.7 | C10: 104317.86 | D10: 14082.913 | E10: 118400.77
A11: 46552 | B11: 938860.83 | C11: 104317.86 | D11: 12796.326 | E11: 117114.19
A12: 46644 | B12: 834542.97 | C12: 104317.86 | D12: 11196.785 | E12: 115514.65
A13: 46735 | B13: 730225.11 | C13: 104317.86 | D13: 9492.9269 | E13: 113810.79
... A20: 47375 | B20: 0 | C20: 104317.85 | D20: 53793.24 | E20: 158111.09

Sheet 101243178
A1: Fecha | B1: Saldo adeudado | C1: Amortización | D1: Intereses corrientes | E1: Total Cuota
A2: 45848 | B2: 26010061
A3: 45879 | B3: 25661049 | C3: 349011.21 | D3: 134385.31 | E3: 483396.52
A4: 45910 | B4: 25312038 | C4: 349011.21 | D4: 132582.09 | E4: 481593.3
A5: 45940 | B5: 24963027 | C5: 349011.21 | D5: 126560.19 | E5: 475571.4
A6: 45971 | B6: 24614016 | C6: 349011.21 | D6: 128975.64 | E6: 477986.85
A7: 46001 | B7: 24265005 | C7: 349011.21 | D7: 123070.08 | E7: 472081.29
A8: 46032 | B8: 23915993 | C8: 349011.21 | D8: 125369.19 | E8: 474380.4
A9: 46063 | B9: 23566982 | C9: 349011.21 | D9: 123565.97 | E9: 472577.18
A10: 46091 | B10: 23217971 | C10: 349011.21 | D10: 109979.25 | E10: 458990.46
A11: 46122 | B11: 22868960 | C11: 349011.21 | D11: 119959.52 | E11: 468970.73
A12: 46152 | B12: 22519949 | C12: 349011.21 | D12: 114344.8 | E12: 463356.01
A13: 46183 | B13: 22170937 | C13: 349011.21 | D13: 116353.07 | E13: 465364.28
A14: 46213 | B14: 20587299 | C14: 1583638.4 | D14: 110854.69 | E14: 1694493.1
... A27: 46609 | B27: 0.068803104 | C27: 1583638.4 | D27: 8182.132 | E27: 1591820.5

Sheet 315101121500077
A1: Fecha | B1: Saldo adeudado | C1: Amortización | D1: Intereses corrientes | E1: Total Cuota
A2: 45721 | B2: 9116955.5
A3: 45838 | B3: 9116955.5 | C3: 0 | D3: 138152.48 | E3: 138152.48
A4: 45925 | B4: 9116955.5 | C4: 0 | D4: 127789.32 | E4: 127789.32
A5: 46017 | B5: 9116955.5 | C5: 0 | D5: 135133.54 | E5: 135133.54
A6: 46107 | B6: 9102050 | C6: 14905.56 | D6: 132195.85 | E6: 147101.41
A7: 46198 | B7: 9087144.4 | C7: 14905.62 | D7: 133446.17 | E7: 148351.79
A8: 46289 | B8: 8803171.1 | C8: 283973.26 | D8: 133227.63 | E8: 417200.89
A9: 46380 | B9: 8519197.8 | C9: 283973.26 | D9: 129064.27 | E9: 413037.53
A10: 46471 | B10: 8235224.6 | C10: 283973.26 | D10: 124900.9 | E10: 408874.16
A11: 46562 | B11: 7951251.3 | C11: 283973.26 | D11: 120737.54 | E11: 404710.8
A12: 46653 | B12: 7667278.1 | C12: 283973.26 | D12: 116574.18 | E12: 400547.44
A13: 46744 | B13: 7383304.8 | C13: 283973.26 | D13: 112410.82 | E13: 396384.08
A14: 46835 | B14: 7099331.5 | C14: 283973.26 | D14: 108247.45 | E14: 392220.71
... A39: 49111 | B39: 0.038867459 | C39: 283973.26 | D39: 4209.12 | E39: 288182.38

Sheet 315101121500078f
A1: Fecha | B1: Saldo adeudado | C1: Amortización | D1: Intereses corrientes | E1: Total Cuota
A2: 45721 | B2: 1109707.9
A3: 45838 | B3: 1109707.9 | C3: 0 | D3: 16421.12 | E3: 16421.12
A4: 45936 | B4: 1109707.9 | C4: 0 | D4: 17581.472 | E4: 17581.472
A5: 46027 | B5: 1109707.9 | C5: 0 | D5: 16325.652 | E5: 16325.652
A6: 46118 | B6: 1107774.2 | C6: 1933.63 | D6: 16325.652 | E6: 18259.282
A7: 46209 | B7: 1105840.6 | C7: 1933.65 | D7: 16297.205 | E7: 18230.855
A8: 46300 | B8: 1066346.3 | C8: 39494.31 | D8: 16268.758 | E8: 55763.068
A9: 46392 | B9: 1026852 | C9: 39494.31 | D9: 15860.124 | E9: 55354.434
A10: 46482 | B10: 987357.66 | C10: 39494.31 | D10: 14940.696 | E10: 54435.006
A11: 46573 | B11: 947863.35 | C11: 39494.31 | D11: 14525.677 | E11: 54019.987
A12: 46665 | B12: 908369.04 | C12: 39494.31 | D12: 14097.888 | E12: 53592.198
A13: 46757 | B13: 868874.73 | C13: 39494.31 | D13: 13510.476 | E13: 53004.786
A14: 46848 | B14: 829380.42 | C14: 39494.31 | D14: 12782.595 | E14: 52276.905
... A35: 48765 | B35: -0.087313402 | C35: 39494.31 | D35: 581.02584 | E35: 40075.336

Sheet 315101121500021
A1: Fecha | B1: Saldo adeudado | C1: Amortización | D1: Intereses corrientes | E1: Total Cuota
A2: 45657 | B2: 2794681.5
A3: 45721 | B3: 2794681.5 | C3: 0 | D3: 17114.156 | E3: 17200.556
A4: 45838 | B4: 2794681.5 | C4: 0 | D4: 38370.47 | E4: 58214.95
A5: 45925 | B5: 2794681.5 | C5: 0 | D5: 17027.76 | E5: 17027.76
A6: 46017 | B6: 2794681.5 | C6: 0 | D6: 18006.37 | E6: 18006.37
A7: 46107 | B7: 2789681.5 | C7: 5000.03 | D7: 18235.06 | E7: 23235.09
A8: 46198 | B8: 2784681.5 | C8: 5000 | D8: 18355.08 | E8: 23355.08
A9: 46289 | B9: 2744464.6 | C9: 40216.85 | D9: 18279.37 | E9: 58496.22
A10: 46380 | B10: 2704247.8 | C10: 40216.85 | D10: 17670.43 | E10: 57887.28
A11: 46471 | B11: 2664030.9 | C11: 40216.85 | D11: 17061.49 | E11: 57278.34
A12: 46562 | B12: 2623814.1 | C12: 40216.85 | D12: 16452.55 | E12: 56669.4
A13: 46653 | B13: 2583597.2 | C13: 40216.85 | D13: 15843.61 | E13: 56060.46
A14: 46744 | B14: 2543380.4 | C14: 40216.85 | D14: 15234.68 | E14: 55451.53
... A40: 49111 | B40: -2.5611371e-09 | C40: 548258.31 | D40: 79526.41 | E40: 627784.72

Sheet 2010014418
A1: Fecha | B1: Saldo adeudado | C1: Amortización | D1: Intereses corrientes | E1: Total Cuota
A2: 45742 | B2: 346343.01
A3: 45832 | B3: 309433.84 | C3: 36909.17 | D3: 4285.87 | E3: 41195.04
A4: 45922 | B4: 271740.35 | C4: 37693.49 | D4: 3732.23 | E4: 41425.72
A5: 46012 | B5: 233245.87 | C5: 38494.48 | D5: 3166.83 | E5: 41661.31
A6: 46102 | B6: 193933.38 | C6: 39312.49 | D6: 2589.41 | E6: 41901.9
A7: 46192 | B7: 153785.5 | C7: 40147.88 | D7: 1999.73 | E7: 42147.61
A8: 46282 | B8: 112784.48 | C8: 41001.02 | D8: 1397.51 | E8: 42398.53
A9: 46372 | B9: 70912.104 | C9: 41872.38 | D9: 782.49 | E9: 42654.87
A10: 46462 | B10: 41229.074 | C10: 29683.03 | D10: 17605.8 | E10: 47288.83
A11: 46552 | B11: 10293.844 | C11: 30935.23 | D11: 14697.99 | E11: 45633.22
A12: 46552 | B12: 0.0040000001 | C12: 10293.84 | D12: 0 | E12: 10293.84

Sheet 2010014118
A1: Fecha | B1: Saldo adeudado | C1: Amortización | D1: Intereses corrientes | E1: Total Cuota
A2: 45742 | B2: 346343.01
A3: 45832 | B3: 309433.84 | C3: 36909.17 | D3: 4285.87 | E3: 41195.04
A4: 45922 | B4: 271740.35 | C4: 37693.49 | D4: 3732.23 | E4: 41425.72
A5: 46012 | B5: 233245.87 | C5: 38494.48 | D5: 3166.83 | E5: 41661.31
A6: 46102 | B6: 193933.38 | C6: 39312.49 | D6: 2589.41 | E6: 41901.9
A7: 46192 | B7: 153785.5 | C7: 40147.88 | D7: 1999.73 | E7: 42147.61
A8: 46282 | B8: 112784.48 | C8: 41001.02 | D8: 1397.51 | E8: 42398.53
A9: 46372 | B9: 70912.104 | C9: 41872.38 | D9: 782.49 | E9: 42654.87
A10: 46462 | B10: 41229.074 | C10: 29683.03 | D10: 17605.8 | E10: 47288.83
A11: 46552 | B11: 10293.844 | C11: 30935.23 | D11: 14697.99 | E11: 45633.22
A12: 46552 | B12: 0.0040000001 | C12: 10293.84 | D12: 0 | E12: 10293.84

Sheet 2010013918
A1: Fecha | B1: Saldo adeudado | C1: Amortización | D1: Intereses corrientes | E1: Total Cuota
A2: 45742 | B2: 346343.01 | C2: 0 | D2: 0 | E2: 0
A3: 45832 | B3: 309433.84 | C3: 36909.17 | D3: 4285.87 | E3: 41195.04
A4: 45922 | B4: 271740.35 | C4: 37693.49 | D4: 3732.23 | E4: 41425.72
A5: 46012 | B5: 233245.87 | C5: 38494.48 | D5: 3166.83 | E5: 41661.31
A6: 46102 | B6: 193933.38 | C6: 39312.49 | D6: 2589.41 | E6: 41901.9
A7: 46192 | B7: 153785.5 | C7: 40147.88 | D7: 1999.73 | E7: 42147.61
A8: 46282 | B8: 112784.48 | C8: 41001.02 | D8: 1397.51 | E8: 42398.53
A9: 46372 | B9: 70912.104 | C9: 41872.38 | D9: 782.49 | E9: 42654.87
A10: 46462 | B10: 41229.074 | C10: 29683.03 | D10: 17605.8 | E10: 47288.83
A11: 46552 | B11: 10293.844 | C11: 30935.23 | D11: 14697.99 | E11: 45633.22
A12: 46552 | B12: 0.0040000001 | C12: 10293.84 | D12: 0 | E12: 10293.84

Sheet 2010014218
A1: Fecha | B1: Saldo adeudado | C1: Amortización | D1: Intereses corrientes | E1: Total Cuota
A2: 45742 | B2: 346343.01
A3: 45832 | B3: 309433.84 | C3: 36909.17 | D3: 4285.87 | E3: 41195.04
A4: 45922 | B4: 271740.35 | C4: 37693.49 | D4: 3732.23 | E4: 41425.72
A5: 46012 | B5: 233245.87 | C5: 38494.48 | D5: 3166.83 | E5: 41661.31
A6: 46102 | B6: 193933.38 | C6: 39312.49 | D6: 2589.41 | E6: 41901.9
A7: 46192 | B7: 153785.5 | C7: 40147.88 | D7: 1999.73 | E7: 42147.61
A8: 46282 | B8: 112784.48 | C8: 41001.02 | D8: 1397.51 | E8: 42398.53
A9: 46372 | B9: 70912.104 | C9: 41872.38 | D9: 782.49 | E9: 42654.87
A10: 46462 | B10: 41229.074 | C10: 29683.03 | D10: 17605.8 | E10: 47288.83
A11: 46552 | B11: 10293.844 | C11: 30935.23 | D11: 14697.99 | E11: 45633.22
A12: 46552 | B12: 0.0040000001 | C12: 10293.84 | D12: 0 | E12: 10293.84

Sheet 2010014318
A1: Fecha | B1: Saldo adeudado | C1: Amortización | D1: Intereses corrientes | E1: Total Cuota
A2: 45724 | B2: 426409.54
A3: 45814 | B3: 388403.55 | C3: 38005.99 | D3: 5069.14 | E3: 43075.13
A4: 45904 | B4: 349589.93 | C4: 38813.62 | D4: 4499.05 | E4: 43312.67
A5: 45994 | B5: 309951.52 | C5: 39638.41 | D5: 3916.84 | E5: 43555.25
A6: 46084 | B6: 269470.8 | C6: 40480.72 | D6: 3322.26 | E6: 43802.98
A7: 46174 | B7: 228129.86 | C7: 41340.94 | D7: 2715.05 | E7: 44055.99
A8: 46264 | B8: 185910.43 | C8: 42219.43 | D8: 2094.94 | E8: 44314.37
A9: 46354 | B9: 142793.83 | C9: 43116.6 | D9: 1461.65 | E9: 44578.25
A10: 46444 | B10: 98761.04 | C10: 44032.79 | D10: 814.9 | E10: 44847.69
A11: 46534 | B11: 70279.53 | C11: 28481.51 | D11: 18828.9 | E11: 47310.41
A12: 46624 | B12: 40596.5 | C12: 29683.03 | D12: 12324.06 | E12: 42007.09
A13: 46714 | B13: 10293.84 | C13: 30302.66 | D13: 16975.03 | E13: 47277.69
A14: 46714 | B14: 4.3655746e-11 | C14: 10293.84 | E14: 10293.84

Sheet 2010014018
A1: Fecha | B1: Saldo adeudado | C1: Amortización | D1: Intereses corrientes | E1: Total Cuota
A2: 45724 | B2: 426409.54
A3: 45814 | B3: 388403.55 | C3: 38005.99 | D3: 5069.14 | E3: 43075.13
A4: 45904 | B4: 349589.93 | C4: 38813.62 | D4: 4499.05 | E4: 43312.67
A5: 45994 | B5: 309951.52 | C5: 39638.41 | D5: 3916.84 | E5: 43555.25
A6: 46084 | B6: 269470.8 | C6: 40480.72 | D6: 3322.26 | E6: 43802.98
A7: 46174 | B7: 228129.86 | C7: 41340.94 | D7: 2715.05 | E7: 44055.99
A8: 46264 | B8: 185910.43 | C8: 42219.43 | D8: 2094.94 | E8: 44314.37
A9: 46354 | B9: 142793.83 | C9: 43116.6 | D9: 1461.65 | E9: 44578.25
A10: 46444 | B10: 98761.04 | C10: 44032.79 | D10: 814.9 | E10: 44847.69
A11: 46534 | B11: 70279.53 | C11: 28481.51 | D11: 18828.9 | E11: 47310.41
A12: 46624 | B12: 40596.5 | C12: 29683.03 | D12: 12324.06 | E12: 42007.09
A13: 46714 | B13: 10293.84 | C13: 30302.66 | D13: 16975.03 | E13: 47277.69
A14: 46714 | B14: 4.3655746e-11 | C14: 10293.84 | E14: 10293.84

Sheet Garantias
A1: numero operación | B1: Entidad Financiera | C1: numero de contrato | D1: =+Caracteristicas!D1 -> Moneda | E1: =+Caracteristicas!E1 -> Tasa | F1: =+Caracteristicas!F1 -> Periodicidad | G1: =+Caracteristicas!H1 -> vencimiento | H1: =+Caracteristicas!K1 -> Saldo a capital | I1: =+Caracteristicas!L1 -> % adeudado por Cemento | J1: =+Caracteristicas!M1 -> Saldo a capital Cemento | K1: existencias de mercaderia | L1: detalle existencia de mercaderia | M1: prendaria | N1: detalle prendaria | O1: hipotecaria | P1: detalle hipotecaria | Q1: covenants | R1: total
A2: =+Caracteristicas!A2 -> 3167401 | B2: =+Caracteristicas!B2 -> Fideicomiso - Banco Unión | C2: Testimonio XXX/2024 | K2: 840000 | L2: Bolsas de 50 kg de cemento y clinker tipo IP 30 | M2: 2.3678982e+08 | N2: - maquinaria ubicada en Irpa Irpa, según avaluo de fecha 24 de abril de 2023, elaborado por CIDEAR | Q2: - Entregar infromación finacniera de maenra semestral debiendo presentar EEFF fiscales auditados hasta agosto de cada gestión. - No realizar distribuciones, pago de dividendos, inversiones en empresas relacionadas, o cualquier forma de pago de crédito o ingresos a favor de sus asociados - en 360 dias vender las acciones de las empresas en las que tenga participación y sean ajenas al giro de su negocio, aplicados a reducir la obligacion presente. - Trimestralmente presentar un informe debidamente firmado por Gerencia General que incluya un resumen de las gestiones comerciales realizadas para concretar la venta de las acciones | R2: =+SUM(K2:Q2) -> 2.3762982e+08
A3: =+Caracteristicas!#REF! -> #REF! | B3: =+Caracteristicas!#REF! -> #REF! | C3: Testimonio 1007/2023 | N3: - Una torre de precalcinación DOPOL, planta Irpa Irpa. - 10 toneladas de Clinker, playas de almacenamiento Irpa Irpa | P3: - Lote de terreno extensión 2762,74 m2, ubicación Tadeo Haenke. - Lote de terreno extensión 143737,22 m2, ubicación PILAT Warnes

Sheet Obligaciones financieras
N1: Nro de la operación | Q1: 3167401 | AE1: Nro de la operación | AG1: 2767412 | AT1: Nro de la operación | AV1: 2764418 | BI1: Nro de la operación | BK1: 1271559 | BY1: Nro de la operación | CA1: 1358960 | CP1: Nro de la operación | CR1: 1295150 | CY1: Nro de la operación | DA1: 101243178 | DN1: Nro de la operación | DP1: 315101121500077 | EC1: Nro de la operación | EE1: 315101121500078f | FA1: Nro de la operación | FC1: 315101121500021 | FK1: Nro de la operación | FM1: 2010014418 | FT1: Nro de la operación | FV1: 2010014118 | GC1: Nro de la operación | GE1: 2010013918 | GL1: Nro de la operación | GN1: 2010014218 | GU1: Nro de la operación | GW1: 2010014318 | HD1: Nro de la operación | HF1: 2010014018
N2: Entidad | Q2: Fideicomiso - Banco Unión | AE2: Entidad | AG2: Banco Unión | AT2: Entidad | AV2: Banco Unión | BI2: Entidad | BK2: Banco Bisa | BY2: Entidad | CA2: Banco Bisa | CP2: Entidad | CR2: Banco Bisa | CY2: Entidad | DA2: Banco Ganadero | DN2: Entidad | DP2: Banco de Desarrollo Productivo | EC2: Entidad | EE2: Banco de Desarrollo Productivo | FA2: Entidad | FC2: Banco de Desarrollo Productivo | FK2: Entidad | FM2: BNB leasing | FT2: Entidad | FV2: BNB leasing | GC2: Entidad | GE2: BNB leasing | GL2: Entidad | GN2: BNB leasing | GU2: Entidad | GW2: BNB leasing | HD2: Entidad | HF2: BNB leasing
N3: Cod. Entidad | Q3: FID - BUN | AE3: Cod. Entidad | AG3: BUN | AT3: Cod. Entidad | AV3: BUN | BI3: Cod. Entidad | BK3: BIS | BY3: Cod. Entidad | CA3: BIS | CP3: Cod. Entidad | CR3: BIS | CY3: Cod. Entidad | DA3: GAN | DN3: Cod. Entidad | DP3: BDP | EC3: Cod. Entidad | EE3: BDP | FA3: Cod. Entidad | FC3: BDP | FK3: Cod. Entidad | FM3: BNL | FT3: Cod. Entidad | FV3: BNL | GC3: Cod. Entidad | GE3: BNL | GL3: Cod. Entidad | GN3: BNL | GU3: Cod. Entidad | GW3: BNL | HD3: Cod. Entidad | HF3: BNL
N4: Moneda | Q4: Bolivanos | AE4: Moneda | AG4: Bolivanos | AT4: Moneda | AV4: Bolivanos | BI4: Moneda | BK4: Bolivanos | BY4: Moneda | CA4: Bolivanos | CP4: Moneda | CR4: Bolivanos | CY4: Moneda | DA4: Bolivanos | DN4: Moneda | DP4: Bolivanos | EC4: Moneda | EE4: Bolivanos | FA4: Moneda | FC4: Bolivanos | FK4: Moneda | FM4: Bolivanos | FT4: Moneda | FV4: Bolivanos | GC4: Moneda | GE4: Bolivanos | GL4: Moneda | GN4: Bolivanos | GU4: Moneda | GW4: Bolivanos | HD4: Moneda | HF4: Bolivanos
N5: Tasa | Q5: 0.06 | AE5: Tasa | AG5: 0.055 | AT5: Tasa | AV5: 0.06 | BI5: Tasa | BK5: 0.06 | BY5: Tasa | CA5: 0.06 | CP5: Tasa | CR5: 0.06 | CY5: Tasa | DA5: 0.06 | DN5: Tasa | DP5: 0.058 | EC5: Tasa | EE5: 0.0582 | FA5: Tasa | FC5: 0.0599 | FK5: Tasa | FM5: 0.06 | FT5: Tasa | FV5: 0.06 | GC5: Tasa | GE5: 0.06 | GL5: Tasa | GN5: 0.06 | GU5: Tasa | GW5: 0.06 | HD5: Tasa | HF5: 0.06
N6: Periodicidad | Q6: Trimestral | AE6: Periodicidad | AG6: Trimestral | AT6: Periodicidad | AV6: Trimestral | BI6: Periodicidad | BK6: Trimestral | BY6: Periodicidad | CA6: Trimestral | CP6: Periodicidad | CR6: Trimestral | CY6: Periodicidad | DA6: Mensual | DN6: Periodicidad | DP6: Trimestral | EC6: Periodicidad | EE6: Trimestral | FA6: Periodicidad | FC6: Trimestral | FK6: Periodicidad | FM6: Trimestral | FT6: Periodicidad | FV6: Trimestral | GC6: Periodicidad | GE6: Trimestral | GL6: Periodicidad | GN6: Trimestral | GU6: Periodicidad | GW6: Trimestral | HD6: Periodicidad | HF6: Trimestral
N7: inicio
N8: vencimiento | Q8: =+MAX(O25:O822) -> 48248 | AE8: vencimiento | AG8: =+MAX(AE25:AE822) -> 48058 | AT8: vencimiento | AV8: =+MAX(AT25:AT822) -> 48997 | BI8: vencimiento | BK8: =+MAX(BI25:BI822) -> 47107 | BY8: vencimiento | CA8: =+MAX(BY25:BY822) -> 47398 | CC8: =4596722.94+169631.13+115779.85 -> 4882133.9 | CP8: vencimiento | CR8: =+MAX(CP25:CP822) -> 47375 | CY8: vencimiento | DA8: =+MAX(CY25:CY822) -> 46609 | DN8: vencimiento | DP8: =+MAX(DN25:DN822) -> 49111 | EC8: vencimiento | EE8: =+MAX(EC25:EC822) -> 48765 | FA8: vencimiento | FC8: =+MAX(FA25:FA822) -> 49111 | FK8: vencimiento | FM8: =+MAX(FK25:FK822) -> 46552 | FT8: vencimiento | FV8: =+MAX(FT25:FT822) -> 46552 | GC8: vencimiento | GE8: =+MAX(GC25:GC822) -> 46552 | GL8: vencimiento | GN8: =+MAX(GL25:GL822) -> 46552 | GU8: vencimiento | GW8: =+MAX(GU25:GU822) -> 46714 | HD8: vencimiento | HF8: =+MAX(HD25:HD822) -> 46714
N9: plazo | Q9: =+Q8-[1]Caracteristicas!$B$19 -> 2348 | AG9: =+AG8-[1]Caracteristicas!$B$19 -> 2158 | AV9: =+AV8-[1]Caracteristicas!$B$19 -> 3097 | BK9: =+BK8-[1]Caracteristicas!$B$19 -> 1207 | CA9: =+CA8-[1]Caracteristicas!$B$19 -> 1498 | CR9: =+CR8-[1]Caracteristicas!$B$19 -> 1475 | DA9: =+DA8-[1]Caracteristicas!$B$19 -> 709 | DP9: =+DP8-[1]Caracteristicas!$B$19 -> 3211 | EE9: =+EE8-[1]Caracteristicas!$B$19 -> 2865 | FC9: =+FC8-[1]Caracteristicas!$B$19 -> 3211 | FM9: =+FM8-[1]Caracteristicas!$B$19 -> 652 | FV9: =+FV8-[1]Caracteristicas!$B$19 -> 652 | GE9: =+GE8-[1]Caracteristicas!$B$19 -> 652 | GN9: =+GN8-[1]Caracteristicas!$B$19 -> 652 | GW9: =+GW8-[1]Caracteristicas!$B$19 -> 814 | HF9: =+HF8-[1]Caracteristicas!$B$19 -> 814
N10: Saldo a capital inicial
N11: Saldo Adeudado | Q11: =+Q13/Q12 -> 2.3034329e+08 | AG11: =+AG13/AG12 -> 1241907.9 | AV11: =+AV13/AV12 -> 51796168 | BK11: =+BK13/BK12 -> 53476614 | CA11: =+CA13/CA12 -> 4571867.8 | CR11: =+CR13/CR12 -> 1669085.9 | DA11: =+DA13/DA12 -> 29810000 | DP11: =+DP13/DP12 -> 9174681.5 | EE11: =+EE13/EE12 -> 8467855 | FC11: =+FC13/FC12 -> 2794681.5 | FM11: =+FM13/FM12 -> 309433.84 | FV11: =+FV13/FV12 -> 309433.84 | GE11: =+GE13/GE12 -> 309433.84 | GN11: =+GN13/GN12 -> 309433.84 | GW11: =+GW13/GW12 -> 388403.55 | HF11: =+HF13/HF12 -> 388403.55
N12: % correspondiente a CEMENTO | Q12: 0.57390185 | AE12: % correspondiente a CEMENTO | AG12: 1 | AT12: % correspondiente a CEMENTO | AV12: =+AV13/AV15 -> 0.3088359 | BI12: % correspondiente a CEMENTO | BK12: 1 | BY12: % correspondiente a CEMENTO | CA12: =+CB27/254312.71 -> 0.22702943 | CP12: % correspondiente a CEMENTO | CR12: 1 | CY12: % correspondiente a CEMENTO | DA12: =++DA13/DA15 -> 0.86082018 | DN12: % correspondiente a CEMENTO | DP12: 0.99370812 | EC12: % correspondiente a CEMENTO | EE12: =+EE13/EE15 -> 0.13104947 | EF12: Antes | EH12: 0.38897016 | FA12: % correspondiente a CEMENTO | FC12: 1 | FK12: % correspondiente a CEMENTO | FM12: 1 | FT12: % correspondiente a CEMENTO | FV12: 1 | GC12: % correspondiente a CEMENTO | GE12: 1 | GL12: % correspondiente a CEMENTO | GN12: 1 | GU12: % correspondiente a CEMENTO | GW12: 1 | GY12: 100 | HD12: % correspondiente a CEMENTO | HF12: 1
N13: Saldo Adeudado CEMENTO | Q13: =+Q29 -> 1.3219444e+08 | AE13: Saldo Adeudado CEMENTO | AG13: =+AG27 -> 1241907.9 | AT13: Saldo Adeudado CEMENTO | AV13: =+AV28 -> 15996516 | BI13: Saldo Adeudado CEMENTO | BK13: =+BK26 -> 53476614 | BY13: Saldo Adeudado CEMENTO | CA13: =+CA28+CC24 -> 1037948.5 | CP13: Saldo Adeudado CEMENTO | CR13: =+CR26 -> 1669085.9 | CY13: Saldo Adeudado CEMENTO | DA13: =+DA26 -> 25661049 | DN13: Saldo Adeudado CEMENTO | DP13: =+DP26 -> 9116955.5 | EC13: Saldo Adeudado CEMENTO | EE13: =+EE25 -> 1109707.9 | EF13: Transferencia a CERAMIL | EH13: =+EH12*EE11 -> 3293742.9 | EI13: =+EH13-EE13 -> 2184035 | FA13: Saldo Adeudado CEMENTO | FC13: =+FC27 -> 2794681.5 | FK13: Saldo Adeudado CEMENTO | FM13: =+FM26 -> 309433.84 | FT13: Saldo Adeudado CEMENTO | FV13: =+FV26 -> 309433.84 | GC13: Saldo Adeudado CEMENTO | GE13: =+GE26 -> 309433.84 | GL13: Saldo Adeudado CEMENTO | GN13: =+GN26 -> 309433.84 | GU13: Saldo Adeudado CEMENTO | GW13: =+GW26 -> 388403.55 | GY13: =+GY12/13.8 -> 7.2463768 | HD13: Saldo Adeudado CEMENTO | HF13: =+HF26 -> 388403.55
N14: Monto desembolsado
N15: Total de Saldo Adeudado | Q15: 2.3061769e+08 | AE15: Total de Saldo Adeudado | AG15: =+AG12*AG13 -> 1241907.9 | AT15: Total de Saldo Adeudado | AV15: =+SUM([2]Consolidado1!$C$241:$C$245) -> 51796168 | AY15: =187920.41+6784.89+626.79 -> 195332.09 | BI15: Total de Saldo Adeudado | BK15: =+BK25 -> 53476614 | BY15: Total de Saldo Adeudado | CA15: =+CA13/CA12 -> 4571867.8 | CP15: Total de Saldo Adeudado | CR15: 1460450.1 | CY15: Total de Saldo Adeudado | DA15: =+SUM([2]Consolidado1!$C$323:$C$328) -> 29810000 | DN15: Total de Saldo Adeudado | DP15: =+DP13/DP12 -> 9174681.5 | EC15: Total de Saldo Adeudado | EE15: =+SUM([2]Consolidado1!$C$315:$C$319) -> 8467855 | FA15: Total de Saldo Adeudado | FK15: Total de Saldo Adeudado | FM15: 346343.01 | FT15: Total de Saldo Adeudado | FV15: 346343.01 | GC15: Total de Saldo Adeudado | GE15: 346343.01 | GL15: Total de Saldo Adeudado | GN15: 346343.01 | GU15: Total de Saldo Adeudado | GW15: 426409.54 | HD15: Total de Saldo Adeudado | HF15: 426409.54
N16: Total de Intereses Diferidos | Q16: 16433143 | AE16: Total de Intereses Diferidos | AT16: Total de Intereses Diferidos | BI16: Total de Intereses Diferidos | BY16: Total de Intereses Diferidos | CP16: Total de Intereses Diferidos | CY16: Total de Intereses Diferidos | DN16: Total de Intereses Diferidos | EC16: Total de Intereses Diferidos | FA16: Total de Intereses Diferidos | FK16: Total de Intereses Diferidos | FT16: Total de Intereses Diferidos | GC16: Total de Intereses Diferidos | GL16: Total de Intereses Diferidos | GU16: Total de Intereses Diferidos | HD16: Total de Intereses Diferidos
N17: Intereses DIferidos CEMENTO | Q17: =+Q16*Q12 -> 9431010.9 | AE17: Intereses DIferidos CEMENTO | AT17: Intereses DIferidos CEMENTO | BI17: Intereses DIferidos CEMENTO | BY17: Intereses DIferidos CEMENTO | CP17: Intereses DIferidos CEMENTO | CY17: Intereses DIferidos CEMENTO | DN17: Intereses DIferidos CEMENTO | EC17: Intereses DIferidos CEMENTO | FA17: Intereses DIferidos CEMENTO | FK17: Intereses DIferidos CEMENTO | FT17: Intereses DIferidos CEMENTO | GC17: Intereses DIferidos CEMENTO | GL17: Intereses DIferidos CEMENTO | GU17: Intereses DIferidos CEMENTO | HD17: Intereses DIferidos CEMENTO
N18: # Cuotas Intereses Diferidos | Q18: 20 | AE18: # Cuotas Intereses Diferidos | AT18: # Cuotas Intereses Diferidos | BI18: # Cuotas Intereses Diferidos | BY18: # Cuotas Intereses Diferidos | CP18: # Cuotas Intereses Diferidos | CY18: # Cuotas Intereses Diferidos | DN18: # Cuotas Intereses Diferidos | EC18: # Cuotas Intereses Diferidos | FA18: # Cuotas Intereses Diferidos | FK18: # Cuotas Intereses Diferidos | FT18: # Cuotas Intereses Diferidos | GC18: # Cuotas Intereses Diferidos | GL18: # Cuotas Intereses Diferidos | GU18: # Cuotas Intereses Diferidos | HD18: # Cuotas Intereses Diferidos
N19: Amortización Trimenstral 1er Año | Q19: 68600 | AE19: Amortización Trimenstral | AG19: 51840.79 | AT19: Amortización Trimenstral | AV19: 51840.79 | BI19: Amortización Trimenstral | BK19: 51840.79 | BY19: Amortización Trimenstral | CA19: =+CB26 -> 57736.47 | CP19: Amortización Trimenstral | CY19: Amortización Trimenstral | DN19: Amortización Trimenstral | EC19: Amortización Trimenstral | FA19: Amortización Trimenstral | FK19: Amortización Trimenstral | FT19: Amortización Trimenstral | GC19: Amortización Trimenstral | GL19: Amortización Trimenstral | GU19: Amortización Trimenstral | HD19: Amortización Trimenstral
N20: Amort. Trim 1er año CEMENTO | Q20: =+Q19*Q12 -> 39369.667
N21: Amortización 5to trimestre | Q21: 30369494
A23: N | B23: semana | C23: Dia | D23: Desembolsos | E23: Saldo adeudado | F23: Capital | G23: Intereses | H23: Total Cuota | I23: Por pagar | J23: Entidad | M23: N | N23: Fin mes | O23: Fecha | P23: Desembolsos | Q23: Saldo adeudado | R23: Amortización | S23: Intereses corrientes | T23: Intereses diferidos | U23: Total Cuota | V23: Número de cuota | W23: fecha de pago | X23: dias de mora | Y23: pago a capital | Z23: intereses corrientes | AA23: cuota pagada | AC23: N | AD23: Fin mes | AE23: Fecha | AF23: Desembolsos | AG23: Saldo adeudado | AH23: Amortización | AI23: Intereses corrientes | AJ23: Total Cuota | AK23: Número de cuota | AL23: fecha de pago | AM23: pago a capital | AN23: intereses corrientes | AO23: cuota pagada | AR23: N | AS23: Fin mes | AT23: Fecha | AU23: Desembolsos | AV23: Saldo adeudado | AW23: Amortización | AX23: Intereses corrientes | AY23: Total Cuota | AZ23: Número de cuota | BA23: fecha de pago | BB23: dias de mora | BC23: pago a capital | BD23: intereses corrientes | BE23: cuota pagada | BG23: N | BH23: Fin mes | BI23: Fecha | BJ23: Desembolsos | BK23: Saldo adeudado | BL23: Amortización | BM23: Intereses corrientes | BN23: Interes prorroga y gracia | BO23: Total Cuota | BP23: Número de cuota | BQ23: fecha de pago | BR23: dias de mora | BS23: pago a capital | BT23: intereses corrientes | BU23: cuota pagada | BW23: N | BX23: Fin mes | BY23: Fecha | BZ23: Desembolsos | CA23: Saldo adeudado | CB23: Amortización | CC23: Amortización cap diferido | CD23: Intereses corrientes | CE23: Intereses prorroga gracia | CF23: Total Cuota | CG23: Número de cuota | CH23: fecha de pago | CI23: dias de mora | CJ23: pago a capital | CK23: intereses corrientes | CL23: cuota pagada | CN23: N | CO23: Fin mes | CP23: Fecha | CQ23: Desembolsos | CR23: Saldo adeudado | CS23: Amortización | CT23: Intereses corrientes | CU23: Total Cuota | CW23: N | CX23: Fin mes | CY23: Fecha | CZ23: Desembolsos | DA23: Saldo adeudado | DB23: Amortización | DC23: Intereses corrientes | DD23: Total Cuota | DE23: Número de cuota | DF23: fecha de pago | DG23: dias de mora | DH23: pago a capital | DI23: intereses corrientes | DJ23: cuota pagada | DL23: N | DM23: Fin mes | DN23: Fecha | DO23: Desembolsos | DP23: Saldo adeudado | DQ23: Amortización | DR23: Intereses corrientes | DS23: Total Cuota | DT23: Número de cuota | DU23: fecha de pago | DV23: dias de mora | DW23: pago a capital | DX23: intereses corrientes | DY23: cuota pagada | EA23: N | EB23: Fin mes | EC23: Fecha | ED23: Desembolsos | EE23: Saldo adeudado | EF23: Amortización | EG23: Intereses corrientes | EH23: Total Cuota | EI23: Número de cuota | EJ23: fecha de pago | EK23: dias de mora | EL23: pago a capital | EM23: intereses corrientes | EN23: cuota pagada | EY23: N | EZ23: Fin mes | FA23: Fecha | FB23: Desembolsos | FC23: Saldo adeudado | FD23: Amortización | FE23: Intereses corrientes | FF23: Intereses prorroga gracia | FG23: Total Cuota | FI23: N | FJ23: Fin mes | FK23: Fecha | FL23: Desembolsos | FM23: Saldo adeudado | FN23: Amortización | FO23: Intereses corrientes | FP23: Total Cuota | FR23: N | FS23: Fin mes | FT23: Fecha | FU23: Desembolsos | FV23: Saldo adeudado | FW23: Amortización | FX23: Intereses corrientes | FY23: Total Cuota | GA23: N | GB23: Fin mes | GC23: Fecha | GD23: Desembolsos | GE23: Saldo adeudado | GF23: Amortización | GG23: Intereses corrientes | GH23: Total Cuota | GJ23: N | GK23: Fin mes | GL23: Fecha | GM23: Desembolsos | GN23: Saldo adeudado | GO23: Amortización | GP23: Intereses corrientes | GQ23: Total Cuota | GS23: N | GT23: Fin mes | GU23: Fecha | GV23: Desembolsos | GW23: Saldo adeudado | GX23: Amortización | GY23: Intereses corrientes | GZ23: Total Cuota | HB23: N | HC23: Fin mes | HD23: Fecha | HE23: Desembolsos | HF23: Saldo adeudado | HG23: Amortización | HH23: Intereses corrientes | HI23: Total Cuota
F24: =+SUM(F26:F1150) -> 58844181 | G24: =+SUM(G26:G1150) -> 22585088 | R24: =+SUM(R30:R1150) -> 1.3219444e+08 | AH24: =+SUM(AH28:AH1150) -> 1241907.9 | AW24: =+SUM(AW29:AW1150) -> 15996516 | BL24: =+SUM(BL29:BL1150) -> 42476614 | CB24: =+SUM(CB28:CB1150) -> 1039256.4 | CC24: =+SUM(CC29:CC1150) -> 56428.57 | CS24: =+SUM(CS28:CS1150) -> 1669085.9 | DB24: =+SUM(DB27:DB1150) -> 25661049 | DQ24: =+SUM(DQ27:DQ1150) -> 9116955.5 | EF24: =+SUM(EF27:EF1150) -> 1109708 | FD24: =+SUM(FD27:FD1150) -> 2794681.5 | FN24: =+SUM(FN27:FN1150) -> 309433.84 | FW24: =+SUM(FW27:FW1150) -> 309433.84 | GF24: =+SUM(GF27:GF1150) -> 309433.84 | GO24: =+SUM(GO27:GO1150) -> 309433.84 | GX24: =+SUM(GX27:GX1150) -> 388403.55 | HG24: =+SUM(HG27:HG1150) -> 388403.55
A25: 0 | B25: =+WEEKNUM(C25,2) -> 14 | C25: 45747 | E25: =+SUM(F26:F1150) -> 58844181 | M25: 0 | N25: =+EOMONTH(O25,0) -> 45535 | O25: 45506 | P25: =+Q13 -> 1.3219444e+08 | Q25: 1.3235192e+08 | AC25: 0 | AD25: =+EOMONTH(AE25,0) -> 45716 | AE25: 45712 | AG25: 1345589.5 | AR25: 0 | AS25: =+EOMONTH(AT25,0) -> 45657 | AT25: 45656 | AV25: 15996516 | BG25: 0 | BH25: =+EOMONTH(BI25,0) -> 45747 | BI25: 45736 | BK25: 53476614 | BW25: 0 | BX25: =+EOMONTH(BY25,0) -> 45688 | BY25: 45677 | CA25: 1154729.4 | CN25: 0 | CO25: =+EOMONTH(CP25,0) -> 45716 | CP25: 45700 | CR25: 1669085.9 | CW25: 0 | CX25: =+EOMONTH(CY25,0) -> 45869 | CY25: 45848 | DA25: 26010061 | DL25: 0 | DM25: =+EOMONTH(DN25,0) -> 45747 | DN25: 45721 | DP25: 9116955.5 | EA25: 0 | EB25: =+EOMONTH(EC25,0) -> 45747 | EC25: 45721 | EE25: 1109707.9 | EY25: 0 | EZ25: =+EOMONTH(FA25,0) -> 45657 | FA25: 45657 | FC25: 2794681.5 | FI25: 0 | FJ25: =+EOMONTH(FK25,0) -> 45747 | FK25: =+FK26-90 -> 45742 | FM25: 346343.01 | FR25: 0 | FS25: =+EOMONTH(FT25,0) -> 45747 | FT25: =+FT26-90 -> 45742 | FV25: 346343.01 | GA25: 0 | GB25: =+EOMONTH(GC25,0) -> 45747 | GC25: =+GC26-90 -> 45742 | GE25: 346343.01 | GJ25: 0 | GK25: =+EOMONTH(GL25,0) -> 45747 | GL25: =+GL26-90 -> 45742 | GN25: 346343.01 | GS25: 0 | GT25: =+EOMONTH(GU25,0) -> 45747 | GU25: =+GU26-90 -> 45724 | GW25: 426409.54 | HB25: 0 | HC25: =+EOMONTH(HD25,0) -> 45747 | HD25: 45724 | HF25: 426409.54
A26: 1 | B26: =+WEEKNUM(C26,2) -> 18 | C26: =+EOMONTH(C25,1) -> 45777 | E26: =+E25+D26-F26 -> 58844181 | F26: =+SUMIF(N:N,C26,R:R)+SUMIF(AD:AD,C26,AH:AH)+SUMIF(AS:AS,C26,AW:AW)+SUMIF(BH:BH,C26,BL:BL)+SUMIF(BX:BX,C26,CB:CB)+SUMIF(BX:BX,C26,CC:CC)+SUMIF(CO:CO,C26,CS:CS)+SUMIF(CX:CX,C26,DB:DB)+SUMIF(DM:DM,C26,DQ:DQ)+SUMIF(EB:EB,C26,EF:EF)+SUMIF(EQ:EQ,C26,EU:EU)+SUMIF(EZ:EZ,C26,FD:FD)+SUMIF(FJ:FJ,C26,FN:FN)+SUMIF(FS:FS,C26,FW:FW)+SUMIF(GB:GB,C26,GF:GF)+SUMIF(GK:GK,C26,GO:GO)+SUMIF(GT:GT,C26,GX:GX)+SUMIF(HC:HC,C26,HG:HG) -> 0 | G26: =+SUMIF(N:N,C26,T:T)+SUMIF(N:N,C26,S:S)+SUMIF(AD:AD,C26,AI:AI)+SUMIF(AS:AS,C26,AX:AX)+SUMIF(BH:BH,C26,BN:BN)+SUMIF(BH:BH,C26,BM:BM)+SUMIF(BX:BX,C26,CD:CD)+SUMIF(BX:BX,C26,CE:CE)+SUMIF(CO:CO,C26,CT:CT)+SUMIF(CX:CX,C26,DC:DC)+SUMIF(DM:DM,C26,DR:DR)+SUMIF(EB:EB,C26,EG:EG)+SUMIF(EQ:EQ,C26,EV:EV)+SUMIF(EZ:EZ,C26,FE:FE)+SUMIF(FJ:FJ,C26,FO:FO)+SUMIF(FS:FS,C26,FX:FX)+SUMIF(GB:GB,C26,GG:GG)+SUMIF(GK:GK,C26,GP:GP)+SUMIF(GT:GT,C26,GY:GY)+SUMIF(HC:HC,C26,HH:HH) -> 0 | H26: =+SUM(F26:G26) -> 0 | M26: 1 | N26: =+EOMONTH(O26,0) -> 45626 | O26: 45611 | Q26: =+Q25-R26 -> 1.3231255e+08 | R26: =+$Q$20 -> 39369.667 | S26: =+Q25*Q$5*(O26-O25)/360 -> 2316158.6 | T26: =+$Q$17/$Q$18 -> 471550.55 | U26: =+SUM(R26:T26) -> 2827078.8 | AC26: 1 | AD26: =+EOMONTH(AE26,0) -> 45808 | AE26: 45779 | AG26: =+AG25+AF26-AH26 -> 1293748.7 | AH26: =+AG19 -> 51840.79 | AI26: =+AG25*AG$5*(AE26-AE25)/360 -> 13773.604 | AJ26: =+SUM(AH26:AI26) -> 65614.394 | AK26: 1 | AL26: 45796 | AM26: =+AH26 -> 51840.79 | AN26: =+AG25*AG$5*(AL26-AE25)/360 -> 17268.399 | AO26: =+AN26+AM26 -> 69109.189 | AR26: 1 | AS26: =+EOMONTH(AT26,0) -> 45716 | AT26: 45708 | AV26: 15996516 | AW26: 0 | AX26: =+AV25*AV$5*(AT26-AT25)/360 -> 138636.47 | AY26: =+SUM(AW26:AX26) -> 138636.47 | AZ26: 1 | BA26: 45744 | BB26: =+BA26-AT26 -> 36 | BC26: =+AW26 -> 0 | BD26: =+AV25*AV$5*(BA26-AT25)/360 -> 234615.57 | BE26: =+BD26+BC26 -> 234615.57 | BG26: 1 | BH26: =+EOMONTH(BI26,0) -> 45838 | BI26: 45828 | BK26: =+BK25+BJ26-BL26 -> 53476614 | BL26: 0 | BM26: =+BK25*BK$5*(BI26-BI25)/360 -> 819974.75 | BN26: 82616.23 | BO26: =+SUM(BL26:BN26) -> 902590.98 | BP26: 1 | BQ26: 45828 | BS26: =+BL26 -> 0 | BT26: =+BK25*BK$5*(BQ26-BI25)/360 -> 819974.75 | BU26: =+BT26+BS26+BN26 -> 902590.98 | BW26: 1 | BX26: =+EOMONTH(BY26,0) -> 45716 | BY26: 45702 | CA26: =+CA25+BZ26-CB26 -> 1096992.9 | CB26: 57736.47 | CC26: 0 | CD26: =+CA25*CA$5*(BY26-BY25)/360 -> 4811.3725 | CE26: 1642.8395 | CF26: =+SUM(CB26:CE26) -> 64190.682 | CG26: 1 | CH26: 45702 | CJ26: =+CB26 -> 57736.47 | CK26: =+CA25*CA$5*(CH26-BY25)/360 -> 4811.3725 | CL26: =+CK26+CJ26+CE26 -> 64190.682 | CN26: 1 | CO26: =+EOMONTH(CP26,0) -> 45838 | CP26: 45822 | CR26: =+CR25+CQ26-CS26 -> 1669085.9 | CS26: 0 | CT26: 29209.003 | CU26: =+SUM(CS26:CT26) -> 29209.003 | CW26: 1 | CX26: =+EOMONTH(CY26,0) -> 45900 | CY26: 45879 | DA26: =+DA25+CZ26-DB26 -> 25661049 | DB26: 349011.21 | DC26: =+DA25*DA$5*(CY26-CY25)/360 -> 134385.31 | DD26: =+SUM(DB26:DC26) -> 483396.52 | DE26: 1 | DF26: =+CY26 -> 45879 | DH26: =+CZ26 -> 0 | DI26: =+CY25*CY$5*(DF26-CW25)/360 -> #VALUE! | DJ26: =+DI26+DH26+DC26 -> #VALUE! | DL26: 1 | DM26: =+EOMONTH(DN26,0) -> 45838 | DN26: 45838 | DP26: =+DP25+DO26-DQ26 -> 9116955.5 | DQ26: 0 | DR26: 138152.48 | DS26: =+SUM(DQ26:DR26) -> 138152.48 | DT26: 1 | DU26: =+DN26 -> 45838 | DW26: =+DO26 -> 0 | DX26: =+DN25*DN$5*(DU26-DL25)/360 -> #VALUE! | DY26: =+DX26+DW26+DR26 -> #VALUE! | EA26: 1 | EB26: =+EOMONTH(EC26,0) -> 45838 | EC26: 45838 | EE26: =+EE25-EF26 -> 1109707.9 | EF26: 0 | EG26: 16421.12 | EH26: =+SUM(EF26:EG26) -> 16421.12 | EI26: 1 | EJ26: =+EC26 -> 45838 | EL26: =+ED26 -> 0 | EM26: =+EG26 -> 16421.12 | EN26: =+EM26+EL26+EG26 -> 32842.24 | EY26: 1 | EZ26: =+EOMONTH(FA26,0) -> 45747 | FA26: 45721 | FC26: =+FC25+FB26-FD26 -> 2794681.5 | FD26: 0 | FE26: 17114.156 | FF26: 86.4 | FG26: =+SUM(FD26:FF26) -> 17200.556 | FI26: 1 | FJ26: =+EOMONTH(FK26,0) -> 45838 | FK26: 45832 | FM26: =+FM25-FN26 -> 309433.84 | FN26: 36909.17 | FO26: 4285.87 | FP26: =+SUM(FN26:FO26) -> 41195.04 | FR26: 1 | FS26: =+EOMONTH(FT26,0) -> 45838 | FT26: 45832 | FV26: =+FV25-FW26 -> 309433.84 | FW26: 36909.17 | FX26: 4285.87 | FY26: =+SUM(FW26:FX26) -> 41195.04 | GA26: 1 | GB26: =+EOMONTH(GC26,0) -> 45838 | GC26: 45832 | GE26: =+GE25-GF26 -> 309433.84 | GF26: 36909.17 | GG26: 4285.87 | GH26: =+SUM(GF26:GG26) -> 41195.04 | GJ26: 1 | GK26: =+EOMONTH(GL26,0) -> 45838 | GL26: 45832 | GN26: =+GN25-GO26 -> 309433.84 | GO26: 36909.17 | GP26: 4285.87 | GQ26: =+SUM(GO26:GP26) -> 41195.04 | GS26: 1 | GT26: =+EOMONTH(GU26,0) -> 45838 | GU26: 45814 | GW26: =+GW25-GX26 -> 388403.55 | GX26: 38005.99 | GY26: 5069.14 | GZ26: =+SUM(GX26:GY26) -> 43075.13 | HB26: 1 | HC26: =+EOMONTH(HD26,0) -> 45838 | HD26: 45814 | HF26: 388403.55 | HG26: 38005.99 | HH26: 5069.14 | HI26: 43075.13
A27: 2 | B27: =+WEEKNUM(C27,2) -> 22 | C27: =+EOMONTH(C26,1) -> 45808 | E27: =+E26+D27-F27 -> 58752971 | F27: =+SUMIF(N:N,C27,R:R)+SUMIF(AD:AD,C27,AH:AH)+SUMIF(AS:AS,C27,AW:AW)+SUMIF(BH:BH,C27,BL:BL)+SUMIF(BX:BX,C27,CB:CB)+SUMIF(BX:BX,C27,CC:CC)+SUMIF(CO:CO,C27,CS:CS)+SUMIF(CX:CX,C27,DB:DB)+SUMIF(DM:DM,C27,DQ:DQ)+SUMIF(EB:EB,C27,EF:EF)+SUMIF(EQ:EQ,C27,EU:EU)+SUMIF(EZ:EZ,C27,FD:FD)+SUMIF(FJ:FJ,C27,FN:FN)+SUMIF(FS:FS,C27,FW:FW)+SUMIF(GB:GB,C27,GF:GF)+SUMIF(GK:GK,C27,GO:GO)+SUMIF(GT:GT,C27,GX:GX)+SUMIF(HC:HC,C27,HG:HG) -> 91210.457 | G27: =+SUMIF(N:N,C27,T:T)+SUMIF(N:N,C27,S:S)+SUMIF(AD:AD,C27,AI:AI)+SUMIF(AS:AS,C27,AX:AX)+SUMIF(BH:BH,C27,BN:BN)+SUMIF(BH:BH,C27,BM:BM)+SUMIF(BX:BX,C27,CD:CD)+SUMIF(BX:BX,C27,CE:CE)+SUMIF(CO:CO,C27,CT:CT)+SUMIF(CX:CX,C27,DC:DC)+SUMIF(DM:DM,C27,DR:DR)+SUMIF(EB:EB,C27,EG:EG)+SUMIF(EQ:EQ,C27,EV:EV)+SUMIF(EZ:EZ,C27,FE:FE)+SUMIF(FJ:FJ,C27,FO:FO)+SUMIF(FS:FS,C27,FX:FX)+SUMIF(GB:GB,C27,GG:GG)+SUMIF(GK:GK,C27,GP:GP)+SUMIF(GT:GT,C27,GY:GY)+SUMIF(HC:HC,C27,HH:HH) -> 2684658 | H27: =+SUM(F27:G27) -> 2775868.4 | M27: 2 | N27: =+EOMONTH(O27,0) -> 45716 | O27: 45703 | Q27: =+Q26-R27 -> 1.3227318e+08 | R27: =+$Q$20 -> 39369.667 | S27: =+Q26*Q$5*(O27-O26)/360 -> 2028792.4 | T27: =+$Q$17/$Q$18 -> 471550.55 | U27: =+SUM(R27:T27) -> 2539712.7 | W27: 45703 | AC27: 2 | AD27: =+EOMONTH(AE27,0) -> 45900 | AE27: 45871 | AG27: =+AG26+AF27-AH27 -> 1241907.9 | AH27: =+AH26 -> 51840.79 | AI27: =+AG26*AG$5*(AE27-AE26)/360 -> 18184.357 | AJ27: =+SUM(AH27:AI27) -> 70025.147 | AK27: 2 | AL27: =+TODAY() -> 46007 | AM27: =+AH27 -> 51840.79 | AN27: =+AG26*AG$5*(AL27-AL26)/360 -> 41705.427 | AO27: =+AN27+AM27 -> 93546.217 | AR27: 2 | AS27: =+EOMONTH(AT27,0) -> 45808 | AT27: 45797 | AV27: =+AV26+AU27-AW27 -> 15996516 | AW27: 0 | AX27: =+AV26*AV$5*(AT27-AT26)/360 -> 237281.65 | AY27: =+SUM(AW27:AX27) -> 237281.65 | AZ27: 2 | BA27: 45838 | BB27: =+BA27-AT27 -> 41 | BC27: =+AW27 -> 0 | BD27: =+AV26*AV$5*(BA27-BA26)/360 -> 250612.08 | BE27: =+BD27+BC27 -> 250612.08 | BG27: 2 | BH27: =+EOMONTH(BI27,0) -> 45930 | BI27: 45920 | BK27: =+BK26+BJ27-BL27-11000000 -> 42476614 | BL27: 0 | BM27: =+BK26*BK$5*(BI27-BI26)/360 -> 819974.75 | BN27: 82616.23 | BO27: =+SUM(BL27:BN27) -> 902590.98 | BP27: 2 | BQ27: 45930 | BS27: =+BL27 -> 0 | BT27: =+BK26*BK$5*(BQ27-BQ26)/360 -> 909102.44 | BU27: =+BT27+BS27+BN27 -> 991718.67 | BW27: 2 | BX27: =+EOMONTH(BY27,0) -> 45869 | BY27: 45858 | CA27: =+CA26+BZ27-CB27 -> 1039256.4 | CB27: 57736.47 | CC27: 2821.4285 | CD27: =+CA26*CA$5*(BY27-BY26)/360 -> 28521.816 | CE27: 1642.8395 | CF27: =+SUM(CB27:CE27) -> 90722.554 | CG27: 2 | CH27: 45866 | CJ27: =+CB27 -> 57736.47 | CK27: =+CA26*CA$5*(CH27-CH26)/360 -> 29984.473 | CL27: =+CK27+CJ27+CE27 -> 89363.783 | CN27: 2 | CO27: =+EOMONTH(CP27,0) -> 45930 | CP27: 45914 | CR27: =+CR26+CQ27-CS27 -> 1669085.9 | CS27: 0 | CT27: 22393.569 | CU27: =+SUM(CS27:CT27) -> 22393.569 | CW27: 2 | CX27: =+EOMONTH(CY27,0) -> 45930 | CY27: 45910 | DA27: =+DA26+CZ27-DB27 -> 25312038 | DB27: 349011.21 | DC27: =+DA26*DA$5*(CY27-CY26)/360 -> 132582.09 | DD27: =+SUM(DB27:DC27) -> 481593.3 | DE27: 2 | DF27: 45911 | DH27: =+CZ27 -> 0 | DI27: =+DA26*DA$5*(DF27-DF26)/360 -> 136858.93 | DJ27: =+DI27+DH27 -> 136858.93 | DL27: 2 | DM27: =+EOMONTH(DN27,0) -> 45930 | DN27: 45925 | DP27: =+DP26+DO27-DQ27 -> 9116955.5 | DQ27: 0 | DR27: 127789.32 | DS27: =+SUM(DQ27:DR27) -> 127789.32 | DT27: 2 | DU27: 45939 | DW27: =+DO27 -> 0 | DX27: =+DP26*DP$5*(DU27-DU26)/360 -> 148353.13 | DY27: =+DX27+DW27 -> 148353.13 | EA27: 2 | EB27: =+EOMONTH(EC27,0) -> 45961 | EC27: 45936 | EE27: =+EE26-EF27 -> 1109707.9 | EF27: 0 | EG27: =+EE26*(EC27-EC26)*$EE$5/360 -> 17581.472 | EH27: =+SUM(EF27:EG27) -> 17581.472 | EI27: 2 | EJ27: 45939 | EL27: =+ED27 -> 0 | EM27: =+EE26*EE$5*(EJ27-EJ26)/360 -> 18119.68 | EN27: =+EM27+EL27 -> 18119.68 | EY27: 2 | EZ27: =+EOMONTH(FA27,0) -> 45838 | FA27: 45838 | FC27: =+FC26+FB27-FD27 -> 2794681.5 | FD27: 0 | FE27: 38370.47 | FF27: 19844.48 | FG27: =+SUM(FD27:FF27) -> 58214.95 | FI27: 2 | FJ27: =+EOMONTH(FK27,0) -> 45930 | FK27: 45922 | FM27: =+FM26-FN27 -> 271740.35 | FN27: 37693.49 | FO27: 3732.23 | FP27: =+SUM(FN27:FO27) -> 41425.72 | FR27: 2 | FS27: =+EOMONTH(FT27,0) -> 45930 | FT27: 45922 | FV27: =+FV26-FW27 -> 271740.35 | FW27: 37693.49 | FX27: 3732.23 | FY27: =+SUM(FW27:FX27) -> 41425.72 | GA27: 2 | GB27: =+EOMONTH(GC27,0) -> 45930 | GC27: 45922 | GE27: =+GE26-GF27 -> 271740.35 | GF27: 37693.49 | GG27: 3732.23 | GH27: =+SUM(GF27:GG27) -> 41425.72 | GJ27: 2 | GK27: =+EOMONTH(GL27,0) -> 45930 | GL27: 45922 | GN27: =+GN26-GO27 -> 271740.35 | GO27: 37693.49 | GP27: 3732.23 | GQ27: =+SUM(GO27:GP27) -> 41425.72 | GS27: 2 | GT27: =+EOMONTH(GU27,0) -> 45930 | GU27: 45904 | GW27: =+GW26-GX27 -> 349589.93 | GX27: 38813.62 | GY27: 4499.05 | GZ27: =+SUM(GX27:GY27) -> 43312.67 | HB27: 2 | HC27: =+EOMONTH(HD27,0) -> 45930 | HD27: 45904 | HF27: 349589.93 | HG27: 38813.62 | HH27: 4499.05 | HI27: 43312.67
A28: 3 | B28: =+WEEKNUM(C28,2) -> 27 | C28: =+EOMONTH(C27,1) -> 45838 | E28: =+E27+D28-F28 -> 58529322 | F28: =+SUMIF(N:N,C28,R:R)+SUMIF(AD:AD,C28,AH:AH)+SUMIF(AS:AS,C28,AW:AW)+SUMIF(BH:BH,C28,BL:BL)+SUMIF(BX:BX,C28,CB:CB)+SUMIF(BX:BX,C28,CC:CC)+SUMIF(CO:CO,C28,CS:CS)+SUMIF(CX:CX,C28,DB:DB)+SUMIF(DM:DM,C28,DQ:DQ)+SUMIF(EB:EB,C28,EF:EF)+SUMIF(EQ:EQ,C28,EU:EU)+SUMIF(EZ:EZ,C28,FD:FD)+SUMIF(FJ:FJ,C28,FN:FN)+SUMIF(FS:FS,C28,FW:FW)+SUMIF(GB:GB,C28,GF:GF)+SUMIF(GK:GK,C28,GO:GO)+SUMIF(GT:GT,C28,GX:GX)+SUMIF(HC:HC,C28,HG:HG) -> 223648.66 | G28: =+SUMIF(N:N,C28,T:T)+SUMIF(N:N,C28,S:S)+SUMIF(AD:AD,C28,AI:AI)+SUMIF(AS:AS,C28,AX:AX)+SUMIF(BH:BH,C28,BN:BN)+SUMIF(BH:BH,C28,BM:BM)+SUMIF(BX:BX,C28,CD:CD)+SUMIF(BX:BX,C28,CE:CE)+SUMIF(CO:CO,C28,CT:CT)+SUMIF(CX:CX,C28,DC:DC)+SUMIF(DM:DM,C28,DR:DR)+SUMIF(EB:EB,C28,EG:EG)+SUMIF(EQ:EQ,C28,EV:EV)+SUMIF(EZ:EZ,C28,FE:FE)+SUMIF(FJ:FJ,C28,FO:FO)+SUMIF(FS:FS,C28,FX:FX)+SUMIF(GB:GB,C28,GG:GG)+SUMIF(GK:GK,C28,GP:GP)+SUMIF(GT:GT,C28,GY:GY)+SUMIF(HC:HC,C28,HH:HH) -> 1152025.8 | H28: =+SUM(F28:G28) -> 1375674.5 | I28: =+AA28 -> 7212761.4 | J28: Fideicomiso | M28: 3 | N28: =+EOMONTH(O28,0) -> 45808 | O28: 45792 | Q28: =+Q27-R28 -> 1.3223381e+08 | R28: =+$Q$20 -> 39369.667 | S28: =+Q27*Q$5*(O28-O27)/360 -> 1962052.2 | T28: =+$Q$17/$Q$18 -> 471550.55 | U28: =+SUM(R28:T28) -> 2472972.4 | V28: 3 | W28: =+TODAY() -> 46007 | X28: =+W28-W27 -> 304 | Y28: =+R28 -> 39369.667 | Z28: =+Q27*Q$5*(W28-O27)/360 -> 6701841.2 | AA28: =+Z28+Y28+T28 -> 7212761.4 | AC28: 3 | AD28: =+EOMONTH(AE28,0) -> 45991 | AE28: 45963 | AG28: =+AG27+AF28-AH28 -> 1190067.1 | AH28: =+AH27 -> 51840.79 | AI28: =+AG27*AG$5*(AE28-AE27)/360 -> 17455.706 | AJ28: =+SUM(AH28:AI28) -> 69296.496 | AR28: 3 | AS28: =+EOMONTH(AT28,0) -> 45900 | AT28: 45889 | AV28: =+AV27+AU28-AW28 -> 15996516 | AW28: 0 | AX28: =+AV27*AV$5*(AT28-AT27)/360 -> 245279.91 | AY28: =+SUM(AW28:AX28) -> 245279.91 | AZ28: 3 | BA28: =+TODAY() -> 46007 | BB28: =+BA28-AT28 -> 118 | BC28: =+AW28 -> 0 | BD28: =+AV27*AV$5*(BA28-BA27)/360 -> 450568.54 | BE28: =+BD28+BC28 -> 450568.54 | BG28: 3 | BH28: =+EOMONTH(BI28,0) -> 46022 | BI28: 46011 | BK28: =+BK27+BJ28-BL28 -> 42476614 | BL28: 0 | BM28: =+BK27*BK$5*(BI28-BI27)/360 -> 644228.65 | BN28: 82616.23 | BO28: =+SUM(BL28:BN28) -> 726844.88 | BW28: 3 | BX28: =+EOMONTH(BY28,0) -> 45961 | BY28: 45950 | CA28: =+CA27+BZ28-CB28 -> 981519.98 | CB28: 57736.47 | CC28: 2821.4285 | CD28: =+CA27*CA$5*(BY28-BY27)/360 -> 15935.266 | CE28: 1642.8395 | CF28: =+SUM(CB28:CE28) -> 78136.004 | CG28: 3 | CH28: 45950 | CJ28: =+CB28 -> 57736.47 | CK28: =+CA27*CA$5*(CH28-CH27)/360 -> 14549.59 | CL28: =+CK28+CJ28+CE28 -> 73928.9 | CM28: =(+CK28)/CA12 -> 64086.802 | CN28: 3 | CO28: =+EOMONTH(CP28,0) -> 46022 | CP28: 46005 | CR28: =+CR27+CQ28-CS28 -> 1564768 | CS28: 104317.86 | CT28: 22150.161 | CU28: =+SUM(CS28:CT28) -> 126468.02 | CW28: 3 | CX28: =+EOMONTH(CY28,0) -> 45961 | CY28: 45940 | DA28: =+DA27+CZ28-DB28 -> 24963027 | DB28: 349011.21 | DC28: =+DA27*DA$5*(CY28-CY27)/360 -> 126560.19 | DD28: =+SUM(DB28:DC28) -> 475571.4 | DE28: 3 | DF28: 45940 | DH28: =+DB28 -> 349011.21 | DI28: =+DA27*DA$5*(DF28-DF27)/360 -> 122341.52 | DJ28: =+DI28+DH28 -> 471352.73 | DL28: 3 | DM28: =+EOMONTH(DN28,0) -> 46022 | DN28: 46017 | DP28: =+DP27+DO28-DQ28 -> 9116955.5 | DQ28: 0 | DR28: 135133.54 | DS28: =+SUM(DQ28:DR28) -> 135133.54 | EA28: 3 | EB28: =+EOMONTH(EC28,0) -> 46053 | EC28: 46027 | EE28: =+EE27-EF28 -> 1109707.9 | EF28: 0 | EG28: =+EE27*(EC28-EC27)*$EE$5/360 -> 16325.652 | EH28: =+SUM(EF28:EG28) -> 16325.652 | EY28: 3 | EZ28: =+EOMONTH(FA28,0) -> 45930 | FA28: 45925 | FC28: =+FC27+FB28-FD28 -> 2794681.5 | FD28: 0 | FE28: 17027.76 | FG28: =+SUM(FD28:FF28) -> 17027.76 | FI28: 3 | FJ28: =+EOMONTH(FK28,0) -> 46022 | FK28: 46012 | FM28: =+FM27-FN28 -> 233245.87 | FN28: 38494.48 | FO28: 3166.83 | FP28: =+SUM(FN28:FO28) -> 41661.31 | FR28: 3 | FS28: =+EOMONTH(FT28,0) -> 46022 | FT28: 46012 | FV28: =+FV27-FW28 -> 233245.87 | FW28: 38494.48 | FX28: 3166.83 | FY28: =+SUM(FW28:FX28) -> 41661.31 | GA28: 3 | GB28: =+EOMONTH(GC28,0) -> 46022 | GC28: 46012 | GE28: =+GE27-GF28 -> 233245.87 | GF28: 38494.48 | GG28: 3166.83 | GH28: =+SUM(GF28:GG28) -> 41661.31 | GJ28: 3 | GK28: =+EOMONTH(GL28,0) -> 46022 | GL28: 46012 | GN28: =+GN27-GO28 -> 233245.87 | GO28: 38494.48 | GP28: 3166.83 | GQ28: =+SUM(GO28:GP28) -> 41661.31 | GS28: 3 | GT28: =+EOMONTH(GU28,0) -> 46022 | GU28: 45994 | GW28: =+GW27-GX28 -> 309951.52 | GX28: 39638.41 | GY28: 3916.84 | GZ28: =+SUM(GX28:GY28) -> 43555.25 | HB28: 3 | HC28: =+EOMONTH(HD28,0) -> 46022 | HD28: 45994 | HF28: 309951.52 | HG28: 39638.41 | HH28: 3916.84 | HI28: 43555.25
A29: 4 | B29: =+WEEKNUM(C29,2) -> 31 | C29: =+EOMONTH(C28,1) -> 45869 | E29: =+E28+D29-F29 -> 58468764 | F29: =+SUMIF(N:N,C29,R:R)+SUMIF(AD:AD,C29,AH:AH)+SUMIF(AS:AS,C29,AW:AW)+SUMIF(BH:BH,C29,BL:BL)+SUMIF(BX:BX,C29,CB:CB)+SUMIF(BX:BX,C29,CC:CC)+SUMIF(CO:CO,C29,CS:CS)+SUMIF(CX:CX,C29,DB:DB)+SUMIF(DM:DM,C29,DQ:DQ)+SUMIF(EB:EB,C29,EF:EF)+SUMIF(EQ:EQ,C29,EU:EU)+SUMIF(EZ:EZ,C29,FD:FD)+SUMIF(FJ:FJ,C29,FN:FN)+SUMIF(FS:FS,C29,FW:FW)+SUMIF(GB:GB,C29,GF:GF)+SUMIF(GK:GK,C29,GO:GO)+SUMIF(GT:GT,C29,GX:GX)+SUMIF(HC:HC,C29,HG:HG) -> 60557.899 | G29: =+SUMIF(N:N,C29,T:T)+SUMIF(N:N,C29,S:S)+SUMIF(AD:AD,C29,AI:AI)+SUMIF(AS:AS,C29,AX:AX)+SUMIF(BH:BH,C29,BN:BN)+SUMIF(BH:BH,C29,BM:BM)+SUMIF(BX:BX,C29,CD:CD)+SUMIF(BX:BX,C29,CE:CE)+SUMIF(CO:CO,C29,CT:CT)+SUMIF(CX:CX,C29,DC:DC)+SUMIF(DM:DM,C29,DR:DR)+SUMIF(EB:EB,C29,EG:EG)+SUMIF(EQ:EQ,C29,EV:EV)+SUMIF(EZ:EZ,C29,FE:FE)+SUMIF(FJ:FJ,C29,FO:FO)+SUMIF(FS:FS,C29,FX:FX)+SUMIF(GB:GB,C29,GG:GG)+SUMIF(GK:GK,C29,GP:GP)+SUMIF(GT:GT,C29,GY:GY)+SUMIF(HC:HC,C29,HH:HH) -> 30164.655 | H29: =+SUM(F29:G29) -> 90722.554 | M29: 4 | N29: =+EOMONTH(O29,0) -> 45900 | O29: 45884 | Q29: =+Q28-R29 -> 1.3219444e+08 | R29: =+$Q$20 -> 39369.667 | S29: =+Q28*Q$5*(O29-O28)/360 -> 2027585.1 | T29: =+$Q$17/$Q$18 -> 471550.55 | U29: =+SUM(R29:T29) -> 2538505.3 | V29: 4 | W29: =+TODAY() -> 46007 | Y29: =+R29 -> 39369.667 | AA29: =+Y29 -> 39369.667 | AC29: 4 | AD29: =+EOMONTH(AE29,0) -> 46081 | AE29: 46055 | AG29: =+AG28+AF29-AH29 -> 1138226.3 | AH29: =+AH28 -> 51840.79 | AI29: =+AG28*AG$5*(AE29-AE28)/360 -> 16727.055 | AJ29: =+SUM(AH29:AI29) -> 68567.845 | AR29: 4 | AS29: =+EOMONTH(AT29,0) -> 45991 | AT29: 45981 | AV29: =+AV28+AU29-AW29 -> 15996516 | AW29: 0 | AX29: =+AV28*AV$5*(AT29-AT28)/360 -> 245279.91 | AY29: =+SUM(AW29:AX29) -> 245279.91 | BG29: 4 | BH29: =+EOMONTH(BI29,0) -> 46112 | BI29: 46101 | BK29: =+BK28+BJ29-BL29 -> 42476614 | BL29: 0 | BM29: =+BK28*BK$5*(BI29-BI28)/360 -> 637149.21 | BN29: 82616.23 | BO29: =+SUM(BL29:BN29) -> 719765.44 | BW29: 4 | BX29: =+EOMONTH(BY29,0) -> 46053 | BY29: 46042 | CA29: =+CA28+BZ29-CB29 -> 923783.51 | CB29: 57736.47 | CC29: 2821.4285 | CD29: =+CA28*CA$5*(BY29-BY28)/360 -> 15049.973 | CE29: 1642.8395 | CF29: =+SUM(CB29:CE29) -> 77250.711 | CM29: =+CM28+CE28 -> 65729.642 | CN29: 4 | CO29: =+EOMONTH(CP29,0) -> 46112 | CP29: 46095 | CR29: =+CR28+CQ29-CS29 -> 1460450.1 | CS29: 104317.86 | CT29: 20341.984 | CU29: =+SUM(CS29:CT29) -> 124659.84 | CW29: 4 | CX29: =+EOMONTH(CY29,0) -> 45991 | CY29: 45971 | DA29: =+DA28+CZ29-DB29 -> 24614016 | DB29: 349011.21 | DC29: =+DA28*DA$5*(CY29-CY28)/360 -> 128975.64 | DD29: =+SUM(DB29:DC29) -> 477986.85 | DL29: 4 | DM29: =+EOMONTH(DN29,0) -> 46112 | DN29: 46107 | DP29: =+DP28+DO29-DQ29 -> 9102050 | DQ29: 14905.56 | DR29: 132195.85 | DS29: =+SUM(DQ29:DR29) -> 147101.41 | EA29: 4 | EB29: =+EOMONTH(EC29,0) -> 46142 | EC29: 46118 | EE29: =+EE28-EF29 -> 1107774.2 | EF29: 1933.63 | EG29: =+EE28*(EC29-EC28)*$EE$5/360 -> 16325.652 | EH29: =+SUM(EF29:EG29) -> 18259.282 | EY29: 4 | EZ29: =+EOMONTH(FA29,0) -> 46022 | FA29: 46017 | FC29: =+FC28+FB29-FD29 -> 2794681.5 | FD29: 0 | FE29: 18006.37 | FF29: 0 | FG29: =+SUM(FD29:FF29) -> 18006.37 | FI29: 4 | FJ29: =+EOMONTH(FK29,0) -> 46112 | FK29: 46102 | FM29: =+FM28-FN29 -> 193933.38 | FN29: 39312.49 | FO29: 2589.41 | FP29: =+SUM(FN29:FO29) -> 41901.9 | FR29: 4 | FS29: =+EOMONTH(FT29,0) -> 46112 | FT29: 46102 | FV29: =+FV28-FW29 -> 193933.38 | FW29: 39312.49 | FX29: 2589.41 | FY29: =+SUM(FW29:FX29) -> 41901.9 | GA29: 4 | GB29: =+EOMONTH(GC29,0) -> 46112 | GC29: 46102 | GE29: =+GE28-GF29 -> 193933.38 | GF29: 39312.49 | GG29: 2589.41 | GH29: =+SUM(GF29:GG29) -> 41901.9 | GJ29: 4 | GK29: =+EOMONTH(GL29,0) -> 46112 | GL29: 46102 | GN29: =+GN28-GO29 -> 193933.38 | GO29: 39312.49 | GP29: 2589.41 | GQ29: =+SUM(GO29:GP29) -> 41901.9 | GS29: 4 | GT29: =+EOMONTH(GU29,0) -> 46112 | GU29: 46084 | GW29: =+GW28-GX29 -> 269470.8 | GX29: 40480.72 | GY29: 3322.26 | GZ29: =+SUM(GX29:GY29) -> 43802.98 | HB29: 4 | HC29: =+EOMONTH(HD29,0) -> 46112 | HD29: 46084 | HF29: 269470.8 | HG29: 40480.72 | HH29: 3322.26 | HI29: 43802.98
A30: 5 | B30: =+WEEKNUM(C30,2) -> 35 | C30: =+EOMONTH(C29,1) -> 45900 | E30: =+E29+D30-F30 -> 58028543 | F30: =+SUMIF(N:N,C30,R:R)+SUMIF(AD:AD,C30,AH:AH)+SUMIF(AS:AS,C30,AW:AW)+SUMIF(BH:BH,C30,BL:BL)+SUMIF(BX:BX,C30,CB:CB)+SUMIF(BX:BX,C30,CC:CC)+SUMIF(CO:CO,C30,CS:CS)+SUMIF(CX:CX,C30,DB:DB)+SUMIF(DM:DM,C30,DQ:DQ)+SUMIF(EB:EB,C30,EF:EF)+SUMIF(EQ:EQ,C30,EU:EU)+SUMIF(EZ:EZ,C30,FD:FD)+SUMIF(FJ:FJ,C30,FN:FN)+SUMIF(FS:FS,C30,FW:FW)+SUMIF(GB:GB,C30,GF:GF)+SUMIF(GK:GK,C30,GO:GO)+SUMIF(GT:GT,C30,GX:GX)+SUMIF(HC:HC,C30,HG:HG) -> 440221.67 | G30: =+SUMIF(N:N,C30,T:T)+SUMIF(N:N,C30,S:S)+SUMIF(AD:AD,C30,AI:AI)+SUMIF(AS:AS,C30,AX:AX)+SUMIF(BH:BH,C30,BN:BN)+SUMIF(BH:BH,C30,BM:BM)+SUMIF(BX:BX,C30,CD:CD)+SUMIF(BX:BX,C30,CE:CE)+SUMIF(CO:CO,C30,CT:CT)+SUMIF(CX:CX,C30,DC:DC)+SUMIF(DM:DM,C30,DR:DR)+SUMIF(EB:EB,C30,EG:EG)+SUMIF(EQ:EQ,C30,EV:EV)+SUMIF(EZ:EZ,C30,FE:FE)+SUMIF(FJ:FJ,C30,FO:FO)+SUMIF(FS:FS,C30,FX:FX)+SUMIF(GB:GB,C30,GG:GG)+SUMIF(GK:GK,C30,GP:GP)+SUMIF(GT:GT,C30,GY:GY)+SUMIF(HC:HC,C30,HH:HH) -> 2896985.2 | H30: =+SUM(F30:G30) -> 3337206.9 | I30: =+F30 -> 440221.67 | J30: Union | M30: 5 | N30: =+EOMONTH(O30,0) -> 45991 | O30: =+DATE(YEAR(O29),MONTH(O29)+3,DAY(O29)) -> 45976 | Q30: =+Q29-R30 -> 1.0182495e+08 | R30: =+Q21 -> 30369494 | S30: =+Q29*Q$5*(O30-O29)/360 -> 2026981.4 | T30: =+$Q$17/$Q$18 -> 471550.55 | U30: =+SUM(R30:T30) -> 32868026 | AC30: 5 | AD30: =+EOMONTH(AE30,0) -> 46173 | AE30: 46144 | AG30: =+AG29+AF30-AH30 -> 1086385.6 | AH30: =+AH29 -> 51840.79 | AI30: =+AG29*AG$5*(AE30-AE29)/360 -> 15476.717 | AJ30: =+SUM(AH30:AI30) -> 67317.507 | AR30: 5 | AS30: =+EOMONTH(AT30,0) -> 46081 | AT30: 46073 | AV30: =+AV29+AU30-AW30 -> 15996516 | AW30: 0 | AX30: =+AV29*AV$5*(AT30-AT29)/360 -> 245279.91 | AY30: =+SUM(AW30:AX30) -> 245279.91 | BG30: 5 | BH30: =+EOMONTH(BI30,0) -> 46203 | BI30: 46193 | BK30: =+BK29+BJ30-BL30 -> 42476614 | BL30: 0 | BM30: =+BK29*BK$5*(BI30-BI29)/360 -> 651308.08 | BN30: 82616.23 | BO30: =+SUM(BL30:BN30) -> 733924.31 | BW30: 5 | BX30: =+EOMONTH(BY30,0) -> 46142 | BY30: 46132 | CA30: =+CA29+BZ30-CB30 -> 866047.04 | CB30: 57736.47 | CC30: 2821.4285 | CD30: =+CA29*CA$5*(BY30-BY29)/360 -> 13856.753 | CE30: 1642.8395 | CF30: =+SUM(CB30:CE30) -> 76057.491 | CN30: 5 | CO30: =+EOMONTH(CP30,0) -> 46203 | CP30: 46187 | CR30: =+CR29+CQ30-CS30 -> 1356132.3 | CS30: 104317.86 | CT30: 19194.488 | CU30: =+SUM(CS30:CT30) -> 123512.35 | CW30: 5 | CX30: =+EOMONTH(CY30,0) -> 46022 | CY30: 46001 | DA30: =+DA29+CZ30-DB30 -> 24265005 | DB30: 349011.21 | DC30: =+DA29*DA$5*(CY30-CY29)/360 -> 123070.08 | DD30: =+SUM(DB30:DC30) -> 472081.29 | DL30: 5 | DM30: =+EOMONTH(DN30,0) -> 46203 | DN30: 46198 | DP30: =+DP29+DO30-DQ30 -> 9087144.4 | DQ30: 14905.62 | DR30: 133446.17 | DS30: =+SUM(DQ30:DR30) -> 148351.79 | EA30: 5 | EB30: =+EOMONTH(EC30,0) -> 46234 | EC30: 46209 | EE30: =+EE29-EF30 -> 1105840.6 | EF30: 1933.65 | EG30: =+EE29*(EC30-EC29)*$EE$5/360 -> 16297.205 | EH30: =+SUM(EF30:EG30) -> 18230.855 | EY30: 5 | EZ30: =+EOMONTH(FA30,0) -> 46112 | FA30: 46107 | FC30: =+FC29+FB30-FD30 -> 2789681.5 | FD30: 5000.03 | FE30: 18235.06 | FG30: =+SUM(FD30:FF30) -> 23235.09 | FI30: 5 | FJ30: =+EOMONTH(FK30,0) -> 46203 | FK30: 46192 | FM30: =+FM29-FN30 -> 153785.5 | FN30: 40147.88 | FO30: 1999.73 | FP30: =+SUM(FN30:FO30) -> 42147.61 | FR30: 5 | FS30: =+EOMONTH(FT30,0) -> 46203 | FT30: 46192 | FV30: =+FV29-FW30 -> 153785.5 | FW30: 40147.88 | FX30: 1999.73 | FY30: =+SUM(FW30:FX30) -> 42147.61 | GA30: 5 | GB30: =+EOMONTH(GC30,0) -> 46203 | GC30: 46192 | GE30: =+GE29-GF30 -> 153785.5 | GF30: 40147.88 | GG30: 1999.73 | GH30: =+SUM(GF30:GG30) -> 42147.61 | GJ30: 5 | GK30: =+EOMONTH(GL30,0) -> 46203 | GL30: 46192 | GN30: =+GN29-GO30 -> 153785.5 | GO30: 40147.88 | GP30: 1999.73 | GQ30: =+SUM(GO30:GP30) -> 42147.61 | GS30: 5 | GT30: =+EOMONTH(GU30,0) -> 46203 | GU30: 46174 | GW30: =+GW29-GX30 -> 228129.86 | GX30: 41340.94 | GY30: 2715.05 | GZ30: =+SUM(GX30:GY30) -> 44055.99 | HB30: 5 | HC30: =+EOMONTH(HD30,0) -> 46203 | HD30: 46174 | HF30: 228129.86 | HG30: 41340.94 | HH30: 2715.05 | HI30: 44055.99
A31: 6 | B31: =+WEEKNUM(C31,2) -> 40 | C31: =+EOMONTH(C30,1) -> 45930 | E31: =+E30+D31-F31 -> 57451130 | F31: =+SUMIF(N:N,C31,R:R)+SUMIF(AD:AD,C31,AH:AH)+SUMIF(AS:AS,C31,AW:AW)+SUMIF(BH:BH,C31,BL:BL)+SUMIF(BX:BX,C31,CB:CB)+SUMIF(BX:BX,C31,CC:CC)+SUMIF(CO:CO,C31,CS:CS)+SUMIF(CX:CX,C31,DB:DB)+SUMIF(DM:DM,C31,DQ:DQ)+SUMIF(EB:EB,C31,EF:EF)+SUMIF(EQ:EQ,C31,EU:EU)+SUMIF(EZ:EZ,C31,FD:FD)+SUMIF(FJ:FJ,C31,FN:FN)+SUMIF(FS:FS,C31,FW:FW)+SUMIF(GB:GB,C31,GF:GF)+SUMIF(GK:GK,C31,GO:GO)+SUMIF(GT:GT,C31,GX:GX)+SUMIF(HC:HC,C31,HG:HG) -> 577412.41 | G31: =+SUMIF(N:N,C31,T:T)+SUMIF(N:N,C31,S:S)+SUMIF(AD:AD,C31,AI:AI)+SUMIF(AS:AS,C31,AX:AX)+SUMIF(BH:BH,C31,BN:BN)+SUMIF(BH:BH,C31,BM:BM)+SUMIF(BX:BX,C31,CD:CD)+SUMIF(BX:BX,C31,CE:CE)+SUMIF(CO:CO,C31,CT:CT)+SUMIF(CX:CX,C31,DC:DC)+SUMIF(DM:DM,C31,DR:DR)+SUMIF(EB:EB,C31,EG:EG)+SUMIF(EQ:EQ,C31,EV:EV)+SUMIF(EZ:EZ,C31,FE:FE)+SUMIF(FJ:FJ,C31,FO:FO)+SUMIF(FS:FS,C31,FX:FX)+SUMIF(GB:GB,C31,GG:GG)+SUMIF(GK:GK,C31,GP:GP)+SUMIF(GT:GT,C31,GY:GY)+SUMIF(HC:HC,C31,HH:HH) -> 1226310.7 | H31: =+SUM(F31:G31) -> 1803723.1 | M31: 6 | N31: =+EOMONTH(O31,0) -> 46081 | O31: =+DATE(YEAR(O30),MONTH(O30)+3,DAY(O30)) -> 46068 | Q31: =+Q30-R31 -> 97751949 | R31: =+$Q$30/25 -> 4072997.9 | S31: =+Q30*Q$5*(O31-O30)/360 -> 1561315.9 | T31: =+$Q$17/$Q$18 -> 471550.55 | U31: =+SUM(R31:T31) -> 6105864.3 | AC31: 6 | AD31: =+EOMONTH(AE31,0) -> 46265 | AE31: 46236 | AG31: =+AG30+AF31-AH31 -> 1034544.8 | AH31: =+AH30 -> 51840.79 | AI31: =+AG30*AG$5*(AE31-AE30)/360 -> 15269.753 | AJ31: =+SUM(AH31:AI31) -> 67110.543 | AR31: 6 | AS31: =+EOMONTH(AT31,0) -> 46173 | AT31: 46162 | AV31: =+AV30+AU31-AW31 -> 15996516 | AW31: 0 | AX31: =+AV30*AV$5*(AT31-AT30)/360 -> 237281.65 | AY31: =+SUM(AW31:AX31) -> 237281.65 | BG31: 6 | BH31: =+EOMONTH(BI31,0) -> 46295 | BI31: 46285 | BK31: =+BK30+BJ31-BL31 -> 38228953 | BL31: =+BK28/10 -> 4247661.4 | BM31: =+BK30*BK$5*(BI31-BI30)/360 -> 651308.08 | BN31: 82616.23 | BO31: =+SUM(BL31:BN31) -> 4981585.7 | BW31: 6 | BX31: =+EOMONTH(BY31,0) -> 46234 | BY31: 46223 | CA31: =+CA30+BZ31-CB31 -> 808310.57 | CB31: 57736.47 | CC31: 2821.4285 | CD31: =+CA30*CA$5*(BY31-BY30)/360 -> 13135.047 | CE31: 1642.8395 | CF31: =+SUM(CB31:CE31) -> 75335.785 | CN31: 6 | CO31: =+EOMONTH(CP31,0) -> 46295 | CP31: 46279 | CR31: =+CR30+CQ31-CS31 -> 1251814.4 | CS31: 104317.86 | CT31: 17594.947 | CU31: =+SUM(CS31:CT31) -> 121912.81 | CW31: 6 | CX31: =+EOMONTH(CY31,0) -> 46053 | CY31: 46032 | DA31: =+DA30+CZ31-DB31 -> 23915993 | DB31: 349011.21 | DC31: =+DA30*DA$5*(CY31-CY30)/360 -> 125369.19 | DD31: =+SUM(DB31:DC31) -> 474380.4 | DL31: 6 | DM31: =+EOMONTH(DN31,0) -> 46295 | DN31: 46289 | DP31: =+DP30+DO31-DQ31 -> 8803171.1 | DQ31: 283973.26 | DR31: 133227.63 | DS31: =+SUM(DQ31:DR31) -> 417200.89 | EA31: 6 | EB31: =+EOMONTH(EC31,0) -> 46326 | EC31: 46300 | EE31: =+EE30-EF31 -> 1066346.3 | EF31: 39494.31 | EG31: =+EE30*(EC31-EC30)*$EE$5/360 -> 16268.758 | EH31: =+SUM(EF31:EG31) -> 55763.068 | EY31: 6 | EZ31: =+EOMONTH(FA31,0) -> 46203 | FA31: 46198 | FC31: =+FC30+FB31-FD31 -> 2784681.5 | FD31: 5000 | FE31: 18355.08 | FG31: =+SUM(FD31:FF31) -> 23355.08 | FI31: 6 | FJ31: =+EOMONTH(FK31,0) -> 46295 | FK31: 46282 | FM31: =+FM30-FN31 -> 112784.48 | FN31: 41001.02 | FO31: 1397.51 | FP31: =+SUM(FN31:FO31) -> 42398.53 | FR31: 6 | FS31: =+EOMONTH(FT31,0) -> 46295 | FT31: 46282 | FV31: =+FV30-FW31 -> 112784.48 | FW31: 41001.02 | FX31: 1397.51 | FY31: =+SUM(FW31:FX31) -> 42398.53 | GA31: 6 | GB31: =+EOMONTH(GC31,0) -> 46295 | GC31: 46282 | GE31: =+GE30-GF31 -> 112784.48 | GF31: 41001.02 | GG31: 1397.51 | GH31: =+SUM(GF31:GG31) -> 42398.53 | GJ31: 6 | GK31: =+EOMONTH(GL31,0) -> 46295 | GL31: 46282 | GN31: =+GN30-GO31 -> 112784.48 | GO31: 41001.02 | GP31: 1397.51 | GQ31: =+SUM(GO31:GP31) -> 42398.53 | GS31: 6 | GT31: =+EOMONTH(GU31,0) -> 46265 | GU31: 46264 | GW31: =+GW30-GX31 -> 185910.43 | GX31: 42219.43 | GY31: 2094.94 | GZ31: =+SUM(GX31:GY31) -> 44314.37 | HB31: 6 | HC31: =+EOMONTH(HD31,0) -> 46265 | HD31: 46264 | HF31: 185910.43 | HG31: 42219.43 | HH31: 2094.94 | HI31: 44314.37
A32: 7 | B32: =+WEEKNUM(C32,2) -> 40 | C32: =+C31+1 -> 45931 | E32: =+E31+D32-F32 -> 57451130 | F32: =+SUMIF(O:O,C32,R:R)+SUMIF(AE:AE,C32,AH:AH)+SUMIF(AT:AT,C32,AW:AW)+SUMIF(BI:BI,C32,BL:BL)+SUMIF(BY:BY,C32,CB:CB)+SUMIF(BY:BY,C32,CC:CC)+SUMIF(CP:CP,C32,CS:CS)+SUMIF(CY:CY,C32,DB:DB)+SUMIF(DN:DN,C32,DQ:DQ)+SUMIF(EC:EC,C32,EF:EF)+SUMIF(ER:ER,C32,EU:EU)+SUMIF(FA:FA,C32,FD:FD)+SUMIF(FK:FK,C32,FN:FN)+SUMIF(FT:FT,C32,FW:FW)+SUMIF(GC:GC,C32,GF:GF)+SUMIF(GL:GL,C32,GO:GO)+SUMIF(GU:GU,C32,GX:GX)+SUMIF(HD:HD,C32,HG:HG) -> 0 | G32: =+SUMIF(O:O,C32,T:T)+SUMIF(O:O,C32,S:S)+SUMIF(AE:AE,C32,AI:AI)+SUMIF(AT:AT,C32,AX:AX)+SUMIF(BI:BI,C32,BN:BN)+SUMIF(BI:BI,C32,BM:BM)+SUMIF(BY:BY,C32,CD:CD)+SUMIF(BY:BY,C32,CE:CE)+SUMIF(CP:CP,C32,CT:CT)+SUMIF(CY:CY,C32,DC:DC)+SUMIF(DN:DN,C32,DR:DR)+SUMIF(EC:EC,C32,EG:EG)+SUMIF(ER:ER,C32,EV:EV)+SUMIF(FA:FA,C32,FE:FE)+SUMIF(FK:FK,C32,FO:FO)+SUMIF(FT:FT,C32,FX:FX)+SUMIF(GC:GC,C32,GG:GG)+SUMIF(GL:GL,C32,GP:GP)+SUMIF(GU:GU,C32,GY:GY)+SUMIF(HD:HD,C32,HH:HH) -> 0 | H32: =+SUM(F32:G32) -> 0 | M32: 7 | N32: =+EOMONTH(O32,0) -> 46173 | O32: =+DATE(YEAR(O31),MONTH(O31)+3,DAY(O31)) -> 46157 | Q32: =+Q31-R32 -> 93678951 | R32: =+$Q$30/25 -> 4072997.9 | S32: =+Q31*Q$5*(O32-O31)/360 -> 1449987.2 | T32: =+$Q$17/$Q$18 -> 471550.55 | U32: =+SUM(R32:T32) -> 5994535.7 | AC32: 7 | AD32: =+EOMONTH(AE32,0) -> 46356 | AE32: 46328 | AG32: =+AG31+AF32-AH32 -> 982703.98 | AH32: =+AH31 -> 51840.79 | AI32: =+AG31*AG$5*(AE32-AE31)/360 -> 14541.101 | AJ32: =+SUM(AH32:AI32) -> 66381.891 | AR32: 7 | AS32: =+EOMONTH(AT32,0) -> 46265 | AT32: 46254 | AV32: =+AV31+AU32-AW32 -> 15471469 | AW32: 525047.46 | AX32: =+AV31*AV$5*(AT32-AT31)/360 -> 245279.91 | AY32: =+SUM(AW32:AX32) -> 770327.38 | BG32: 7 | BH32: =+EOMONTH(BI32,0) -> 46387 | BI32: 46376 | BK32: =+BK31+BJ32-BL32 -> 33981291 | BL32: =+BL31 -> 4247661.4 | BM32: =+BK31*BK$5*(BI32-BI31)/360 -> 579805.78 | BN32: 82616.23 | BO32: =+SUM(BL32:BN32) -> 4910083.4 | BW32: 7 | BX32: =+EOMONTH(BY32,0) -> 46326 | BY32: 46315 | CA32: =+CA31+BZ32-CB32 -> 750574.1 | CB32: 57736.47 | CC32: 2821.4285 | CD32: =+CA31*CA$5*(BY32-BY31)/360 -> 12394.095 | CE32: 1642.8395 | CF32: =+SUM(CB32:CE32) -> 74594.833 | CN32: 7 | CO32: =+EOMONTH(CP32,0) -> 46387 | CP32: 46370 | CR32: =+CR31+CQ32-CS32 -> 1147496.5 | CS32: 104317.86 | CT32: 15821.544 | CU32: =+SUM(CS32:CT32) -> 120139.4 | CW32: 7 | CX32: =+EOMONTH(CY32,0) -> 46081 | CY32: 46063 | DA32: =+DA31+CZ32-DB32 -> 23566982 | DB32: 349011.21 | DC32: =+DA31*DA$5*(CY32-CY31)/360 -> 123565.97 | DD32: =+SUM(DB32:DC32) -> 472577.18 | DL32: 7 | DM32: =+EOMONTH(DN32,0) -> 46387 | DN32: 46380 | DP32: =+DP31+DO32-DQ32 -> 8519197.8 | DQ32: 283973.26 | DR32: 129064.27 | DS32: =+SUM(DQ32:DR32) -> 413037.53 | EA32: 7 | EB32: =+EOMONTH(EC32,0) -> 46418 | EC32: 46392 | EE32: =+EE31-EF32 -> 1026852 | EF32: 39494.31 | EG32: =+EE31*(EC32-EC31)*$EE$5/360 -> 15860.124 | EH32: =+SUM(EF32:EG32) -> 55354.434 | EY32: 7 | EZ32: =+EOMONTH(FA32,0) -> 46295 | FA32: 46289 | FC32: =+FC31+FB32-FD32 -> 2744464.6 | FD32: 40216.85 | FE32: 18279.37 | FG32: =+SUM(FD32:FF32) -> 58496.22 | FI32: 7 | FJ32: =+EOMONTH(FK32,0) -> 46387 | FK32: 46372 | FM32: =+FM31-FN32 -> 70912.104 | FN32: 41872.38 | FO32: 782.49 | FP32: =+SUM(FN32:FO32) -> 42654.87 | FR32: 7 | FS32: =+EOMONTH(FT32,0) -> 46387 | FT32: 46372 | FV32: =+FV31-FW32 -> 70912.104 | FW32: 41872.38 | FX32: 782.49 | FY32: =+SUM(FW32:FX32) -> 42654.87 | GA32: 7 | GB32: =+EOMONTH(GC32,0) -> 46387 | GC32: 46372 | GE32: =+GE31-GF32 -> 70912.104 | GF32: 41872.38 | GG32: 782.49 | GH32: =+SUM(GF32:GG32) -> 42654.87 | GJ32: 7 | GK32: =+EOMONTH(GL32,0) -> 46387 | GL32: 46372 | GN32: =+GN31-GO32 -> 70912.104 | GO32: 41872.38 | GP32: 782.49 | GQ32: =+SUM(GO32:GP32) -> 42654.87 | GS32: 7 | GT32: =+EOMONTH(GU32,0) -> 46356 | GU32: 46354 | GW32: =+GW31-GX32 -> 142793.83 | GX32: 43116.6 | GY32: 1461.65 | GZ32: =+SUM(GX32:GY32) -> 44578.25 | HB32: 7 | HC32: =+EOMONTH(HD32,0) -> 46356 | HD32: 46354 | HF32: 142793.83 | HG32: 43116.6 | HH32: 1461.65 | HI32: 44578.25
A33: 8 | B33: =+WEEKNUM(C33,2) -> 40 | C33: =+C32+1 -> 45932 | E33: =+E32+D33-F33 -> 57451130 | F33: =+SUMIF(O:O,C33,R:R)+SUMIF(AE:AE,C33,AH:AH)+SUMIF(AT:AT,C33,AW:AW)+SUMIF(BI:BI,C33,BL:BL)+SUMIF(BY:BY,C33,CB:CB)+SUMIF(BY:BY,C33,CC:CC)+SUMIF(CP:CP,C33,CS:CS)+SUMIF(CY:CY,C33,DB:DB)+SUMIF(DN:DN,C33,DQ:DQ)+SUMIF(EC:EC,C33,EF:EF)+SUMIF(ER:ER,C33,EU:EU)+SUMIF(FA:FA,C33,FD:FD)+SUMIF(FK:FK,C33,FN:FN)+SUMIF(FT:FT,C33,FW:FW)+SUMIF(GC:GC,C33,GF:GF)+SUMIF(GL:GL,C33,GO:GO)+SUMIF(GU:GU,C33,GX:GX)+SUMIF(HD:HD,C33,HG:HG) -> 0 | G33: =+SUMIF(O:O,C33,T:T)+SUMIF(O:O,C33,S:S)+SUMIF(AE:AE,C33,AI:AI)+SUMIF(AT:AT,C33,AX:AX)+SUMIF(BI:BI,C33,BN:BN)+SUMIF(BI:BI,C33,BM:BM)+SUMIF(BY:BY,C33,CD:CD)+SUMIF(BY:BY,C33,CE:CE)+SUMIF(CP:CP,C33,CT:CT)+SUMIF(CY:CY,C33,DC:DC)+SUMIF(DN:DN,C33,DR:DR)+SUMIF(EC:EC,C33,EG:EG)+SUMIF(ER:ER,C33,EV:EV)+SUMIF(FA:FA,C33,FE:FE)+SUMIF(FK:FK,C33,FO:FO)+SUMIF(FT:FT,C33,FX:FX)+SUMIF(GC:GC,C33,GG:GG)+SUMIF(GL:GL,C33,GP:GP)+SUMIF(GU:GU,C33,GY:GY)+SUMIF(HD:HD,C33,HH:HH) -> 0 | H33: =+SUM(F33:G33) -> 0 | M33: 8 | N33: =+EOMONTH(O33,0) -> 46265 | O33: =+DATE(YEAR(O32),MONTH(O32)+3,DAY(O32)) -> 46249 | Q33: =+Q32-R33 -> 89605953 | R33: =+$Q$30/25 -> 4072997.9 | S33: =+Q32*Q$5*(O33-O32)/360 -> 1436410.6 | T33: =+$Q$17/$Q$18 -> 471550.55 | U33: =+SUM(R33:T33) -> 5980959 | AC33: 8 | AD33: =+EOMONTH(AE33,0) -> 46446 | AE33: 46420 | AG33: =+AG32+AF33-AH33 -> 930863.19 | AH33: =+AH32 -> 51840.79 | AI33: =+AG32*AG$5*(AE33-AE32)/360 -> 13812.45 | AJ33: =+SUM(AH33:AI33) -> 65653.24 | AR33: 8 | AS33: =+EOMONTH(AT33,0) -> 46356 | AT33: 46346 | AV33: =+AV32+AU33-AW33 -> 14946421 | AW33: 525047.46 | AX33: =+AV32*AV$5*(AT33-AT32)/360 -> 237229.19 | AY33: =+SUM(AW33:AX33) -> 762276.65 | BG33: 8 | BH33: =+EOMONTH(BI33,0) -> 46477 | BI33: 46466 | BK33: =+BK32+BJ33-BL33 -> 29733630 | BL33: =+BL32 -> 4247661.4 | BM33: =+BK32*BK$5*(BI33-BI32)/360 -> 509719.37 | BN33: 82616.23 | BO33: =+SUM(BL33:BN33) -> 4839997 | BW33: 8 | BX33: =+EOMONTH(BY33,0) -> 46418 | BY33: 46407 | CA33: =+CA32+BZ33-CB33 -> 692837.63 | CB33: 57736.47 | CC33: 2821.4285 | CD33: =+CA32*CA$5*(BY33-BY32)/360 -> 11508.803 | CE33: 1642.8395 | CF33: =+SUM(CB33:CE33) -> 73709.541 | CN33: 8 | CO33: =+EOMONTH(CP33,0) -> 46477 | CP33: 46460 | CR33: =+CR32+CQ33-CS33 -> 1043178.7 | CS33: 104317.86 | CT33: 14082.913 | CU33: =+SUM(CS33:CT33) -> 118400.77 | CW33: 8 | CX33: =+EOMONTH(CY33,0) -> 46112 | CY33: 46091 | DA33: =+DA32+CZ33-DB33 -> 23217971 | DB33: 349011.21 | DC33: =+DA32*DA$5*(CY33-CY32)/360 -> 109979.25 | DD33: =+SUM(DB33:DC33) -> 458990.46 | DL33: 8 | DM33: =+EOMONTH(DN33,0) -> 46477 | DN33: 46471 | DP33: =+DP32+DO33-DQ33 -> 8235224.6 | DQ33: 283973.26 | DR33: 124900.9 | DS33: =+SUM(DQ33:DR33) -> 408874.16 | EA33: 8 | EB33: =+EOMONTH(EC33,0) -> 46507 | EC33: 46482 | EE33: =+EE32-EF33 -> 987357.66 | EF33: 39494.31 | EG33: =+EE32*(EC33-EC32)*$EE$5/360 -> 14940.696 | EH33: =+SUM(EF33:EG33) -> 54435.006 | EY33: 8 | EZ33: =+EOMONTH(FA33,0) -> 46387 | FA33: 46380 | FC33: =+FC32+FB33-FD33 -> 2704247.8 | FD33: 40216.85 | FE33: 17670.43 | FG33: =+SUM(FD33:FF33) -> 57887.28 | FI33: 8 | FJ33: =+EOMONTH(FK33,0) -> 46477 | FK33: 46462 | FM33: =+FM32-FN33 -> 41229.074 | FN33: 29683.03 | FO33: 17605.8 | FP33: =+SUM(FN33:FO33) -> 47288.83 | FR33: 8 | FS33: =+EOMONTH(FT33,0) -> 46477 | FT33: 46462 | FV33: =+FV32-FW33 -> 41229.074 | FW33: 29683.03 | FX33: 17605.8 | FY33: =+SUM(FW33:FX33) -> 47288.83 | GA33: 8 | GB33: =+EOMONTH(GC33,0) -> 46477 | GC33: 46462 | GE33: =+GE32-GF33 -> 41229.074 | GF33: 29683.03 | GG33: 17605.8 | GH33: =+SUM(GF33:GG33) -> 47288.83 | GJ33: 8 | GK33: =+EOMONTH(GL33,0) -> 46477 | GL33: 46462 | GN33: =+GN32-GO33 -> 41229.074 | GO33: 29683.03 | GP33: 17605.8 | GQ33: =+SUM(GO33:GP33) -> 47288.83 | GS33: 8 | GT33: =+EOMONTH(GU33,0) -> 46446 | GU33: 46444 | GW33: =+GW32-GX33 -> 98761.04 | GX33: 44032.79 | GY33: 814.9 | GZ33: =+SUM(GX33:GY33) -> 44847.69 | HB33: 8 | HC33: =+EOMONTH(HD33,0) -> 46446 | HD33: 46444 | HF33: 98761.04 | HG33: 44032.79 | HH33: 814.9 | HI33: 44847.69
A34: 9 | B34: =+WEEKNUM(C34,2) -> 40 | C34: =+C33+1 -> 45933 | E34: =+E33+D34-F34 -> 57451130 | F34: =+SUMIF(O:O,C34,R:R)+SUMIF(AE:AE,C34,AH:AH)+SUMIF(AT:AT,C34,AW:AW)+SUMIF(BI:BI,C34,BL:BL)+SUMIF(BY:BY,C34,CB:CB)+SUMIF(BY:BY,C34,CC:CC)+SUMIF(CP:CP,C34,CS:CS)+SUMIF(CY:CY,C34,DB:DB)+SUMIF(DN:DN,C34,DQ:DQ)+SUMIF(EC:EC,C34,EF:EF)+SUMIF(ER:ER,C34,EU:EU)+SUMIF(FA:FA,C34,FD:FD)+SUMIF(FK:FK,C34,FN:FN)+SUMIF(FT:FT,C34,FW:FW)+SUMIF(GC:GC,C34,GF:GF)+SUMIF(GL:GL,C34,GO:GO)+SUMIF(GU:GU,C34,GX:GX)+SUMIF(HD:HD,C34,HG:HG) -> 0 | G34: =+SUMIF(O:O,C34,T:T)+SUMIF(O:O,C34,S:S)+SUMIF(AE:AE,C34,AI:AI)+SUMIF(AT:AT,C34,AX:AX)+SUMIF(BI:BI,C34,BN:BN)+SUMIF(BI:BI,C34,BM:BM)+SUMIF(BY:BY,C34,CD:CD)+SUMIF(BY:BY,C34,CE:CE)+SUMIF(CP:CP,C34,CT:CT)+SUMIF(CY:CY,C34,DC:DC)+SUMIF(DN:DN,C34,DR:DR)+SUMIF(EC:EC,C34,EG:EG)+SUMIF(ER:ER,C34,EV:EV)+SUMIF(FA:FA,C34,FE:FE)+SUMIF(FK:FK,C34,FO:FO)+SUMIF(FT:FT,C34,FX:FX)+SUMIF(GC:GC,C34,GG:GG)+SUMIF(GL:GL,C34,GP:GP)+SUMIF(GU:GU,C34,GY:GY)+SUMIF(HD:HD,C34,HH:HH) -> 0 | H34: =+SUM(F34:G34) -> 0 | M34: 9 | N34: =+EOMONTH(O34,0) -> 46356 | O34: =+DATE(YEAR(O33),MONTH(O33)+3,DAY(O33)) -> 46341 | Q34: =+Q33-R34 -> 85532956 | R34: =+$Q$30/25 -> 4072997.9 | S34: =+Q33*Q$5*(O34-O33)/360 -> 1373958 | T34: =+$Q$17/$Q$18 -> 471550.55 | U34: =+SUM(R34:T34) -> 5918506.4 | AC34: 9 | AD34: =+EOMONTH(AE34,0) -> 46538 | AE34: 46509 | AG34: =+AG33+AF34-AH34 -> 879022.4 | AH34: =+AH33 -> 51840.79 | AI34: =+AG33*AG$5*(AE34-AE33)/360 -> 12657.154 | AJ34: =+SUM(AH34:AI34) -> 64497.944 | AR34: 9 | AS34: =+EOMONTH(AT34,0) -> 46446 | AT34: 46438 | AV34: =+AV33+AU34-AW34 -> 14421374 | AW34: 525047.46 | AX34: =+AV33*AV$5*(AT34-AT33)/360 -> 229178.46 | AY34: =+SUM(AW34:AX34) -> 754225.92 | BG34: 9 | BH34: =+EOMONTH(BI34,0) -> 46568 | BI34: 46558 | BK34: =+BK33+BJ34-BL34 -> 25485968 | BL34: =+BL33 -> 4247661.4 | BM34: =+BK33*BK$5*(BI34-BI33)/360 -> 455915.66 | BN34: 82616.23 | BO34: =+SUM(BL34:BN34) -> 4786193.3 | BW34: 9 | BX34: =+EOMONTH(BY34,0) -> 46507 | BY34: 46497 | CA34: =+CA33+BZ34-CB34 -> 635101.16 | CB34: 57736.47 | CC34: 2821.4285 | CD34: =+CA33*CA$5*(BY34-BY33)/360 -> 10392.564 | CE34: 1642.8395 | CF34: =+SUM(CB34:CE34) -> 72593.302 | CN34: 9 | CO34: =+EOMONTH(CP34,0) -> 46568 | CP34: 46552 | CR34: =+CR33+CQ34-CS34 -> 938860.83 | CS34: 104317.86 | CT34: 12796.326 | CU34: =+SUM(CS34:CT34) -> 117114.19 | CW34: 9 | CX34: =+EOMONTH(CY34,0) -> 46142 | CY34: 46122 | DA34: =+DA33+CZ34-DB34 -> 22868960 | DB34: 349011.21 | DC34: =+DA33*DA$5*(CY34-CY33)/360 -> 119959.52 | DD34: =+SUM(DB34:DC34) -> 468970.73 | DL34: 9 | DM34: =+EOMONTH(DN34,0) -> 46568 | DN34: 46562 | DP34: =+DP33+DO34-DQ34 -> 7951251.3 | DQ34: 283973.26 | DR34: 120737.54 | DS34: =+SUM(DQ34:DR34) -> 404710.8 | EA34: 9 | EB34: =+EOMONTH(EC34,0) -> 46599 | EC34: 46573 | EE34: =+EE33-EF34 -> 947863.35 | EF34: 39494.31 | EG34: =+EE33*(EC34-EC33)*$EE$5/360 -> 14525.677 | EH34: =+SUM(EF34:EG34) -> 54019.987 | EY34: 9 | EZ34: =+EOMONTH(FA34,0) -> 46477 | FA34: 46471 | FC34: =+FC33+FB34-FD34 -> 2664030.9 | FD34: 40216.85 | FE34: 17061.49 | FG34: =+SUM(FD34:FF34) -> 57278.34 | FI34: 9 | FJ34: =+EOMONTH(FK34,0) -> 46568 | FK34: 46552 | FM34: =+FM33-FN34 -> 10293.844 | FN34: 30935.23 | FO34: 14697.99 | FP34: =+SUM(FN34:FO34) -> 45633.22 | FR34: 9 | FS34: =+EOMONTH(FT34,0) -> 46568 | FT34: 46552 | FV34: =+FV33-FW34 -> 10293.844 | FW34: 30935.23 | FX34: 14697.99 | FY34: =+SUM(FW34:FX34) -> 45633.22 | GA34: 9 | GB34: =+EOMONTH(GC34,0) -> 46568 | GC34: 46552 | GE34: =+GE33-GF34 -> 10293.844 | GF34: 30935.23 | GG34: 14697.99 | GH34: =+SUM(GF34:GG34) -> 45633.22 | GJ34: 9 | GK34: =+EOMONTH(GL34,0) -> 46568 | GL34: 46552 | GN34: =+GN33-GO34 -> 10293.844 | GO34: 30935.23 | GP34: 14697.99 | GQ34: =+SUM(GO34:GP34) -> 45633.22 | GS34: 9 | GT34: =+EOMONTH(GU34,0) -> 46538 | GU34: 46534 | GW34: =+GW33-GX34 -> 70279.53 | GX34: 28481.51 | GY34: 18828.9 | GZ34: =+SUM(GX34:GY34) -> 47310.41 | HB34: 9 | HC34: =+EOMONTH(HD34,0) -> 46538 | HD34: 46534 | HF34: 70279.53 | HG34: 28481.51 | HH34: 18828.9 | HI34: 47310.41
A35: 10 | B35: =+WEEKNUM(C35,2) -> 40 | C35: =+C34+1 -> 45934 | E35: =+E34+D35-F35 -> 57451130 | F35: =+SUMIF(O:O,C35,R:R)+SUMIF(AE:AE,C35,AH:AH)+SUMIF(AT:AT,C35,AW:AW)+SUMIF(BI:BI,C35,BL:BL)+SUMIF(BY:BY,C35,CB:CB)+SUMIF(BY:BY,C35,CC:CC)+SUMIF(CP:CP,C35,CS:CS)+SUMIF(CY:CY,C35,DB:DB)+SUMIF(DN:DN,C35,DQ:DQ)+SUMIF(EC:EC,C35,EF:EF)+SUMIF(ER:ER,C35,EU:EU)+SUMIF(FA:FA,C35,FD:FD)+SUMIF(FK:FK,C35,FN:FN)+SUMIF(FT:FT,C35,FW:FW)+SUMIF(GC:GC,C35,GF:GF)+SUMIF(GL:GL,C35,GO:GO)+SUMIF(GU:GU,C35,GX:GX)+SUMIF(HD:HD,C35,HG:HG) -> 0 | G35: =+SUMIF(O:O,C35,T:T)+SUMIF(O:O,C35,S:S)+SUMIF(AE:AE,C35,AI:AI)+SUMIF(AT:AT,C35,AX:AX)+SUMIF(BI:BI,C35,BN:BN)+SUMIF(BI:BI,C35,BM:BM)+SUMIF(BY:BY,C35,CD:CD)+SUMIF(BY:BY,C35,CE:CE)+SUMIF(CP:CP,C35,CT:CT)+SUMIF(CY:CY,C35,DC:DC)+SUMIF(DN:DN,C35,DR:DR)+SUMIF(EC:EC,C35,EG:EG)+SUMIF(ER:ER,C35,EV:EV)+SUMIF(FA:FA,C35,FE:FE)+SUMIF(FK:FK,C35,FO:FO)+SUMIF(FT:FT,C35,FX:FX)+SUMIF(GC:GC,C35,GG:GG)+SUMIF(GL:GL,C35,GP:GP)+SUMIF(GU:GU,C35,GY:GY)+SUMIF(HD:HD,C35,HH:HH) -> 0 | H35: =+SUM(F35:G35) -> 0 | I35: 0 | M35: 10 | N35: =+EOMONTH(O35,0) -> 46446 | O35: =+DATE(YEAR(O34),MONTH(O34)+3,DAY(O34)) -> 46433 | Q35: =+Q34-R35 -> 81459958 | R35: =+$Q$30/25 -> 4072997.9 | S35: =+Q34*Q$5*(O35-O34)/360 -> 1311505.3 | T35: =+$Q$17/$Q$18 -> 471550.55 | U35: =+SUM(R35:T35) -> 5856053.7 | AC35: 10 | AD35: =+EOMONTH(AE35,0) -> 46630 | AE35: 46601 | AG35: =+AG34+AF35-AH35 -> 827181.61 | AH35: =+AH34 -> 51840.79 | AI35: =+AG34*AG$5*(AE35-AE34)/360 -> 12355.148 | AJ35: =+SUM(AH35:AI35) -> 64195.938 | AR35: 10 | AS35: =+EOMONTH(AT35,0) -> 46538 | AT35: 46527 | AV35: =+AV34+AU35-AW35 -> 13896326 | AW35: 525047.46 | AX35: =+AV34*AV$5*(AT35-AT34)/360 -> 213917.04 | AY35: =+SUM(AW35:AX35) -> 738964.51 | BG35: 10 | BH35: =+EOMONTH(BI35,0) -> 46660 | BI35: 46650 | BK35: =+BK34+BJ35-BL35 -> 21238307 | BL35: =+BL34 -> 4247661.4 | BM35: =+BK34*BK$5*(BI35-BI34)/360 -> 390784.85 | BN35: 82616.23 | BO35: =+SUM(BL35:BN35) -> 4721062.5 | BW35: 10 | BX35: =+EOMONTH(BY35,0) -> 46599 | BY35: 46588 | CA35: =+CA34+BZ35-CB35 -> 577364.69 | CB35: 57736.47 | CC35: 2821.4285 | CD35: =+CA34*CA$5*(BY35-BY34)/360 -> 9632.3676 | CE35: 1642.8395 | CF35: =+SUM(CB35:CE35) -> 71833.106 | CN35: 10 | CO35: =+EOMONTH(CP35,0) -> 46660 | CP35: 46644 | CR35: =+CR34+CQ35-CS35 -> 834542.97 | CS35: 104317.86 | CT35: 11196.785 | CU35: =+SUM(CS35:CT35) -> 115514.65 | CW35: 10 | CX35: =+EOMONTH(CY35,0) -> 46173 | CY35: 46152 | DA35: =+DA34+CZ35-DB35 -> 22519949 | DB35: 349011.21 | DC35: =+DA34*DA$5*(CY35-CY34)/360 -> 114344.8 | DD35: =+SUM(DB35:DC35) -> 463356.01 | DL35: 10 | DM35: =+EOMONTH(DN35,0) -> 46660 | DN35: 46653 | DP35: =+DP34+DO35-DQ35 -> 7667278.1 | DQ35: 283973.26 | DR35: 116574.18 | DS35: =+SUM(DQ35:DR35) -> 400547.44 | EA35: 10 | EB35: =+EOMONTH(EC35,0) -> 46691 | EC35: 46665 | EE35: =+EE34-EF35 -> 908369.04 | EF35: 39494.31 | EG35: =+EE34*(EC35-EC34)*$EE$5/360 -> 14097.888 | EH35: =+SUM(EF35:EG35) -> 53592.198 | EY35: 10 | EZ35: =+EOMONTH(FA35,0) -> 46568 | FA35: 46562 | FC35: =+FC34+FB35-FD35 -> 2623814.1 | FD35: 40216.85 | FE35: 16452.55 | FG35: =+SUM(FD35:FF35) -> 56669.4 | FI35: 10 | FJ35: =+EOMONTH(FK35,0) -> 46568 | FK35: 46552 | FM35: =+FM34-FN35 -> 0.0040000001 | FN35: 10293.84 | FO35: 0 | FP35: =+SUM(FN35:FO35) -> 10293.84 | FR35: 10 | FS35: =+EOMONTH(FT35,0) -> 46568 | FT35: 46552 | FV35: =+FV34-FW35 -> 0.0040000001 | FW35: 10293.84 | FX35: 0 | FY35: =+SUM(FW35:FX35) -> 10293.84 | GA35: 10 | GB35: =+EOMONTH(GC35,0) -> 46568 | GC35: 46552 | GE35: =+GE34-GF35 -> 0.0040000001 | GF35: 10293.84 | GG35: 0 | GH35: =+SUM(GF35:GG35) -> 10293.84 | GJ35: 10 | GK35: =+EOMONTH(GL35,0) -> 46568 | GL35: 46552 | GN35: =+GN34-GO35 -> 0.0040000001 | GO35: 10293.84 | GP35: 0 | GQ35: =+SUM(GO35:GP35) -> 10293.84 | GS35: 10 | GT35: =+EOMONTH(GU35,0) -> 46630 | GU35: 46624 | GW35: =+GW34-GX35 -> 40596.5 | GX35: 29683.03 | GY35: 12324.06 | GZ35: =+SUM(GX35:GY35) -> 42007.09 | HB35: 10 | HC35: =+EOMONTH(HD35,0) -> 46630 | HD35: 46624 | HF35: 40596.5 | HG35: 29683.03 | HH35: 12324.06 | HI35: 42007.09
A36: 11 | B36: =+WEEKNUM(C36,2) -> 40 | C36: =+C35+1 -> 45935 | E36: =+E35+D36-F36 -> 57451130 | F36: =+SUMIF(O:O,C36,R:R)+SUMIF(AE:AE,C36,AH:AH)+SUMIF(AT:AT,C36,AW:AW)+SUMIF(BI:BI,C36,BL:BL)+SUMIF(BY:BY,C36,CB:CB)+SUMIF(BY:BY,C36,CC:CC)+SUMIF(CP:CP,C36,CS:CS)+SUMIF(CY:CY,C36,DB:DB)+SUMIF(DN:DN,C36,DQ:DQ)+SUMIF(EC:EC,C36,EF:EF)+SUMIF(ER:ER,C36,EU:EU)+SUMIF(FA:FA,C36,FD:FD)+SUMIF(FK:FK,C36,FN:FN)+SUMIF(FT:FT,C36,FW:FW)+SUMIF(GC:GC,C36,GF:GF)+SUMIF(GL:GL,C36,GO:GO)+SUMIF(GU:GU,C36,GX:GX)+SUMIF(HD:HD,C36,HG:HG) -> 0 | G36: =+SUMIF(O:O,C36,T:T)+SUMIF(O:O,C36,S:S)+SUMIF(AE:AE,C36,AI:AI)+SUMIF(AT:AT,C36,AX:AX)+SUMIF(BI:BI,C36,BN:BN)+SUMIF(BI:BI,C36,BM:BM)+SUMIF(BY:BY,C36,CD:CD)+SUMIF(BY:BY,C36,CE:CE)+SUMIF(CP:CP,C36,CT:CT)+SUMIF(CY:CY,C36,DC:DC)+SUMIF(DN:DN,C36,DR:DR)+SUMIF(EC:EC,C36,EG:EG)+SUMIF(ER:ER,C36,EV:EV)+SUMIF(FA:FA,C36,FE:FE)+SUMIF(FK:FK,C36,FO:FO)+SUMIF(FT:FT,C36,FX:FX)+SUMIF(GC:GC,C36,GG:GG)+SUMIF(GL:GL,C36,GP:GP)+SUMIF(GU:GU,C36,GY:GY)+SUMIF(HD:HD,C36,HH:HH) -> 0 | H36: =+SUM(F36:G36) -> 0 | M36: 11 | N36: =+EOMONTH(O36,0) -> 46538 | O36: =+DATE(YEAR(O35),MONTH(O35)+3,DAY(O35)) -> 46522 | Q36: =+Q35-R36 -> 77386960 | R36: =+$Q$30/25 -> 4072997.9 | S36: =+Q35*Q$5*(O36-O35)/360 -> 1208322.7 | T36: =+$Q$17/$Q$18 -> 471550.55 | U36: =+SUM(R36:T36) -> 5752871.1 | AC36: 11 | AD36: =+EOMONTH(AE36,0) -> 46721 | AE36: 46693 | AG36: =+AG35+AF36-AH36 -> 775340.82 | AH36: =+AH35 -> 51840.79 | AI36: =+AG35*AG$5*(AE36-AE35)/360 -> 11626.497 | AJ36: =+SUM(AH36:AI36) -> 63467.287 | AR36: 11 | AS36: =+EOMONTH(AT36,0) -> 46630 | AT36: 46619 | AV36: =+AV35+AU36-AW36 -> 13371279 | AW36: 525047.46 | AX36: =+AV35*AV$5*(AT36-AT35)/360 -> 213077 | AY36: =+SUM(AW36:AX36) -> 738124.47 | BG36: 11 | BH36: =+EOMONTH(BI36,0) -> 46752 | BI36: 46741 | BK36: =+BK35+BJ36-BL36 -> 16990646 | BL36: =+BL35 -> 4247661.4 | BM36: =+BK35*BK$5*(BI36-BI35)/360 -> 322114.32 | BN36: 82616.23 | BO36: =+SUM(BL36:BN36) -> 4652392 | BW36: 11 | BX36: =+EOMONTH(BY36,0) -> 46691 | BY36: 46680 | CA36: =+CA35+BZ36-CB36 -> 519628.22 | CB36: 57736.47 | CC36: 2821.4285 | CD36: =+CA35*CA$5*(BY36-BY35)/360 -> 8852.9252 | CE36: 1642.8395 | CF36: =+SUM(CB36:CE36) -> 71053.663 | CN36: 11 | CO36: =+EOMONTH(CP36,0) -> 46752 | CP36: 46735 | CR36: =+CR35+CQ36-CS36 -> 730225.11 | CS36: 104317.86 | CT36: 9492.9269 | CU36: =+SUM(CS36:CT36) -> 113810.79 | CW36: 11 | CX36: =+EOMONTH(CY36,0) -> 46203 | CY36: 46183 | DA36: =+DA35+CZ36-DB36 -> 22170937 | DB36: 349011.21 | DC36: =+DA35*DA$5*(CY36-CY35)/360 -> 116353.07 | DD36: =+SUM(DB36:DC36) -> 465364.28 | DL36: 11 | DM36: =+EOMONTH(DN36,0) -> 46752 | DN36: 46744 | DP36: =+DP35+DO36-DQ36 -> 7383304.8 | DQ36: 283973.26 | DR36: 112410.82 | DS36: =+SUM(DQ36:DR36) -> 396384.08 | EA36: 11 | EB36: =+EOMONTH(EC36,0) -> 46783 | EC36: 46757 | EE36: =+EE35-EF36 -> 868874.73 | EF36: 39494.31 | EG36: =+EE35*(EC36-EC35)*$EE$5/360 -> 13510.476 | EH36: =+SUM(EF36:EG36) -> 53004.786 | EY36: 11 | EZ36: =+EOMONTH(FA36,0) -> 46660 | FA36: 46653 | FC36: =+FC35+FB36-FD36 -> 2583597.2 | FD36: 40216.85 | FE36: 15843.61 | FG36: =+SUM(FD36:FF36) -> 56060.46 | GS36: 11 | GT36: =+EOMONTH(GU36,0) -> 46721 | GU36: 46714 | GW36: =+GW35-GX36 -> 10293.84 | GX36: 30302.66 | GY36: 16975.03 | GZ36: =+SUM(GX36:GY36) -> 47277.69 | HB36: 11 | HC36: =+EOMONTH(HD36,0) -> 46721 | HD36: 46714 | HF36: 10293.84 | HG36: 30302.66 | HH36: 16975.03 | HI36: 47277.69
A37: 12 | B37: =+WEEKNUM(C37,2) -> 41 | C37: =+C36+1 -> 45936 | E37: =+E36+D37-F37 -> 57451130 | F37: =+SUMIF(O:O,C37,R:R)+SUMIF(AE:AE,C37,AH:AH)+SUMIF(AT:AT,C37,AW:AW)+SUMIF(BI:BI,C37,BL:BL)+SUMIF(BY:BY,C37,CB:CB)+SUMIF(BY:BY,C37,CC:CC)+SUMIF(CP:CP,C37,CS:CS)+SUMIF(CY:CY,C37,DB:DB)+SUMIF(DN:DN,C37,DQ:DQ)+SUMIF(EC:EC,C37,EF:EF)+SUMIF(ER:ER,C37,EU:EU)+SUMIF(FA:FA,C37,FD:FD)+SUMIF(FK:FK,C37,FN:FN)+SUMIF(FT:FT,C37,FW:FW)+SUMIF(GC:GC,C37,GF:GF)+SUMIF(GL:GL,C37,GO:GO)+SUMIF(GU:GU,C37,GX:GX)+SUMIF(HD:HD,C37,HG:HG) -> 0 | G37: =+SUMIF(O:O,C37,T:T)+SUMIF(O:O,C37,S:S)+SUMIF(AE:AE,C37,AI:AI)+SUMIF(AT:AT,C37,AX:AX)+SUMIF(BI:BI,C37,BN:BN)+SUMIF(BI:BI,C37,BM:BM)+SUMIF(BY:BY,C37,CD:CD)+SUMIF(BY:BY,C37,CE:CE)+SUMIF(CP:CP,C37,CT:CT)+SUMIF(CY:CY,C37,DC:DC)+SUMIF(DN:DN,C37,DR:DR)+SUMIF(EC:EC,C37,EG:EG)+SUMIF(ER:ER,C37,EV:EV)+SUMIF(FA:FA,C37,FE:FE)+SUMIF(FK:FK,C37,FO:FO)+SUMIF(FT:FT,C37,FX:FX)+SUMIF(GC:GC,C37,GG:GG)+SUMIF(GL:GL,C37,GP:GP)+SUMIF(GU:GU,C37,GY:GY)+SUMIF(HD:HD,C37,HH:HH) -> 17581.472 | H37: =+SUM(F37:G37) -> 17581.472 | I37: 0 | J37: BDP | M37: 12 | N37: =+EOMONTH(O37,0) -> 46630 | O37: =+DATE(YEAR(O36),MONTH(O36)+3,DAY(O36)) -> 46614 | Q37: =+Q36-R37 -> 73313962 | R37: =+$Q$30/25 -> 4072997.9 | S37: =+Q36*Q$5*(O37-O36)/360 -> 1186600 | T37: =+$Q$17/$Q$18 -> 471550.55 | U37: =+SUM(R37:T37) -> 5731148.5 | AC37: 12 | AD37: =+EOMONTH(AE37,0) -> 46812 | AE37: 46785 | AG37: =+AG36+AF37-AH37 -> 723500.03 | AH37: =+AH36 -> 51840.79 | AI37: =+AG36*AG$5*(AE37-AE36)/360 -> 10897.846 | AJ37: =+SUM(AH37:AI37) -> 62738.636 | AR37: 12 | AS37: =+EOMONTH(AT37,0) -> 46721 | AT37: 46711 | AV37: =+AV36+AU37-AW37 -> 12846231 | AW37: 525047.46 | AX37: =+AV36*AV$5*(AT37-AT36)/360 -> 205026.27 | AY37: =+SUM(AW37:AX37) -> 730073.74 | BG37: 12 | BH37: =+EOMONTH(BI37,0) -> 46843 | BI37: 46832 | BK37: =+BK36+BJ37-BL37 -> 12742984 | BL37: =+BL36 -> 4247661.4 | BM37: =+BK36*BK$5*(BI37-BI36)/360 -> 257691.46 | BN37: 82616.23 | BO37: =+SUM(BL37:BN37) -> 4587969.1 | BW37: 12 | BX37: =+EOMONTH(BY37,0) -> 46783 | BY37: 46772 | CA37: =+CA36+BZ37-CB37 -> 461891.75 | CB37: 57736.47 | CC37: 2821.4285 | CD37: =+CA36*CA$5*(BY37-BY36)/360 -> 7967.6327 | CE37: 1642.8395 | CF37: =+SUM(CB37:CE37) -> 70168.371 | CN37: 12 | CO37: =+EOMONTH(CP37,0) -> 46843 | CP37: 46826 | CR37: =+CR36+CQ37-CS37 -> 625907.25 | CS37: 104317.86 | CT37: 7910.7727 | CU37: =+SUM(CS37:CT37) -> 112228.63 | CW37: 12 | CX37: =+EOMONTH(CY37,0) -> 46234 | CY37: 46213 | DA37: =+DA36+CZ37-DB37 -> 20587299 | DB37: 1583638.4 | DC37: =+DA36*DA$5*(CY37-CY36)/360 -> 110854.69 | DD37: =+SUM(DB37:DC37) -> 1694493.1 | DL37: 12 | DM37: =+EOMONTH(DN37,0) -> 46843 | DN37: 46835 | DP37: =+DP36+DO37-DQ37 -> 7099331.5 | DQ37: 283973.26 | DR37: 108247.45 | DS37: =+SUM(DQ37:DR37) -> 392220.71 | EA37: 12 | EB37: =+EOMONTH(EC37,0) -> 46873 | EC37: 46848 | EE37: =+EE36-EF37 -> 829380.42 | EF37: 39494.31 | EG37: =+EE36*(EC37-EC36)*$EE$5/360 -> 12782.595 | EH37: =+SUM(EF37:EG37) -> 52276.905 | EY37: 12 | EZ37: =+EOMONTH(FA37,0) -> 46752 | FA37: 46744 | FC37: =+FC36+FB37-FD37 -> 2543380.4 | FD37: 40216.85 | FE37: 15234.68 | FG37: =+SUM(FD37:FF37) -> 55451.53 | GS37: 12 | GT37: =+EOMONTH(GU37,0) -> 46721 | GU37: 46714 | GW37: =+GW36-GX37 -> 4.3655746e-11 | GX37: 10293.84 | GZ37: =+SUM(GX37:GY37) -> 10293.84 | HB37: 12 | HC37: =+EOMONTH(HD37,0) -> 46721 | HD37: 46714 | HF37: 4.3655746e-11 | HG37: 10293.84 | HI37: 10293.84
A38: 13 | B38: =+WEEKNUM(C38,2) -> 41 | C38: =+C37+1 -> 45937 | E38: =+E37+D38-F38 -> 57451130 | F38: =+SUMIF(O:O,C38,R:R)+SUMIF(AE:AE,C38,AH:AH)+SUMIF(AT:AT,C38,AW:AW)+SUMIF(BI:BI,C38,BL:BL)+SUMIF(BY:BY,C38,CB:CB)+SUMIF(BY:BY,C38,CC:CC)+SUMIF(CP:CP,C38,CS:CS)+SUMIF(CY:CY,C38,DB:DB)+SUMIF(DN:DN,C38,DQ:DQ)+SUMIF(EC:EC,C38,EF:EF)+SUMIF(ER:ER,C38,EU:EU)+SUMIF(FA:FA,C38,FD:FD)+SUMIF(FK:FK,C38,FN:FN)+SUMIF(FT:FT,C38,FW:FW)+SUMIF(GC:GC,C38,GF:GF)+SUMIF(GL:GL,C38,GO:GO)+SUMIF(GU:GU,C38,GX:GX)+SUMIF(HD:HD,C38,HG:HG) -> 0 | G38: =+SUMIF(O:O,C38,T:T)+SUMIF(O:O,C38,S:S)+SUMIF(AE:AE,C38,AI:AI)+SUMIF(AT:AT,C38,AX:AX)+SUMIF(BI:BI,C38,BN:BN)+SUMIF(BI:BI,C38,BM:BM)+SUMIF(BY:BY,C38,CD:CD)+SUMIF(BY:BY,C38,CE:CE)+SUMIF(CP:CP,C38,CT:CT)+SUMIF(CY:CY,C38,DC:DC)+SUMIF(DN:DN,C38,DR:DR)+SUMIF(EC:EC,C38,EG:EG)+SUMIF(ER:ER,C38,EV:EV)+SUMIF(FA:FA,C38,FE:FE)+SUMIF(FK:FK,C38,FO:FO)+SUMIF(FT:FT,C38,FX:FX)+SUMIF(GC:GC,C38,GG:GG)+SUMIF(GL:GL,C38,GP:GP)+SUMIF(GU:GU,C38,GY:GY)+SUMIF(HD:HD,C38,HH:HH) -> 0 | H38: =+SUM(F38:G38) -> 0 | M38: 13 | N38: =+EOMONTH(O38,0) -> 46721 | O38: =+DATE(YEAR(O37),MONTH(O37)+3,DAY(O37)) -> 46706 | Q38: =+Q37-R38 -> 69240964 | R38: =+$Q$30/25 -> 4072997.9 | S38: =+Q37*Q$5*(O38-O37)/360 -> 1124147.4 | T38: =+$Q$17/$Q$18 -> 471550.55 | U38: =+SUM(R38:T38) -> 5668695.8 | AC38: 13 | AD38: =+EOMONTH(AE38,0) -> 46904 | AE38: 46875 | AG38: =+AG37+AF38-AH38 -> 671659.24 | AH38: =+AH37 -> 51840.79 | AI38: =+AG37*AG$5*(AE38-AE37)/360 -> 9948.1254 | AJ38: =+SUM(AH38:AI38) -> 61788.915 | AR38: 13 | AS38: =+EOMONTH(AT38,0) -> 46812 | AT38: 46803 | AV38: =+AV37+AU38-AW38 -> 12321184 | AW38: 525047.46 | AX38: =+AV37*AV$5*(AT38-AT37)/360 -> 196975.55 | AY38: =+SUM(AW38:AX38) -> 722023.01 | BG38: 13 | BH38: =+EOMONTH(BI38,0) -> 46934 | BI38: 46924 | BK38: =+BK37+BJ38-BL38 -> 8495322.8 | BL38: =+BL37 -> 4247661.4 | BM38: =+BK37*BK$5*(BI38-BI37)/360 -> 195392.42 | BN38: 82616.23 | BO38: =+SUM(BL38:BN38) -> 4525670.1 | BW38: 13 | BX38: =+EOMONTH(BY38,0) -> 46873 | BY38: 46863 | CA38: =+CA37+BZ38-CB38 -> 404155.28 | CB38: 57736.47 | CC38: 2821.4285 | CD38: =+CA37*CA$5*(BY38-BY37)/360 -> 7005.3582 | CE38: 1642.8395 | CF38: =+SUM(CB38:CE38) -> 69206.096 | CN38: 13 | CO38: =+EOMONTH(CP38,0) -> 46934 | CP38: 46918 | CR38: =+CR37+CQ38-CS38 -> 521589.39 | CS38: 104317.86 | CT38: 6398.1638 | CU38: =+SUM(CS38:CT38) -> 110716.02 | CW38: 13 | CX38: =+EOMONTH(CY38,0) -> 46265 | CY38: 46244 | DA38: =+DA37+CZ38-DB38 -> 19003661 | DB38: 1583638.4 | DC38: =+DA37*DA$5*(CY38-CY37)/360 -> 106367.71 | DD38: =+SUM(DB38:DC38) -> 1690006.1 | DL38: 13 | DM38: =+EOMONTH(DN38,0) -> 46934 | DN38: 46926 | DP38: =+DP37+DO38-DQ38 -> 6815358.3 | DQ38: 283973.26 | DR38: 104084.09 | DS38: =+SUM(DQ38:DR38) -> 388057.35 | EA38: 13 | EB38: =+EOMONTH(EC38,0) -> 46965 | EC38: 46939 | EE38: =+EE37-EF38 -> 789886.11 | EF38: 39494.31 | EG38: =+EE37*(EC38-EC37)*$EE$5/360 -> 12201.568 | EH38: =+SUM(EF38:EG38) -> 51695.878 | EY38: 13 | EZ38: =+EOMONTH(FA38,0) -> 46843 | FA38: 46835 | FC38: =+FC37+FB38-FD38 -> 2503163.5 | FD38: 40216.85 | FE38: 14625.74 | FG38: =+SUM(FD38:FF38) -> 54842.59
A39: 14 | B39: =+WEEKNUM(C39,2) -> 41 | C39: =+C38+1 -> 45938 | E39: =+E38+D39-F39 -> 57451130 | F39: =+SUMIF(O:O,C39,R:R)+SUMIF(AE:AE,C39,AH:AH)+SUMIF(AT:AT,C39,AW:AW)+SUMIF(BI:BI,C39,BL:BL)+SUMIF(BY:BY,C39,CB:CB)+SUMIF(BY:BY,C39,CC:CC)+SUMIF(CP:CP,C39,CS:CS)+SUMIF(CY:CY,C39,DB:DB)+SUMIF(DN:DN,C39,DQ:DQ)+SUMIF(EC:EC,C39,EF:EF)+SUMIF(ER:ER,C39,EU:EU)+SUMIF(FA:FA,C39,FD:FD)+SUMIF(FK:FK,C39,FN:FN)+SUMIF(FT:FT,C39,FW:FW)+SUMIF(GC:GC,C39,GF:GF)+SUMIF(GL:GL,C39,GO:GO)+SUMIF(GU:GU,C39,GX:GX)+SUMIF(HD:HD,C39,HG:HG) -> 0 | G39: =+SUMIF(O:O,C39,T:T)+SUMIF(O:O,C39,S:S)+SUMIF(AE:AE,C39,AI:AI)+SUMIF(AT:AT,C39,AX:AX)+SUMIF(BI:BI,C39,BN:BN)+SUMIF(BI:BI,C39,BM:BM)+SUMIF(BY:BY,C39,CD:CD)+SUMIF(BY:BY,C39,CE:CE)+SUMIF(CP:CP,C39,CT:CT)+SUMIF(CY:CY,C39,DC:DC)+SUMIF(DN:DN,C39,DR:DR)+SUMIF(EC:EC,C39,EG:EG)+SUMIF(ER:ER,C39,EV:EV)+SUMIF(FA:FA,C39,FE:FE)+SUMIF(FK:FK,C39,FO:FO)+SUMIF(FT:FT,C39,FX:FX)+SUMIF(GC:GC,C39,GG:GG)+SUMIF(GL:GL,C39,GP:GP)+SUMIF(GU:GU,C39,GY:GY)+SUMIF(HD:HD,C39,HH:HH) -> 0 | H39: =+SUM(F39:G39) -> 0 | M39: 14 | N39: =+EOMONTH(O39,0) -> 46812 | O39: =+DATE(YEAR(O38),MONTH(O38)+3,DAY(O38)) -> 46798 | Q39: =+Q38-R39 -> 65167966 | R39: =+$Q$30/25 -> 4072997.9 | S39: =+Q38*Q$5*(O39-O38)/360 -> 1061694.8 | T39: =+$Q$17/$Q$18 -> 471550.55 | U39: =+SUM(R39:T39) -> 5606243.2 | AC39: 14 | AD39: =+EOMONTH(AE39,0) -> 46996 | AE39: 46967 | AG39: =+AG38+AF39-AH39 -> 619818.45 | AH39: =+AH38 -> 51840.79 | AI39: =+AG38*AG$5*(AE39-AE38)/360 -> 9440.5438 | AJ39: =+SUM(AH39:AI39) -> 61281.334 | AR39: 14 | AS39: =+EOMONTH(AT39,0) -> 46904 | AT39: 46893 | AV39: =+AV38+AU39-AW39 -> 11796136 | AW39: 525047.46 | AX39: =+AV38*AV$5*(AT39-AT38)/360 -> 184817.76 | AY39: =+SUM(AW39:AX39) -> 709865.22 | BG39: 14 | BH39: =+EOMONTH(BI39,0) -> 47026 | BI39: 47016 | BK39: =+BK38+BJ39-BL39 -> 4247661.4 | BL39: =+BL38 -> 4247661.4 | BM39: =+BK38*BK$5*(BI39-BI38)/360 -> 130261.62 | BN39: 82616.23 | BO39: =+SUM(BL39:BN39) -> 4460539.2 | BW39: 14 | BX39: =+EOMONTH(BY39,0) -> 46965 | BY39: 46954 | CA39: =+CA38+BZ39-CB39 -> 346418.81 | CB39: 57736.47 | CC39: 2821.4285 | CD39: =+CA38*CA$5*(BY39-BY38)/360 -> 6129.6884 | CE39: 1642.8395 | CF39: =+SUM(CB39:CE39) -> 68330.426 | CN39: 14 | CO39: =+EOMONTH(CP39,0) -> 47026 | CP39: 47010 | CR39: =+CR38+CQ39-CS39 -> 417271.53 | CS39: 104317.86 | CT39: 4798.6232 | CU39: =+SUM(CS39:CT39) -> 109116.48 | CW39: 14 | CX39: =+EOMONTH(CY39,0) -> 46295 | CY39: 46275 | DA39: =+DA38+CZ39-DB39 -> 17420022 | DB39: 1583638.4 | DC39: =+DA38*DA$5*(CY39-CY38)/360 -> 98185.58 | DD39: =+SUM(DB39:DC39) -> 1681824 | DL39: 14 | DM39: =+EOMONTH(DN39,0) -> 47026 | DN39: 47017 | DP39: =+DP38+DO39-DQ39 -> 6531385 | DQ39: 283973.26 | DR39: 99920.72 | DS39: =+SUM(DQ39:DR39) -> 383893.98 | EA39: 14 | EB39: =+EOMONTH(EC39,0) -> 47057 | EC39: 47031 | EE39: =+EE38-EF39 -> 750391.8 | EF39: 39494.31 | EG39: =+EE38*(EC39-EC38)*$EE$5/360 -> 11748.239 | EH39: =+SUM(EF39:EG39) -> 51242.549 | EY39: 14 | EZ39: =+EOMONTH(FA39,0) -> 46934 | FA39: 46926 | FC39: =+FC38+FB39-FD39 -> 2462946.7 | FD39: 40216.85 | FE39: 14016.8 | FG39: =+SUM(FD39:FF39) -> 54233.65
A40: 15 | B40: =+WEEKNUM(C40,2) -> 41 | C40: =+C39+1 -> 45939 | E40: =+E39+D40-F40 -> 57451130 | F40: =+SUMIF(O:O,C40,R:R)+SUMIF(AE:AE,C40,AH:AH)+SUMIF(AT:AT,C40,AW:AW)+SUMIF(BI:BI,C40,BL:BL)+SUMIF(BY:BY,C40,CB:CB)+SUMIF(BY:BY,C40,CC:CC)+SUMIF(CP:CP,C40,CS:CS)+SUMIF(CY:CY,C40,DB:DB)+SUMIF(DN:DN,C40,DQ:DQ)+SUMIF(EC:EC,C40,EF:EF)+SUMIF(ER:ER,C40,EU:EU)+SUMIF(FA:FA,C40,FD:FD)+SUMIF(FK:FK,C40,FN:FN)+SUMIF(FT:FT,C40,FW:FW)+SUMIF(GC:GC,C40,GF:GF)+SUMIF(GL:GL,C40,GO:GO)+SUMIF(GU:GU,C40,GX:GX)+SUMIF(HD:HD,C40,HG:HG) -> 0 | G40: =+SUMIF(O:O,C40,T:T)+SUMIF(O:O,C40,S:S)+SUMIF(AE:AE,C40,AI:AI)+SUMIF(AT:AT,C40,AX:AX)+SUMIF(BI:BI,C40,BN:BN)+SUMIF(BI:BI,C40,BM:BM)+SUMIF(BY:BY,C40,CD:CD)+SUMIF(BY:BY,C40,CE:CE)+SUMIF(CP:CP,C40,CT:CT)+SUMIF(CY:CY,C40,DC:DC)+SUMIF(DN:DN,C40,DR:DR)+SUMIF(EC:EC,C40,EG:EG)+SUMIF(ER:ER,C40,EV:EV)+SUMIF(FA:FA,C40,FE:FE)+SUMIF(FK:FK,C40,FO:FO)+SUMIF(FT:FT,C40,FX:FX)+SUMIF(GC:GC,C40,GG:GG)+SUMIF(GL:GL,C40,GP:GP)+SUMIF(GU:GU,C40,GY:GY)+SUMIF(HD:HD,C40,HH:HH) -> 0 | H40: =+SUM(F40:G40) -> 0 | M40: 15 | N40: =+EOMONTH(O40,0) -> 46904 | O40: =+DATE(YEAR(O39),MONTH(O39)+3,DAY(O39)) -> 46888 | Q40: =+Q39-R40 -> 61094968 | R40: =+$Q$30/25 -> 4072997.9 | S40: =+Q39*Q$5*(O40-O39)/360 -> 977519.49 | T40: =+$Q$17/$Q$18 -> 471550.55 | U40: =+SUM(R40:T40) -> 5522067.9 | AC40: 15 | AD40: =+EOMONTH(AE40,0) -> 47087 | AE40: 47059 | AG40: =+AG39+AF40-AH40 -> 567977.66 | AH40: =+AH39 -> 51840.79 | AI40: =+AG39*AG$5*(AE40-AE39)/360 -> 8711.8927 | AJ40: =+SUM(AH40:AI40) -> 60552.683 | AR40: 15 | AS40: =+EOMONTH(AT40,0) -> 46996 | AT40: 46985 | AV40: =+AV39+AU40-AW40 -> 11271089 | AW40: 525047.46 | AX40: =+AV39*AV$5*(AT40-AT39)/360 -> 180874.09 | AY40: =+SUM(AW40:AX40) -> 705921.56 | BG40: 15 | BH40: =+EOMONTH(BI40,0) -> 47118 | BI40: 47107 | BK40: =+BK39+BJ40-BL40 -> 0 | BL40: =+BL39 -> 4247661.4 | BM40: =+BK39*BK$5*(BI40-BI39)/360 -> 64422.865 | BN40: 82616.23 | BO40: =+SUM(BL40:BN40) -> 4394700.5 | BW40: 15 | BX40: =+EOMONTH(BY40,0) -> 47057 | BY40: 47046 | CA40: =+CA39+BZ40-CB40 -> 288682.34 | CB40: 57736.47 | CC40: 2821.4285 | CD40: =+CA39*CA$5*(BY40-BY39)/360 -> 5311.7551 | CE40: 1642.8395 | CF40: =+SUM(CB40:CE40) -> 67512.493 | CN40: 15 | CO40: =+EOMONTH(CP40,0) -> 47118 | CP40: 47101 | CR40: =+CR39+CQ40-CS40 -> 312953.67 | CS40: 104317.86 | CT40: 3164.3101 | CU40: =+SUM(CS40:CT40) -> 107482.17 | CW40: 15 | CX40: =+EOMONTH(CY40,0) -> 46326 | CY40: 46305 | DA40: =+DA39+CZ40-DB40 -> 15836384 | DB40: 1583638.4 | DC40: =+DA39*DA$5*(CY40-CY39)/360 -> 87100.111 | DD40: =+SUM(DB40:DC40) -> 1670738.5 | DL40: 15 | DM40: =+EOMONTH(DN40,0) -> 47118 | DN40: 47108 | DP40: =+DP39+DO40-DQ40 -> 6247411.8 | DQ40: 283973.26 | DR40: 95757.36 | DS40: =+SUM(DQ40:DR40) -> 379730.62 | EA40: 15 | EB40: =+EOMONTH(EC40,0) -> 47149 | EC40: 47123 | EE40: =+EE39-EF40 -> 710897.49 | EF40: 39494.31 | EG40: =+EE39*(EC40-EC39)*$EE$5/360 -> 11160.827 | EH40: =+SUM(EF40:EG40) -> 50655.137 | EY40: 15 | EZ40: =+EOMONTH(FA40,0) -> 47026 | FA40: 47017 | FC40: =+FC39+FB40-FD40 -> 2422729.8 | FD40: 40216.85 | FE40: 13407.86 | FG40: =+SUM(FD40:FF40) -> 53624.71
A41: 16 | B41: =+WEEKNUM(C41,2) -> 41 | C41: =+C40+1 -> 45940 | E41: =+E40+D41-F41 -> 57102119 | F41: =+SUMIF(O:O,C41,R:R)+SUMIF(AE:AE,C41,AH:AH)+SUMIF(AT:AT,C41,AW:AW)+SUMIF(BI:BI,C41,BL:BL)+SUMIF(BY:BY,C41,CB:CB)+SUMIF(BY:BY,C41,CC:CC)+SUMIF(CP:CP,C41,CS:CS)+SUMIF(CY:CY,C41,DB:DB)+SUMIF(DN:DN,C41,DQ:DQ)+SUMIF(EC:EC,C41,EF:EF)+SUMIF(ER:ER,C41,EU:EU)+SUMIF(FA:FA,C41,FD:FD)+SUMIF(FK:FK,C41,FN:FN)+SUMIF(FT:FT,C41,FW:FW)+SUMIF(GC:GC,C41,GF:GF)+SUMIF(GL:GL,C41,GO:GO)+SUMIF(GU:GU,C41,GX:GX)+SUMIF(HD:HD,C41,HG:HG) -> 349011.21 | G41: =+SUMIF(O:O,C41,T:T)+SUMIF(O:O,C41,S:S)+SUMIF(AE:AE,C41,AI:AI)+SUMIF(AT:AT,C41,AX:AX)+SUMIF(BI:BI,C41,BN:BN)+SUMIF(BI:BI,C41,BM:BM)+SUMIF(BY:BY,C41,CD:CD)+SUMIF(BY:BY,C41,CE:CE)+SUMIF(CP:CP,C41,CT:CT)+SUMIF(CY:CY,C41,DC:DC)+SUMIF(DN:DN,C41,DR:DR)+SUMIF(EC:EC,C41,EG:EG)+SUMIF(ER:ER,C41,EV:EV)+SUMIF(FA:FA,C41,FE:FE)+SUMIF(FK:FK,C41,FO:FO)+SUMIF(FT:FT,C41,FX:FX)+SUMIF(GC:GC,C41,GG:GG)+SUMIF(GL:GL,C41,GP:GP)+SUMIF(GU:GU,C41,GY:GY)+SUMIF(HD:HD,C41,HH:HH) -> 126560.19 | H41: =+SUM(F41:G41) -> 475571.4 | I41: 0 | J41: GANADERO | M41: 16 | N41: =+EOMONTH(O41,0) -> 46996 | O41: =+DATE(YEAR(O40),MONTH(O40)+3,DAY(O40)) -> 46980 | Q41: =+Q40-R41 -> 57021970 | R41: =+$Q$30/25 -> 4072997.9 | S41: =+Q40*Q$5*(O41-O40)/360 -> 936789.51 | T41: =+$Q$17/$Q$18 -> 471550.55 | U41: =+SUM(R41:T41) -> 5481337.9 | AC41: 16 | AD41: =+EOMONTH(AE41,0) -> 47177 | AE41: 47151 | AG41: =+AG40+AF41-AH41 -> 516136.87 | AH41: =+AH40 -> 51840.79 | AI41: =+AG40*AG$5*(AE41-AE40)/360 -> 7983.2416 | AJ41: =+SUM(AH41:AI41) -> 59824.032 | AR41: 16 | AS41: =+EOMONTH(AT41,0) -> 47087 | AT41: 47077 | AV41: =+AV40+AU41-AW41 -> 10746041 | AW41: 525047.46 | AX41: =+AV40*AV$5*(AT41-AT40)/360 -> 172823.36 | AY41: =+SUM(AW41:AX41) -> 697870.83 | BW41: 16 | BX41: =+EOMONTH(BY41,0) -> 47149 | BY41: 47138 | CA41: =+CA40+BZ41-CB41 -> 230945.87 | CB41: 57736.47 | CC41: 2821.4285 | CD41: =+CA40*CA$5*(BY41-BY40)/360 -> 4426.4625 | CE41: 1642.8395 | CF41: =+SUM(CB41:CE41) -> 66627.201 | CN41: 16 | CO41: =+EOMONTH(CP41,0) -> 47208 | CP41: 47191 | CR41: =+CR40+CQ41-CS41 -> 208635.7 | CS41: 104317.97 | CT41: 1564.7695 | CU41: =+SUM(CS41:CT41) -> 105882.74 | CW41: 16 | CX41: =+EOMONTH(CY41,0) -> 46356 | CY41: 46336 | DA41: =+DA40+CZ41-DB41 -> 14252745 | DB41: 1583638.4 | DC41: =+DA40*DA$5*(CY41-CY40)/360 -> 81821.317 | DD41: =+SUM(DB41:DC41) -> 1665459.7 | DL41: 16 | DM41: =+EOMONTH(DN41,0) -> 47208 | DN41: 47199 | DP41: =+DP40+DO41-DQ41 -> 5963438.5 | DQ41: 283973.26 | DR41: 91594 | DS41: =+SUM(DQ41:DR41) -> 375567.26 | EA41: 16 | EB41: =+EOMONTH(EC41,0) -> 47238 | EC41: 47213 | EE41: =+EE40-EF41 -> 671403.18 | EF41: 39494.31 | EG41: =+EE40*(EC41-EC40)*$EE$5/360 -> 10343.559 | EH41: =+SUM(EF41:EG41) -> 49837.869 | EY41: 16 | EZ41: =+EOMONTH(FA41,0) -> 47118 | FA41: 47108 | FC41: =+FC40+FB41-FD41 -> 2382513 | FD41: 40216.85 | FE41: 12798.92 | FG41: =+SUM(FD41:FF41) -> 53015.77
A42: 17 | B42: =+WEEKNUM(C42,2) -> 41 | C42: =+C41+1 -> 45941 | E42: =+E41+D42-F42 -> 57102119 | F42: =+SUMIF(O:O,C42,R:R)+SUMIF(AE:AE,C42,AH:AH)+SUMIF(AT:AT,C42,AW:AW)+SUMIF(BI:BI,C42,BL:BL)+SUMIF(BY:BY,C42,CB:CB)+SUMIF(BY:BY,C42,CC:CC)+SUMIF(CP:CP,C42,CS:CS)+SUMIF(CY:CY,C42,DB:DB)+SUMIF(DN:DN,C42,DQ:DQ)+SUMIF(EC:EC,C42,EF:EF)+SUMIF(ER:ER,C42,EU:EU)+SUMIF(FA:FA,C42,FD:FD)+SUMIF(FK:FK,C42,FN:FN)+SUMIF(FT:FT,C42,FW:FW)+SUMIF(GC:GC,C42,GF:GF)+SUMIF(GL:GL,C42,GO:GO)+SUMIF(GU:GU,C42,GX:GX)+SUMIF(HD:HD,C42,HG:HG) -> 0 | G42: =+SUMIF(O:O,C42,T:T)+SUMIF(O:O,C42,S:S)+SUMIF(AE:AE,C42,AI:AI)+SUMIF(AT:AT,C42,AX:AX)+SUMIF(BI:BI,C42,BN:BN)+SUMIF(BI:BI,C42,BM:BM)+SUMIF(BY:BY,C42,CD:CD)+SUMIF(BY:BY,C42,CE:CE)+SUMIF(CP:CP,C42,CT:CT)+SUMIF(CY:CY,C42,DC:DC)+SUMIF(DN:DN,C42,DR:DR)+SUMIF(EC:EC,C42,EG:EG)+SUMIF(ER:ER,C42,EV:EV)+SUMIF(FA:FA,C42,FE:FE)+SUMIF(FK:FK,C42,FO:FO)+SUMIF(FT:FT,C42,FX:FX)+SUMIF(GC:GC,C42,GG:GG)+SUMIF(GL:GL,C42,GP:GP)+SUMIF(GU:GU,C42,GY:GY)+SUMIF(HD:HD,C42,HH:HH) -> 0 | H42: =+SUM(F42:G42) -> 0 | M42: 17 | N42: =+EOMONTH(O42,0) -> 47087 | O42: =+DATE(YEAR(O41),MONTH(O41)+3,DAY(O41)) -> 47072 | Q42: =+Q41-R42 -> 52948972 | R42: =+$Q$30/25 -> 4072997.9 | S42: =+Q41*Q$5*(O42-O41)/360 -> 874336.88 | T42: =+$Q$17/$Q$18 -> 471550.55 | U42: =+SUM(R42:T42) -> 5418885.3 | AC42: 17 | AD42: =+EOMONTH(AE42,0) -> 47269 | AE42: 47240 | AG42: =+AG41+AF42-AH42 -> 464296.08 | AH42: =+AH41 -> 51840.79 | AI42: =+AG41*AG$5*(AE42-AE41)/360 -> 7018.0277 | AJ42: =+SUM(AH42:AI42) -> 58858.818 | AR42: 17 | AS42: =+EOMONTH(AT42,0) -> 47177 | AT42: 47169 | AV42: =+AV41+AU42-AW42 -> 10220994 | AW42: 525047.46 | AX42: =+AV41*AV$5*(AT42-AT41)/360 -> 164772.64 | AY42: =+SUM(AW42:AX42) -> 689820.1 | BW42: 17 | BX42: =+EOMONTH(BY42,0) -> 47238 | BY42: 47228 | CA42: =+CA41+BZ42-CB42 -> 173209.4 | CB42: 57736.47 | CC42: 2821.4285 | CD42: =+CA41*CA$5*(BY42-BY41)/360 -> 3464.188 | CE42: 1642.8395 | CF42: =+SUM(CB42:CE42) -> 65664.926 | CN42: 17 | CO42: =+EOMONTH(CP42,0) -> 47299 | CP42: 47283 | CR42: =+CR41+CQ42-CS42 -> 104317.85 | CS42: 104317.85 | CT42: 55983.92 | CU42: =+SUM(CS42:CT42) -> 160301.77 | CW42: 17 | CX42: =+EOMONTH(CY42,0) -> 46387 | CY42: 46366 | DA42: =+DA41+CZ42-DB42 -> 12669107 | DB42: 1583638.4 | DC42: =+DA41*DA$5*(CY42-CY41)/360 -> 71263.727 | DD42: =+SUM(DB42:DC42) -> 1654902.1 | DL42: 17 | DM42: =+EOMONTH(DN42,0) -> 47299 | DN42: 47291 | DP42: =+DP41+DO42-DQ42 -> 5679465.2 | DQ42: 283973.26 | DR42: 88391.41 | DS42: =+SUM(DQ42:DR42) -> 372364.67 | EA42: 17 | EB42: =+EOMONTH(EC42,0) -> 47330 | EC42: 47304 | EE42: =+EE41-EF42 -> 631908.87 | EF42: 39494.31 | EG42: =+EE41*(EC42-EC41)*$EE$5/360 -> 9877.4598 | EH42: =+SUM(EF42:EG42) -> 49371.77 | EY42: 17 | EZ42: =+EOMONTH(FA42,0) -> 47208 | FA42: 47199 | FC42: =+FC41+FB42-FD42 -> 2342296.1 | FD42: 40216.85 | FE42: 12189.98 | FG42: =+SUM(FD42:FF42) -> 52406.83
A43: 18 | B43: =+WEEKNUM(C43,2) -> 41 | C43: =+C42+1 -> 45942 | E43: =+E42+D43-F43 -> 57102119 | F43: =+SUMIF(O:O,C43,R:R)+SUMIF(AE:AE,C43,AH:AH)+SUMIF(AT:AT,C43,AW:AW)+SUMIF(BI:BI,C43,BL:BL)+SUMIF(BY:BY,C43,CB:CB)+SUMIF(BY:BY,C43,CC:CC)+SUMIF(CP:CP,C43,CS:CS)+SUMIF(CY:CY,C43,DB:DB)+SUMIF(DN:DN,C43,DQ:DQ)+SUMIF(EC:EC,C43,EF:EF)+SUMIF(ER:ER,C43,EU:EU)+SUMIF(FA:FA,C43,FD:FD)+SUMIF(FK:FK,C43,FN:FN)+SUMIF(FT:FT,C43,FW:FW)+SUMIF(GC:GC,C43,GF:GF)+SUMIF(GL:GL,C43,GO:GO)+SUMIF(GU:GU,C43,GX:GX)+SUMIF(HD:HD,C43,HG:HG) -> 0 | G43: =+SUMIF(O:O,C43,T:T)+SUMIF(O:O,C43,S:S)+SUMIF(AE:AE,C43,AI:AI)+SUMIF(AT:AT,C43,AX:AX)+SUMIF(BI:BI,C43,BN:BN)+SUMIF(BI:BI,C43,BM:BM)+SUMIF(BY:BY,C43,CD:CD)+SUMIF(BY:BY,C43,CE:CE)+SUMIF(CP:CP,C43,CT:CT)+SUMIF(CY:CY,C43,DC:DC)+SUMIF(DN:DN,C43,DR:DR)+SUMIF(EC:EC,C43,EG:EG)+SUMIF(ER:ER,C43,EV:EV)+SUMIF(FA:FA,C43,FE:FE)+SUMIF(FK:FK,C43,FO:FO)+SUMIF(FT:FT,C43,FX:FX)+SUMIF(GC:GC,C43,GG:GG)+SUMIF(GL:GL,C43,GP:GP)+SUMIF(GU:GU,C43,GY:GY)+SUMIF(HD:HD,C43,HH:HH) -> 0 | H43: =+SUM(F43:G43) -> 0 | M43: 18 | N43: =+EOMONTH(O43,0) -> 47177 | O43: =+DATE(YEAR(O42),MONTH(O42)+3,DAY(O42)) -> 47164 | Q43: =+Q42-R43 -> 48875975 | R43: =+$Q$30/25 -> 4072997.9 | S43: =+Q42*Q$5*(O43-O42)/360 -> 811884.24 | T43: =+$Q$17/$Q$18 -> 471550.55 | U43: =+SUM(R43:T43) -> 5356432.7 | AC43: 18 | AD43: =+EOMONTH(AE43,0) -> 47361 | AE43: 47332 | AG43: =+AG42+AF43-AH43 -> 412455.29 | AH43: =+AH42 -> 51840.79 | AI43: =+AG42*AG$5*(AE43-AE42)/360 -> 6525.9393 | AJ43: =+SUM(AH43:AI43) -> 58366.729 | AR43: 18 | AS43: =+EOMONTH(AT43,0) -> 47269 | AT43: 47258 | AV43: =+AV42+AU43-AW43 -> 9695946.5 | AW43: 525047.46 | AX43: =+AV42*AV$5*(AT43-AT42)/360 -> 151611.41 | AY43: =+SUM(AW43:AX43) -> 676658.87 | BW43: 18 | BX43: =+EOMONTH(BY43,0) -> 47330 | BY43: 47319 | CA43: =+CA42+BZ43-CB43 -> 115472.93 | CB43: 57736.47 | CC43: 2821.4285 | CD43: =+CA42*CA$5*(BY43-BY42)/360 -> 2627.0092 | CE43: 1642.8395 | CF43: =+SUM(CB43:CE43) -> 64827.747 | CN43: 18 | CO43: =+EOMONTH(CP43,0) -> 47391 | CP43: 47375 | CR43: =+CR42+CQ43-CS43 -> 0 | CS43: 104317.85 | CT43: 53793.24 | CU43: =+SUM(CS43:CT43) -> 158111.09 | CW43: 18 | CX43: =+EOMONTH(CY43,0) -> 46418 | CY43: 46397 | DA43: =+DA42+CZ43-DB43 -> 11085469 | DB43: 1583638.4 | DC43: =+DA42*DA$5*(CY43-CY42)/360 -> 65457.053 | DD43: =+SUM(DB43:DC43) -> 1649095.4 | DL43: 18 | DM43: =+EOMONTH(DN43,0) -> 47391 | DN43: 47381 | DP43: =+DP42+DO43-DQ43 -> 5395492 | DQ43: 283973.26 | DR43: 82352.25 | DS43: =+SUM(DQ43:DR43) -> 366325.51 | EA43: 18 | EB43: =+EOMONTH(EC43,0) -> 47422 | EC43: 47396 | EE43: =+EE42-EF43 -> 592414.56 | EF43: 39494.31 | EG43: =+EE42*(EC43-EC42)*$EE$5/360 -> 9398.5913 | EH43: =+SUM(EF43:EG43) -> 48892.901 | EY43: 18 | EZ43: =+EOMONTH(FA43,0) -> 47299 | FA43: 47291 | FC43: =+FC42+FB43-FD43 -> 2302079.3 | FD43: 40216.85 | FE43: 11701.49 | FG43: =+SUM(FD43:FF43) -> 51918.34
A44: 19 | B44: =+WEEKNUM(C44,2) -> 42 | C44: =+C43+1 -> 45943 | E44: =+E43+D44-F44 -> 57102119 | F44: =+SUMIF(O:O,C44,R:R)+SUMIF(AE:AE,C44,AH:AH)+SUMIF(AT:AT,C44,AW:AW)+SUMIF(BI:BI,C44,BL:BL)+SUMIF(BY:BY,C44,CB:CB)+SUMIF(BY:BY,C44,CC:CC)+SUMIF(CP:CP,C44,CS:CS)+SUMIF(CY:CY,C44,DB:DB)+SUMIF(DN:DN,C44,DQ:DQ)+SUMIF(EC:EC,C44,EF:EF)+SUMIF(ER:ER,C44,EU:EU)+SUMIF(FA:FA,C44,FD:FD)+SUMIF(FK:FK,C44,FN:FN)+SUMIF(FT:FT,C44,FW:FW)+SUMIF(GC:GC,C44,GF:GF)+SUMIF(GL:GL,C44,GO:GO)+SUMIF(GU:GU,C44,GX:GX)+SUMIF(HD:HD,C44,HG:HG) -> 0 | G44: =+SUMIF(O:O,C44,T:T)+SUMIF(O:O,C44,S:S)+SUMIF(AE:AE,C44,AI:AI)+SUMIF(AT:AT,C44,AX:AX)+SUMIF(BI:BI,C44,BN:BN)+SUMIF(BI:BI,C44,BM:BM)+SUMIF(BY:BY,C44,CD:CD)+SUMIF(BY:BY,C44,CE:CE)+SUMIF(CP:CP,C44,CT:CT)+SUMIF(CY:CY,C44,DC:DC)+SUMIF(DN:DN,C44,DR:DR)+SUMIF(EC:EC,C44,EG:EG)+SUMIF(ER:ER,C44,EV:EV)+SUMIF(FA:FA,C44,FE:FE)+SUMIF(FK:FK,C44,FO:FO)+SUMIF(FT:FT,C44,FX:FX)+SUMIF(GC:GC,C44,GG:GG)+SUMIF(GL:GL,C44,GP:GP)+SUMIF(GU:GU,C44,GY:GY)+SUMIF(HD:HD,C44,HH:HH) -> 0 | H44: =+SUM(F44:G44) -> 0 | M44: 19 | N44: =+EOMONTH(O44,0) -> 47269 | O44: =+DATE(YEAR(O43),MONTH(O43)+3,DAY(O43)) -> 47253 | Q44: =+Q43-R44 -> 44802977 | R44: =+$Q$30/25 -> 4072997.9 | S44: =+Q43*Q$5*(O44-O43)/360 -> 724993.62 | T44: =+$Q$17/$Q$18 -> 471550.55 | U44: =+SUM(R44:T44) -> 5269542.1 | AC44: 19 | AD44: =+EOMONTH(AE44,0) -> 47452 | AE44: 47424 | AG44: =+AG43+AF44-AH44 -> 360614.5 | AH44: =+AH43 -> 51840.79 | AI44: =+AG43*AG$5*(AE44-AE43)/360 -> 5797.2882 | AJ44: =+SUM(AH44:AI44) -> 57638.078 | AR44: 19 | AS44: =+EOMONTH(AT44,0) -> 47361 | AT44: 47350 | AV44: =+AV43+AU44-AW44 -> 9170899 | AW44: 525047.46 | AX44: =+AV43*AV$5*(AT44-AT43)/360 -> 148671.18 | AY44: =+SUM(AW44:AX44) -> 673718.64 | BW44: 19 | BX44: =+EOMONTH(BY44,0) -> 47422 | BY44: 47398 | CA44: =+CA43+BZ44-CB44 -> 0.0056757364 | CB44: 115472.92 | CC44: 14107.143 | CD44: =+CA43*CA$5*(BY44-BY43)/360 -> 1520.3935 | CE44: 1642.8395 | CF44: =+SUM(CB44:CE44) -> 132743.3 | CW44: 19 | CX44: =+EOMONTH(CY44,0) -> 46446 | CY44: 46428 | DA44: =+DA43+CZ44-DB44 -> 9501830.3 | DB44: 1583638.4 | DC44: =+DA43*DA$5*(CY44-CY43)/360 -> 57274.922 | DD44: =+SUM(DB44:DC44) -> 1640913.3 | DL44: 19 | DM44: =+EOMONTH(DN44,0) -> 47483 | DN44: 47472 | DP44: =+DP43+DO44-DQ44 -> 5111518.7 | DQ44: 283973.26 | DR44: 79103.91 | DS44: =+SUM(DQ44:DR44) -> 363077.17 | EA44: 19 | EB44: =+EOMONTH(EC44,0) -> 47514 | EC44: 47490 | EE44: =+EE43-EF44 -> 552920.25 | EF44: 39494.31 | EG44: =+EE43*(EC44-EC43)*$EE$5/360 -> 9002.7266 | EH44: =+SUM(EF44:EG44) -> 48497.037 | EY44: 19 | EZ44: =+EOMONTH(FA44,0) -> 47391 | FA44: 47381 | FC44: =+FC43+FB44-FD44 -> 2261862.4 | FD44: 40216.85 | FE44: 10858.34 | FG44: =+SUM(FD44:FF44) -> 51075.19
A45: 20 | B45: =+WEEKNUM(C45,2) -> 42 | C45: =+C44+1 -> 45944 | E45: =+E44+D45-F45 -> 57102119 | F45: =+SUMIF(O:O,C45,R:R)+SUMIF(AE:AE,C45,AH:AH)+SUMIF(AT:AT,C45,AW:AW)+SUMIF(BI:BI,C45,BL:BL)+SUMIF(BY:BY,C45,CB:CB)+SUMIF(BY:BY,C45,CC:CC)+SUMIF(CP:CP,C45,CS:CS)+SUMIF(CY:CY,C45,DB:DB)+SUMIF(DN:DN,C45,DQ:DQ)+SUMIF(EC:EC,C45,EF:EF)+SUMIF(ER:ER,C45,EU:EU)+SUMIF(FA:FA,C45,FD:FD)+SUMIF(FK:FK,C45,FN:FN)+SUMIF(FT:FT,C45,FW:FW)+SUMIF(GC:GC,C45,GF:GF)+SUMIF(GL:GL,C45,GO:GO)+SUMIF(GU:GU,C45,GX:GX)+SUMIF(HD:HD,C45,HG:HG) -> 0 | G45: =+SUMIF(O:O,C45,T:T)+SUMIF(O:O,C45,S:S)+SUMIF(AE:AE,C45,AI:AI)+SUMIF(AT:AT,C45,AX:AX)+SUMIF(BI:BI,C45,BN:BN)+SUMIF(BI:BI,C45,BM:BM)+SUMIF(BY:BY,C45,CD:CD)+SUMIF(BY:BY,C45,CE:CE)+SUMIF(CP:CP,C45,CT:CT)+SUMIF(CY:CY,C45,DC:DC)+SUMIF(DN:DN,C45,DR:DR)+SUMIF(EC:EC,C45,EG:EG)+SUMIF(ER:ER,C45,EV:EV)+SUMIF(FA:FA,C45,FE:FE)+SUMIF(FK:FK,C45,FO:FO)+SUMIF(FT:FT,C45,FX:FX)+SUMIF(GC:GC,C45,GG:GG)+SUMIF(GL:GL,C45,GP:GP)+SUMIF(GU:GU,C45,GY:GY)+SUMIF(HD:HD,C45,HH:HH) -> 0 | H45: =+SUM(F45:G45) -> 0 | M45: 20 | N45: =+EOMONTH(O45,0) -> 47361 | O45: =+DATE(YEAR(O44),MONTH(O44)+3,DAY(O44)) -> 47345 | Q45: =+Q44-R45 -> 40729979 | R45: =+$Q$30/25 -> 4072997.9 | S45: =+Q44*Q$5*(O45-O44)/360 -> 686978.98 | T45: =+$Q$17/$Q$18 -> 471550.55 | U45: =+SUM(R45:T45) -> 5231527.4 | AC45: 20 | AD45: =+EOMONTH(AE45,0) -> 47542 | AE45: 47516 | AG45: =+AG44+AF45-AH45 -> 308773.71 | AH45: =+AH44 -> 51840.79 | AI45: =+AG44*AG$5*(AE45-AE44)/360 -> 5068.6371 | AJ45: =+SUM(AH45:AI45) -> 56909.427 | AR45: 20 | AS45: =+EOMONTH(AT45,0) -> 47452 | AT45: 47442 | AV45: =+AV44+AU45-AW45 -> 8645851.6 | AW45: 525047.46 | AX45: =+AV44*AV$5*(AT45-AT44)/360 -> 140620.45 | AY45: =+SUM(AW45:AX45) -> 665667.92 | CW45: 20 | CX45: =+EOMONTH(CY45,0) -> 46477 | CY45: 46456 | DA45: =+DA44+CZ45-DB45 -> 7918192 | DB45: 1583638.4 | DC45: =+DA44*DA$5*(CY45-CY44)/360 -> 44341.875 | DD45: =+SUM(DB45:DC45) -> 1627980.3 | DL45: 20 | DM45: =+EOMONTH(DN45,0) -> 47573 | DN45: 47563 | DP45: =+DP44+DO45-DQ45 -> 4827545.5 | DQ45: 283973.26 | DR45: 74940.55 | DS45: =+SUM(DQ45:DR45) -> 358913.81 | EA45: 20 | EB45: =+EOMONTH(EC45,0) -> 47603 | EC45: 47578 | EE45: =+EE44-EF45 -> 513425.94 | EF45: 39494.31 | EG45: =+EE44*(EC45-EC44)*$EE$5/360 -> 7866.2121 | EH45: =+SUM(EF45:EG45) -> 47360.522 | EY45: 20 | EZ45: =+EOMONTH(FA45,0) -> 47483 | FA45: 47472 | FC45: =+FC44+FB45-FD45 -> 2221645.6 | FD45: 40216.85 | FE45: 10363.16 | FG45: =+SUM(FD45:FF45) -> 50580.01
A46: 21 | B46: =+WEEKNUM(C46,2) -> 42 | C46: =+C45+1 -> 45945 | E46: =+E45+D46-F46 -> 57102119 | F46: =+SUMIF(O:O,C46,R:R)+SUMIF(AE:AE,C46,AH:AH)+SUMIF(AT:AT,C46,AW:AW)+SUMIF(BI:BI,C46,BL:BL)+SUMIF(BY:BY,C46,CB:CB)+SUMIF(BY:BY,C46,CC:CC)+SUMIF(CP:CP,C46,CS:CS)+SUMIF(CY:CY,C46,DB:DB)+SUMIF(DN:DN,C46,DQ:DQ)+SUMIF(EC:EC,C46,EF:EF)+SUMIF(ER:ER,C46,EU:EU)+SUMIF(FA:FA,C46,FD:FD)+SUMIF(FK:FK,C46,FN:FN)+SUMIF(FT:FT,C46,FW:FW)+SUMIF(GC:GC,C46,GF:GF)+SUMIF(GL:GL,C46,GO:GO)+SUMIF(GU:GU,C46,GX:GX)+SUMIF(HD:HD,C46,HG:HG) -> 0 | G46: =+SUMIF(O:O,C46,T:T)+SUMIF(O:O,C46,S:S)+SUMIF(AE:AE,C46,AI:AI)+SUMIF(AT:AT,C46,AX:AX)+SUMIF(BI:BI,C46,BN:BN)+SUMIF(BI:BI,C46,BM:BM)+SUMIF(BY:BY,C46,CD:CD)+SUMIF(BY:BY,C46,CE:CE)+SUMIF(CP:CP,C46,CT:CT)+SUMIF(CY:CY,C46,DC:DC)+SUMIF(DN:DN,C46,DR:DR)+SUMIF(EC:EC,C46,EG:EG)+SUMIF(ER:ER,C46,EV:EV)+SUMIF(FA:FA,C46,FE:FE)+SUMIF(FK:FK,C46,FO:FO)+SUMIF(FT:FT,C46,FX:FX)+SUMIF(GC:GC,C46,GG:GG)+SUMIF(GL:GL,C46,GP:GP)+SUMIF(GU:GU,C46,GY:GY)+SUMIF(HD:HD,C46,HH:HH) -> 0 | H46: =+SUM(F46:G46) -> 0 | M46: 21 | N46: =+EOMONTH(O46,0) -> 47452 | O46: =+DATE(YEAR(O45),MONTH(O45)+3,DAY(O45)) -> 47437 | Q46: =+Q45-R46 -> 36656981 | R46: =+$Q$30/25 -> 4072997.9 | S46: =+Q45*Q$5*(O46-O45)/360 -> 624526.34 | U46: =+SUM(R46:T46) -> 4697524.2 | AC46: 21 | AD46: =+EOMONTH(AE46,0) -> 47634 | AE46: 47605 | AG46: =+AG45+AF46-AH46 -> 256932.92 | AH46: =+AH45 -> 51840.79 | AI46: =+AG45*AG$5*(AE46-AE45)/360 -> 4198.4648 | AJ46: =+SUM(AH46:AI46) -> 56039.255 | AR46: 21 | AS46: =+EOMONTH(AT46,0) -> 47542 | AT46: 47534 | AV46: =+AV45+AU46-AW46 -> 8120804.1 | AW46: 525047.46 | AX46: =+AV45*AV$5*(AT46-AT45)/360 -> 132569.72 | AY46: =+SUM(AW46:AX46) -> 657617.19 | CW46: 21 | CX46: =+EOMONTH(CY46,0) -> 46507 | CY46: 46487 | DA46: =+DA45+CZ46-DB46 -> 6334553.6 | DB46: 1583638.4 | DC46: =+DA45*DA$5*(CY46-CY45)/360 -> 40910.659 | DD46: =+SUM(DB46:DC46) -> 1624549 | DL46: 21 | DM46: =+EOMONTH(DN46,0) -> 47664 | DN46: 47656 | DP46: =+DP45+DO46-DQ46 -> 4543572.2 | DQ46: 283973.26 | DR46: 72332.72 | DS46: =+SUM(DQ46:DR46) -> 356305.98 | EA46: 21 | EB46: =+EOMONTH(EC46,0) -> 47695 | EC46: 47669 | EE46: =+EE45-EF46 -> 473931.63 | EF46: 39494.31 | EG46: =+EE45*(EC46-EC45)*$EE$5/360 -> 7553.3513 | EH46: =+SUM(EF46:EG46) -> 47047.661 | EY46: 21 | EZ46: =+EOMONTH(FA46,0) -> 47573 | FA46: 47563 | FC46: =+FC45+FB46-FD46 -> 2181428.7 | FD46: 40216.85 | FE46: 9754.22 | FG46: =+SUM(FD46:FF46) -> 49971.07
A47: 22 | B47: =+WEEKNUM(C47,2) -> 42 | C47: =+C46+1 -> 45946 | E47: =+E46+D47-F47 -> 57102119 | F47: =+SUMIF(O:O,C47,R:R)+SUMIF(AE:AE,C47,AH:AH)+SUMIF(AT:AT,C47,AW:AW)+SUMIF(BI:BI,C47,BL:BL)+SUMIF(BY:BY,C47,CB:CB)+SUMIF(BY:BY,C47,CC:CC)+SUMIF(CP:CP,C47,CS:CS)+SUMIF(CY:CY,C47,DB:DB)+SUMIF(DN:DN,C47,DQ:DQ)+SUMIF(EC:EC,C47,EF:EF)+SUMIF(ER:ER,C47,EU:EU)+SUMIF(FA:FA,C47,FD:FD)+SUMIF(FK:FK,C47,FN:FN)+SUMIF(FT:FT,C47,FW:FW)+SUMIF(GC:GC,C47,GF:GF)+SUMIF(GL:GL,C47,GO:GO)+SUMIF(GU:GU,C47,GX:GX)+SUMIF(HD:HD,C47,HG:HG) -> 0 | G47: =+SUMIF(O:O,C47,T:T)+SUMIF(O:O,C47,S:S)+SUMIF(AE:AE,C47,AI:AI)+SUMIF(AT:AT,C47,AX:AX)+SUMIF(BI:BI,C47,BN:BN)+SUMIF(BI:BI,C47,BM:BM)+SUMIF(BY:BY,C47,CD:CD)+SUMIF(BY:BY,C47,CE:CE)+SUMIF(CP:CP,C47,CT:CT)+SUMIF(CY:CY,C47,DC:DC)+SUMIF(DN:DN,C47,DR:DR)+SUMIF(EC:EC,C47,EG:EG)+SUMIF(ER:ER,C47,EV:EV)+SUMIF(FA:FA,C47,FE:FE)+SUMIF(FK:FK,C47,FO:FO)+SUMIF(FT:FT,C47,FX:FX)+SUMIF(GC:GC,C47,GG:GG)+SUMIF(GL:GL,C47,GP:GP)+SUMIF(GU:GU,C47,GY:GY)+SUMIF(HD:HD,C47,HH:HH) -> 0 | H47: =+SUM(F47:G47) -> 0 | M47: 22 | N47: =+EOMONTH(O47,0) -> 47542 | O47: =+DATE(YEAR(O46),MONTH(O46)+3,DAY(O46)) -> 47529 | Q47: =+Q46-R47 -> 32583983 | R47: =+$Q$30/25 -> 4072997.9 | S47: =+Q46*Q$5*(O47-O46)/360 -> 562073.71 | U47: =+SUM(R47:T47) -> 4635071.6 | AC47: 22 | AD47: =+EOMONTH(AE47,0) -> 47726 | AE47: 47697 | AG47: =+AG46+AF47-AH47 -> 205092.13 | AH47: =+AH46 -> 51840.79 | AI47: =+AG46*AG$5*(AE47-AE46)/360 -> 3611.3349 | AJ47: =+SUM(AH47:AI47) -> 55452.125 | AR47: 22 | AS47: =+EOMONTH(AT47,0) -> 47634 | AT47: 47623 | AV47: =+AV46+AU47-AW47 -> 7595756.6 | AW47: 525047.46 | AX47: =+AV46*AV$5*(AT47-AT46)/360 -> 120458.59 | AY47: =+SUM(AW47:AX47) -> 645506.06 | CW47: 22 | CX47: =+EOMONTH(CY47,0) -> 46538 | CY47: 46517 | DA47: =+DA46+CZ47-DB47 -> 4750915.2 | DB47: 1583638.4 | DC47: =+DA46*DA$5*(CY47-CY46)/360 -> 31672.768 | DD47: =+SUM(DB47:DC47) -> 1615311.1 | DL47: 22 | DM47: =+EOMONTH(DN47,0) -> 47756 | DN47: 47745 | DP47: =+DP46+DO47-DQ47 -> 4259598.9 | DQ47: 283973.26 | DR47: 65149.78 | DS47: =+SUM(DQ47:DR47) -> 349123.04 | EA47: 22 | EB47: =+EOMONTH(EC47,0) -> 47787 | EC47: 47763 | EE47: =+EE46-EF47 -> 434437.32 | EF47: 39494.31 | EG47: =+EE46*(EC47-EC46)*$EE$5/360 -> 7202.181 | EH47: =+SUM(EF47:EG47) -> 46696.491 | EY47: 22 | EZ47: =+EOMONTH(FA47,0) -> 47664 | FA47: 47656 | FC47: =+FC46+FB47-FD47 -> 2141211.9 | FD47: 40216.85 | FE47: 9332.65 | FG47: =+SUM(FD47:FF47) -> 49549.5
A48: 23 | B48: =+WEEKNUM(C48,2) -> 42 | C48: =+C47+1 -> 45947 | E48: =+E47+D48-F48 -> 57102119 | F48: =+SUMIF(O:O,C48,R:R)+SUMIF(AE:AE,C48,AH:AH)+SUMIF(AT:AT,C48,AW:AW)+SUMIF(BI:BI,C48,BL:BL)+SUMIF(BY:BY,C48,CB:CB)+SUMIF(BY:BY,C48,CC:CC)+SUMIF(CP:CP,C48,CS:CS)+SUMIF(CY:CY,C48,DB:DB)+SUMIF(DN:DN,C48,DQ:DQ)+SUMIF(EC:EC,C48,EF:EF)+SUMIF(ER:ER,C48,EU:EU)+SUMIF(FA:FA,C48,FD:FD)+SUMIF(FK:FK,C48,FN:FN)+SUMIF(FT:FT,C48,FW:FW)+SUMIF(GC:GC,C48,GF:GF)+SUMIF(GL:GL,C48,GO:GO)+SUMIF(GU:GU,C48,GX:GX)+SUMIF(HD:HD,C48,HG:HG) -> 0 | G48: =+SUMIF(O:O,C48,T:T)+SUMIF(O:O,C48,S:S)+SUMIF(AE:AE,C48,AI:AI)+SUMIF(AT:AT,C48,AX:AX)+SUMIF(BI:BI,C48,BN:BN)+SUMIF(BI:BI,C48,BM:BM)+SUMIF(BY:BY,C48,CD:CD)+SUMIF(BY:BY,C48,CE:CE)+SUMIF(CP:CP,C48,CT:CT)+SUMIF(CY:CY,C48,DC:DC)+SUMIF(DN:DN,C48,DR:DR)+SUMIF(EC:EC,C48,EG:EG)+SUMIF(ER:ER,C48,EV:EV)+SUMIF(FA:FA,C48,FE:FE)+SUMIF(FK:FK,C48,FO:FO)+SUMIF(FT:FT,C48,FX:FX)+SUMIF(GC:GC,C48,GG:GG)+SUMIF(GL:GL,C48,GP:GP)+SUMIF(GU:GU,C48,GY:GY)+SUMIF(HD:HD,C48,HH:HH) -> 0 | H48: =+SUM(F48:G48) -> 0 | M48: 23 | N48: =+EOMONTH(O48,0) -> 47634 | O48: =+DATE(YEAR(O47),MONTH(O47)+3,DAY(O47)) -> 47618 | Q48: =+Q47-R48 -> 28510985 | R48: =+$Q$30/25 -> 4072997.9 | S48: =+Q47*Q$5*(O48-O47)/360 -> 483329.08 | U48: =+SUM(R48:T48) -> 4556327 | AC48: 23 | AD48: =+EOMONTH(AE48,0) -> 47817 | AE48: 47789 | AG48: =+AG47+AF48-AH48 -> 153251.34 | AH48: =+AH47 -> 51840.79 | AI48: =+AG47*AG$5*(AE48-AE47)/360 -> 2882.6838 | AJ48: =+SUM(AH48:AI48) -> 54723.474 | AR48: 23 | AS48: =+EOMONTH(AT48,0) -> 47726 | AT48: 47715 | AV48: =+AV47+AU48-AW48 -> 7070709.2 | AW48: 525047.46 | AX48: =+AV47*AV$5*(AT48-AT47)/360 -> 116468.27 | AY48: =+SUM(AW48:AX48) -> 641515.73 | CW48: 23 | CX48: =+EOMONTH(CY48,0) -> 46568 | CY48: 46548 | DA48: =+DA47+CZ48-DB48 -> 3167276.8 | DB48: 1583638.4 | DC48: =+DA47*DA$5*(CY48-CY47)/360 -> 24546.395 | DD48: =+SUM(DB48:DC48) -> 1608184.8 | DL48: 23 | DM48: =+EOMONTH(DN48,0) -> 47848 | DN48: 47836 | DP48: =+DP47+DO48-DQ48 -> 3975625.7 | DQ48: 283973.26 | DR48: 62450.45 | DS48: =+SUM(DQ48:DR48) -> 346423.71 | EA48: 23 | EB48: =+EOMONTH(EC48,0) -> 47879 | EC48: 47854 | EE48: =+EE47-EF48 -> 394943.01 | EF48: 39494.31 | EG48: =+EE47*(EC48-EC47)*$EE$5/360 -> 6391.2971 | EH48: =+SUM(EF48:EG48) -> 45885.607 | EY48: 23 | EZ48: =+EOMONTH(FA48,0) -> 47756 | FA48: 47745 | FC48: =+FC47+FB48-FD48 -> 2100995 | FD48: 40216.85 | FE48: 8362.36 | FG48: =+SUM(FD48:FF48) -> 48579.21
A49: 24 | B49: =+WEEKNUM(C49,2) -> 42 | C49: =+C48+1 -> 45948 | E49: =+E48+D49-F49 -> 57102119 | F49: =+SUMIF(O:O,C49,R:R)+SUMIF(AE:AE,C49,AH:AH)+SUMIF(AT:AT,C49,AW:AW)+SUMIF(BI:BI,C49,BL:BL)+SUMIF(BY:BY,C49,CB:CB)+SUMIF(BY:BY,C49,CC:CC)+SUMIF(CP:CP,C49,CS:CS)+SUMIF(CY:CY,C49,DB:DB)+SUMIF(DN:DN,C49,DQ:DQ)+SUMIF(EC:EC,C49,EF:EF)+SUMIF(ER:ER,C49,EU:EU)+SUMIF(FA:FA,C49,FD:FD)+SUMIF(FK:FK,C49,FN:FN)+SUMIF(FT:FT,C49,FW:FW)+SUMIF(GC:GC,C49,GF:GF)+SUMIF(GL:GL,C49,GO:GO)+SUMIF(GU:GU,C49,GX:GX)+SUMIF(HD:HD,C49,HG:HG) -> 0 | G49: =+SUMIF(O:O,C49,T:T)+SUMIF(O:O,C49,S:S)+SUMIF(AE:AE,C49,AI:AI)+SUMIF(AT:AT,C49,AX:AX)+SUMIF(BI:BI,C49,BN:BN)+SUMIF(BI:BI,C49,BM:BM)+SUMIF(BY:BY,C49,CD:CD)+SUMIF(BY:BY,C49,CE:CE)+SUMIF(CP:CP,C49,CT:CT)+SUMIF(CY:CY,C49,DC:DC)+SUMIF(DN:DN,C49,DR:DR)+SUMIF(EC:EC,C49,EG:EG)+SUMIF(ER:ER,C49,EV:EV)+SUMIF(FA:FA,C49,FE:FE)+SUMIF(FK:FK,C49,FO:FO)+SUMIF(FT:FT,C49,FX:FX)+SUMIF(GC:GC,C49,GG:GG)+SUMIF(GL:GL,C49,GP:GP)+SUMIF(GU:GU,C49,GY:GY)+SUMIF(HD:HD,C49,HH:HH) -> 0 | H49: =+SUM(F49:G49) -> 0 | M49: 24 | N49: =+EOMONTH(O49,0) -> 47726 | O49: =+DATE(YEAR(O48),MONTH(O48)+3,DAY(O48)) -> 47710 | Q49: =+Q48-R49 -> 24437987 | R49: =+$Q$30/25 -> 4072997.9 | S49: =+Q48*Q$5*(O49-O48)/360 -> 437168.44 | U49: =+SUM(R49:T49) -> 4510166.3 | AC49: 24 | AD49: =+EOMONTH(AE49,0) -> 47907 | AE49: 47881 | AG49: =+AG48+AF49-AH49 -> 101410.55 | AH49: =+AH48 -> 51840.79 | AI49: =+AG48*AG$5*(AE49-AE48)/360 -> 2154.0327 | AJ49: =+SUM(AH49:AI49) -> 53994.823 | AR49: 24 | AS49: =+EOMONTH(AT49,0) -> 47817 | AT49: 47807 | AV49: =+AV48+AU49-AW49 -> 6545661.7 | AW49: 525047.46 | AX49: =+AV48*AV$5*(AT49-AT48)/360 -> 108417.54 | AY49: =+SUM(AW49:AX49) -> 633465.01 | CW49: 24 | CX49: =+EOMONTH(CY49,0) -> 46599 | CY49: 46578 | DA49: =+DA48+CZ49-DB49 -> 1583638.4 | DB49: 1583638.4 | DC49: =+DA48*DA$5*(CY49-CY48)/360 -> 15836.384 | DD49: =+SUM(DB49:DC49) -> 1599474.8 | DL49: 24 | DM49: =+EOMONTH(DN49,0) -> 47938 | DN49: 47927 | DP49: =+DP48+DO49-DQ49 -> 3691652.4 | DQ49: 283973.26 | DR49: 58287.09 | DS49: =+SUM(DQ49:DR49) -> 342260.35 | EA49: 24 | EB49: =+EOMONTH(EC49,0) -> 47968 | EC49: 47945 | EE49: =+EE48-EF49 -> 355448.7 | EF49: 39494.31 | EG49: =+EE48*(EC49-EC48)*$EE$5/360 -> 5810.27 | EH49: =+SUM(EF49:EG49) -> 45304.58 | EY49: 24 | EZ49: =+EOMONTH(FA49,0) -> 47848 | FA49: 47836 | FC49: =+FC48+FB49-FD49 -> 2060778.2 | FD49: 40216.85 | FE49: 7927.41 | FG49: =+SUM(FD49:FF49) -> 48144.26
A50: 25 | B50: =+WEEKNUM(C50,2) -> 42 | C50: =+C49+1 -> 45949 | E50: =+E49+D50-F50 -> 57102119 | F50: =+SUMIF(O:O,C50,R:R)+SUMIF(AE:AE,C50,AH:AH)+SUMIF(AT:AT,C50,AW:AW)+SUMIF(BI:BI,C50,BL:BL)+SUMIF(BY:BY,C50,CB:CB)+SUMIF(BY:BY,C50,CC:CC)+SUMIF(CP:CP,C50,CS:CS)+SUMIF(CY:CY,C50,DB:DB)+SUMIF(DN:DN,C50,DQ:DQ)+SUMIF(EC:EC,C50,EF:EF)+SUMIF(ER:ER,C50,EU:EU)+SUMIF(FA:FA,C50,FD:FD)+SUMIF(FK:FK,C50,FN:FN)+SUMIF(FT:FT,C50,FW:FW)+SUMIF(GC:GC,C50,GF:GF)+SUMIF(GL:GL,C50,GO:GO)+SUMIF(GU:GU,C50,GX:GX)+SUMIF(HD:HD,C50,HG:HG) -> 0 | G50: =+SUMIF(O:O,C50,T:T)+SUMIF(O:O,C50,S:S)+SUMIF(AE:AE,C50,AI:AI)+SUMIF(AT:AT,C50,AX:AX)+SUMIF(BI:BI,C50,BN:BN)+SUMIF(BI:BI,C50,BM:BM)+SUMIF(BY:BY,C50,CD:CD)+SUMIF(BY:BY,C50,CE:CE)+SUMIF(CP:CP,C50,CT:CT)+SUMIF(CY:CY,C50,DC:DC)+SUMIF(DN:DN,C50,DR:DR)+SUMIF(EC:EC,C50,EG:EG)+SUMIF(ER:ER,C50,EV:EV)+SUMIF(FA:FA,C50,FE:FE)+SUMIF(FK:FK,C50,FO:FO)+SUMIF(FT:FT,C50,FX:FX)+SUMIF(GC:GC,C50,GG:GG)+SUMIF(GL:GL,C50,GP:GP)+SUMIF(GU:GU,C50,GY:GY)+SUMIF(HD:HD,C50,HH:HH) -> 0 | H50: =+SUM(F50:G50) -> 0 | M50: 25 | N50: =+EOMONTH(O50,0) -> 47817 | O50: =+DATE(YEAR(O49),MONTH(O49)+3,DAY(O49)) -> 47802 | Q50: =+Q49-R50 -> 20364989 | R50: =+$Q$30/25 -> 4072997.9 | S50: =+Q49*Q$5*(O50-O49)/360 -> 374715.81 | U50: =+SUM(R50:T50) -> 4447713.7 | AC50: 25 | AD50: =+EOMONTH(AE50,0) -> 47999 | AE50: 47970 | AG50: =+AG49+AF50-AH50 -> 49569.76 | AH50: =+AH49 -> 51840.79 | AI50: =+AG49*AG$5*(AE50-AE49)/360 -> 1378.9018 | AJ50: =+SUM(AH50:AI50) -> 53219.692 | AR50: 25 | AS50: =+EOMONTH(AT50,0) -> 47907 | AT50: 47899 | AV50: =+AV49+AU50-AW50 -> 6020614.2 | AW50: 525047.46 | AX50: =+AV49*AV$5*(AT50-AT49)/360 -> 100366.81 | AY50: =+SUM(AW50:AX50) -> 625414.28 | CW50: 25 | CX50: =+EOMONTH(CY50,0) -> 46630 | CY50: 46609 | DA50: =+DA49+CZ50-DB50 -> 0.068803104 | DB50: 1583638.4 | DC50: =+DA49*DA$5*(CY50-CY49)/360 -> 8182.132 | DD50: =+SUM(DB50:DC50) -> 1591820.5 | DL50: 25 | DM50: =+EOMONTH(DN50,0) -> 48029 | DN50: 48018 | DP50: =+DP49+DO50-DQ50 -> 3407679.2 | DQ50: 283973.26 | DR50: 54123.72 | DS50: =+SUM(DQ50:DR50) -> 338096.98 | EA50: 25 | EB50: =+EOMONTH(EC50,0) -> 48060 | EC50: 48036 | EE50: =+EE49-EF50 -> 315954.39 | EF50: 39494.31 | EG50: =+EE49*(EC50-EC49)*$EE$5/360 -> 5229.2428 | EH50: =+SUM(EF50:EG50) -> 44723.553 | EY50: 25 | EZ50: =+EOMONTH(FA50,0) -> 47938 | FA50: 47927 | FC50: =+FC49+FB50-FD50 -> 2020561.3 | FD50: 40216.85 | FE50: 7318.47 | FG50: =+SUM(FD50:FF50) -> 47535.32
A51: 26 | B51: =+WEEKNUM(C51,2) -> 43 | C51: =+C50+1 -> 45950 | E51: =+E50+D51-F51 -> 57041561 | F51: =+SUMIF(O:O,C51,R:R)+SUMIF(AE:AE,C51,AH:AH)+SUMIF(AT:AT,C51,AW:AW)+SUMIF(BI:BI,C51,BL:BL)+SUMIF(BY:BY,C51,CB:CB)+SUMIF(BY:BY,C51,CC:CC)+SUMIF(CP:CP,C51,CS:CS)+SUMIF(CY:CY,C51,DB:DB)+SUMIF(DN:DN,C51,DQ:DQ)+SUMIF(EC:EC,C51,EF:EF)+SUMIF(ER:ER,C51,EU:EU)+SUMIF(FA:FA,C51,FD:FD)+SUMIF(FK:FK,C51,FN:FN)+SUMIF(FT:FT,C51,FW:FW)+SUMIF(GC:GC,C51,GF:GF)+SUMIF(GL:GL,C51,GO:GO)+SUMIF(GU:GU,C51,GX:GX)+SUMIF(HD:HD,C51,HG:HG) -> 60557.899 | G51: =+SUMIF(O:O,C51,T:T)+SUMIF(O:O,C51,S:S)+SUMIF(AE:AE,C51,AI:AI)+SUMIF(AT:AT,C51,AX:AX)+SUMIF(BI:BI,C51,BN:BN)+SUMIF(BI:BI,C51,BM:BM)+SUMIF(BY:BY,C51,CD:CD)+SUMIF(BY:BY,C51,CE:CE)+SUMIF(CP:CP,C51,CT:CT)+SUMIF(CY:CY,C51,DC:DC)+SUMIF(DN:DN,C51,DR:DR)+SUMIF(EC:EC,C51,EG:EG)+SUMIF(ER:ER,C51,EV:EV)+SUMIF(FA:FA,C51,FE:FE)+SUMIF(FK:FK,C51,FO:FO)+SUMIF(FT:FT,C51,FX:FX)+SUMIF(GC:GC,C51,GG:GG)+SUMIF(GL:GL,C51,GP:GP)+SUMIF(GU:GU,C51,GY:GY)+SUMIF(HD:HD,C51,HH:HH) -> 17578.105 | H51: =+SUM(F51:G51) -> 78136.004 | I51: 0 | J51: BISA | M51: 26 | N51: =+EOMONTH(O51,0) -> 47907 | O51: =+DATE(YEAR(O50),MONTH(O50)+3,DAY(O50)) -> 47894 | Q51: =+Q50-R51 -> 16291992 | R51: =+$Q$30/25 -> 4072997.9 | S51: =+Q50*Q$5*(O51-O50)/360 -> 312263.17 | U51: =+SUM(R51:T51) -> 4385261.1 | AC51: 26 | AD51: =+EOMONTH(AE51,0) -> 48060 | AE51: 48058 | AG51: =+AG50+AF51-AH51 -> -4.802132e-10 | AH51: 49569.76 | AI51: =+AG50*AG$5*(AE51-AE50)/360 -> 666.43788 | AJ51: =+SUM(AH51:AI51) -> 50236.198 | AR51: 26 | AS51: =+EOMONTH(AT51,0) -> 47999 | AT51: 47988 | AV51: =+AV50+AU51-AW51 -> 5495566.8 | AW51: 525047.46 | AX51: =+AV50*AV$5*(AT51-AT50)/360 -> 89305.778 | AY51: =+SUM(AW51:AX51) -> 614353.24 | DL51: 26 | DM51: =+EOMONTH(DN51,0) -> 48121 | DN51: 48109 | DP51: =+DP50+DO51-DQ51 -> 3123705.9 | DQ51: 283973.26 | DR51: 49960.37 | DS51: =+SUM(DQ51:DR51) -> 333933.63 | EA51: 26 | EB51: =+EOMONTH(EC51,0) -> 48152 | EC51: 48127 | EE51: =+EE50-EF51 -> 276460.08 | EF51: 39494.31 | EG51: =+EE50*(EC51-EC50)*$EE$5/360 -> 4648.2157 | EH51: =+SUM(EF51:EG51) -> 44142.526 | EY51: 26 | EZ51: =+EOMONTH(FA51,0) -> 48029 | FA51: 48018 | FC51: =+FC50+FB51-FD51 -> 1980344.5 | FD51: 40216.85 | FE51: 6709.53 | FG51: =+SUM(FD51:FF51) -> 46926.38
A52: 27 | B52: =+WEEKNUM(C52,2) -> 43 | C52: =+C51+1 -> 45951 | E52: =+E51+D52-F52 -> 57041561 | F52: =+SUMIF(O:O,C52,R:R)+SUMIF(AE:AE,C52,AH:AH)+SUMIF(AT:AT,C52,AW:AW)+SUMIF(BI:BI,C52,BL:BL)+SUMIF(BY:BY,C52,CB:CB)+SUMIF(BY:BY,C52,CC:CC)+SUMIF(CP:CP,C52,CS:CS)+SUMIF(CY:CY,C52,DB:DB)+SUMIF(DN:DN,C52,DQ:DQ)+SUMIF(EC:EC,C52,EF:EF)+SUMIF(ER:ER,C52,EU:EU)+SUMIF(FA:FA,C52,FD:FD)+SUMIF(FK:FK,C52,FN:FN)+SUMIF(FT:FT,C52,FW:FW)+SUMIF(GC:GC,C52,GF:GF)+SUMIF(GL:GL,C52,GO:GO)+SUMIF(GU:GU,C52,GX:GX)+SUMIF(HD:HD,C52,HG:HG) -> 0 | G52: =+SUMIF(O:O,C52,T:T)+SUMIF(O:O,C52,S:S)+SUMIF(AE:AE,C52,AI:AI)+SUMIF(AT:AT,C52,AX:AX)+SUMIF(BI:BI,C52,BN:BN)+SUMIF(BI:BI,C52,BM:BM)+SUMIF(BY:BY,C52,CD:CD)+SUMIF(BY:BY,C52,CE:CE)+SUMIF(CP:CP,C52,CT:CT)+SUMIF(CY:CY,C52,DC:DC)+SUMIF(DN:DN,C52,DR:DR)+SUMIF(EC:EC,C52,EG:EG)+SUMIF(ER:ER,C52,EV:EV)+SUMIF(FA:FA,C52,FE:FE)+SUMIF(FK:FK,C52,FO:FO)+SUMIF(FT:FT,C52,FX:FX)+SUMIF(GC:GC,C52,GG:GG)+SUMIF(GL:GL,C52,GP:GP)+SUMIF(GU:GU,C52,GY:GY)+SUMIF(HD:HD,C52,HH:HH) -> 0 | H52: =+SUM(F52:G52) -> 0 | M52: 27 | N52: =+EOMONTH(O52,0) -> 47999 | O52: =+DATE(YEAR(O51),MONTH(O51)+3,DAY(O51)) -> 47983 | Q52: =+Q51-R52 -> 12218994 | R52: =+$Q$30/25 -> 4072997.9 | S52: =+Q51*Q$5*(O52-O51)/360 -> 241664.54 | U52: =+SUM(R52:T52) -> 4314662.4 | AR52: 27 | AS52: =+EOMONTH(AT52,0) -> 48091 | AT52: 48080 | AV52: =+AV51+AU52-AW52 -> 4970519.3 | AW52: 525047.46 | AX52: =+AV51*AV$5*(AT52-AT51)/360 -> 84265.357 | AY52: =+SUM(AW52:AX52) -> 609312.82 | DL52: 27 | DM52: =+EOMONTH(DN52,0) -> 48213 | DN52: 48200 | DP52: =+DP51+DO52-DQ52 -> 2839732.6 | DQ52: 283973.26 | DR52: 45797 | DS52: =+SUM(DQ52:DR52) -> 329770.26 | EA52: 27 | EB52: =+EOMONTH(EC52,0) -> 48244 | EC52: 48218 | EE52: =+EE51-EF52 -> 236965.77 | EF52: 39494.31 | EG52: =+EE51*(EC52-EC51)*$EE$5/360 -> 4067.1886 | EH52: =+SUM(EF52:EG52) -> 43561.499 | EY52: 27 | EZ52: =+EOMONTH(FA52,0) -> 48121 | FA52: 48109 | FC52: =+FC51+FB52-FD52 -> 1940127.6 | FD52: 40216.85 | FE52: 6100.59 | FG52: =+SUM(FD52:FF52) -> 46317.44
A53: 28 | B53: =+WEEKNUM(C53,2) -> 43 | C53: =+C52+1 -> 45952 | E53: =+E52+D53-F53 -> 57041561 | F53: =+SUMIF(O:O,C53,R:R)+SUMIF(AE:AE,C53,AH:AH)+SUMIF(AT:AT,C53,AW:AW)+SUMIF(BI:BI,C53,BL:BL)+SUMIF(BY:BY,C53,CB:CB)+SUMIF(BY:BY,C53,CC:CC)+SUMIF(CP:CP,C53,CS:CS)+SUMIF(CY:CY,C53,DB:DB)+SUMIF(DN:DN,C53,DQ:DQ)+SUMIF(EC:EC,C53,EF:EF)+SUMIF(ER:ER,C53,EU:EU)+SUMIF(FA:FA,C53,FD:FD)+SUMIF(FK:FK,C53,FN:FN)+SUMIF(FT:FT,C53,FW:FW)+SUMIF(GC:GC,C53,GF:GF)+SUMIF(GL:GL,C53,GO:GO)+SUMIF(GU:GU,C53,GX:GX)+SUMIF(HD:HD,C53,HG:HG) -> 0 | G53: =+SUMIF(O:O,C53,T:T)+SUMIF(O:O,C53,S:S)+SUMIF(AE:AE,C53,AI:AI)+SUMIF(AT:AT,C53,AX:AX)+SUMIF(BI:BI,C53,BN:BN)+SUMIF(BI:BI,C53,BM:BM)+SUMIF(BY:BY,C53,CD:CD)+SUMIF(BY:BY,C53,CE:CE)+SUMIF(CP:CP,C53,CT:CT)+SUMIF(CY:CY,C53,DC:DC)+SUMIF(DN:DN,C53,DR:DR)+SUMIF(EC:EC,C53,EG:EG)+SUMIF(ER:ER,C53,EV:EV)+SUMIF(FA:FA,C53,FE:FE)+SUMIF(FK:FK,C53,FO:FO)+SUMIF(FT:FT,C53,FX:FX)+SUMIF(GC:GC,C53,GG:GG)+SUMIF(GL:GL,C53,GP:GP)+SUMIF(GU:GU,C53,GY:GY)+SUMIF(HD:HD,C53,HH:HH) -> 0 | H53: =+SUM(F53:G53) -> 0 | M53: 28 | N53: =+EOMONTH(O53,0) -> 48091 | O53: =+DATE(YEAR(O52),MONTH(O52)+3,DAY(O52)) -> 48075 | Q53: =+Q52-R53 -> 8145995.8 | R53: =+$Q$30/25 -> 4072997.9 | S53: =+Q52*Q$5*(O53-O52)/360 -> 187357.9 | U53: =+SUM(R53:T53) -> 4260355.8 | AR53: 28 | AS53: =+EOMONTH(AT53,0) -> 48182 | AT53: 48172 | AV53: =+AV52+AU53-AW53 -> 4445471.8 | AW53: 525047.46 | AX53: =+AV52*AV$5*(AT53-AT52)/360 -> 76214.629 | AY53: =+SUM(AW53:AX53) -> 601262.09 | DL53: 28 | DM53: =+EOMONTH(DN53,0) -> 48304 | DN53: 48291 | DP53: =+DP52+DO53-DQ53 -> 2555759.4 | DQ53: 283973.26 | DR53: 41633.64 | DS53: =+SUM(DQ53:DR53) -> 325606.9 | EA53: 28 | EB53: =+EOMONTH(EC53,0) -> 48334 | EC53: 48309 | EE53: =+EE52-EF53 -> 197471.46 | EF53: 39494.31 | EG53: =+EE52*(EC53-EC52)*$EE$5/360 -> 3486.1615 | EH53: =+SUM(EF53:EG53) -> 42980.471 | EY53: 28 | EZ53: =+EOMONTH(FA53,0) -> 48213 | FA53: 48200 | FC53: =+FC52+FB53-FD53 -> 1899910.8 | FD53: 40216.85 | FE53: 5491.65 | FG53: =+SUM(FD53:FF53) -> 45708.5
A54: 29 | B54: =+WEEKNUM(C54,2) -> 43 | C54: =+C53+1 -> 45953 | E54: =+E53+D54-F54 -> 57041561 | F54: =+SUMIF(O:O,C54,R:R)+SUMIF(AE:AE,C54,AH:AH)+SUMIF(AT:AT,C54,AW:AW)+SUMIF(BI:BI,C54,BL:BL)+SUMIF(BY:BY,C54,CB:CB)+SUMIF(BY:BY,C54,CC:CC)+SUMIF(CP:CP,C54,CS:CS)+SUMIF(CY:CY,C54,DB:DB)+SUMIF(DN:DN,C54,DQ:DQ)+SUMIF(EC:EC,C54,EF:EF)+SUMIF(ER:ER,C54,EU:EU)+SUMIF(FA:FA,C54,FD:FD)+SUMIF(FK:FK,C54,FN:FN)+SUMIF(FT:FT,C54,FW:FW)+SUMIF(GC:GC,C54,GF:GF)+SUMIF(GL:GL,C54,GO:GO)+SUMIF(GU:GU,C54,GX:GX)+SUMIF(HD:HD,C54,HG:HG) -> 0 | G54: =+SUMIF(O:O,C54,T:T)+SUMIF(O:O,C54,S:S)+SUMIF(AE:AE,C54,AI:AI)+SUMIF(AT:AT,C54,AX:AX)+SUMIF(BI:BI,C54,BN:BN)+SUMIF(BI:BI,C54,BM:BM)+SUMIF(BY:BY,C54,CD:CD)+SUMIF(BY:BY,C54,CE:CE)+SUMIF(CP:CP,C54,CT:CT)+SUMIF(CY:CY,C54,DC:DC)+SUMIF(DN:DN,C54,DR:DR)+SUMIF(EC:EC,C54,EG:EG)+SUMIF(ER:ER,C54,EV:EV)+SUMIF(FA:FA,C54,FE:FE)+SUMIF(FK:FK,C54,FO:FO)+SUMIF(FT:FT,C54,FX:FX)+SUMIF(GC:GC,C54,GG:GG)+SUMIF(GL:GL,C54,GP:GP)+SUMIF(GU:GU,C54,GY:GY)+SUMIF(HD:HD,C54,HH:HH) -> 0 | H54: =+SUM(F54:G54) -> 0 | M54: 29 | N54: =+EOMONTH(O54,0) -> 48182 | O54: =+DATE(YEAR(O53),MONTH(O53)+3,DAY(O53)) -> 48167 | Q54: =+Q53-R54 -> 4072997.9 | R54: =+$Q$30/25 -> 4072997.9 | S54: =+Q53*Q$5*(O54-O53)/360 -> 124905.27 | U54: =+SUM(R54:T54) -> 4197903.1 | AR54: 29 | AS54: =+EOMONTH(AT54,0) -> 48273 | AT54: 48264 | AV54: =+AV53+AU54-AW54 -> 3920424.4 | AW54: 525047.46 | AX54: =+AV53*AV$5*(AT54-AT53)/360 -> 68163.902 | AY54: =+SUM(AW54:AX54) -> 593211.37 | DL54: 29 | DM54: =+EOMONTH(DN54,0) -> 48395 | DN54: 48382 | DP54: =+DP53+DO54-DQ54 -> 2271786.1 | DQ54: 283973.26 | DR54: 37470.27 | DS54: =+SUM(DQ54:DR54) -> 321443.53 | EA54: 29 | EB54: =+EOMONTH(EC54,0) -> 48426 | EC54: 48400 | EE54: =+EE53-EF54 -> 157977.15 | EF54: 39494.31 | EG54: =+EE53*(EC54-EC53)*$EE$5/360 -> 2905.1343 | EH54: =+SUM(EF54:EG54) -> 42399.444 | EY54: 29 | EZ54: =+EOMONTH(FA54,0) -> 48304 | FA54: 48291 | FC54: =+FC53+FB54-FD54 -> 1859693.9 | FD54: 40216.85 | FE54: 4882.71 | FG54: =+SUM(FD54:FF54) -> 45099.56
A55: 30 | B55: =+WEEKNUM(C55,2) -> 43 | C55: =+C54+1 -> 45954 | E55: =+E54+D55-F55 -> 57041561 | F55: =+SUMIF(O:O,C55,R:R)+SUMIF(AE:AE,C55,AH:AH)+SUMIF(AT:AT,C55,AW:AW)+SUMIF(BI:BI,C55,BL:BL)+SUMIF(BY:BY,C55,CB:CB)+SUMIF(BY:BY,C55,CC:CC)+SUMIF(CP:CP,C55,CS:CS)+SUMIF(CY:CY,C55,DB:DB)+SUMIF(DN:DN,C55,DQ:DQ)+SUMIF(EC:EC,C55,EF:EF)+SUMIF(ER:ER,C55,EU:EU)+SUMIF(FA:FA,C55,FD:FD)+SUMIF(FK:FK,C55,FN:FN)+SUMIF(FT:FT,C55,FW:FW)+SUMIF(GC:GC,C55,GF:GF)+SUMIF(GL:GL,C55,GO:GO)+SUMIF(GU:GU,C55,GX:GX)+SUMIF(HD:HD,C55,HG:HG) -> 0 | G55: =+SUMIF(O:O,C55,T:T)+SUMIF(O:O,C55,S:S)+SUMIF(AE:AE,C55,AI:AI)+SUMIF(AT:AT,C55,AX:AX)+SUMIF(BI:BI,C55,BN:BN)+SUMIF(BI:BI,C55,BM:BM)+SUMIF(BY:BY,C55,CD:CD)+SUMIF(BY:BY,C55,CE:CE)+SUMIF(CP:CP,C55,CT:CT)+SUMIF(CY:CY,C55,DC:DC)+SUMIF(DN:DN,C55,DR:DR)+SUMIF(EC:EC,C55,EG:EG)+SUMIF(ER:ER,C55,EV:EV)+SUMIF(FA:FA,C55,FE:FE)+SUMIF(FK:FK,C55,FO:FO)+SUMIF(FT:FT,C55,FX:FX)+SUMIF(GC:GC,C55,GG:GG)+SUMIF(GL:GL,C55,GP:GP)+SUMIF(GU:GU,C55,GY:GY)+SUMIF(HD:HD,C55,HH:HH) -> 0 | H55: =+SUM(F55:G55) -> 0 | M55: 30 | N55: =+EOMONTH(O55,0) -> 48273 | O55: =+DATE(YEAR(O54),MONTH(O54)+3,4) -> 48248 | Q55: =+Q54-R55 -> 5.5879354e-08 | R55: =+$Q$30/25 -> 4072997.9 | S55: =+Q54*Q$5*(O55-O54)/360 -> 54985.471 | U55: =+SUM(R55:T55) -> 4127983.4 | AR55: 30 | AS55: =+EOMONTH(AT55,0) -> 48365 | AT55: 48354 | AV55: =+AV54+AU55-AW55 -> 3395376.9 | AW55: 525047.46 | AX55: =+AV54*AV$5*(AT55-AT54)/360 -> 58806.366 | AY55: =+SUM(AW55:AX55) -> 583853.83 | DL55: 30 | DM55: =+EOMONTH(DN55,0) -> 48487 | DN55: 48473 | DP55: =+DP54+DO55-DQ55 -> 1987812.9 | DQ55: 283973.26 | DR55: 33306.91 | DS55: =+SUM(DQ55:DR55) -> 317280.17 | EA55: 30 | EB55: =+EOMONTH(EC55,0) -> 48518 | EC55: 48492 | EE55: =+EE54-EF55 -> 118482.84 | EF55: 39494.31 | EG55: =+EE54*(EC55-EC54)*$EE$5/360 -> 2349.6469 | EH55: =+SUM(EF55:EG55) -> 41843.957 | EY55: 30 | EZ55: =+EOMONTH(FA55,0) -> 48395 | FA55: 48382 | FC55: =+FC54+FB55-FD55 -> 1819477.1 | FD55: 40216.85 | FE55: 4273.77 | FG55: =+SUM(FD55:FF55) -> 44490.62
A56: 31 | B56: =+WEEKNUM(C56,2) -> 43 | C56: =+C55+1 -> 45955 | E56: =+E55+D56-F56 -> 57041561 | F56: =+SUMIF(O:O,C56,R:R)+SUMIF(AE:AE,C56,AH:AH)+SUMIF(AT:AT,C56,AW:AW)+SUMIF(BI:BI,C56,BL:BL)+SUMIF(BY:BY,C56,CB:CB)+SUMIF(BY:BY,C56,CC:CC)+SUMIF(CP:CP,C56,CS:CS)+SUMIF(CY:CY,C56,DB:DB)+SUMIF(DN:DN,C56,DQ:DQ)+SUMIF(EC:EC,C56,EF:EF)+SUMIF(ER:ER,C56,EU:EU)+SUMIF(FA:FA,C56,FD:FD)+SUMIF(FK:FK,C56,FN:FN)+SUMIF(FT:FT,C56,FW:FW)+SUMIF(GC:GC,C56,GF:GF)+SUMIF(GL:GL,C56,GO:GO)+SUMIF(GU:GU,C56,GX:GX)+SUMIF(HD:HD,C56,HG:HG) -> 0 | G56: =+SUMIF(O:O,C56,T:T)+SUMIF(O:O,C56,S:S)+SUMIF(AE:AE,C56,AI:AI)+SUMIF(AT:AT,C56,AX:AX)+SUMIF(BI:BI,C56,BN:BN)+SUMIF(BI:BI,C56,BM:BM)+SUMIF(BY:BY,C56,CD:CD)+SUMIF(BY:BY,C56,CE:CE)+SUMIF(CP:CP,C56,CT:CT)+SUMIF(CY:CY,C56,DC:DC)+SUMIF(DN:DN,C56,DR:DR)+SUMIF(EC:EC,C56,EG:EG)+SUMIF(ER:ER,C56,EV:EV)+SUMIF(FA:FA,C56,FE:FE)+SUMIF(FK:FK,C56,FO:FO)+SUMIF(FT:FT,C56,FX:FX)+SUMIF(GC:GC,C56,GG:GG)+SUMIF(GL:GL,C56,GP:GP)+SUMIF(GU:GU,C56,GY:GY)+SUMIF(HD:HD,C56,HH:HH) -> 0 | H56: =+SUM(F56:G56) -> 0 | AR56: 31 | AS56: =+EOMONTH(AT56,0) -> 48457 | AT56: 48446 | AV56: =+AV55+AU56-AW56 -> 2870329.4 | AW56: 525047.46 | AX56: =+AV55*AV$5*(AT56-AT55)/360 -> 52062.446 | AY56: =+SUM(AW56:AX56) -> 577109.91 | DL56: 31 | DM56: =+EOMONTH(DN56,0) -> 48579 | DN56: 48564 | DP56: =+DP55+DO56-DQ56 -> 1703839.6 | DQ56: 283973.26 | DR56: 29143.54 | DS56: =+SUM(DQ56:DR56) -> 313116.8 | EA56: 31 | EB56: =+EOMONTH(EC56,0) -> 48610 | EC56: 48584 | EE56: =+EE55-EF56 -> 78988.533 | EF56: 39494.31 | EG56: =+EE55*(EC56-EC55)*$EE$5/360 -> 1762.2348 | EH56: =+SUM(EF56:EG56) -> 41256.545 | EY56: 31 | EZ56: =+EOMONTH(FA56,0) -> 48487 | FA56: 48473 | FC56: =+FC55+FB56-FD56 -> 1779260.2 | FD56: 40216.85 | FE56: 3664.84 | FG56: =+SUM(FD56:FF56) -> 43881.69
A57: 32 | B57: =+WEEKNUM(C57,2) -> 43 | C57: =+C56+1 -> 45956 | E57: =+E56+D57-F57 -> 57041561 | F57: =+SUMIF(O:O,C57,R:R)+SUMIF(AE:AE,C57,AH:AH)+SUMIF(AT:AT,C57,AW:AW)+SUMIF(BI:BI,C57,BL:BL)+SUMIF(BY:BY,C57,CB:CB)+SUMIF(BY:BY,C57,CC:CC)+SUMIF(CP:CP,C57,CS:CS)+SUMIF(CY:CY,C57,DB:DB)+SUMIF(DN:DN,C57,DQ:DQ)+SUMIF(EC:EC,C57,EF:EF)+SUMIF(ER:ER,C57,EU:EU)+SUMIF(FA:FA,C57,FD:FD)+SUMIF(FK:FK,C57,FN:FN)+SUMIF(FT:FT,C57,FW:FW)+SUMIF(GC:GC,C57,GF:GF)+SUMIF(GL:GL,C57,GO:GO)+SUMIF(GU:GU,C57,GX:GX)+SUMIF(HD:HD,C57,HG:HG) -> 0 | G57: =+SUMIF(O:O,C57,T:T)+SUMIF(O:O,C57,S:S)+SUMIF(AE:AE,C57,AI:AI)+SUMIF(AT:AT,C57,AX:AX)+SUMIF(BI:BI,C57,BN:BN)+SUMIF(BI:BI,C57,BM:BM)+SUMIF(BY:BY,C57,CD:CD)+SUMIF(BY:BY,C57,CE:CE)+SUMIF(CP:CP,C57,CT:CT)+SUMIF(CY:CY,C57,DC:DC)+SUMIF(DN:DN,C57,DR:DR)+SUMIF(EC:EC,C57,EG:EG)+SUMIF(ER:ER,C57,EV:EV)+SUMIF(FA:FA,C57,FE:FE)+SUMIF(FK:FK,C57,FO:FO)+SUMIF(FT:FT,C57,FX:FX)+SUMIF(GC:GC,C57,GG:GG)+SUMIF(GL:GL,C57,GP:GP)+SUMIF(GU:GU,C57,GY:GY)+SUMIF(HD:HD,C57,HH:HH) -> 0 | H57: =+SUM(F57:G57) -> 0 | AR57: 32 | AS57: =+EOMONTH(AT57,0) -> 48548 | AT57: 48538 | AV57: =+AV56+AU57-AW57 -> 2345282 | AW57: 525047.46 | AX57: =+AV56*AV$5*(AT57-AT56)/360 -> 44011.718 | AY57: =+SUM(AW57:AX57) -> 569059.18 | DL57: 32 | DM57: =+EOMONTH(DN57,0) -> 48669 | DN57: 48655 | DP57: =+DP56+DO57-DQ57 -> 1419866.3 | DQ57: 283973.26 | DR57: 24980.18 | DS57: =+SUM(DQ57:DR57) -> 308953.44 | EA57: 32 | EB57: =+EOMONTH(EC57,0) -> 48699 | EC57: 48674 | EE57: =+EE56-EF57 -> 39494.223 | EF57: 39494.31 | EG57: =+EE56*(EC57-EC56)*$EE$5/360 -> 1149.2832 | EH57: =+SUM(EF57:EG57) -> 40643.593 | EY57: 32 | EZ57: =+EOMONTH(FA57,0) -> 48579 | FA57: 48564 | FC57: =+FC56+FB57-FD57 -> 1739043.4 | FD57: 40216.85 | FE57: 3055.9 | FG57: =+SUM(FD57:FF57) -> 43272.75
A58: 33 | B58: =+WEEKNUM(C58,2) -> 44 | C58: =+C57+1 -> 45957 | E58: =+E57+D58-F58 -> 57041561 | F58: =+SUMIF(O:O,C58,R:R)+SUMIF(AE:AE,C58,AH:AH)+SUMIF(AT:AT,C58,AW:AW)+SUMIF(BI:BI,C58,BL:BL)+SUMIF(BY:BY,C58,CB:CB)+SUMIF(BY:BY,C58,CC:CC)+SUMIF(CP:CP,C58,CS:CS)+SUMIF(CY:CY,C58,DB:DB)+SUMIF(DN:DN,C58,DQ:DQ)+SUMIF(EC:EC,C58,EF:EF)+SUMIF(ER:ER,C58,EU:EU)+SUMIF(FA:FA,C58,FD:FD)+SUMIF(FK:FK,C58,FN:FN)+SUMIF(FT:FT,C58,FW:FW)+SUMIF(GC:GC,C58,GF:GF)+SUMIF(GL:GL,C58,GO:GO)+SUMIF(GU:GU,C58,GX:GX)+SUMIF(HD:HD,C58,HG:HG) -> 0 | G58: =+SUMIF(O:O,C58,T:T)+SUMIF(O:O,C58,S:S)+SUMIF(AE:AE,C58,AI:AI)+SUMIF(AT:AT,C58,AX:AX)+SUMIF(BI:BI,C58,BN:BN)+SUMIF(BI:BI,C58,BM:BM)+SUMIF(BY:BY,C58,CD:CD)+SUMIF(BY:BY,C58,CE:CE)+SUMIF(CP:CP,C58,CT:CT)+SUMIF(CY:CY,C58,DC:DC)+SUMIF(DN:DN,C58,DR:DR)+SUMIF(EC:EC,C58,EG:EG)+SUMIF(ER:ER,C58,EV:EV)+SUMIF(FA:FA,C58,FE:FE)+SUMIF(FK:FK,C58,FO:FO)+SUMIF(FT:FT,C58,FX:FX)+SUMIF(GC:GC,C58,GG:GG)+SUMIF(GL:GL,C58,GP:GP)+SUMIF(GU:GU,C58,GY:GY)+SUMIF(HD:HD,C58,HH:HH) -> 0 | H58: =+SUM(F58:G58) -> 0 | AR58: 33 | AS58: =+EOMONTH(AT58,0) -> 48638 | AT58: 48630 | AV58: =+AV57+AU58-AW58 -> 1820234.5 | AW58: 525047.46 | AX58: =+AV57*AV$5*(AT58-AT57)/360 -> 35960.99 | AY58: =+SUM(AW58:AX58) -> 561008.46 | DL58: 33 | DM58: =+EOMONTH(DN58,0) -> 48760 | DN58: 48747 | DP58: =+DP57+DO58-DQ58 -> 1135893.1 | DQ58: 283973.26 | DR58: 21045.58 | DS58: =+SUM(DQ58:DR58) -> 305018.84 | EA58: 33 | EB58: =+EOMONTH(EC58,0) -> 48791 | EC58: 48765 | EE58: =+EE57-EF58 -> -0.087313402 | EF58: 39494.31 | EG58: =+EE57*(EC58-EC57)*$EE$5/360 -> 581.02584 | EH58: =+SUM(EF58:EG58) -> 40075.336 | EY58: 33 | EZ58: =+EOMONTH(FA58,0) -> 48669 | FA58: 48655 | FC58: =+FC57+FB58-FD58 -> 1698826.5 | FD58: 40216.85 | FE58: 2446.96 | FG58: =+SUM(FD58:FF58) -> 42663.81
A59: 34 | B59: =+WEEKNUM(C59,2) -> 44 | C59: =+C58+1 -> 45958 | E59: =+E58+D59-F59 -> 57041561 | F59: =+SUMIF(O:O,C59,R:R)+SUMIF(AE:AE,C59,AH:AH)+SUMIF(AT:AT,C59,AW:AW)+SUMIF(BI:BI,C59,BL:BL)+SUMIF(BY:BY,C59,CB:CB)+SUMIF(BY:BY,C59,CC:CC)+SUMIF(CP:CP,C59,CS:CS)+SUMIF(CY:CY,C59,DB:DB)+SUMIF(DN:DN,C59,DQ:DQ)+SUMIF(EC:EC,C59,EF:EF)+SUMIF(ER:ER,C59,EU:EU)+SUMIF(FA:FA,C59,FD:FD)+SUMIF(FK:FK,C59,FN:FN)+SUMIF(FT:FT,C59,FW:FW)+SUMIF(GC:GC,C59,GF:GF)+SUMIF(GL:GL,C59,GO:GO)+SUMIF(GU:GU,C59,GX:GX)+SUMIF(HD:HD,C59,HG:HG) -> 0 | G59: =+SUMIF(O:O,C59,T:T)+SUMIF(O:O,C59,S:S)+SUMIF(AE:AE,C59,AI:AI)+SUMIF(AT:AT,C59,AX:AX)+SUMIF(BI:BI,C59,BN:BN)+SUMIF(BI:BI,C59,BM:BM)+SUMIF(BY:BY,C59,CD:CD)+SUMIF(BY:BY,C59,CE:CE)+SUMIF(CP:CP,C59,CT:CT)+SUMIF(CY:CY,C59,DC:DC)+SUMIF(DN:DN,C59,DR:DR)+SUMIF(EC:EC,C59,EG:EG)+SUMIF(ER:ER,C59,EV:EV)+SUMIF(FA:FA,C59,FE:FE)+SUMIF(FK:FK,C59,FO:FO)+SUMIF(FT:FT,C59,FX:FX)+SUMIF(GC:GC,C59,GG:GG)+SUMIF(GL:GL,C59,GP:GP)+SUMIF(GU:GU,C59,GY:GY)+SUMIF(HD:HD,C59,HH:HH) -> 0 | H59: =+SUM(F59:G59) -> 0 | AR59: 34 | AS59: =+EOMONTH(AT59,0) -> 48730 | AT59: 48719 | AV59: =+AV58+AU59-AW59 -> 1295187.1 | AW59: 525047.46 | AX59: =+AV58*AV$5*(AT59-AT58)/360 -> 27000.145 | AY59: =+SUM(AW59:AX59) -> 552047.61 | DL59: 34 | DM59: =+EOMONTH(DN59,0) -> 48852 | DN59: 48837 | DP59: =+DP58+DO59-DQ59 -> 851919.82 | DQ59: 283973.26 | DR59: 16470.45 | DS59: =+SUM(DQ59:DR59) -> 300443.71 | EY59: 34 | EZ59: =+EOMONTH(FA59,0) -> 48760 | FA59: 48747 | FC59: =+FC58+FB59-FD59 -> 1658609.7 | FD59: 40216.85 | FE59: 1851.4 | FG59: =+SUM(FD59:FF59) -> 42068.25
A60: 35 | B60: =+WEEKNUM(C60,2) -> 44 | C60: =+C59+1 -> 45959 | E60: =+E59+D60-F60 -> 57041561 | F60: =+SUMIF(O:O,C60,R:R)+SUMIF(AE:AE,C60,AH:AH)+SUMIF(AT:AT,C60,AW:AW)+SUMIF(BI:BI,C60,BL:BL)+SUMIF(BY:BY,C60,CB:CB)+SUMIF(BY:BY,C60,CC:CC)+SUMIF(CP:CP,C60,CS:CS)+SUMIF(CY:CY,C60,DB:DB)+SUMIF(DN:DN,C60,DQ:DQ)+SUMIF(EC:EC,C60,EF:EF)+SUMIF(ER:ER,C60,EU:EU)+SUMIF(FA:FA,C60,FD:FD)+SUMIF(FK:FK,C60,FN:FN)+SUMIF(FT:FT,C60,FW:FW)+SUMIF(GC:GC,C60,GF:GF)+SUMIF(GL:GL,C60,GO:GO)+SUMIF(GU:GU,C60,GX:GX)+SUMIF(HD:HD,C60,HG:HG) -> 0 | G60: =+SUMIF(O:O,C60,T:T)+SUMIF(O:O,C60,S:S)+SUMIF(AE:AE,C60,AI:AI)+SUMIF(AT:AT,C60,AX:AX)+SUMIF(BI:BI,C60,BN:BN)+SUMIF(BI:BI,C60,BM:BM)+SUMIF(BY:BY,C60,CD:CD)+SUMIF(BY:BY,C60,CE:CE)+SUMIF(CP:CP,C60,CT:CT)+SUMIF(CY:CY,C60,DC:DC)+SUMIF(DN:DN,C60,DR:DR)+SUMIF(EC:EC,C60,EG:EG)+SUMIF(ER:ER,C60,EV:EV)+SUMIF(FA:FA,C60,FE:FE)+SUMIF(FK:FK,C60,FO:FO)+SUMIF(FT:FT,C60,FX:FX)+SUMIF(GC:GC,C60,GG:GG)+SUMIF(GL:GL,C60,GP:GP)+SUMIF(GU:GU,C60,GY:GY)+SUMIF(HD:HD,C60,HH:HH) -> 0 | H60: =+SUM(F60:G60) -> 0 | AR60: 35 | AS60: =+EOMONTH(AT60,0) -> 48822 | AT60: 48811 | AV60: =+AV59+AU60-AW60 -> 770139.59 | AW60: 525047.46 | AX60: =+AV59*AV$5*(AT60-AT59)/360 -> 19859.535 | AY60: =+SUM(AW60:AX60) -> 544907 | DL60: 35 | DM60: =+EOMONTH(DN60,0) -> 48944 | DN60: 48928 | DP60: =+DP59+DO60-DQ60 -> 567946.56 | DQ60: 283973.26 | DR60: 12490.09 | DS60: =+SUM(DQ60:DR60) -> 296463.35 | EY60: 35 | EZ60: =+EOMONTH(FA60,0) -> 48852 | FA60: 48837 | FC60: =+FC59+FB60-FD60 -> 1618392.8 | FD60: 40216.87 | FE60: 1222.39 | FG60: =+SUM(FD60:FF60) -> 41439.26
A61: 36 | B61: =+WEEKNUM(C61,2) -> 44 | C61: =+C60+1 -> 45960 | E61: =+E60+D61-F61 -> 57041561 | F61: =+SUMIF(O:O,C61,R:R)+SUMIF(AE:AE,C61,AH:AH)+SUMIF(AT:AT,C61,AW:AW)+SUMIF(BI:BI,C61,BL:BL)+SUMIF(BY:BY,C61,CB:CB)+SUMIF(BY:BY,C61,CC:CC)+SUMIF(CP:CP,C61,CS:CS)+SUMIF(CY:CY,C61,DB:DB)+SUMIF(DN:DN,C61,DQ:DQ)+SUMIF(EC:EC,C61,EF:EF)+SUMIF(ER:ER,C61,EU:EU)+SUMIF(FA:FA,C61,FD:FD)+SUMIF(FK:FK,C61,FN:FN)+SUMIF(FT:FT,C61,FW:FW)+SUMIF(GC:GC,C61,GF:GF)+SUMIF(GL:GL,C61,GO:GO)+SUMIF(GU:GU,C61,GX:GX)+SUMIF(HD:HD,C61,HG:HG) -> 0 | G61: =+SUMIF(O:O,C61,T:T)+SUMIF(O:O,C61,S:S)+SUMIF(AE:AE,C61,AI:AI)+SUMIF(AT:AT,C61,AX:AX)+SUMIF(BI:BI,C61,BN:BN)+SUMIF(BI:BI,C61,BM:BM)+SUMIF(BY:BY,C61,CD:CD)+SUMIF(BY:BY,C61,CE:CE)+SUMIF(CP:CP,C61,CT:CT)+SUMIF(CY:CY,C61,DC:DC)+SUMIF(DN:DN,C61,DR:DR)+SUMIF(EC:EC,C61,EG:EG)+SUMIF(ER:ER,C61,EV:EV)+SUMIF(FA:FA,C61,FE:FE)+SUMIF(FK:FK,C61,FO:FO)+SUMIF(FT:FT,C61,FX:FX)+SUMIF(GC:GC,C61,GG:GG)+SUMIF(GL:GL,C61,GP:GP)+SUMIF(GU:GU,C61,GY:GY)+SUMIF(HD:HD,C61,HH:HH) -> 0 | H61: =+SUM(F61:G61) -> 0 | I61: =+H61 -> 0 | AR61: 36 | AS61: =+EOMONTH(AT61,0) -> 48913 | AT61: 48903 | AV61: =+AV60+AU61-AW61 -> 245092.12 | AW61: 525047.46 | AX61: =+AV60*AV$5*(AT61-AT60)/360 -> 11808.807 | AY61: =+SUM(AW61:AX61) -> 536856.27 | DL61: 36 | DM61: =+EOMONTH(DN61,0) -> 49034 | DN61: 49019 | DP61: =+DP60+DO61-DQ61 -> 283973.3 | DQ61: 283973.26 | DR61: 8326.73 | DS61: =+SUM(DQ61:DR61) -> 292299.99 | EY61: 36 | EZ61: =+EOMONTH(FA61,0) -> 48944 | FA61: 48928 | FC61: =+FC60+FB61-FD61 -> 1087389.8 | FD61: 531003.01 | FE61: 620.14 | FG61: =+SUM(FD61:FF61) -> 531623.15
A62: 37 | B62: =+WEEKNUM(C62,2) -> 44 | C62: =+C61+1 -> 45961 | E62: =+E61+D62-F62 -> 57041561 | F62: =+SUMIF(O:O,C62,R:R)+SUMIF(AE:AE,C62,AH:AH)+SUMIF(AT:AT,C62,AW:AW)+SUMIF(BI:BI,C62,BL:BL)+SUMIF(BY:BY,C62,CB:CB)+SUMIF(BY:BY,C62,CC:CC)+SUMIF(CP:CP,C62,CS:CS)+SUMIF(CY:CY,C62,DB:DB)+SUMIF(DN:DN,C62,DQ:DQ)+SUMIF(EC:EC,C62,EF:EF)+SUMIF(ER:ER,C62,EU:EU)+SUMIF(FA:FA,C62,FD:FD)+SUMIF(FK:FK,C62,FN:FN)+SUMIF(FT:FT,C62,FW:FW)+SUMIF(GC:GC,C62,GF:GF)+SUMIF(GL:GL,C62,GO:GO)+SUMIF(GU:GU,C62,GX:GX)+SUMIF(HD:HD,C62,HG:HG) -> 0 | G62: =+SUMIF(O:O,C62,T:T)+SUMIF(O:O,C62,S:S)+SUMIF(AE:AE,C62,AI:AI)+SUMIF(AT:AT,C62,AX:AX)+SUMIF(BI:BI,C62,BN:BN)+SUMIF(BI:BI,C62,BM:BM)+SUMIF(BY:BY,C62,CD:CD)+SUMIF(BY:BY,C62,CE:CE)+SUMIF(CP:CP,C62,CT:CT)+SUMIF(CY:CY,C62,DC:DC)+SUMIF(DN:DN,C62,DR:DR)+SUMIF(EC:EC,C62,EG:EG)+SUMIF(ER:ER,C62,EV:EV)+SUMIF(FA:FA,C62,FE:FE)+SUMIF(FK:FK,C62,FO:FO)+SUMIF(FT:FT,C62,FX:FX)+SUMIF(GC:GC,C62,GG:GG)+SUMIF(GL:GL,C62,GP:GP)+SUMIF(GU:GU,C62,GY:GY)+SUMIF(HD:HD,C62,HH:HH) -> 0 | H62: =+SUM(F62:G62) -> 0 | AR62: 37 | AS62: =+EOMONTH(AT62,0) -> 49003 | AT62: 48997 | AV62: =+AV61+AU62-AW62 -> -7.4214768e-09 | AW62: 245092.12 | AX62: =+AV61*AV$5*(AT62-AT61)/360 -> 3839.7766 | AY62: =+SUM(AW62:AX62) -> 248931.9 | DL62: 37 | DM62: =+EOMONTH(DN62,0) -> 49125 | DN62: 49111 | DP62: =+DP61+DO62-DQ62 -> 0.038867459 | DQ62: 283973.26 | DR62: 4209.12 | DS62: =+SUM(DQ62:DR62) -> 288182.38 | EY62: 37 | EZ62: =+EOMONTH(FA62,0) -> 49034 | FA62: 49019 | FC62: =+FC61+FB62-FD62 -> 548258.31 | FD62: 539131.48 | FE62: 88653.24 | FG62: =+SUM(FD62:FF62) -> 627784.72
A63: 38 | B63: =+WEEKNUM(C63,2) -> 44 | C63: =+C62+1 -> 45962 | E63: =+E62+D63-F63 -> 57041561 | F63: =+SUMIF(O:O,C63,R:R)+SUMIF(AE:AE,C63,AH:AH)+SUMIF(AT:AT,C63,AW:AW)+SUMIF(BI:BI,C63,BL:BL)+SUMIF(BY:BY,C63,CB:CB)+SUMIF(BY:BY,C63,CC:CC)+SUMIF(CP:CP,C63,CS:CS)+SUMIF(CY:CY,C63,DB:DB)+SUMIF(DN:DN,C63,DQ:DQ)+SUMIF(EC:EC,C63,EF:EF)+SUMIF(ER:ER,C63,EU:EU)+SUMIF(FA:FA,C63,FD:FD)+SUMIF(FK:FK,C63,FN:FN)+SUMIF(FT:FT,C63,FW:FW)+SUMIF(GC:GC,C63,GF:GF)+SUMIF(GL:GL,C63,GO:GO)+SUMIF(GU:GU,C63,GX:GX)+SUMIF(HD:HD,C63,HG:HG) -> 0 | G63: =+SUMIF(O:O,C63,T:T)+SUMIF(O:O,C63,S:S)+SUMIF(AE:AE,C63,AI:AI)+SUMIF(AT:AT,C63,AX:AX)+SUMIF(BI:BI,C63,BN:BN)+SUMIF(BI:BI,C63,BM:BM)+SUMIF(BY:BY,C63,CD:CD)+SUMIF(BY:BY,C63,CE:CE)+SUMIF(CP:CP,C63,CT:CT)+SUMIF(CY:CY,C63,DC:DC)+SUMIF(DN:DN,C63,DR:DR)+SUMIF(EC:EC,C63,EG:EG)+SUMIF(ER:ER,C63,EV:EV)+SUMIF(FA:FA,C63,FE:FE)+SUMIF(FK:FK,C63,FO:FO)+SUMIF(FT:FT,C63,FX:FX)+SUMIF(GC:GC,C63,GG:GG)+SUMIF(GL:GL,C63,GP:GP)+SUMIF(GU:GU,C63,GY:GY)+SUMIF(HD:HD,C63,HH:HH) -> 0 | H63: =+SUM(F63:G63) -> 0 | EY63: 38 | EZ63: =+EOMONTH(FA63,0) -> 49125 | FA63: 49111 | FC63: =+FC62+FB63-FD63 -> -2.5611371e-09 | FD63: 548258.31 | FE63: 79526.41 | FG63: =+SUM(FD63:FF63) -> 627784.72
A64: 39 | B64: =+WEEKNUM(C64,2) -> 44 | C64: =+C63+1 -> 45963 | E64: =+E63+D64-F64 -> 56989720 | F64: =+SUMIF(O:O,C64,R:R)+SUMIF(AE:AE,C64,AH:AH)+SUMIF(AT:AT,C64,AW:AW)+SUMIF(BI:BI,C64,BL:BL)+SUMIF(BY:BY,C64,CB:CB)+SUMIF(BY:BY,C64,CC:CC)+SUMIF(CP:CP,C64,CS:CS)+SUMIF(CY:CY,C64,DB:DB)+SUMIF(DN:DN,C64,DQ:DQ)+SUMIF(EC:EC,C64,EF:EF)+SUMIF(ER:ER,C64,EU:EU)+SUMIF(FA:FA,C64,FD:FD)+SUMIF(FK:FK,C64,FN:FN)+SUMIF(FT:FT,C64,FW:FW)+SUMIF(GC:GC,C64,GF:GF)+SUMIF(GL:GL,C64,GO:GO)+SUMIF(GU:GU,C64,GX:GX)+SUMIF(HD:HD,C64,HG:HG) -> 51840.79 | G64: =+SUMIF(O:O,C64,T:T)+SUMIF(O:O,C64,S:S)+SUMIF(AE:AE,C64,AI:AI)+SUMIF(AT:AT,C64,AX:AX)+SUMIF(BI:BI,C64,BN:BN)+SUMIF(BI:BI,C64,BM:BM)+SUMIF(BY:BY,C64,CD:CD)+SUMIF(BY:BY,C64,CE:CE)+SUMIF(CP:CP,C64,CT:CT)+SUMIF(CY:CY,C64,DC:DC)+SUMIF(DN:DN,C64,DR:DR)+SUMIF(EC:EC,C64,EG:EG)+SUMIF(ER:ER,C64,EV:EV)+SUMIF(FA:FA,C64,FE:FE)+SUMIF(FK:FK,C64,FO:FO)+SUMIF(FT:FT,C64,FX:FX)+SUMIF(GC:GC,C64,GG:GG)+SUMIF(GL:GL,C64,GP:GP)+SUMIF(GU:GU,C64,GY:GY)+SUMIF(HD:HD,C64,HH:HH) -> 17455.706 | H64: =+SUM(F64:G64) -> 69296.496
A65: 40 | B65: =+WEEKNUM(C65,2) -> 45 | C65: =+C64+1 -> 45964 | E65: =+E64+D65-F65 -> 56989720 | F65: =+SUMIF(O:O,C65,R:R)+SUMIF(AE:AE,C65,AH:AH)+SUMIF(AT:AT,C65,AW:AW)+SUMIF(BI:BI,C65,BL:BL)+SUMIF(BY:BY,C65,CB:CB)+SUMIF(BY:BY,C65,CC:CC)+SUMIF(CP:CP,C65,CS:CS)+SUMIF(CY:CY,C65,DB:DB)+SUMIF(DN:DN,C65,DQ:DQ)+SUMIF(EC:EC,C65,EF:EF)+SUMIF(ER:ER,C65,EU:EU)+SUMIF(FA:FA,C65,FD:FD)+SUMIF(FK:FK,C65,FN:FN)+SUMIF(FT:FT,C65,FW:FW)+SUMIF(GC:GC,C65,GF:GF)+SUMIF(GL:GL,C65,GO:GO)+SUMIF(GU:GU,C65,GX:GX)+SUMIF(HD:HD,C65,HG:HG) -> 0 | G65: =+SUMIF(O:O,C65,T:T)+SUMIF(O:O,C65,S:S)+SUMIF(AE:AE,C65,AI:AI)+SUMIF(AT:AT,C65,AX:AX)+SUMIF(BI:BI,C65,BN:BN)+SUMIF(BI:BI,C65,BM:BM)+SUMIF(BY:BY,C65,CD:CD)+SUMIF(BY:BY,C65,CE:CE)+SUMIF(CP:CP,C65,CT:CT)+SUMIF(CY:CY,C65,DC:DC)+SUMIF(DN:DN,C65,DR:DR)+SUMIF(EC:EC,C65,EG:EG)+SUMIF(ER:ER,C65,EV:EV)+SUMIF(FA:FA,C65,FE:FE)+SUMIF(FK:FK,C65,FO:FO)+SUMIF(FT:FT,C65,FX:FX)+SUMIF(GC:GC,C65,GG:GG)+SUMIF(GL:GL,C65,GP:GP)+SUMIF(GU:GU,C65,GY:GY)+SUMIF(HD:HD,C65,HH:HH) -> 0 | H65: =+SUM(F65:G65) -> 0
A66: 41 | B66: =+WEEKNUM(C66,2) -> 45 | C66: =+C65+1 -> 45965 | E66: =+E65+D66-F66 -> 56989720 | F66: =+SUMIF(O:O,C66,R:R)+SUMIF(AE:AE,C66,AH:AH)+SUMIF(AT:AT,C66,AW:AW)+SUMIF(BI:BI,C66,BL:BL)+SUMIF(BY:BY,C66,CB:CB)+SUMIF(BY:BY,C66,CC:CC)+SUMIF(CP:CP,C66,CS:CS)+SUMIF(CY:CY,C66,DB:DB)+SUMIF(DN:DN,C66,DQ:DQ)+SUMIF(EC:EC,C66,EF:EF)+SUMIF(ER:ER,C66,EU:EU)+SUMIF(FA:FA,C66,FD:FD)+SUMIF(FK:FK,C66,FN:FN)+SUMIF(FT:FT,C66,FW:FW)+SUMIF(GC:GC,C66,GF:GF)+SUMIF(GL:GL,C66,GO:GO)+SUMIF(GU:GU,C66,GX:GX)+SUMIF(HD:HD,C66,HG:HG) -> 0 | G66: =+SUMIF(O:O,C66,T:T)+SUMIF(O:O,C66,S:S)+SUMIF(AE:AE,C66,AI:AI)+SUMIF(AT:AT,C66,AX:AX)+SUMIF(BI:BI,C66,BN:BN)+SUMIF(BI:BI,C66,BM:BM)+SUMIF(BY:BY,C66,CD:CD)+SUMIF(BY:BY,C66,CE:CE)+SUMIF(CP:CP,C66,CT:CT)+SUMIF(CY:CY,C66,DC:DC)+SUMIF(DN:DN,C66,DR:DR)+SUMIF(EC:EC,C66,EG:EG)+SUMIF(ER:ER,C66,EV:EV)+SUMIF(FA:FA,C66,FE:FE)+SUMIF(FK:FK,C66,FO:FO)+SUMIF(FT:FT,C66,FX:FX)+SUMIF(GC:GC,C66,GG:GG)+SUMIF(GL:GL,C66,GP:GP)+SUMIF(GU:GU,C66,GY:GY)+SUMIF(HD:HD,C66,HH:HH) -> 0 | H66: =+SUM(F66:G66) -> 0
A67: 42 | B67: =+WEEKNUM(C67,2) -> 45 | C67: =+C66+1 -> 45966 | E67: =+E66+D67-F67 -> 56989720 | F67: =+SUMIF(O:O,C67,R:R)+SUMIF(AE:AE,C67,AH:AH)+SUMIF(AT:AT,C67,AW:AW)+SUMIF(BI:BI,C67,BL:BL)+SUMIF(BY:BY,C67,CB:CB)+SUMIF(BY:BY,C67,CC:CC)+SUMIF(CP:CP,C67,CS:CS)+SUMIF(CY:CY,C67,DB:DB)+SUMIF(DN:DN,C67,DQ:DQ)+SUMIF(EC:EC,C67,EF:EF)+SUMIF(ER:ER,C67,EU:EU)+SUMIF(FA:FA,C67,FD:FD)+SUMIF(FK:FK,C67,FN:FN)+SUMIF(FT:FT,C67,FW:FW)+SUMIF(GC:GC,C67,GF:GF)+SUMIF(GL:GL,C67,GO:GO)+SUMIF(GU:GU,C67,GX:GX)+SUMIF(HD:HD,C67,HG:HG) -> 0 | G67: =+SUMIF(O:O,C67,T:T)+SUMIF(O:O,C67,S:S)+SUMIF(AE:AE,C67,AI:AI)+SUMIF(AT:AT,C67,AX:AX)+SUMIF(BI:BI,C67,BN:BN)+SUMIF(BI:BI,C67,BM:BM)+SUMIF(BY:BY,C67,CD:CD)+SUMIF(BY:BY,C67,CE:CE)+SUMIF(CP:CP,C67,CT:CT)+SUMIF(CY:CY,C67,DC:DC)+SUMIF(DN:DN,C67,DR:DR)+SUMIF(EC:EC,C67,EG:EG)+SUMIF(ER:ER,C67,EV:EV)+SUMIF(FA:FA,C67,FE:FE)+SUMIF(FK:FK,C67,FO:FO)+SUMIF(FT:FT,C67,FX:FX)+SUMIF(GC:GC,C67,GG:GG)+SUMIF(GL:GL,C67,GP:GP)+SUMIF(GU:GU,C67,GY:GY)+SUMIF(HD:HD,C67,HH:HH) -> 0 | H67: =+SUM(F67:G67) -> 0
A68: 43 | B68: =+WEEKNUM(C68,2) -> 45 | C68: =+C67+1 -> 45967 | E68: =+E67+D68-F68 -> 56989720 | F68: =+SUMIF(O:O,C68,R:R)+SUMIF(AE:AE,C68,AH:AH)+SUMIF(AT:AT,C68,AW:AW)+SUMIF(BI:BI,C68,BL:BL)+SUMIF(BY:BY,C68,CB:CB)+SUMIF(BY:BY,C68,CC:CC)+SUMIF(CP:CP,C68,CS:CS)+SUMIF(CY:CY,C68,DB:DB)+SUMIF(DN:DN,C68,DQ:DQ)+SUMIF(EC:EC,C68,EF:EF)+SUMIF(ER:ER,C68,EU:EU)+SUMIF(FA:FA,C68,FD:FD)+SUMIF(FK:FK,C68,FN:FN)+SUMIF(FT:FT,C68,FW:FW)+SUMIF(GC:GC,C68,GF:GF)+SUMIF(GL:GL,C68,GO:GO)+SUMIF(GU:GU,C68,GX:GX)+SUMIF(HD:HD,C68,HG:HG) -> 0 | G68: =+SUMIF(O:O,C68,T:T)+SUMIF(O:O,C68,S:S)+SUMIF(AE:AE,C68,AI:AI)+SUMIF(AT:AT,C68,AX:AX)+SUMIF(BI:BI,C68,BN:BN)+SUMIF(BI:BI,C68,BM:BM)+SUMIF(BY:BY,C68,CD:CD)+SUMIF(BY:BY,C68,CE:CE)+SUMIF(CP:CP,C68,CT:CT)+SUMIF(CY:CY,C68,DC:DC)+SUMIF(DN:DN,C68,DR:DR)+SUMIF(EC:EC,C68,EG:EG)+SUMIF(ER:ER,C68,EV:EV)+SUMIF(FA:FA,C68,FE:FE)+SUMIF(FK:FK,C68,FO:FO)+SUMIF(FT:FT,C68,FX:FX)+SUMIF(GC:GC,C68,GG:GG)+SUMIF(GL:GL,C68,GP:GP)+SUMIF(GU:GU,C68,GY:GY)+SUMIF(HD:HD,C68,HH:HH) -> 0 | H68: =+SUM(F68:G68) -> 0
A69: 44 | B69: =+WEEKNUM(C69,2) -> 45 | C69: =+C68+1 -> 45968 | E69: =+E68+D69-F69 -> 56989720 | F69: =+SUMIF(O:O,C69,R:R)+SUMIF(AE:AE,C69,AH:AH)+SUMIF(AT:AT,C69,AW:AW)+SUMIF(BI:BI,C69,BL:BL)+SUMIF(BY:BY,C69,CB:CB)+SUMIF(BY:BY,C69,CC:CC)+SUMIF(CP:CP,C69,CS:CS)+SUMIF(CY:CY,C69,DB:DB)+SUMIF(DN:DN,C69,DQ:DQ)+SUMIF(EC:EC,C69,EF:EF)+SUMIF(ER:ER,C69,EU:EU)+SUMIF(FA:FA,C69,FD:FD)+SUMIF(FK:FK,C69,FN:FN)+SUMIF(FT:FT,C69,FW:FW)+SUMIF(GC:GC,C69,GF:GF)+SUMIF(GL:GL,C69,GO:GO)+SUMIF(GU:GU,C69,GX:GX)+SUMIF(HD:HD,C69,HG:HG) -> 0 | G69: =+SUMIF(O:O,C69,T:T)+SUMIF(O:O,C69,S:S)+SUMIF(AE:AE,C69,AI:AI)+SUMIF(AT:AT,C69,AX:AX)+SUMIF(BI:BI,C69,BN:BN)+SUMIF(BI:BI,C69,BM:BM)+SUMIF(BY:BY,C69,CD:CD)+SUMIF(BY:BY,C69,CE:CE)+SUMIF(CP:CP,C69,CT:CT)+SUMIF(CY:CY,C69,DC:DC)+SUMIF(DN:DN,C69,DR:DR)+SUMIF(EC:EC,C69,EG:EG)+SUMIF(ER:ER,C69,EV:EV)+SUMIF(FA:FA,C69,FE:FE)+SUMIF(FK:FK,C69,FO:FO)+SUMIF(FT:FT,C69,FX:FX)+SUMIF(GC:GC,C69,GG:GG)+SUMIF(GL:GL,C69,GP:GP)+SUMIF(GU:GU,C69,GY:GY)+SUMIF(HD:HD,C69,HH:HH) -> 0 | H69: =+SUM(F69:G69) -> 0 | I69: =+H69 -> 0
A70: 45 | B70: =+WEEKNUM(C70,2) -> 45 | C70: =+C69+1 -> 45969 | E70: =+E69+D70-F70 -> 56989720 | F70: =+SUMIF(O:O,C70,R:R)+SUMIF(AE:AE,C70,AH:AH)+SUMIF(AT:AT,C70,AW:AW)+SUMIF(BI:BI,C70,BL:BL)+SUMIF(BY:BY,C70,CB:CB)+SUMIF(BY:BY,C70,CC:CC)+SUMIF(CP:CP,C70,CS:CS)+SUMIF(CY:CY,C70,DB:DB)+SUMIF(DN:DN,C70,DQ:DQ)+SUMIF(EC:EC,C70,EF:EF)+SUMIF(ER:ER,C70,EU:EU)+SUMIF(FA:FA,C70,FD:FD)+SUMIF(FK:FK,C70,FN:FN)+SUMIF(FT:FT,C70,FW:FW)+SUMIF(GC:GC,C70,GF:GF)+SUMIF(GL:GL,C70,GO:GO)+SUMIF(GU:GU,C70,GX:GX)+SUMIF(HD:HD,C70,HG:HG) -> 0 | G70: =+SUMIF(O:O,C70,T:T)+SUMIF(O:O,C70,S:S)+SUMIF(AE:AE,C70,AI:AI)+SUMIF(AT:AT,C70,AX:AX)+SUMIF(BI:BI,C70,BN:BN)+SUMIF(BI:BI,C70,BM:BM)+SUMIF(BY:BY,C70,CD:CD)+SUMIF(BY:BY,C70,CE:CE)+SUMIF(CP:CP,C70,CT:CT)+SUMIF(CY:CY,C70,DC:DC)+SUMIF(DN:DN,C70,DR:DR)+SUMIF(EC:EC,C70,EG:EG)+SUMIF(ER:ER,C70,EV:EV)+SUMIF(FA:FA,C70,FE:FE)+SUMIF(FK:FK,C70,FO:FO)+SUMIF(FT:FT,C70,FX:FX)+SUMIF(GC:GC,C70,GG:GG)+SUMIF(GL:GL,C70,GP:GP)+SUMIF(GU:GU,C70,GY:GY)+SUMIF(HD:HD,C70,HH:HH) -> 0 | H70: =+SUM(F70:G70) -> 0
A71: 46 | B71: =+WEEKNUM(C71,2) -> 45 | C71: =+C70+1 -> 45970 | E71: =+E70+D71-F71 -> 56989720 | F71: =+SUMIF(O:O,C71,R:R)+SUMIF(AE:AE,C71,AH:AH)+SUMIF(AT:AT,C71,AW:AW)+SUMIF(BI:BI,C71,BL:BL)+SUMIF(BY:BY,C71,CB:CB)+SUMIF(BY:BY,C71,CC:CC)+SUMIF(CP:CP,C71,CS:CS)+SUMIF(CY:CY,C71,DB:DB)+SUMIF(DN:DN,C71,DQ:DQ)+SUMIF(EC:EC,C71,EF:EF)+SUMIF(ER:ER,C71,EU:EU)+SUMIF(FA:FA,C71,FD:FD)+SUMIF(FK:FK,C71,FN:FN)+SUMIF(FT:FT,C71,FW:FW)+SUMIF(GC:GC,C71,GF:GF)+SUMIF(GL:GL,C71,GO:GO)+SUMIF(GU:GU,C71,GX:GX)+SUMIF(HD:HD,C71,HG:HG) -> 0 | G71: =+SUMIF(O:O,C71,T:T)+SUMIF(O:O,C71,S:S)+SUMIF(AE:AE,C71,AI:AI)+SUMIF(AT:AT,C71,AX:AX)+SUMIF(BI:BI,C71,BN:BN)+SUMIF(BI:BI,C71,BM:BM)+SUMIF(BY:BY,C71,CD:CD)+SUMIF(BY:BY,C71,CE:CE)+SUMIF(CP:CP,C71,CT:CT)+SUMIF(CY:CY,C71,DC:DC)+SUMIF(DN:DN,C71,DR:DR)+SUMIF(EC:EC,C71,EG:EG)+SUMIF(ER:ER,C71,EV:EV)+SUMIF(FA:FA,C71,FE:FE)+SUMIF(FK:FK,C71,FO:FO)+SUMIF(FT:FT,C71,FX:FX)+SUMIF(GC:GC,C71,GG:GG)+SUMIF(GL:GL,C71,GP:GP)+SUMIF(GU:GU,C71,GY:GY)+SUMIF(HD:HD,C71,HH:HH) -> 0 | H71: =+SUM(F71:G71) -> 0
A72: 47 | B72: =+WEEKNUM(C72,2) -> 46 | C72: =+C71+1 -> 45971 | E72: =+E71+D72-F72 -> 56640709 | F72: =+SUMIF(O:O,C72,R:R)+SUMIF(AE:AE,C72,AH:AH)+SUMIF(AT:AT,C72,AW:AW)+SUMIF(BI:BI,C72,BL:BL)+SUMIF(BY:BY,C72,CB:CB)+SUMIF(BY:BY,C72,CC:CC)+SUMIF(CP:CP,C72,CS:CS)+SUMIF(CY:CY,C72,DB:DB)+SUMIF(DN:DN,C72,DQ:DQ)+SUMIF(EC:EC,C72,EF:EF)+SUMIF(ER:ER,C72,EU:EU)+SUMIF(FA:FA,C72,FD:FD)+SUMIF(FK:FK,C72,FN:FN)+SUMIF(FT:FT,C72,FW:FW)+SUMIF(GC:GC,C72,GF:GF)+SUMIF(GL:GL,C72,GO:GO)+SUMIF(GU:GU,C72,GX:GX)+SUMIF(HD:HD,C72,HG:HG) -> 349011.21 | G72: =+SUMIF(O:O,C72,T:T)+SUMIF(O:O,C72,S:S)+SUMIF(AE:AE,C72,AI:AI)+SUMIF(AT:AT,C72,AX:AX)+SUMIF(BI:BI,C72,BN:BN)+SUMIF(BI:BI,C72,BM:BM)+SUMIF(BY:BY,C72,CD:CD)+SUMIF(BY:BY,C72,CE:CE)+SUMIF(CP:CP,C72,CT:CT)+SUMIF(CY:CY,C72,DC:DC)+SUMIF(DN:DN,C72,DR:DR)+SUMIF(EC:EC,C72,EG:EG)+SUMIF(ER:ER,C72,EV:EV)+SUMIF(FA:FA,C72,FE:FE)+SUMIF(FK:FK,C72,FO:FO)+SUMIF(FT:FT,C72,FX:FX)+SUMIF(GC:GC,C72,GG:GG)+SUMIF(GL:GL,C72,GP:GP)+SUMIF(GU:GU,C72,GY:GY)+SUMIF(HD:HD,C72,HH:HH) -> 128975.64 | H72: =+SUM(F72:G72) -> 477986.85
A73: 48 | B73: =+WEEKNUM(C73,2) -> 46 | C73: =+C72+1 -> 45972 | E73: =+E72+D73-F73 -> 56640709 | F73: =+SUMIF(O:O,C73,R:R)+SUMIF(AE:AE,C73,AH:AH)+SUMIF(AT:AT,C73,AW:AW)+SUMIF(BI:BI,C73,BL:BL)+SUMIF(BY:BY,C73,CB:CB)+SUMIF(BY:BY,C73,CC:CC)+SUMIF(CP:CP,C73,CS:CS)+SUMIF(CY:CY,C73,DB:DB)+SUMIF(DN:DN,C73,DQ:DQ)+SUMIF(EC:EC,C73,EF:EF)+SUMIF(ER:ER,C73,EU:EU)+SUMIF(FA:FA,C73,FD:FD)+SUMIF(FK:FK,C73,FN:FN)+SUMIF(FT:FT,C73,FW:FW)+SUMIF(GC:GC,C73,GF:GF)+SUMIF(GL:GL,C73,GO:GO)+SUMIF(GU:GU,C73,GX:GX)+SUMIF(HD:HD,C73,HG:HG) -> 0 | G73: =+SUMIF(O:O,C73,T:T)+SUMIF(O:O,C73,S:S)+SUMIF(AE:AE,C73,AI:AI)+SUMIF(AT:AT,C73,AX:AX)+SUMIF(BI:BI,C73,BN:BN)+SUMIF(BI:BI,C73,BM:BM)+SUMIF(BY:BY,C73,CD:CD)+SUMIF(BY:BY,C73,CE:CE)+SUMIF(CP:CP,C73,CT:CT)+SUMIF(CY:CY,C73,DC:DC)+SUMIF(DN:DN,C73,DR:DR)+SUMIF(EC:EC,C73,EG:EG)+SUMIF(ER:ER,C73,EV:EV)+SUMIF(FA:FA,C73,FE:FE)+SUMIF(FK:FK,C73,FO:FO)+SUMIF(FT:FT,C73,FX:FX)+SUMIF(GC:GC,C73,GG:GG)+SUMIF(GL:GL,C73,GP:GP)+SUMIF(GU:GU,C73,GY:GY)+SUMIF(HD:HD,C73,HH:HH) -> 0 | H73: =+SUM(F73:G73) -> 0
A74: 49 | B74: =+WEEKNUM(C74,2) -> 46 | C74: =+C73+1 -> 45973 | E74: =+E73+D74-F74 -> 56640709 | F74: =+SUMIF(O:O,C74,R:R)+SUMIF(AE:AE,C74,AH:AH)+SUMIF(AT:AT,C74,AW:AW)+SUMIF(BI:BI,C74,BL:BL)+SUMIF(BY:BY,C74,CB:CB)+SUMIF(BY:BY,C74,CC:CC)+SUMIF(CP:CP,C74,CS:CS)+SUMIF(CY:CY,C74,DB:DB)+SUMIF(DN:DN,C74,DQ:DQ)+SUMIF(EC:EC,C74,EF:EF)+SUMIF(ER:ER,C74,EU:EU)+SUMIF(FA:FA,C74,FD:FD)+SUMIF(FK:FK,C74,FN:FN)+SUMIF(FT:FT,C74,FW:FW)+SUMIF(GC:GC,C74,GF:GF)+SUMIF(GL:GL,C74,GO:GO)+SUMIF(GU:GU,C74,GX:GX)+SUMIF(HD:HD,C74,HG:HG) -> 0 | G74: =+SUMIF(O:O,C74,T:T)+SUMIF(O:O,C74,S:S)+SUMIF(AE:AE,C74,AI:AI)+SUMIF(AT:AT,C74,AX:AX)+SUMIF(BI:BI,C74,BN:BN)+SUMIF(BI:BI,C74,BM:BM)+SUMIF(BY:BY,C74,CD:CD)+SUMIF(BY:BY,C74,CE:CE)+SUMIF(CP:CP,C74,CT:CT)+SUMIF(CY:CY,C74,DC:DC)+SUMIF(DN:DN,C74,DR:DR)+SUMIF(EC:EC,C74,EG:EG)+SUMIF(ER:ER,C74,EV:EV)+SUMIF(FA:FA,C74,FE:FE)+SUMIF(FK:FK,C74,FO:FO)+SUMIF(FT:FT,C74,FX:FX)+SUMIF(GC:GC,C74,GG:GG)+SUMIF(GL:GL,C74,GP:GP)+SUMIF(GU:GU,C74,GY:GY)+SUMIF(HD:HD,C74,HH:HH) -> 0 | H74: =+SUM(F74:G74) -> 0 | I74: =+H74 -> 0
A75: 50 | B75: =+WEEKNUM(C75,2) -> 46 | C75: =+C74+1 -> 45974 | E75: =+E74+D75-F75 -> 56640709 | F75: =+SUMIF(O:O,C75,R:R)+SUMIF(AE:AE,C75,AH:AH)+SUMIF(AT:AT,C75,AW:AW)+SUMIF(BI:BI,C75,BL:BL)+SUMIF(BY:BY,C75,CB:CB)+SUMIF(BY:BY,C75,CC:CC)+SUMIF(CP:CP,C75,CS:CS)+SUMIF(CY:CY,C75,DB:DB)+SUMIF(DN:DN,C75,DQ:DQ)+SUMIF(EC:EC,C75,EF:EF)+SUMIF(ER:ER,C75,EU:EU)+SUMIF(FA:FA,C75,FD:FD)+SUMIF(FK:FK,C75,FN:FN)+SUMIF(FT:FT,C75,FW:FW)+SUMIF(GC:GC,C75,GF:GF)+SUMIF(GL:GL,C75,GO:GO)+SUMIF(GU:GU,C75,GX:GX)+SUMIF(HD:HD,C75,HG:HG) -> 0 | G75: =+SUMIF(O:O,C75,T:T)+SUMIF(O:O,C75,S:S)+SUMIF(AE:AE,C75,AI:AI)+SUMIF(AT:AT,C75,AX:AX)+SUMIF(BI:BI,C75,BN:BN)+SUMIF(BI:BI,C75,BM:BM)+SUMIF(BY:BY,C75,CD:CD)+SUMIF(BY:BY,C75,CE:CE)+SUMIF(CP:CP,C75,CT:CT)+SUMIF(CY:CY,C75,DC:DC)+SUMIF(DN:DN,C75,DR:DR)+SUMIF(EC:EC,C75,EG:EG)+SUMIF(ER:ER,C75,EV:EV)+SUMIF(FA:FA,C75,FE:FE)+SUMIF(FK:FK,C75,FO:FO)+SUMIF(FT:FT,C75,FX:FX)+SUMIF(GC:GC,C75,GG:GG)+SUMIF(GL:GL,C75,GP:GP)+SUMIF(GU:GU,C75,GY:GY)+SUMIF(HD:HD,C75,HH:HH) -> 0 | H75: =+SUM(F75:G75) -> 0 | I75: =+H75 -> 0
A76: 51 | B76: =+WEEKNUM(C76,2) -> 46 | C76: =+C75+1 -> 45975 | E76: =+E75+D76-F76 -> 56640709 | F76: =+SUMIF(O:O,C76,R:R)+SUMIF(AE:AE,C76,AH:AH)+SUMIF(AT:AT,C76,AW:AW)+SUMIF(BI:BI,C76,BL:BL)+SUMIF(BY:BY,C76,CB:CB)+SUMIF(BY:BY,C76,CC:CC)+SUMIF(CP:CP,C76,CS:CS)+SUMIF(CY:CY,C76,DB:DB)+SUMIF(DN:DN,C76,DQ:DQ)+SUMIF(EC:EC,C76,EF:EF)+SUMIF(ER:ER,C76,EU:EU)+SUMIF(FA:FA,C76,FD:FD)+SUMIF(FK:FK,C76,FN:FN)+SUMIF(FT:FT,C76,FW:FW)+SUMIF(GC:GC,C76,GF:GF)+SUMIF(GL:GL,C76,GO:GO)+SUMIF(GU:GU,C76,GX:GX)+SUMIF(HD:HD,C76,HG:HG) -> 0 | G76: =+SUMIF(O:O,C76,T:T)+SUMIF(O:O,C76,S:S)+SUMIF(AE:AE,C76,AI:AI)+SUMIF(AT:AT,C76,AX:AX)+SUMIF(BI:BI,C76,BN:BN)+SUMIF(BI:BI,C76,BM:BM)+SUMIF(BY:BY,C76,CD:CD)+SUMIF(BY:BY,C76,CE:CE)+SUMIF(CP:CP,C76,CT:CT)+SUMIF(CY:CY,C76,DC:DC)+SUMIF(DN:DN,C76,DR:DR)+SUMIF(EC:EC,C76,EG:EG)+SUMIF(ER:ER,C76,EV:EV)+SUMIF(FA:FA,C76,FE:FE)+SUMIF(FK:FK,C76,FO:FO)+SUMIF(FT:FT,C76,FX:FX)+SUMIF(GC:GC,C76,GG:GG)+SUMIF(GL:GL,C76,GP:GP)+SUMIF(GU:GU,C76,GY:GY)+SUMIF(HD:HD,C76,HH:HH) -> 0 | H76: =+SUM(F76:G76) -> 0
A77: 52 | B77: =+WEEKNUM(C77,2) -> 46 | C77: =+C76+1 -> 45976 | E77: =+E76+D77-F77 -> 26271215 | F77: =+SUMIF(O:O,C77,R:R)+SUMIF(AE:AE,C77,AH:AH)+SUMIF(AT:AT,C77,AW:AW)+SUMIF(BI:BI,C77,BL:BL)+SUMIF(BY:BY,C77,CB:CB)+SUMIF(BY:BY,C77,CC:CC)+SUMIF(CP:CP,C77,CS:CS)+SUMIF(CY:CY,C77,DB:DB)+SUMIF(DN:DN,C77,DQ:DQ)+SUMIF(EC:EC,C77,EF:EF)+SUMIF(ER:ER,C77,EU:EU)+SUMIF(FA:FA,C77,FD:FD)+SUMIF(FK:FK,C77,FN:FN)+SUMIF(FT:FT,C77,FW:FW)+SUMIF(GC:GC,C77,GF:GF)+SUMIF(GL:GL,C77,GO:GO)+SUMIF(GU:GU,C77,GX:GX)+SUMIF(HD:HD,C77,HG:HG) -> 30369494 | G77: =+SUMIF(O:O,C77,T:T)+SUMIF(O:O,C77,S:S)+SUMIF(AE:AE,C77,AI:AI)+SUMIF(AT:AT,C77,AX:AX)+SUMIF(BI:BI,C77,BN:BN)+SUMIF(BI:BI,C77,BM:BM)+SUMIF(BY:BY,C77,CD:CD)+SUMIF(BY:BY,C77,CE:CE)+SUMIF(CP:CP,C77,CT:CT)+SUMIF(CY:CY,C77,DC:DC)+SUMIF(DN:DN,C77,DR:DR)+SUMIF(EC:EC,C77,EG:EG)+SUMIF(ER:ER,C77,EV:EV)+SUMIF(FA:FA,C77,FE:FE)+SUMIF(FK:FK,C77,FO:FO)+SUMIF(FT:FT,C77,FX:FX)+SUMIF(GC:GC,C77,GG:GG)+SUMIF(GL:GL,C77,GP:GP)+SUMIF(GU:GU,C77,GY:GY)+SUMIF(HD:HD,C77,HH:HH) -> 2498532 | H77: =+SUM(F77:G77) -> 32868026
A78: 53 | B78: =+WEEKNUM(C78,2) -> 46 | C78: =+C77+1 -> 45977 | E78: =+E77+D78-F78 -> 26271215 | F78: =+SUMIF(O:O,C78,R:R)+SUMIF(AE:AE,C78,AH:AH)+SUMIF(AT:AT,C78,AW:AW)+SUMIF(BI:BI,C78,BL:BL)+SUMIF(BY:BY,C78,CB:CB)+SUMIF(BY:BY,C78,CC:CC)+SUMIF(CP:CP,C78,CS:CS)+SUMIF(CY:CY,C78,DB:DB)+SUMIF(DN:DN,C78,DQ:DQ)+SUMIF(EC:EC,C78,EF:EF)+SUMIF(ER:ER,C78,EU:EU)+SUMIF(FA:FA,C78,FD:FD)+SUMIF(FK:FK,C78,FN:FN)+SUMIF(FT:FT,C78,FW:FW)+SUMIF(GC:GC,C78,GF:GF)+SUMIF(GL:GL,C78,GO:GO)+SUMIF(GU:GU,C78,GX:GX)+SUMIF(HD:HD,C78,HG:HG) -> 0 | G78: =+SUMIF(O:O,C78,T:T)+SUMIF(O:O,C78,S:S)+SUMIF(AE:AE,C78,AI:AI)+SUMIF(AT:AT,C78,AX:AX)+SUMIF(BI:BI,C78,BN:BN)+SUMIF(BI:BI,C78,BM:BM)+SUMIF(BY:BY,C78,CD:CD)+SUMIF(BY:BY,C78,CE:CE)+SUMIF(CP:CP,C78,CT:CT)+SUMIF(CY:CY,C78,DC:DC)+SUMIF(DN:DN,C78,DR:DR)+SUMIF(EC:EC,C78,EG:EG)+SUMIF(ER:ER,C78,EV:EV)+SUMIF(FA:FA,C78,FE:FE)+SUMIF(FK:FK,C78,FO:FO)+SUMIF(FT:FT,C78,FX:FX)+SUMIF(GC:GC,C78,GG:GG)+SUMIF(GL:GL,C78,GP:GP)+SUMIF(GU:GU,C78,GY:GY)+SUMIF(HD:HD,C78,HH:HH) -> 0 | H78: =+SUM(F78:G78) -> 0
A79: 54 | B79: =+WEEKNUM(C79,2) -> 47 | C79: =+C78+1 -> 45978 | E79: =+E78+D79-F79 -> 26271215 | F79: =+SUMIF(O:O,C79,R:R)+SUMIF(AE:AE,C79,AH:AH)+SUMIF(AT:AT,C79,AW:AW)+SUMIF(BI:BI,C79,BL:BL)+SUMIF(BY:BY,C79,CB:CB)+SUMIF(BY:BY,C79,CC:CC)+SUMIF(CP:CP,C79,CS:CS)+SUMIF(CY:CY,C79,DB:DB)+SUMIF(DN:DN,C79,DQ:DQ)+SUMIF(EC:EC,C79,EF:EF)+SUMIF(ER:ER,C79,EU:EU)+SUMIF(FA:FA,C79,FD:FD)+SUMIF(FK:FK,C79,FN:FN)+SUMIF(FT:FT,C79,FW:FW)+SUMIF(GC:GC,C79,GF:GF)+SUMIF(GL:GL,C79,GO:GO)+SUMIF(GU:GU,C79,GX:GX)+SUMIF(HD:HD,C79,HG:HG) -> 0 | G79: =+SUMIF(O:O,C79,T:T)+SUMIF(O:O,C79,S:S)+SUMIF(AE:AE,C79,AI:AI)+SUMIF(AT:AT,C79,AX:AX)+SUMIF(BI:BI,C79,BN:BN)+SUMIF(BI:BI,C79,BM:BM)+SUMIF(BY:BY,C79,CD:CD)+SUMIF(BY:BY,C79,CE:CE)+SUMIF(CP:CP,C79,CT:CT)+SUMIF(CY:CY,C79,DC:DC)+SUMIF(DN:DN,C79,DR:DR)+SUMIF(EC:EC,C79,EG:EG)+SUMIF(ER:ER,C79,EV:EV)+SUMIF(FA:FA,C79,FE:FE)+SUMIF(FK:FK,C79,FO:FO)+SUMIF(FT:FT,C79,FX:FX)+SUMIF(GC:GC,C79,GG:GG)+SUMIF(GL:GL,C79,GP:GP)+SUMIF(GU:GU,C79,GY:GY)+SUMIF(HD:HD,C79,HH:HH) -> 0 | H79: =+SUM(F79:G79) -> 0 | I79: =+H79 -> 0
A80: 55 | B80: =+WEEKNUM(C80,2) -> 47 | C80: =+C79+1 -> 45979 | E80: =+E79+D80-F80 -> 26271215 | F80: =+SUMIF(O:O,C80,R:R)+SUMIF(AE:AE,C80,AH:AH)+SUMIF(AT:AT,C80,AW:AW)+SUMIF(BI:BI,C80,BL:BL)+SUMIF(BY:BY,C80,CB:CB)+SUMIF(BY:BY,C80,CC:CC)+SUMIF(CP:CP,C80,CS:CS)+SUMIF(CY:CY,C80,DB:DB)+SUMIF(DN:DN,C80,DQ:DQ)+SUMIF(EC:EC,C80,EF:EF)+SUMIF(ER:ER,C80,EU:EU)+SUMIF(FA:FA,C80,FD:FD)+SUMIF(FK:FK,C80,FN:FN)+SUMIF(FT:FT,C80,FW:FW)+SUMIF(GC:GC,C80,GF:GF)+SUMIF(GL:GL,C80,GO:GO)+SUMIF(GU:GU,C80,GX:GX)+SUMIF(HD:HD,C80,HG:HG) -> 0 | G80: =+SUMIF(O:O,C80,T:T)+SUMIF(O:O,C80,S:S)+SUMIF(AE:AE,C80,AI:AI)+SUMIF(AT:AT,C80,AX:AX)+SUMIF(BI:BI,C80,BN:BN)+SUMIF(BI:BI,C80,BM:BM)+SUMIF(BY:BY,C80,CD:CD)+SUMIF(BY:BY,C80,CE:CE)+SUMIF(CP:CP,C80,CT:CT)+SUMIF(CY:CY,C80,DC:DC)+SUMIF(DN:DN,C80,DR:DR)+SUMIF(EC:EC,C80,EG:EG)+SUMIF(ER:ER,C80,EV:EV)+SUMIF(FA:FA,C80,FE:FE)+SUMIF(FK:FK,C80,FO:FO)+SUMIF(FT:FT,C80,FX:FX)+SUMIF(GC:GC,C80,GG:GG)+SUMIF(GL:GL,C80,GP:GP)+SUMIF(GU:GU,C80,GY:GY)+SUMIF(HD:HD,C80,HH:HH) -> 0 | H80: =+SUM(F80:G80) -> 0
A81: 56 | B81: =+WEEKNUM(C81,2) -> 47 | C81: =+C80+1 -> 45980 | E81: =+E80+D81-F81 -> 26271215 | F81: =+SUMIF(O:O,C81,R:R)+SUMIF(AE:AE,C81,AH:AH)+SUMIF(AT:AT,C81,AW:AW)+SUMIF(BI:BI,C81,BL:BL)+SUMIF(BY:BY,C81,CB:CB)+SUMIF(BY:BY,C81,CC:CC)+SUMIF(CP:CP,C81,CS:CS)+SUMIF(CY:CY,C81,DB:DB)+SUMIF(DN:DN,C81,DQ:DQ)+SUMIF(EC:EC,C81,EF:EF)+SUMIF(ER:ER,C81,EU:EU)+SUMIF(FA:FA,C81,FD:FD)+SUMIF(FK:FK,C81,FN:FN)+SUMIF(FT:FT,C81,FW:FW)+SUMIF(GC:GC,C81,GF:GF)+SUMIF(GL:GL,C81,GO:GO)+SUMIF(GU:GU,C81,GX:GX)+SUMIF(HD:HD,C81,HG:HG) -> 0 | G81: =+SUMIF(O:O,C81,T:T)+SUMIF(O:O,C81,S:S)+SUMIF(AE:AE,C81,AI:AI)+SUMIF(AT:AT,C81,AX:AX)+SUMIF(BI:BI,C81,BN:BN)+SUMIF(BI:BI,C81,BM:BM)+SUMIF(BY:BY,C81,CD:CD)+SUMIF(BY:BY,C81,CE:CE)+SUMIF(CP:CP,C81,CT:CT)+SUMIF(CY:CY,C81,DC:DC)+SUMIF(DN:DN,C81,DR:DR)+SUMIF(EC:EC,C81,EG:EG)+SUMIF(ER:ER,C81,EV:EV)+SUMIF(FA:FA,C81,FE:FE)+SUMIF(FK:FK,C81,FO:FO)+SUMIF(FT:FT,C81,FX:FX)+SUMIF(GC:GC,C81,GG:GG)+SUMIF(GL:GL,C81,GP:GP)+SUMIF(GU:GU,C81,GY:GY)+SUMIF(HD:HD,C81,HH:HH) -> 0 | H81: =+SUM(F81:G81) -> 0
A82: 57 | B82: =+WEEKNUM(C82,2) -> 47 | C82: =+C81+1 -> 45981 | E82: =+E81+D82-F82 -> 26271215 | F82: =+SUMIF(O:O,C82,R:R)+SUMIF(AE:AE,C82,AH:AH)+SUMIF(AT:AT,C82,AW:AW)+SUMIF(BI:BI,C82,BL:BL)+SUMIF(BY:BY,C82,CB:CB)+SUMIF(BY:BY,C82,CC:CC)+SUMIF(CP:CP,C82,CS:CS)+SUMIF(CY:CY,C82,DB:DB)+SUMIF(DN:DN,C82,DQ:DQ)+SUMIF(EC:EC,C82,EF:EF)+SUMIF(ER:ER,C82,EU:EU)+SUMIF(FA:FA,C82,FD:FD)+SUMIF(FK:FK,C82,FN:FN)+SUMIF(FT:FT,C82,FW:FW)+SUMIF(GC:GC,C82,GF:GF)+SUMIF(GL:GL,C82,GO:GO)+SUMIF(GU:GU,C82,GX:GX)+SUMIF(HD:HD,C82,HG:HG) -> 0 | G82: =+SUMIF(O:O,C82,T:T)+SUMIF(O:O,C82,S:S)+SUMIF(AE:AE,C82,AI:AI)+SUMIF(AT:AT,C82,AX:AX)+SUMIF(BI:BI,C82,BN:BN)+SUMIF(BI:BI,C82,BM:BM)+SUMIF(BY:BY,C82,CD:CD)+SUMIF(BY:BY,C82,CE:CE)+SUMIF(CP:CP,C82,CT:CT)+SUMIF(CY:CY,C82,DC:DC)+SUMIF(DN:DN,C82,DR:DR)+SUMIF(EC:EC,C82,EG:EG)+SUMIF(ER:ER,C82,EV:EV)+SUMIF(FA:FA,C82,FE:FE)+SUMIF(FK:FK,C82,FO:FO)+SUMIF(FT:FT,C82,FX:FX)+SUMIF(GC:GC,C82,GG:GG)+SUMIF(GL:GL,C82,GP:GP)+SUMIF(GU:GU,C82,GY:GY)+SUMIF(HD:HD,C82,HH:HH) -> 245279.91 | H82: =+SUM(F82:G82) -> 245279.91
A83: 58 | B83: =+WEEKNUM(C83,2) -> 47 | C83: =+C82+1 -> 45982 | E83: =+E82+D83-F83 -> 26271215 | F83: =+SUMIF(O:O,C83,R:R)+SUMIF(AE:AE,C83,AH:AH)+SUMIF(AT:AT,C83,AW:AW)+SUMIF(BI:BI,C83,BL:BL)+SUMIF(BY:BY,C83,CB:CB)+SUMIF(BY:BY,C83,CC:CC)+SUMIF(CP:CP,C83,CS:CS)+SUMIF(CY:CY,C83,DB:DB)+SUMIF(DN:DN,C83,DQ:DQ)+SUMIF(EC:EC,C83,EF:EF)+SUMIF(ER:ER,C83,EU:EU)+SUMIF(FA:FA,C83,FD:FD)+SUMIF(FK:FK,C83,FN:FN)+SUMIF(FT:FT,C83,FW:FW)+SUMIF(GC:GC,C83,GF:GF)+SUMIF(GL:GL,C83,GO:GO)+SUMIF(GU:GU,C83,GX:GX)+SUMIF(HD:HD,C83,HG:HG) -> 0 | G83: =+SUMIF(O:O,C83,T:T)+SUMIF(O:O,C83,S:S)+SUMIF(AE:AE,C83,AI:AI)+SUMIF(AT:AT,C83,AX:AX)+SUMIF(BI:BI,C83,BN:BN)+SUMIF(BI:BI,C83,BM:BM)+SUMIF(BY:BY,C83,CD:CD)+SUMIF(BY:BY,C83,CE:CE)+SUMIF(CP:CP,C83,CT:CT)+SUMIF(CY:CY,C83,DC:DC)+SUMIF(DN:DN,C83,DR:DR)+SUMIF(EC:EC,C83,EG:EG)+SUMIF(ER:ER,C83,EV:EV)+SUMIF(FA:FA,C83,FE:FE)+SUMIF(FK:FK,C83,FO:FO)+SUMIF(FT:FT,C83,FX:FX)+SUMIF(GC:GC,C83,GG:GG)+SUMIF(GL:GL,C83,GP:GP)+SUMIF(GU:GU,C83,GY:GY)+SUMIF(HD:HD,C83,HH:HH) -> 0 | H83: =+SUM(F83:G83) -> 0
A84: 59 | B84: =+WEEKNUM(C84,2) -> 47 | C84: =+C83+1 -> 45983 | E84: =+E83+D84-F84 -> 26271215 | F84: =+SUMIF(O:O,C84,R:R)+SUMIF(AE:AE,C84,AH:AH)+SUMIF(AT:AT,C84,AW:AW)+SUMIF(BI:BI,C84,BL:BL)+SUMIF(BY:BY,C84,CB:CB)+SUMIF(BY:BY,C84,CC:CC)+SUMIF(CP:CP,C84,CS:CS)+SUMIF(CY:CY,C84,DB:DB)+SUMIF(DN:DN,C84,DQ:DQ)+SUMIF(EC:EC,C84,EF:EF)+SUMIF(ER:ER,C84,EU:EU)+SUMIF(FA:FA,C84,FD:FD)+SUMIF(FK:FK,C84,FN:FN)+SUMIF(FT:FT,C84,FW:FW)+SUMIF(GC:GC,C84,GF:GF)+SUMIF(GL:GL,C84,GO:GO)+SUMIF(GU:GU,C84,GX:GX)+SUMIF(HD:HD,C84,HG:HG) -> 0 | G84: =+SUMIF(O:O,C84,T:T)+SUMIF(O:O,C84,S:S)+SUMIF(AE:AE,C84,AI:AI)+SUMIF(AT:AT,C84,AX:AX)+SUMIF(BI:BI,C84,BN:BN)+SUMIF(BI:BI,C84,BM:BM)+SUMIF(BY:BY,C84,CD:CD)+SUMIF(BY:BY,C84,CE:CE)+SUMIF(CP:CP,C84,CT:CT)+SUMIF(CY:CY,C84,DC:DC)+SUMIF(DN:DN,C84,DR:DR)+SUMIF(EC:EC,C84,EG:EG)+SUMIF(ER:ER,C84,EV:EV)+SUMIF(FA:FA,C84,FE:FE)+SUMIF(FK:FK,C84,FO:FO)+SUMIF(FT:FT,C84,FX:FX)+SUMIF(GC:GC,C84,GG:GG)+SUMIF(GL:GL,C84,GP:GP)+SUMIF(GU:GU,C84,GY:GY)+SUMIF(HD:HD,C84,HH:HH) -> 0 | H84: =+SUM(F84:G84) -> 0
A85: 60 | B85: =+WEEKNUM(C85,2) -> 47 | C85: =+C84+1 -> 45984 | E85: =+E84+D85-F85 -> 26271215 | F85: =+SUMIF(O:O,C85,R:R)+SUMIF(AE:AE,C85,AH:AH)+SUMIF(AT:AT,C85,AW:AW)+SUMIF(BI:BI,C85,BL:BL)+SUMIF(BY:BY,C85,CB:CB)+SUMIF(BY:BY,C85,CC:CC)+SUMIF(CP:CP,C85,CS:CS)+SUMIF(CY:CY,C85,DB:DB)+SUMIF(DN:DN,C85,DQ:DQ)+SUMIF(EC:EC,C85,EF:EF)+SUMIF(ER:ER,C85,EU:EU)+SUMIF(FA:FA,C85,FD:FD)+SUMIF(FK:FK,C85,FN:FN)+SUMIF(FT:FT,C85,FW:FW)+SUMIF(GC:GC,C85,GF:GF)+SUMIF(GL:GL,C85,GO:GO)+SUMIF(GU:GU,C85,GX:GX)+SUMIF(HD:HD,C85,HG:HG) -> 0 | G85: =+SUMIF(O:O,C85,T:T)+SUMIF(O:O,C85,S:S)+SUMIF(AE:AE,C85,AI:AI)+SUMIF(AT:AT,C85,AX:AX)+SUMIF(BI:BI,C85,BN:BN)+SUMIF(BI:BI,C85,BM:BM)+SUMIF(BY:BY,C85,CD:CD)+SUMIF(BY:BY,C85,CE:CE)+SUMIF(CP:CP,C85,CT:CT)+SUMIF(CY:CY,C85,DC:DC)+SUMIF(DN:DN,C85,DR:DR)+SUMIF(EC:EC,C85,EG:EG)+SUMIF(ER:ER,C85,EV:EV)+SUMIF(FA:FA,C85,FE:FE)+SUMIF(FK:FK,C85,FO:FO)+SUMIF(FT:FT,C85,FX:FX)+SUMIF(GC:GC,C85,GG:GG)+SUMIF(GL:GL,C85,GP:GP)+SUMIF(GU:GU,C85,GY:GY)+SUMIF(HD:HD,C85,HH:HH) -> 0 | H85: =+SUM(F85:G85) -> 0
A86: 61 | B86: =+WEEKNUM(C86,2) -> 48 | C86: =+C85+1 -> 45985 | E86: =+E85+D86-F86 -> 26271215 | F86: =+SUMIF(O:O,C86,R:R)+SUMIF(AE:AE,C86,AH:AH)+SUMIF(AT:AT,C86,AW:AW)+SUMIF(BI:BI,C86,BL:BL)+SUMIF(BY:BY,C86,CB:CB)+SUMIF(BY:BY,C86,CC:CC)+SUMIF(CP:CP,C86,CS:CS)+SUMIF(CY:CY,C86,DB:DB)+SUMIF(DN:DN,C86,DQ:DQ)+SUMIF(EC:EC,C86,EF:EF)+SUMIF(ER:ER,C86,EU:EU)+SUMIF(FA:FA,C86,FD:FD)+SUMIF(FK:FK,C86,FN:FN)+SUMIF(FT:FT,C86,FW:FW)+SUMIF(GC:GC,C86,GF:GF)+SUMIF(GL:GL,C86,GO:GO)+SUMIF(GU:GU,C86,GX:GX)+SUMIF(HD:HD,C86,HG:HG) -> 0 | G86: =+SUMIF(O:O,C86,T:T)+SUMIF(O:O,C86,S:S)+SUMIF(AE:AE,C86,AI:AI)+SUMIF(AT:AT,C86,AX:AX)+SUMIF(BI:BI,C86,BN:BN)+SUMIF(BI:BI,C86,BM:BM)+SUMIF(BY:BY,C86,CD:CD)+SUMIF(BY:BY,C86,CE:CE)+SUMIF(CP:CP,C86,CT:CT)+SUMIF(CY:CY,C86,DC:DC)+SUMIF(DN:DN,C86,DR:DR)+SUMIF(EC:EC,C86,EG:EG)+SUMIF(ER:ER,C86,EV:EV)+SUMIF(FA:FA,C86,FE:FE)+SUMIF(FK:FK,C86,FO:FO)+SUMIF(FT:FT,C86,FX:FX)+SUMIF(GC:GC,C86,GG:GG)+SUMIF(GL:GL,C86,GP:GP)+SUMIF(GU:GU,C86,GY:GY)+SUMIF(HD:HD,C86,HH:HH) -> 0 | H86: =+SUM(F86:G86) -> 0
A87: 62 | B87: =+WEEKNUM(C87,2) -> 48 | C87: =+C86+1 -> 45986 | E87: =+E86+D87-F87 -> 26271215 | F87: =+SUMIF(O:O,C87,R:R)+SUMIF(AE:AE,C87,AH:AH)+SUMIF(AT:AT,C87,AW:AW)+SUMIF(BI:BI,C87,BL:BL)+SUMIF(BY:BY,C87,CB:CB)+SUMIF(BY:BY,C87,CC:CC)+SUMIF(CP:CP,C87,CS:CS)+SUMIF(CY:CY,C87,DB:DB)+SUMIF(DN:DN,C87,DQ:DQ)+SUMIF(EC:EC,C87,EF:EF)+SUMIF(ER:ER,C87,EU:EU)+SUMIF(FA:FA,C87,FD:FD)+SUMIF(FK:FK,C87,FN:FN)+SUMIF(FT:FT,C87,FW:FW)+SUMIF(GC:GC,C87,GF:GF)+SUMIF(GL:GL,C87,GO:GO)+SUMIF(GU:GU,C87,GX:GX)+SUMIF(HD:HD,C87,HG:HG) -> 0 | G87: =+SUMIF(O:O,C87,T:T)+SUMIF(O:O,C87,S:S)+SUMIF(AE:AE,C87,AI:AI)+SUMIF(AT:AT,C87,AX:AX)+SUMIF(BI:BI,C87,BN:BN)+SUMIF(BI:BI,C87,BM:BM)+SUMIF(BY:BY,C87,CD:CD)+SUMIF(BY:BY,C87,CE:CE)+SUMIF(CP:CP,C87,CT:CT)+SUMIF(CY:CY,C87,DC:DC)+SUMIF(DN:DN,C87,DR:DR)+SUMIF(EC:EC,C87,EG:EG)+SUMIF(ER:ER,C87,EV:EV)+SUMIF(FA:FA,C87,FE:FE)+SUMIF(FK:FK,C87,FO:FO)+SUMIF(FT:FT,C87,FX:FX)+SUMIF(GC:GC,C87,GG:GG)+SUMIF(GL:GL,C87,GP:GP)+SUMIF(GU:GU,C87,GY:GY)+SUMIF(HD:HD,C87,HH:HH) -> 0 | H87: =+SUM(F87:G87) -> 0
A88: 63 | B88: =+WEEKNUM(C88,2) -> 48 | C88: =+C87+1 -> 45987 | E88: =+E87+D88-F88 -> 26271215 | F88: =+SUMIF(O:O,C88,R:R)+SUMIF(AE:AE,C88,AH:AH)+SUMIF(AT:AT,C88,AW:AW)+SUMIF(BI:BI,C88,BL:BL)+SUMIF(BY:BY,C88,CB:CB)+SUMIF(BY:BY,C88,CC:CC)+SUMIF(CP:CP,C88,CS:CS)+SUMIF(CY:CY,C88,DB:DB)+SUMIF(DN:DN,C88,DQ:DQ)+SUMIF(EC:EC,C88,EF:EF)+SUMIF(ER:ER,C88,EU:EU)+SUMIF(FA:FA,C88,FD:FD)+SUMIF(FK:FK,C88,FN:FN)+SUMIF(FT:FT,C88,FW:FW)+SUMIF(GC:GC,C88,GF:GF)+SUMIF(GL:GL,C88,GO:GO)+SUMIF(GU:GU,C88,GX:GX)+SUMIF(HD:HD,C88,HG:HG) -> 0 | G88: =+SUMIF(O:O,C88,T:T)+SUMIF(O:O,C88,S:S)+SUMIF(AE:AE,C88,AI:AI)+SUMIF(AT:AT,C88,AX:AX)+SUMIF(BI:BI,C88,BN:BN)+SUMIF(BI:BI,C88,BM:BM)+SUMIF(BY:BY,C88,CD:CD)+SUMIF(BY:BY,C88,CE:CE)+SUMIF(CP:CP,C88,CT:CT)+SUMIF(CY:CY,C88,DC:DC)+SUMIF(DN:DN,C88,DR:DR)+SUMIF(EC:EC,C88,EG:EG)+SUMIF(ER:ER,C88,EV:EV)+SUMIF(FA:FA,C88,FE:FE)+SUMIF(FK:FK,C88,FO:FO)+SUMIF(FT:FT,C88,FX:FX)+SUMIF(GC:GC,C88,GG:GG)+SUMIF(GL:GL,C88,GP:GP)+SUMIF(GU:GU,C88,GY:GY)+SUMIF(HD:HD,C88,HH:HH) -> 0 | H88: =+SUM(F88:G88) -> 0
A89: 64 | B89: =+WEEKNUM(C89,2) -> 48 | C89: =+C88+1 -> 45988 | E89: =+E88+D89-F89 -> 26271215 | F89: =+SUMIF(O:O,C89,R:R)+SUMIF(AE:AE,C89,AH:AH)+SUMIF(AT:AT,C89,AW:AW)+SUMIF(BI:BI,C89,BL:BL)+SUMIF(BY:BY,C89,CB:CB)+SUMIF(BY:BY,C89,CC:CC)+SUMIF(CP:CP,C89,CS:CS)+SUMIF(CY:CY,C89,DB:DB)+SUMIF(DN:DN,C89,DQ:DQ)+SUMIF(EC:EC,C89,EF:EF)+SUMIF(ER:ER,C89,EU:EU)+SUMIF(FA:FA,C89,FD:FD)+SUMIF(FK:FK,C89,FN:FN)+SUMIF(FT:FT,C89,FW:FW)+SUMIF(GC:GC,C89,GF:GF)+SUMIF(GL:GL,C89,GO:GO)+SUMIF(GU:GU,C89,GX:GX)+SUMIF(HD:HD,C89,HG:HG) -> 0 | G89: =+SUMIF(O:O,C89,T:T)+SUMIF(O:O,C89,S:S)+SUMIF(AE:AE,C89,AI:AI)+SUMIF(AT:AT,C89,AX:AX)+SUMIF(BI:BI,C89,BN:BN)+SUMIF(BI:BI,C89,BM:BM)+SUMIF(BY:BY,C89,CD:CD)+SUMIF(BY:BY,C89,CE:CE)+SUMIF(CP:CP,C89,CT:CT)+SUMIF(CY:CY,C89,DC:DC)+SUMIF(DN:DN,C89,DR:DR)+SUMIF(EC:EC,C89,EG:EG)+SUMIF(ER:ER,C89,EV:EV)+SUMIF(FA:FA,C89,FE:FE)+SUMIF(FK:FK,C89,FO:FO)+SUMIF(FT:FT,C89,FX:FX)+SUMIF(GC:GC,C89,GG:GG)+SUMIF(GL:GL,C89,GP:GP)+SUMIF(GU:GU,C89,GY:GY)+SUMIF(HD:HD,C89,HH:HH) -> 0 | H89: =+SUM(F89:G89) -> 0
A90: 65 | B90: =+WEEKNUM(C90,2) -> 48 | C90: =+C89+1 -> 45989 | E90: =+E89+D90-F90 -> 26271215 | F90: =+SUMIF(O:O,C90,R:R)+SUMIF(AE:AE,C90,AH:AH)+SUMIF(AT:AT,C90,AW:AW)+SUMIF(BI:BI,C90,BL:BL)+SUMIF(BY:BY,C90,CB:CB)+SUMIF(BY:BY,C90,CC:CC)+SUMIF(CP:CP,C90,CS:CS)+SUMIF(CY:CY,C90,DB:DB)+SUMIF(DN:DN,C90,DQ:DQ)+SUMIF(EC:EC,C90,EF:EF)+SUMIF(ER:ER,C90,EU:EU)+SUMIF(FA:FA,C90,FD:FD)+SUMIF(FK:FK,C90,FN:FN)+SUMIF(FT:FT,C90,FW:FW)+SUMIF(GC:GC,C90,GF:GF)+SUMIF(GL:GL,C90,GO:GO)+SUMIF(GU:GU,C90,GX:GX)+SUMIF(HD:HD,C90,HG:HG) -> 0 | G90: =+SUMIF(O:O,C90,T:T)+SUMIF(O:O,C90,S:S)+SUMIF(AE:AE,C90,AI:AI)+SUMIF(AT:AT,C90,AX:AX)+SUMIF(BI:BI,C90,BN:BN)+SUMIF(BI:BI,C90,BM:BM)+SUMIF(BY:BY,C90,CD:CD)+SUMIF(BY:BY,C90,CE:CE)+SUMIF(CP:CP,C90,CT:CT)+SUMIF(CY:CY,C90,DC:DC)+SUMIF(DN:DN,C90,DR:DR)+SUMIF(EC:EC,C90,EG:EG)+SUMIF(ER:ER,C90,EV:EV)+SUMIF(FA:FA,C90,FE:FE)+SUMIF(FK:FK,C90,FO:FO)+SUMIF(FT:FT,C90,FX:FX)+SUMIF(GC:GC,C90,GG:GG)+SUMIF(GL:GL,C90,GP:GP)+SUMIF(GU:GU,C90,GY:GY)+SUMIF(HD:HD,C90,HH:HH) -> 0 | H90: =+SUM(F90:G90) -> 0
A91: 66 | B91: =+WEEKNUM(C91,2) -> 48 | C91: =+C90+1 -> 45990 | E91: =+E90+D91-F91 -> 26271215 | F91: =+SUMIF(O:O,C91,R:R)+SUMIF(AE:AE,C91,AH:AH)+SUMIF(AT:AT,C91,AW:AW)+SUMIF(BI:BI,C91,BL:BL)+SUMIF(BY:BY,C91,CB:CB)+SUMIF(BY:BY,C91,CC:CC)+SUMIF(CP:CP,C91,CS:CS)+SUMIF(CY:CY,C91,DB:DB)+SUMIF(DN:DN,C91,DQ:DQ)+SUMIF(EC:EC,C91,EF:EF)+SUMIF(ER:ER,C91,EU:EU)+SUMIF(FA:FA,C91,FD:FD)+SUMIF(FK:FK,C91,FN:FN)+SUMIF(FT:FT,C91,FW:FW)+SUMIF(GC:GC,C91,GF:GF)+SUMIF(GL:GL,C91,GO:GO)+SUMIF(GU:GU,C91,GX:GX)+SUMIF(HD:HD,C91,HG:HG) -> 0 | G91: =+SUMIF(O:O,C91,T:T)+SUMIF(O:O,C91,S:S)+SUMIF(AE:AE,C91,AI:AI)+SUMIF(AT:AT,C91,AX:AX)+SUMIF(BI:BI,C91,BN:BN)+SUMIF(BI:BI,C91,BM:BM)+SUMIF(BY:BY,C91,CD:CD)+SUMIF(BY:BY,C91,CE:CE)+SUMIF(CP:CP,C91,CT:CT)+SUMIF(CY:CY,C91,DC:DC)+SUMIF(DN:DN,C91,DR:DR)+SUMIF(EC:EC,C91,EG:EG)+SUMIF(ER:ER,C91,EV:EV)+SUMIF(FA:FA,C91,FE:FE)+SUMIF(FK:FK,C91,FO:FO)+SUMIF(FT:FT,C91,FX:FX)+SUMIF(GC:GC,C91,GG:GG)+SUMIF(GL:GL,C91,GP:GP)+SUMIF(GU:GU,C91,GY:GY)+SUMIF(HD:HD,C91,HH:HH) -> 0 | H91: =+SUM(F91:G91) -> 0
... A105: 80 | B105: =+WEEKNUM(C105,2) -> 50 | C105: =+C104+1 -> 46004 | E105: =+E104+D105-F105 -> 25842927 | F105: =+SUMIF(O:O,C105,R:R)+SUMIF(AE:AE,C105,AH:AH)+SUMIF(AT:AT,C105,AW:AW)+SUMIF(BI:BI,C105,BL:BL)+SUMIF(BY:BY,C105,CB:CB)+SUMIF(BY:BY,C105,CC:CC)+SUMIF(CP:CP,C105,CS:CS)+SUMIF(CY:CY,C105,DB:DB)+SUMIF(DN:DN,C105,DQ:DQ)+SUMIF(EC:EC,C105,EF:EF)+SUMIF(ER:ER,C105,EU:EU)+SUMIF(FA:FA,C105,FD:FD)+SUMIF(FK:FK,C105,FN:FN)+SUMIF(FT:FT,C105,FW:FW)+SUMIF(GC:GC,C105,GF:GF)+SUMIF(GL:GL,C105,GO:GO)+SUMIF(GU:GU,C105,GX:GX)+SUMIF(HD:HD,C105,HG:HG) -> 0 | G105: =+SUMIF(O:O,C105,T:T)+SUMIF(O:O,C105,S:S)+SUMIF(AE:AE,C105,AI:AI)+SUMIF(AT:AT,C105,AX:AX)+SUMIF(BI:BI,C105,BN:BN)+SUMIF(BI:BI,C105,BM:BM)+SUMIF(BY:BY,C105,CD:CD)+SUMIF(BY:BY,C105,CE:CE)+SUMIF(CP:CP,C105,CT:CT)+SUMIF(CY:CY,C105,DC:DC)+SUMIF(DN:DN,C105,DR:DR)+SUMIF(EC:EC,C105,EG:EG)+SUMIF(ER:ER,C105,EV:EV)+SUMIF(FA:FA,C105,FE:FE)+SUMIF(FK:FK,C105,FO:FO)+SUMIF(FT:FT,C105,FX:FX)+SUMIF(GC:GC,C105,GG:GG)+SUMIF(GL:GL,C105,GP:GP)+SUMIF(GU:GU,C105,GY:GY)+SUMIF(HD:HD,C105,HH:HH) -> 0 | H105: =+SUM(F105:G105) -> 0
A106: 81 | B106: =+WEEKNUM(C106,2) -> 50 | C106: =+C105+1 -> 46005 | E106: =+E105+D106-F106 -> 25738609 | F106: =+SUMIF(O:O,C106,R:R)+SUMIF(AE:AE,C106,AH:AH)+SUMIF(AT:AT,C106,AW:AW)+SUMIF(BI:BI,C106,BL:BL)+SUMIF(BY:BY,C106,CB:CB)+SUMIF(BY:BY,C106,CC:CC)+SUMIF(CP:CP,C106,CS:CS)+SUMIF(CY:CY,C106,DB:DB)+SUMIF(DN:DN,C106,DQ:DQ)+SUMIF(EC:EC,C106,EF:EF)+SUMIF(ER:ER,C106,EU:EU)+SUMIF(FA:FA,C106,FD:FD)+SUMIF(FK:FK,C106,FN:FN)+SUMIF(FT:FT,C106,FW:FW)+SUMIF(GC:GC,C106,GF:GF)+SUMIF(GL:GL,C106,GO:GO)+SUMIF(GU:GU,C106,GX:GX)+SUMIF(HD:HD,C106,HG:HG) -> 104317.86 | G106: =+SUMIF(O:O,C106,T:T)+SUMIF(O:O,C106,S:S)+SUMIF(AE:AE,C106,AI:AI)+SUMIF(AT:AT,C106,AX:AX)+SUMIF(BI:BI,C106,BN:BN)+SUMIF(BI:BI,C106,BM:BM)+SUMIF(BY:BY,C106,CD:CD)+SUMIF(BY:BY,C106,CE:CE)+SUMIF(CP:CP,C106,CT:CT)+SUMIF(CY:CY,C106,DC:DC)+SUMIF(DN:DN,C106,DR:DR)+SUMIF(EC:EC,C106,EG:EG)+SUMIF(ER:ER,C106,EV:EV)+SUMIF(FA:FA,C106,FE:FE)+SUMIF(FK:FK,C106,FO:FO)+SUMIF(FT:FT,C106,FX:FX)+SUMIF(GC:GC,C106,GG:GG)+SUMIF(GL:GL,C106,GP:GP)+SUMIF(GU:GU,C106,GY:GY)+SUMIF(HD:HD,C106,HH:HH) -> 22150.161 | H106: =+SUM(F106:G106) -> 126468.02 | I106: 0
A107: 82 | B107: =+WEEKNUM(C107,2) -> 51 | C107: =+C106+1 -> 46006 | E107: =+E106+D107-F107 -> 25738609 | F107: =+SUMIF(O:O,C107,R:R)+SUMIF(AE:AE,C107,AH:AH)+SUMIF(AT:AT,C107,AW:AW)+SUMIF(BI:BI,C107,BL:BL)+SUMIF(BY:BY,C107,CB:CB)+SUMIF(BY:BY,C107,CC:CC)+SUMIF(CP:CP,C107,CS:CS)+SUMIF(CY:CY,C107,DB:DB)+SUMIF(DN:DN,C107,DQ:DQ)+SUMIF(EC:EC,C107,EF:EF)+SUMIF(ER:ER,C107,EU:EU)+SUMIF(FA:FA,C107,FD:FD)+SUMIF(FK:FK,C107,FN:FN)+SUMIF(FT:FT,C107,FW:FW)+SUMIF(GC:GC,C107,GF:GF)+SUMIF(GL:GL,C107,GO:GO)+SUMIF(GU:GU,C107,GX:GX)+SUMIF(HD:HD,C107,HG:HG) -> 0 | G107: =+SUMIF(O:O,C107,T:T)+SUMIF(O:O,C107,S:S)+SUMIF(AE:AE,C107,AI:AI)+SUMIF(AT:AT,C107,AX:AX)+SUMIF(BI:BI,C107,BN:BN)+SUMIF(BI:BI,C107,BM:BM)+SUMIF(BY:BY,C107,CD:CD)+SUMIF(BY:BY,C107,CE:CE)+SUMIF(CP:CP,C107,CT:CT)+SUMIF(CY:CY,C107,DC:DC)+SUMIF(DN:DN,C107,DR:DR)+SUMIF(EC:EC,C107,EG:EG)+SUMIF(ER:ER,C107,EV:EV)+SUMIF(FA:FA,C107,FE:FE)+SUMIF(FK:FK,C107,FO:FO)+SUMIF(FT:FT,C107,FX:FX)+SUMIF(GC:GC,C107,GG:GG)+SUMIF(GL:GL,C107,GP:GP)+SUMIF(GU:GU,C107,GY:GY)+SUMIF(HD:HD,C107,HH:HH) -> 0 | H107: =+SUM(F107:G107) -> 0
A108: 83 | B108: =+WEEKNUM(C108,2) -> 51 | C108: =+C107+1 -> 46007 | E108: =+E107+D108-F108 -> 25738609 | F108: =+SUMIF(O:O,C108,R:R)+SUMIF(AE:AE,C108,AH:AH)+SUMIF(AT:AT,C108,AW:AW)+SUMIF(BI:BI,C108,BL:BL)+SUMIF(BY:BY,C108,CB:CB)+SUMIF(BY:BY,C108,CC:CC)+SUMIF(CP:CP,C108,CS:CS)+SUMIF(CY:CY,C108,DB:DB)+SUMIF(DN:DN,C108,DQ:DQ)+SUMIF(EC:EC,C108,EF:EF)+SUMIF(ER:ER,C108,EU:EU)+SUMIF(FA:FA,C108,FD:FD)+SUMIF(FK:FK,C108,FN:FN)+SUMIF(FT:FT,C108,FW:FW)+SUMIF(GC:GC,C108,GF:GF)+SUMIF(GL:GL,C108,GO:GO)+SUMIF(GU:GU,C108,GX:GX)+SUMIF(HD:HD,C108,HG:HG) -> 0 | G108: =+SUMIF(O:O,C108,T:T)+SUMIF(O:O,C108,S:S)+SUMIF(AE:AE,C108,AI:AI)+SUMIF(AT:AT,C108,AX:AX)+SUMIF(BI:BI,C108,BN:BN)+SUMIF(BI:BI,C108,BM:BM)+SUMIF(BY:BY,C108,CD:CD)+SUMIF(BY:BY,C108,CE:CE)+SUMIF(CP:CP,C108,CT:CT)+SUMIF(CY:CY,C108,DC:DC)+SUMIF(DN:DN,C108,DR:DR)+SUMIF(EC:EC,C108,EG:EG)+SUMIF(ER:ER,C108,EV:EV)+SUMIF(FA:FA,C108,FE:FE)+SUMIF(FK:FK,C108,FO:FO)+SUMIF(FT:FT,C108,FX:FX)+SUMIF(GC:GC,C108,GG:GG)+SUMIF(GL:GL,C108,GP:GP)+SUMIF(GU:GU,C108,GY:GY)+SUMIF(HD:HD,C108,HH:HH) -> 0 | H108: =+SUM(F108:G108) -> 0
A109: 84 | B109: =+WEEKNUM(C109,2) -> 51 | C109: =+C108+1 -> 46008 | E109: =+E108+D109-F109 -> 25738609 | F109: =+SUMIF(O:O,C109,R:R)+SUMIF(AE:AE,C109,AH:AH)+SUMIF(AT:AT,C109,AW:AW)+SUMIF(BI:BI,C109,BL:BL)+SUMIF(BY:BY,C109,CB:CB)+SUMIF(BY:BY,C109,CC:CC)+SUMIF(CP:CP,C109,CS:CS)+SUMIF(CY:CY,C109,DB:DB)+SUMIF(DN:DN,C109,DQ:DQ)+SUMIF(EC:EC,C109,EF:EF)+SUMIF(ER:ER,C109,EU:EU)+SUMIF(FA:FA,C109,FD:FD)+SUMIF(FK:FK,C109,FN:FN)+SUMIF(FT:FT,C109,FW:FW)+SUMIF(GC:GC,C109,GF:GF)+SUMIF(GL:GL,C109,GO:GO)+SUMIF(GU:GU,C109,GX:GX)+SUMIF(HD:HD,C109,HG:HG) -> 0 | G109: =+SUMIF(O:O,C109,T:T)+SUMIF(O:O,C109,S:S)+SUMIF(AE:AE,C109,AI:AI)+SUMIF(AT:AT,C109,AX:AX)+SUMIF(BI:BI,C109,BN:BN)+SUMIF(BI:BI,C109,BM:BM)+SUMIF(BY:BY,C109,CD:CD)+SUMIF(BY:BY,C109,CE:CE)+SUMIF(CP:CP,C109,CT:CT)+SUMIF(CY:CY,C109,DC:DC)+SUMIF(DN:DN,C109,DR:DR)+SUMIF(EC:EC,C109,EG:EG)+SUMIF(ER:ER,C109,EV:EV)+SUMIF(FA:FA,C109,FE:FE)+SUMIF(FK:FK,C109,FO:FO)+SUMIF(FT:FT,C109,FX:FX)+SUMIF(GC:GC,C109,GG:GG)+SUMIF(GL:GL,C109,GP:GP)+SUMIF(GU:GU,C109,GY:GY)+SUMIF(HD:HD,C109,HH:HH) -> 0 | H109: =+SUM(F109:G109) -> 0
A110: 85 | B110: =+WEEKNUM(C110,2) -> 51 | C110: =+C109+1 -> 46009 | E110: =+E109+D110-F110 -> 25738609 | F110: =+SUMIF(O:O,C110,R:R)+SUMIF(AE:AE,C110,AH:AH)+SUMIF(AT:AT,C110,AW:AW)+SUMIF(BI:BI,C110,BL:BL)+SUMIF(BY:BY,C110,CB:CB)+SUMIF(BY:BY,C110,CC:CC)+SUMIF(CP:CP,C110,CS:CS)+SUMIF(CY:CY,C110,DB:DB)+SUMIF(DN:DN,C110,DQ:DQ)+SUMIF(EC:EC,C110,EF:EF)+SUMIF(ER:ER,C110,EU:EU)+SUMIF(FA:FA,C110,FD:FD)+SUMIF(FK:FK,C110,FN:FN)+SUMIF(FT:FT,C110,FW:FW)+SUMIF(GC:GC,C110,GF:GF)+SUMIF(GL:GL,C110,GO:GO)+SUMIF(GU:GU,C110,GX:GX)+SUMIF(HD:HD,C110,HG:HG) -> 0 | G110: =+SUMIF(O:O,C110,T:T)+SUMIF(O:O,C110,S:S)+SUMIF(AE:AE,C110,AI:AI)+SUMIF(AT:AT,C110,AX:AX)+SUMIF(BI:BI,C110,BN:BN)+SUMIF(BI:BI,C110,BM:BM)+SUMIF(BY:BY,C110,CD:CD)+SUMIF(BY:BY,C110,CE:CE)+SUMIF(CP:CP,C110,CT:CT)+SUMIF(CY:CY,C110,DC:DC)+SUMIF(DN:DN,C110,DR:DR)+SUMIF(EC:EC,C110,EG:EG)+SUMIF(ER:ER,C110,EV:EV)+SUMIF(FA:FA,C110,FE:FE)+SUMIF(FK:FK,C110,FO:FO)+SUMIF(FT:FT,C110,FX:FX)+SUMIF(GC:GC,C110,GG:GG)+SUMIF(GL:GL,C110,GP:GP)+SUMIF(GU:GU,C110,GY:GY)+SUMIF(HD:HD,C110,HH:HH) -> 0 | H110: =+SUM(F110:G110) -> 0
A111: 86 | B111: =+WEEKNUM(C111,2) -> 51 | C111: =+C110+1 -> 46010 | E111: =+E110+D111-F111 -> 25738609 | F111: =+SUMIF(O:O,C111,R:R)+SUMIF(AE:AE,C111,AH:AH)+SUMIF(AT:AT,C111,AW:AW)+SUMIF(BI:BI,C111,BL:BL)+SUMIF(BY:BY,C111,CB:CB)+SUMIF(BY:BY,C111,CC:CC)+SUMIF(CP:CP,C111,CS:CS)+SUMIF(CY:CY,C111,DB:DB)+SUMIF(DN:DN,C111,DQ:DQ)+SUMIF(EC:EC,C111,EF:EF)+SUMIF(ER:ER,C111,EU:EU)+SUMIF(FA:FA,C111,FD:FD)+SUMIF(FK:FK,C111,FN:FN)+SUMIF(FT:FT,C111,FW:FW)+SUMIF(GC:GC,C111,GF:GF)+SUMIF(GL:GL,C111,GO:GO)+SUMIF(GU:GU,C111,GX:GX)+SUMIF(HD:HD,C111,HG:HG) -> 0 | G111: =+SUMIF(O:O,C111,T:T)+SUMIF(O:O,C111,S:S)+SUMIF(AE:AE,C111,AI:AI)+SUMIF(AT:AT,C111,AX:AX)+SUMIF(BI:BI,C111,BN:BN)+SUMIF(BI:BI,C111,BM:BM)+SUMIF(BY:BY,C111,CD:CD)+SUMIF(BY:BY,C111,CE:CE)+SUMIF(CP:CP,C111,CT:CT)+SUMIF(CY:CY,C111,DC:DC)+SUMIF(DN:DN,C111,DR:DR)+SUMIF(EC:EC,C111,EG:EG)+SUMIF(ER:ER,C111,EV:EV)+SUMIF(FA:FA,C111,FE:FE)+SUMIF(FK:FK,C111,FO:FO)+SUMIF(FT:FT,C111,FX:FX)+SUMIF(GC:GC,C111,GG:GG)+SUMIF(GL:GL,C111,GP:GP)+SUMIF(GU:GU,C111,GY:GY)+SUMIF(HD:HD,C111,HH:HH) -> 0 | H111: =+SUM(F111:G111) -> 0
A112: 87 | B112: =+WEEKNUM(C112,2) -> 51 | C112: =+C111+1 -> 46011 | E112: =+E111+D112-F112 -> 25738609 | F112: =+SUMIF(O:O,C112,R:R)+SUMIF(AE:AE,C112,AH:AH)+SUMIF(AT:AT,C112,AW:AW)+SUMIF(BI:BI,C112,BL:BL)+SUMIF(BY:BY,C112,CB:CB)+SUMIF(BY:BY,C112,CC:CC)+SUMIF(CP:CP,C112,CS:CS)+SUMIF(CY:CY,C112,DB:DB)+SUMIF(DN:DN,C112,DQ:DQ)+SUMIF(EC:EC,C112,EF:EF)+SUMIF(ER:ER,C112,EU:EU)+SUMIF(FA:FA,C112,FD:FD)+SUMIF(FK:FK,C112,FN:FN)+SUMIF(FT:FT,C112,FW:FW)+SUMIF(GC:GC,C112,GF:GF)+SUMIF(GL:GL,C112,GO:GO)+SUMIF(GU:GU,C112,GX:GX)+SUMIF(HD:HD,C112,HG:HG) -> 0 | G112: =+SUMIF(O:O,C112,T:T)+SUMIF(O:O,C112,S:S)+SUMIF(AE:AE,C112,AI:AI)+SUMIF(AT:AT,C112,AX:AX)+SUMIF(BI:BI,C112,BN:BN)+SUMIF(BI:BI,C112,BM:BM)+SUMIF(BY:BY,C112,CD:CD)+SUMIF(BY:BY,C112,CE:CE)+SUMIF(CP:CP,C112,CT:CT)+SUMIF(CY:CY,C112,DC:DC)+SUMIF(DN:DN,C112,DR:DR)+SUMIF(EC:EC,C112,EG:EG)+SUMIF(ER:ER,C112,EV:EV)+SUMIF(FA:FA,C112,FE:FE)+SUMIF(FK:FK,C112,FO:FO)+SUMIF(FT:FT,C112,FX:FX)+SUMIF(GC:GC,C112,GG:GG)+SUMIF(GL:GL,C112,GP:GP)+SUMIF(GU:GU,C112,GY:GY)+SUMIF(HD:HD,C112,HH:HH) -> 726844.88 | H112: =+SUM(F112:G112) -> 726844.88
